[
    {
        "text": " \n \nRegistration No : 1991823021\nRoll No         : 211991823021\n \nFollowing are the marks obtained by NIRANJAN  KUMAR\nof GEMS Polytechnic College, Aurangabad\nat Semester II of Diploma in Computer Science & Engineering\nExamination 2024 (EVEN) held in the month of JUL, 2024\n \n \nResult Published On: 30/07/2024\nSTATE BOARD OF TECHNICAL EDUCATION\nBIHAR\n-----------------------------------------------------------------------------------------------\nSUBJECT  FULL MARKS PASS MARKS MARKS OBTAINED\nNAME OF SUBJECTS CREDITS INTFINTOTAL FINTOTAL INT FIN TOTAL GRADE\n-----------------------------------------------------------------------------------------------\nTHEORY PAPERS\nMATHEMATICS-II 4 3070 100 28 40211435  F\nAPPLIED PHYSICS-II 3 3070 100 28 40273057  D\nINTRODUCTION TO IT SYSTEMS 2 3070 100 28 40163753  D\nFUNDA OF ELECT AND EC ENGG 3 3070 100 28 40262854  D\nENGG. MECHANICS 3 3070 100 28 40273865  C\n-----------------------------------------------------------------------------------------------\nPRACTICAL PAPERS\nAPPLIED PHYSICS LAB-II 1 1535 050 - 20132740  A\nINTRODUCTION TO IT SYSTEM LAB 2 1535 050 - 20142842  A\nFUNDA OF ELECT AND EC ENGG LAB 1 1535 050 - 20142943  A\nENGG. MECHANICS LAB 2 1535 050 - 20132740  A\n-----------------------------------------------------------------------------------------------\nTERM WORK PAPERS\nC.U MOOCS/ SWAYAM/ ETC/ OTHERS 2 0614 020 - 08061117  A\nKYP/IT ESSEN/ PYTHON/ OTHERS 1 0614 020 - 08061117  A\nENVIRONMENTAL SCIENCE 0 10 -010 - 0409 -09  A+\n-----------------------------------------------------------------------------------------------\nGRAND TOTAL 24 750 472\n-----------------------------------------------------------------------------------------------\nSGPA \n-----------------------------------------------------------------------------------------------\nREMARKS : Carry in - MATHEMATICS-II",
        "college": "GEMS Polytechnic College, Aurangabad",
        "name": "NIRANJAN KUMAR",
        "roll": "211991823021",
        "branch": "18",
        "marks": 472,
        "remarks": "Carry in - MATHEMATICS-II",
        "theory": 147
    },
    {
        "text": " \n \nRegistration No : 1991823049\nRoll No         : 211991823049\n \nFollowing are the marks obtained by VRISHKETU  RAY\nof GEMS Polytechnic College, Aurangabad\nat Semester II of Diploma in Computer Science & Engineering\nExamination 2024 (EVEN) held in the month of JUL, 2024\n \n \nResult Published On: 30/07/2024\nSTATE BOARD OF TECHNICAL EDUCATION\nBIHAR\n-----------------------------------------------------------------------------------------------\nSUBJECT  FULL MARKS PASS MARKS MARKS OBTAINED\nNAME OF SUBJECTS CREDITS INTFINTOTAL FINTOTAL INT FIN TOTAL GRADE\n-----------------------------------------------------------------------------------------------\nTHEORY PAPERS\nMATHEMATICS-II 4 3070 100 28 40262854  D\nAPPLIED PHYSICS-II 3 3070 100 28 40272855  D\nINTRODUCTION TO IT SYSTEMS 2 3070 100 28 40284674  B\nFUNDA OF ELECT AND EC ENGG 3 3070 100 28 40283967  C\nENGG. MECHANICS 3 3070 100 28 40275077  B\n-----------------------------------------------------------------------------------------------\nPRACTICAL PAPERS\nAPPLIED PHYSICS LAB-II 1 1535 050 - 20153045  A+\nINTRODUCTION TO IT SYSTEM LAB 2 1535 050 - 20142943  A\nFUNDA OF ELECT AND EC ENGG LAB 1 1535 050 - 20153146  A+\nENGG. MECHANICS LAB 2 1535 050 - 20152742  A\n-----------------------------------------------------------------------------------------------\nTERM WORK PAPERS\nC.U MOOCS/ SWAYAM/ ETC/ OTHERS 2 0614 020 - 08060915  B\nKYP/IT ESSEN/ PYTHON/ OTHERS 1 0614 020 - 08060814  B\nENVIRONMENTAL SCIENCE 0 10 -010 - 0410 -10  A+\n-----------------------------------------------------------------------------------------------\nGRAND TOTAL 24 750 542\n-----------------------------------------------------------------------------------------------\nSGPA 7.62\n-----------------------------------------------------------------------------------------------\nREMARKS : First Class",
        "college": "GEMS Polytechnic College, Aurangabad",
        "name": "VRISHKETU RAY",
        "roll": "211991823049",
        "branch": "18",
        "marks": 542,
        "remarks": "First Class",
        "theory": 191
    },
    {
        "text": " \n \nRegistration No : 1991823027\nRoll No         : 211991823027\n \nFollowing are the marks obtained by RAUSHAN KUMAR\nof GEMS Polytechnic College, Aurangabad\nat Semester II of Diploma in Computer Science & Engineering\nExamination 2024 (EVEN) held in the month of JUL, 2024\n \n \nResult Published On: 30/07/2024\nSTATE BOARD OF TECHNICAL EDUCATION\nBIHAR\n-----------------------------------------------------------------------------------------------\nSUBJECT  FULL MARKS PASS MARKS MARKS OBTAINED\nNAME OF SUBJECTS CREDITS INTFINTOTAL FINTOTAL INT FIN TOTAL GRADE\n-----------------------------------------------------------------------------------------------\nTHEORY PAPERS\nMATHEMATICS-II 4 3070 100 28 40201434  F\nAPPLIED PHYSICS-II 3 3070 100 28 40271239  F\nINTRODUCTION TO IT SYSTEMS 2 3070 100 28 40233861  C\nFUNDA OF ELECT AND EC ENGG 3 3070 100 28 40272249  E\nENGG. MECHANICS 3 3070 100 28 40274269  C\n-----------------------------------------------------------------------------------------------\nPRACTICAL PAPERS\nAPPLIED PHYSICS LAB-II 1 1535 050 - 20133043  A\nINTRODUCTION TO IT SYSTEM LAB 2 1535 050 - 20142539  B\nFUNDA OF ELECT AND EC ENGG LAB 1 1535 050 - 20143145  A+\nENGG. MECHANICS LAB 2 1535 050 - 20132437  B\n-----------------------------------------------------------------------------------------------\nTERM WORK PAPERS\nC.U MOOCS/ SWAYAM/ ETC/ OTHERS 2 0614 020 - 08060915  B\nKYP/IT ESSEN/ PYTHON/ OTHERS 1 0614 020 - 08060915  B\nENVIRONMENTAL SCIENCE 0 10 -010 - 0409 -09  A+\n-----------------------------------------------------------------------------------------------\nGRAND TOTAL 24 750 455\n-----------------------------------------------------------------------------------------------\nSGPA \n-----------------------------------------------------------------------------------------------\nREMARKS : Fail",
        "college": "GEMS Polytechnic College, Aurangabad",
        "name": "RAUSHAN KUMAR",
        "roll": "211991823027",
        "branch": "18",
        "marks": 455,
        "remarks": "Fail",
        "theory": 128
    },
    {
        "text": " \n \nRegistration No : 1991823039\nRoll No         : 211991823039\n \nFollowing are the marks obtained by SAURABH KUMAR\nof GEMS Polytechnic College, Aurangabad\nat Semester II of Diploma in Computer Science & Engineering\nExamination 2024 (EVEN) held in the month of JUL, 2024\n \n \nResult Published On: 30/07/2024\nSTATE BOARD OF TECHNICAL EDUCATION\nBIHAR\n-----------------------------------------------------------------------------------------------\nSUBJECT  FULL MARKS PASS MARKS MARKS OBTAINED\nNAME OF SUBJECTS CREDITS INTFINTOTAL FINTOTAL INT FIN TOTAL GRADE\n-----------------------------------------------------------------------------------------------\nTHEORY PAPERS\nMATHEMATICS-II 4 3070 100 28 40202848  E\nAPPLIED PHYSICS-II 3 3070 100 28 40252853  D\nINTRODUCTION TO IT SYSTEMS 2 3070 100 28 40255277  B\nFUNDA OF ELECT AND EC ENGG 3 3070 100 28 40252853  D\nENGG. MECHANICS 3 3070 100 28 40253257  D\n-----------------------------------------------------------------------------------------------\nPRACTICAL PAPERS\nAPPLIED PHYSICS LAB-II 1 1535 050 - 20143044  A\nINTRODUCTION TO IT SYSTEM LAB 2 1535 050 - 20152843  A\nFUNDA OF ELECT AND EC ENGG LAB 1 1535 050 - 20143044  A\nENGG. MECHANICS LAB 2 1535 050 - 20142438  B\n-----------------------------------------------------------------------------------------------\nTERM WORK PAPERS\nC.U MOOCS/ SWAYAM/ ETC/ OTHERS 2 0614 020 - 08060814  B\nKYP/IT ESSEN/ PYTHON/ OTHERS 1 0614 020 - 08060915  B\nENVIRONMENTAL SCIENCE 0 10 -010 - 0409 -09  A+\n-----------------------------------------------------------------------------------------------\nGRAND TOTAL 24 750 495\n-----------------------------------------------------------------------------------------------\nSGPA 6.92\n-----------------------------------------------------------------------------------------------\nREMARKS : First Class",
        "college": "GEMS Polytechnic College, Aurangabad",
        "name": "SAURABH KUMAR",
        "roll": "211991823039",
        "branch": "18",
        "marks": 495,
        "remarks": "First Class",
        "theory": 168
    },
    {
        "text": " \n \nRegistration No : 1991823035\nRoll No         : 211991823035\n \nFollowing are the marks obtained by RUNAM  KUMARI\nof GEMS Polytechnic College, Aurangabad\nat Semester II of Diploma in Computer Science & Engineering\nExamination 2024 (EVEN) held in the month of JUL, 2024\n \n \nResult Published On: 30/07/2024\nSTATE BOARD OF TECHNICAL EDUCATION\nBIHAR\n-----------------------------------------------------------------------------------------------\nSUBJECT  FULL MARKS PASS MARKS MARKS OBTAINED\nNAME OF SUBJECTS CREDITS INTFINTOTAL FINTOTAL INT FIN TOTAL GRADE\n-----------------------------------------------------------------------------------------------\nTHEORY PAPERS\nMATHEMATICS-II 4 3070 100 28 40161228  F\nAPPLIED PHYSICS-II 3 3070 100 28 40214061  C\nINTRODUCTION TO IT SYSTEMS 2 3070 100 28 40153651  D\nFUNDA OF ELECT AND EC ENGG 3 3070 100 28 40233255  D\nENGG. MECHANICS 3 3070 100 28 40213253  D\n-----------------------------------------------------------------------------------------------\nPRACTICAL PAPERS\nAPPLIED PHYSICS LAB-II 1 1535 050 - 20122537  B\nINTRODUCTION TO IT SYSTEM LAB 2 1535 050 - 20142034  C\nFUNDA OF ELECT AND EC ENGG LAB 1 1535 050 - 20142943  A\nENGG. MECHANICS LAB 2 1535 050 - 20122436  B\n-----------------------------------------------------------------------------------------------\nTERM WORK PAPERS\nC.U MOOCS/ SWAYAM/ ETC/ OTHERS 2 0614 020 - 08051116  A\nKYP/IT ESSEN/ PYTHON/ OTHERS 1 0614 020 - 08051015  B\nENVIRONMENTAL SCIENCE 0 10 -010 - 0410 -10  A+\n-----------------------------------------------------------------------------------------------\nGRAND TOTAL 24 750 439\n-----------------------------------------------------------------------------------------------\nSGPA \n-----------------------------------------------------------------------------------------------\nREMARKS : Carry in - MATHEMATICS-II",
        "college": "GEMS Polytechnic College, Aurangabad",
        "name": "RUNAM KUMARI",
        "roll": "211991823035",
        "branch": "18",
        "marks": 439,
        "remarks": "Carry in - MATHEMATICS-II",
        "theory": 152
    },
    {
        "text": " \n \nRegistration No : 1991823012\nRoll No         : 211991823012\n \nFollowing are the marks obtained by ISHU  RAJ\nof GEMS Polytechnic College, Aurangabad\nat Semester II of Diploma in Computer Science & Engineering\nExamination 2024 (EVEN) held in the month of JUL, 2024\n \n \nResult Published On: 30/07/2024\nSTATE BOARD OF TECHNICAL EDUCATION\nBIHAR\n-----------------------------------------------------------------------------------------------\nSUBJECT  FULL MARKS PASS MARKS MARKS OBTAINED\nNAME OF SUBJECTS CREDITS INTFINTOTAL FINTOTAL INT FIN TOTAL GRADE\n-----------------------------------------------------------------------------------------------\nTHEORY PAPERS\nMATHEMATICS-II 4 3070 100 28 40273259  D\nAPPLIED PHYSICS-II 3 3070 100 28 40303868  C\nINTRODUCTION TO IT SYSTEMS 2 3070 100 28 40304373  B\nFUNDA OF ELECT AND EC ENGG 3 3070 100 28 40304272  B\nENGG. MECHANICS 3 3070 100 28 40303060  C\n-----------------------------------------------------------------------------------------------\nPRACTICAL PAPERS\nAPPLIED PHYSICS LAB-II 1 1535 050 - 20152742  A\nINTRODUCTION TO IT SYSTEM LAB 2 1535 050 - 20153247  A+\nFUNDA OF ELECT AND EC ENGG LAB 1 1535 050 - 20153247  A+\nENGG. MECHANICS LAB 2 1535 050 - 20153348  A+\n-----------------------------------------------------------------------------------------------\nTERM WORK PAPERS\nC.U MOOCS/ SWAYAM/ ETC/ OTHERS 2 0614 020 - 08061420  A+\nKYP/IT ESSEN/ PYTHON/ OTHERS 1 0614 020 - 08061420  A+\nENVIRONMENTAL SCIENCE 0 10 -010 - 0410 -10  A+\n-----------------------------------------------------------------------------------------------\nGRAND TOTAL 24 750 566\n-----------------------------------------------------------------------------------------------\nSGPA 8.12\n-----------------------------------------------------------------------------------------------\nREMARKS : First Class with Distinction",
        "college": "GEMS Polytechnic College, Aurangabad",
        "name": "ISHU RAJ",
        "roll": "211991823012",
        "branch": "18",
        "marks": 566,
        "remarks": "First Class with Distinction",
        "theory": 185
    },
    {
        "text": " \n \nRegistration No : 1991823048\nRoll No         : 211991823048\n \nFollowing are the marks obtained by VIVEK  KUMAR\nof GEMS Polytechnic College, Aurangabad\nat Semester II of Diploma in Computer Science & Engineering\nExamination 2024 (EVEN) held in the month of JUL, 2024\n \n \nResult Published On: 30/07/2024\nSTATE BOARD OF TECHNICAL EDUCATION\nBIHAR\n-----------------------------------------------------------------------------------------------\nSUBJECT  FULL MARKS PASS MARKS MARKS OBTAINED\nNAME OF SUBJECTS CREDITS INTFINTOTAL FINTOTAL INT FIN TOTAL GRADE\n-----------------------------------------------------------------------------------------------\nTHEORY PAPERS\nMATHEMATICS-II 4 3070 100 28 40212849  E\nAPPLIED PHYSICS-II 3 3070 100 28 40263258  D\nINTRODUCTION TO IT SYSTEMS 2 3070 100 28 40222850  D\nFUNDA OF ELECT AND EC ENGG 3 3070 100 28 402523+553  D\nENGG. MECHANICS 3 3070 100 28 402641-562  C\n-----------------------------------------------------------------------------------------------\nPRACTICAL PAPERS\nAPPLIED PHYSICS LAB-II 1 1535 050 - 20132740  A\nINTRODUCTION TO IT SYSTEM LAB 2 1535 050 - 20142539  B\nFUNDA OF ELECT AND EC ENGG LAB 1 1535 050 - 20142943  A\nENGG. MECHANICS LAB 2 1535 050 - 20132437  B\n-----------------------------------------------------------------------------------------------\nTERM WORK PAPERS\nC.U MOOCS/ SWAYAM/ ETC/ OTHERS 2 0614 020 - 08060915  B\nKYP/IT ESSEN/ PYTHON/ OTHERS 1 0614 020 - 08050914  B\nENVIRONMENTAL SCIENCE 0 10 -010 - 0409 -09  A+\n-----------------------------------------------------------------------------------------------\nGRAND TOTAL 24 750 469\n-----------------------------------------------------------------------------------------------\nSGPA 6.79\n-----------------------------------------------------------------------------------------------\nREMARKS : First Class (U/R)",
        "college": "GEMS Polytechnic College, Aurangabad",
        "name": "VIVEK KUMAR",
        "roll": "211991823048",
        "branch": "18",
        "marks": 469,
        "remarks": "First Class (U/R)",
        "theory": 152
    },
    {
        "text": " \n \nRegistration No : 1991823029\nRoll No         : 211991823029\n \nFollowing are the marks obtained by RISHI KUMAR\nof GEMS Polytechnic College, Aurangabad\nat Semester II of Diploma in Computer Science & Engineering\nExamination 2024 (EVEN) held in the month of JUL, 2024\n \n \nResult Published On: 30/07/2024\nSTATE BOARD OF TECHNICAL EDUCATION\nBIHAR\n-----------------------------------------------------------------------------------------------\nSUBJECT  FULL MARKS PASS MARKS MARKS OBTAINED\nNAME OF SUBJECTS CREDITS INTFINTOTAL FINTOTAL INT FIN TOTAL GRADE\n-----------------------------------------------------------------------------------------------\nTHEORY PAPERS\nMATHEMATICS-II 4 3070 100 28 40192847  E\nAPPLIED PHYSICS-II 3 3070 100 28 40273764  C\nINTRODUCTION TO IT SYSTEMS 2 3070 100 28 40173653  D\nFUNDA OF ELECT AND EC ENGG 3 3070 100 28 40272855  D\nENGG. MECHANICS 3 3070 100 28 40274269  C\n-----------------------------------------------------------------------------------------------\nPRACTICAL PAPERS\nAPPLIED PHYSICS LAB-II 1 1535 050 - 20133144  A\nINTRODUCTION TO IT SYSTEM LAB 2 1535 050 - 20142539  B\nFUNDA OF ELECT AND EC ENGG LAB 1 1535 050 - 20143044  A\nENGG. MECHANICS LAB 2 1535 050 - 20132740  A\n-----------------------------------------------------------------------------------------------\nTERM WORK PAPERS\nC.U MOOCS/ SWAYAM/ ETC/ OTHERS 2 0614 020 - 08060915  B\nKYP/IT ESSEN/ PYTHON/ OTHERS 1 0614 020 - 08060915  B\nENVIRONMENTAL SCIENCE 0 10 -010 - 0409 -09  A+\n-----------------------------------------------------------------------------------------------\nGRAND TOTAL 24 750 494\n-----------------------------------------------------------------------------------------------\nSGPA 7.0\n-----------------------------------------------------------------------------------------------\nREMARKS : First Class",
        "college": "GEMS Polytechnic College, Aurangabad",
        "name": "RISHI KUMAR",
        "roll": "211991823029",
        "branch": "18",
        "marks": 494,
        "remarks": "First Class",
        "theory": 171
    },
    {
        "text": " \n \nRegistration No : 1991823034\nRoll No         : 211991823034\n \nFollowing are the marks obtained by RUMANA  AKHTAR\nof GEMS Polytechnic College, Aurangabad\nat Semester II of Diploma in Computer Science & Engineering\nExamination 2024 (EVEN) held in the month of JUL, 2024\n \n \nResult Published On: 30/07/2024\nSTATE BOARD OF TECHNICAL EDUCATION\nBIHAR\n-----------------------------------------------------------------------------------------------\nSUBJECT  FULL MARKS PASS MARKS MARKS OBTAINED\nNAME OF SUBJECTS CREDITS INTFINTOTAL FINTOTAL INT FIN TOTAL GRADE\n-----------------------------------------------------------------------------------------------\nTHEORY PAPERS\nMATHEMATICS-II 4 3070 100 28 40295180  A\nAPPLIED PHYSICS-II 3 3070 100 28 40305383  A\nINTRODUCTION TO IT SYSTEMS 2 3070 100 28 40306191  A+\nFUNDA OF ELECT AND EC ENGG 3 3070 100 28 40304777  B\nENGG. MECHANICS 3 3070 100 28 40305888  A\n-----------------------------------------------------------------------------------------------\nPRACTICAL PAPERS\nAPPLIED PHYSICS LAB-II 1 1535 050 - 20152944  A\nINTRODUCTION TO IT SYSTEM LAB 2 1535 050 - 20153247  A+\nFUNDA OF ELECT AND EC ENGG LAB 1 1535 050 - 20153247  A+\nENGG. MECHANICS LAB 2 1535 050 - 20153348  A+\n-----------------------------------------------------------------------------------------------\nTERM WORK PAPERS\nC.U MOOCS/ SWAYAM/ ETC/ OTHERS 2 0614 020 - 08060814  B\nKYP/IT ESSEN/ PYTHON/ OTHERS 1 0614 020 - 08061218  A+\nENVIRONMENTAL SCIENCE 0 10 -010 - 0410 -10  A+\n-----------------------------------------------------------------------------------------------\nGRAND TOTAL 24 750 647\n-----------------------------------------------------------------------------------------------\nSGPA 9.12\n-----------------------------------------------------------------------------------------------\nREMARKS : First Class with Distinction",
        "college": "GEMS Polytechnic College, Aurangabad",
        "name": "RUMANA AKHTAR",
        "roll": "211991823034",
        "branch": "18",
        "marks": 647,
        "remarks": "First Class with Distinction",
        "theory": 270
    },
    {
        "text": " \n \nRegistration No : 1731823006\nRoll No         : 211731823006\n \nFollowing are the marks obtained by SUJAL SINGH RAJPUT\nof Millia Polytechnic, Purnea\nat Semester II of Diploma in Computer Science & Engineering\nExamination 2024 (EVEN) held in the month of JUL, 2024\n \n \nResult Published On: 30/07/2024\nSTATE BOARD OF TECHNICAL EDUCATION\nBIHAR\n-----------------------------------------------------------------------------------------------\nSUBJECT  FULL MARKS PASS MARKS MARKS OBTAINED\nNAME OF SUBJECTS CREDITS INTFINTOTAL FINTOTAL INT FIN TOTAL GRADE\n-----------------------------------------------------------------------------------------------\nTHEORY PAPERS\nMATHEMATICS-II 4 3070 100 28 40252954  D\nAPPLIED PHYSICS-II 3 3070 100 28 40253964  C\nINTRODUCTION TO IT SYSTEMS 2 3070 100 28 40273663  C\nFUNDA OF ELECT AND EC ENGG 3 3070 100 28 40254570  B\nENGG. MECHANICS 3 3070 100 28 40254974  B\n-----------------------------------------------------------------------------------------------\nPRACTICAL PAPERS\nAPPLIED PHYSICS LAB-II 1 1535 050 - 20143246  A+\nINTRODUCTION TO IT SYSTEM LAB 2 1535 050 - 20133144  A\nFUNDA OF ELECT AND EC ENGG LAB 1 1535 050 - 20132336  B\nENGG. MECHANICS LAB 2 1535 050 - 20142337  B\n-----------------------------------------------------------------------------------------------\nTERM WORK PAPERS\nC.U MOOCS/ SWAYAM/ ETC/ OTHERS 2 0614 020 - 08051318  A+\nKYP/IT ESSEN/ PYTHON/ OTHERS 1 0614 020 - 08051217  A\nENVIRONMENTAL SCIENCE 0 10 -010 - 0409 -09  A+\n-----------------------------------------------------------------------------------------------\nGRAND TOTAL 24 750 532\n-----------------------------------------------------------------------------------------------\nSGPA 7.83\n-----------------------------------------------------------------------------------------------\nREMARKS : First Class",
        "college": "Millia Polytechnic, Purnea",
        "name": "SUJAL SINGH RAJPUT",
        "roll": "211731823006",
        "branch": "18",
        "marks": 532,
        "remarks": "First Class",
        "theory": 198
    },
    {
        "text": " \n \nRegistration No : 1731823008\nRoll No         : 211731823008\n \nFollowing are the marks obtained by ABHISHEK KUMAR\nof Millia Polytechnic, Purnea\nat Semester II of Diploma in Computer Science & Engineering\nExamination 2024 (EVEN) held in the month of JUL, 2024\n \n \nResult Published On: 30/07/2024\nSTATE BOARD OF TECHNICAL EDUCATION\nBIHAR\n-----------------------------------------------------------------------------------------------\nSUBJECT  FULL MARKS PASS MARKS MARKS OBTAINED\nNAME OF SUBJECTS CREDITS INTFINTOTAL FINTOTAL INT FIN TOTAL GRADE\n-----------------------------------------------------------------------------------------------\nTHEORY PAPERS\nMATHEMATICS-II 4 3070 100 28 40263662  C\nAPPLIED PHYSICS-II 3 3070 100 28 40274168  C\nINTRODUCTION TO IT SYSTEMS 2 3070 100 28 40274471  B\nFUNDA OF ELECT AND EC ENGG 3 3070 100 28 40254469  C\nENGG. MECHANICS 3 3070 100 28 40254166  C\n-----------------------------------------------------------------------------------------------\nPRACTICAL PAPERS\nAPPLIED PHYSICS LAB-II 1 1535 050 - 20143246  A+\nINTRODUCTION TO IT SYSTEM LAB 2 1535 050 - 20133144  A\nFUNDA OF ELECT AND EC ENGG LAB 1 1535 050 - 20143246  A+\nENGG. MECHANICS LAB 2 1535 050 - 20143145  A+\n-----------------------------------------------------------------------------------------------\nTERM WORK PAPERS\nC.U MOOCS/ SWAYAM/ ETC/ OTHERS 2 0614 020 - 08041317  A\nKYP/IT ESSEN/ PYTHON/ OTHERS 1 0614 020 - 08051217  A\nENVIRONMENTAL SCIENCE 0 10 -010 - 0409 -09  A+\n-----------------------------------------------------------------------------------------------\nGRAND TOTAL 24 750 560\n-----------------------------------------------------------------------------------------------\nSGPA 8.0\n-----------------------------------------------------------------------------------------------\nREMARKS : First Class",
        "college": "Millia Polytechnic, Purnea",
        "name": "ABHISHEK KUMAR",
        "roll": "211731823008",
        "branch": "18",
        "marks": 560,
        "remarks": "First Class",
        "theory": 206
    },
    {
        "text": " \n \nRegistration No : 1731823010\nRoll No         : 211731823010\n \nFollowing are the marks obtained by AVISHEK KUMAR\nof Millia Polytechnic, Purnea\nat Semester II of Diploma in Computer Science & Engineering\nExamination 2024 (EVEN) held in the month of JUL, 2024\n \n \nResult Published On: 30/07/2024\nSTATE BOARD OF TECHNICAL EDUCATION\nBIHAR\n-----------------------------------------------------------------------------------------------\nSUBJECT  FULL MARKS PASS MARKS MARKS OBTAINED\nNAME OF SUBJECTS CREDITS INTFINTOTAL FINTOTAL INT FIN TOTAL GRADE\n-----------------------------------------------------------------------------------------------\nTHEORY PAPERS\nMATHEMATICS-II 4 3070 100 28 40263359  D\nAPPLIED PHYSICS-II 3 3070 100 28 40252954  D\nINTRODUCTION TO IT SYSTEMS 2 3070 100 28 40254267  C\nFUNDA OF ELECT AND EC ENGG 3 3070 100 28 40253257  D\nENGG. MECHANICS 3 3070 100 28 40253964  C\n-----------------------------------------------------------------------------------------------\nPRACTICAL PAPERS\nAPPLIED PHYSICS LAB-II 1 1535 050 - 20133144  A\nINTRODUCTION TO IT SYSTEM LAB 2 1535 050 - 20143246  A+\nFUNDA OF ELECT AND EC ENGG LAB 1 1535 050 - 20132336  B\nENGG. MECHANICS LAB 2 1535 050 - 20142337  B\n-----------------------------------------------------------------------------------------------\nTERM WORK PAPERS\nC.U MOOCS/ SWAYAM/ ETC/ OTHERS 2 0614 020 - 08051217  A\nKYP/IT ESSEN/ PYTHON/ OTHERS 1 0614 020 - 08051318  A+\nENVIRONMENTAL SCIENCE 0 10 -010 - 0409 -09  A+\n-----------------------------------------------------------------------------------------------\nGRAND TOTAL 24 750 508\n-----------------------------------------------------------------------------------------------\nSGPA 7.33\n-----------------------------------------------------------------------------------------------\nREMARKS : First Class",
        "college": "Millia Polytechnic, Purnea",
        "name": "AVISHEK KUMAR",
        "roll": "211731823010",
        "branch": "18",
        "marks": 508,
        "remarks": "First Class",
        "theory": 175
    },
    {
        "text": " \n \nRegistration No : 1732523012\nRoll No         : 211732523012\n \nFollowing are the marks obtained by RAHUL KUMAR\nof Millia Polytechnic, Purnea\nat Semester II of Diploma in Mechanical Engineering\nExamination 2024 (EVEN) held in the month of JUL, 2024\n \n \nResult Published On: 30/07/2024\nSTATE BOARD OF TECHNICAL EDUCATION\nBIHAR\n-----------------------------------------------------------------------------------------------\nSUBJECT  FULL MARKS PASS MARKS MARKS OBTAINED\nNAME OF SUBJECTS CREDITS INTFINTOTAL FINTOTAL INT FIN TOTAL GRADE\n-----------------------------------------------------------------------------------------------\nTHEORY PAPERS\nMATHEMATICS-II 4 3070 100 28 40252853  D\nAPPLIED PHYSICS-II 3 3070 100 28 40254267  C\nINTRODUCTION TO IT SYSTEMS 2 3070 100 28 40263056  D\nFUNDA OF ELECT AND EC ENGG 3 3070 100 28 40253055  D\nENGG. MECHANICS 3 3070 100 28 40253863  C\n-----------------------------------------------------------------------------------------------\nPRACTICAL PAPERS\nAPPLIED PHYSICS LAB-II 1 1535 050 - 20133144  A\nINTRODUCTION TO IT SYSTEM LAB 2 1535 050 - 20133245  A+\nFUNDA OF ELECT AND EC ENGG LAB 1 1535 050 - 20133144  A\nENGG. MECHANICS LAB 2 1535 050 - 20133245  A+\n-----------------------------------------------------------------------------------------------\nTERM WORK PAPERS\nC.U MOOCS/ SWAYAM/ ETC/ OTHERS 2 0614 020 - 08041317  A\nKYP/IT ESSEN/ PYTHON/ OTHERS 1 0614 020 - 08051217  A\nENVIRONMENTAL SCIENCE 0 10 -010 - 0409 -09  A+\n-----------------------------------------------------------------------------------------------\nGRAND TOTAL 24 750 515\n-----------------------------------------------------------------------------------------------\nSGPA 7.54\n-----------------------------------------------------------------------------------------------\nREMARKS : First Class",
        "college": "Millia Polytechnic, Purnea",
        "name": "RAHUL KUMAR",
        "roll": "211732523012",
        "branch": "25",
        "marks": 515,
        "remarks": "First Class",
        "theory": 168
    },
    {
        "text": " \n \nRegistration No : 1732523007\nRoll No         : 211732523007\n \nFollowing are the marks obtained by RONAK KUMAR\nof Millia Polytechnic, Purnea\nat Semester II of Diploma in Mechanical Engineering\nExamination 2024 (EVEN) held in the month of JUL, 2024\n \n \nResult Published On: 30/07/2024\nSTATE BOARD OF TECHNICAL EDUCATION\nBIHAR\n-----------------------------------------------------------------------------------------------\nSUBJECT  FULL MARKS PASS MARKS MARKS OBTAINED\nNAME OF SUBJECTS CREDITS INTFINTOTAL FINTOTAL INT FIN TOTAL GRADE\n-----------------------------------------------------------------------------------------------\nTHEORY PAPERS\nMATHEMATICS-II 4 3070 100 28 40275178  B\nAPPLIED PHYSICS-II 3 3070 100 28 40262854  D\nINTRODUCTION TO IT SYSTEMS 2 3070 100 28 40275279  B\nFUNDA OF ELECT AND EC ENGG 3 3070 100 28 40253358  D\nENGG. MECHANICS 3 3070 100 28 40254974  B\n-----------------------------------------------------------------------------------------------\nPRACTICAL PAPERS\nAPPLIED PHYSICS LAB-II 1 1535 050 - 20133144  A\nINTRODUCTION TO IT SYSTEM LAB 2 1535 050 - 20143246  A+\nFUNDA OF ELECT AND EC ENGG LAB 1 1535 050 - 20133144  A\nENGG. MECHANICS LAB 2 1535 050 - 20143246  A+\n-----------------------------------------------------------------------------------------------\nTERM WORK PAPERS\nC.U MOOCS/ SWAYAM/ ETC/ OTHERS 2 0614 020 - 08051318  A+\nKYP/IT ESSEN/ PYTHON/ OTHERS 1 0614 020 - 08051217  A\nENVIRONMENTAL SCIENCE 0 10 -010 - 0409 -09  A+\n-----------------------------------------------------------------------------------------------\nGRAND TOTAL 24 750 567\n-----------------------------------------------------------------------------------------------\nSGPA 8.12\n-----------------------------------------------------------------------------------------------\nREMARKS : First Class with Distinction",
        "college": "Millia Polytechnic, Purnea",
        "name": "RONAK KUMAR",
        "roll": "211732523007",
        "branch": "25",
        "marks": 567,
        "remarks": "First Class with Distinction",
        "theory": 213
    },
    {
        "text": " \n \nRegistration No : 1741823044\nRoll No         : 211741823044\n \nFollowing are the marks obtained by SHIVANI  KUMARI\nof Buddha Institute of Technology, Gaya\nat Semester II of Diploma in Computer Science & Engineering\nExamination 2024 (EVEN) held in the month of JUL, 2024\n \n \nResult Published On: 30/07/2024\nSTATE BOARD OF TECHNICAL EDUCATION\nBIHAR\n-----------------------------------------------------------------------------------------------\nSUBJECT  FULL MARKS PASS MARKS MARKS OBTAINED\nNAME OF SUBJECTS CREDITS INTFINTOTAL FINTOTAL INT FIN TOTAL GRADE\n-----------------------------------------------------------------------------------------------\nTHEORY PAPERS\nMATHEMATICS-II 4 3070 100 28 40260632  F\nAPPLIED PHYSICS-II 3 3070 100 28 40273158  D\nINTRODUCTION TO IT SYSTEMS 2 3070 100 28 40252853  D\nFUNDA OF ELECT AND EC ENGG 3 3070 100 28 40263460  C\nENGG. MECHANICS 3 3070 100 28 40262046  E\n-----------------------------------------------------------------------------------------------\nPRACTICAL PAPERS\nAPPLIED PHYSICS LAB-II 1 1535 050 - 20133144  A\nINTRODUCTION TO IT SYSTEM LAB 2 1535 050 - 20133245  A+\nFUNDA OF ELECT AND EC ENGG LAB 1 1535 050 - 20132639  B\nENGG. MECHANICS LAB 2 1535 050 - 20132841  A\n-----------------------------------------------------------------------------------------------\nTERM WORK PAPERS\nC.U MOOCS/ SWAYAM/ ETC/ OTHERS 2 0614 020 - 08051217  A\nKYP/IT ESSEN/ PYTHON/ OTHERS 1 0614 020 - 08051116  A\nENVIRONMENTAL SCIENCE 0 10 -010 - 0408 -08  A\n-----------------------------------------------------------------------------------------------\nGRAND TOTAL 24 750 459\n-----------------------------------------------------------------------------------------------\nSGPA \n-----------------------------------------------------------------------------------------------\nREMARKS : Carry in - MATHEMATICS-II\n ENGG. MECHANICS",
        "college": "Buddha Institute",
        "name": "SHIVANI KUMARI",
        "roll": "211741823044",
        "branch": "18",
        "marks": 459,
        "remarks": "Carry in - MATHEMATICS-II",
        "theory": 119
    },
    {
        "text": " \n \nRegistration No : 1741823008\nRoll No         : 211741823008\n \nFollowing are the marks obtained by ANKIT KUMAR\nof Buddha Institute of Technology, Gaya\nat Semester II of Diploma in Computer Science & Engineering\nExamination 2024 (EVEN) held in the month of JUL, 2024\n \n \nResult Published On: 30/07/2024\nSTATE BOARD OF TECHNICAL EDUCATION\nBIHAR\n-----------------------------------------------------------------------------------------------\nSUBJECT  FULL MARKS PASS MARKS MARKS OBTAINED\nNAME OF SUBJECTS CREDITS INTFINTOTAL FINTOTAL INT FIN TOTAL GRADE\n-----------------------------------------------------------------------------------------------\nTHEORY PAPERS\nMATHEMATICS-II 4 3070 100 28 40263056  D\nAPPLIED PHYSICS-II 3 3070 100 28 40263258  D\nINTRODUCTION TO IT SYSTEMS 2 3070 100 28 402639-560  C\nFUNDA OF ELECT AND EC ENGG 3 3070 100 28 402623+554  D\nENGG. MECHANICS 3 3070 100 28 40253257  D\n-----------------------------------------------------------------------------------------------\nPRACTICAL PAPERS\nAPPLIED PHYSICS LAB-II 1 1535 050 - 20142842  A\nINTRODUCTION TO IT SYSTEM LAB 2 1535 050 - 20133144  A\nFUNDA OF ELECT AND EC ENGG LAB 1 1535 050 - 20132740  A\nENGG. MECHANICS LAB 2 1535 050 - 20132740  A\n-----------------------------------------------------------------------------------------------\nTERM WORK PAPERS\nC.U MOOCS/ SWAYAM/ ETC/ OTHERS 2 0614 020 - 08051217  A\nKYP/IT ESSEN/ PYTHON/ OTHERS 1 0614 020 - 08051015  B\nENVIRONMENTAL SCIENCE 0 10 -010 - 0409 -09  A+\n-----------------------------------------------------------------------------------------------\nGRAND TOTAL 24 750 492\n-----------------------------------------------------------------------------------------------\nSGPA 7.17\n-----------------------------------------------------------------------------------------------\nREMARKS : First Class (U/R)",
        "college": "Buddha Institute",
        "name": "ANKIT KUMAR",
        "roll": "211741823008",
        "branch": "18",
        "marks": 492,
        "remarks": "First Class (U/R)",
        "theory": 156
    },
    {
        "text": " \n \nRegistration No : 1741823011\nRoll No         : 211741823011\n \nFollowing are the marks obtained by VAIBHAV KUMAR\nof Buddha Institute of Technology, Gaya\nat Semester II of Diploma in Computer Science & Engineering\nExamination 2024 (EVEN) held in the month of JUL, 2024\n \n \nResult Published On: 30/07/2024\nSTATE BOARD OF TECHNICAL EDUCATION\nBIHAR\n-----------------------------------------------------------------------------------------------\nSUBJECT  FULL MARKS PASS MARKS MARKS OBTAINED\nNAME OF SUBJECTS CREDITS INTFINTOTAL FINTOTAL INT FIN TOTAL GRADE\n-----------------------------------------------------------------------------------------------\nTHEORY PAPERS\nMATHEMATICS-II 4 3070 100 28 40251641  E\nAPPLIED PHYSICS-II 3 3070 100 28 40261743  E\nINTRODUCTION TO IT SYSTEMS 2 3070 100 28 40262854  D\nFUNDA OF ELECT AND EC ENGG 3 3070 100 28 40251439  F\nENGG. MECHANICS 3 3070 100 28 40251742  E\n-----------------------------------------------------------------------------------------------\nPRACTICAL PAPERS\nAPPLIED PHYSICS LAB-II 1 1535 050 - 20142842  A\nINTRODUCTION TO IT SYSTEM LAB 2 1535 050 - 20133346  A+\nFUNDA OF ELECT AND EC ENGG LAB 1 1535 050 - 20132740  A\nENGG. MECHANICS LAB 2 1535 050 - 20132942  A\n-----------------------------------------------------------------------------------------------\nTERM WORK PAPERS\nC.U MOOCS/ SWAYAM/ ETC/ OTHERS 2 0614 020 - 08061319  A+\nKYP/IT ESSEN/ PYTHON/ OTHERS 1 0614 020 - 08051116  A\nENVIRONMENTAL SCIENCE 0 10 -010 - 0408 -08  A\n-----------------------------------------------------------------------------------------------\nGRAND TOTAL 24 750 432\n-----------------------------------------------------------------------------------------------\nSGPA \n-----------------------------------------------------------------------------------------------\nREMARKS : Fail",
        "college": "Buddha Institute",
        "name": "VAIBHAV KUMAR",
        "roll": "211741823011",
        "branch": "18",
        "marks": 432,
        "remarks": "Fail",
        "theory": 92
    },
    {
        "text": " \n \nRegistration No : 1741823046\nRoll No         : 211741823046\n \nFollowing are the marks obtained by SHUBHAM KUMAR\nof Buddha Institute of Technology, Gaya\nat Semester II of Diploma in Computer Science & Engineering\nExamination 2024 (EVEN) held in the month of JUL, 2024\n \n \nResult Published On: 30/07/2024\nSTATE BOARD OF TECHNICAL EDUCATION\nBIHAR\n-----------------------------------------------------------------------------------------------\nSUBJECT  FULL MARKS PASS MARKS MARKS OBTAINED\nNAME OF SUBJECTS CREDITS INTFINTOTAL FINTOTAL INT FIN TOTAL GRADE\n-----------------------------------------------------------------------------------------------\nTHEORY PAPERS\nMATHEMATICS-II 4 3070 100 28 40262854  D\nAPPLIED PHYSICS-II 3 3070 100 28 40272855  D\nINTRODUCTION TO IT SYSTEMS 2 3070 100 28 40262854  D\nFUNDA OF ELECT AND EC ENGG 3 3070 100 28 40261945  E\nENGG. MECHANICS 3 3070 100 28 40262854  D\n-----------------------------------------------------------------------------------------------\nPRACTICAL PAPERS\nAPPLIED PHYSICS LAB-II 1 1535 050 - 20142943  A\nINTRODUCTION TO IT SYSTEM LAB 2 1535 050 - 20133144  A\nFUNDA OF ELECT AND EC ENGG LAB 1 1535 050 - 20142943  A\nENGG. MECHANICS LAB 2 1535 050 - 20143145  A+\n-----------------------------------------------------------------------------------------------\nTERM WORK PAPERS\nC.U MOOCS/ SWAYAM/ ETC/ OTHERS 2 0614 020 - 08061218  A+\nKYP/IT ESSEN/ PYTHON/ OTHERS 1 0614 020 - 08051217  A\nENVIRONMENTAL SCIENCE 0 10 -010 - 0409 -09  A+\n-----------------------------------------------------------------------------------------------\nGRAND TOTAL 24 750 481\n-----------------------------------------------------------------------------------------------\nSGPA \n-----------------------------------------------------------------------------------------------\nREMARKS : Carry in - FUNDA OF ELECT AND EC ENGG",
        "college": "Buddha Institute",
        "name": "SHUBHAM KUMAR",
        "roll": "211741823046",
        "branch": "18",
        "marks": 481,
        "remarks": "Carry in - FUNDA OF ELECT AND EC ENGG",
        "theory": 131
    },
    {
        "text": " \n \nRegistration No : 1741823024\nRoll No         : 211741823024\n \nFollowing are the marks obtained by SATISH KUMAR\nof Buddha Institute of Technology, Gaya\nat Semester II of Diploma in Computer Science & Engineering\nExamination 2024 (EVEN) held in the month of JUL, 2024\n \n \nResult Published On: 30/07/2024\nSTATE BOARD OF TECHNICAL EDUCATION\nBIHAR\n-----------------------------------------------------------------------------------------------\nSUBJECT  FULL MARKS PASS MARKS MARKS OBTAINED\nNAME OF SUBJECTS CREDITS INTFINTOTAL FINTOTAL INT FIN TOTAL GRADE\n-----------------------------------------------------------------------------------------------\nTHEORY PAPERS\nMATHEMATICS-II 4 3070 100 28 40260632  F\nAPPLIED PHYSICS-II 3 3070 100 28 40260834  F\nINTRODUCTION TO IT SYSTEMS 2 3070 100 28 40252853  D\nFUNDA OF ELECT AND EC ENGG 3 3070 100 28 40251338  F\nENGG. MECHANICS 3 3070 100 28 40260834  F\n-----------------------------------------------------------------------------------------------\nPRACTICAL PAPERS\nAPPLIED PHYSICS LAB-II 1 1535 050 - 2013 A13  F\nINTRODUCTION TO IT SYSTEM LAB 2 1535 050 - 2013 A13  F\nFUNDA OF ELECT AND EC ENGG LAB 1 1535 050 - 2014 A14  F\nENGG. MECHANICS LAB 2 1535 050 - 2013 A13  F\n-----------------------------------------------------------------------------------------------\nTERM WORK PAPERS\nC.U MOOCS/ SWAYAM/ ETC/ OTHERS 2 0614 020 - 0805 A05  F\nKYP/IT ESSEN/ PYTHON/ OTHERS 1 0614 020 - 0806 A06  F\nENVIRONMENTAL SCIENCE 0 10 -010 - 0409 -09  A+\n-----------------------------------------------------------------------------------------------\nGRAND TOTAL 24 750 264\n-----------------------------------------------------------------------------------------------\nSGPA \n-----------------------------------------------------------------------------------------------\nREMARKS : Fail in Term Work",
        "college": "Buddha Institute",
        "name": "SATISH KUMAR",
        "roll": "211741823024",
        "branch": "18",
        "marks": 264,
        "remarks": "Fail in Term Work",
        "theory": 63
    },
    {
        "text": " \n \nRegistration No : 1741823028\nRoll No         : 211741823028\n \nFollowing are the marks obtained by SANDEEP KUMAR\nof Buddha Institute of Technology, Gaya\nat Semester II of Diploma in Computer Science & Engineering\nExamination 2024 (EVEN) held in the month of JUL, 2024\n \n \nResult Published On: 30/07/2024\nSTATE BOARD OF TECHNICAL EDUCATION\nBIHAR\n-----------------------------------------------------------------------------------------------\nSUBJECT  FULL MARKS PASS MARKS MARKS OBTAINED\nNAME OF SUBJECTS CREDITS INTFINTOTAL FINTOTAL INT FIN TOTAL GRADE\n-----------------------------------------------------------------------------------------------\nTHEORY PAPERS\nMATHEMATICS-II 4 3070 100 28 40262955  D\nAPPLIED PHYSICS-II 3 3070 100 28 40262854  D\nINTRODUCTION TO IT SYSTEMS 2 3070 100 28 40262854  D\nFUNDA OF ELECT AND EC ENGG 3 3070 100 28 40262854  D\nENGG. MECHANICS 3 3070 100 28 40263056  D\n-----------------------------------------------------------------------------------------------\nPRACTICAL PAPERS\nAPPLIED PHYSICS LAB-II 1 1535 050 - 20143145  A+\nINTRODUCTION TO IT SYSTEM LAB 2 1535 050 - 20143044  A\nFUNDA OF ELECT AND EC ENGG LAB 1 1535 050 - 20142842  A\nENGG. MECHANICS LAB 2 1535 050 - 20142842  A\n-----------------------------------------------------------------------------------------------\nTERM WORK PAPERS\nC.U MOOCS/ SWAYAM/ ETC/ OTHERS 2 0614 020 - 08061117  A\nKYP/IT ESSEN/ PYTHON/ OTHERS 1 0614 020 - 08061117  A\nENVIRONMENTAL SCIENCE 0 10 -010 - 0409 -09  A+\n-----------------------------------------------------------------------------------------------\nGRAND TOTAL 24 750 489\n-----------------------------------------------------------------------------------------------\nSGPA 7.17\n-----------------------------------------------------------------------------------------------\nREMARKS : First Class",
        "college": "Buddha Institute",
        "name": "SANDEEP KUMAR",
        "roll": "211741823028",
        "branch": "18",
        "marks": 489,
        "remarks": "First Class",
        "theory": 143
    },
    {
        "text": " \n \nRegistration No : 1741823034\nRoll No         : 211741823034\n \nFollowing are the marks obtained by THAKUR RUDRAKSH SINGH\nof Buddha Institute of Technology, Gaya\nat Semester II of Diploma in Computer Science & Engineering\nExamination 2024 (EVEN) held in the month of JUL, 2024\n \n \nResult Published On: 30/07/2024\nSTATE BOARD OF TECHNICAL EDUCATION\nBIHAR\n-----------------------------------------------------------------------------------------------\nSUBJECT  FULL MARKS PASS MARKS MARKS OBTAINED\nNAME OF SUBJECTS CREDITS INTFINTOTAL FINTOTAL INT FIN TOTAL GRADE\n-----------------------------------------------------------------------------------------------\nTHEORY PAPERS\nMATHEMATICS-II 4 3070 100 28 40261036  F\nAPPLIED PHYSICS-II 3 3070 100 28 40262854  D\nINTRODUCTION TO IT SYSTEMS 2 3070 100 28 40252954  D\nFUNDA OF ELECT AND EC ENGG 3 3070 100 28 40251237  F\nENGG. MECHANICS 3 3070 100 28 40252853  D\n-----------------------------------------------------------------------------------------------\nPRACTICAL PAPERS\nAPPLIED PHYSICS LAB-II 1 1535 050 - 20142943  A\nINTRODUCTION TO IT SYSTEM LAB 2 1535 050 - 20133043  A\nFUNDA OF ELECT AND EC ENGG LAB 1 1535 050 - 20142640  A\nENGG. MECHANICS LAB 2 1535 050 - 20132942  A\n-----------------------------------------------------------------------------------------------\nTERM WORK PAPERS\nC.U MOOCS/ SWAYAM/ ETC/ OTHERS 2 0614 020 - 08061218  A+\nKYP/IT ESSEN/ PYTHON/ OTHERS 1 0614 020 - 08061117  A\nENVIRONMENTAL SCIENCE 0 10 -010 - 0408 -08  A\n-----------------------------------------------------------------------------------------------\nGRAND TOTAL 24 750 445\n-----------------------------------------------------------------------------------------------\nSGPA \n-----------------------------------------------------------------------------------------------\nREMARKS : Carry in - MATHEMATICS-II\n FUNDA OF ELECT AND EC ENGG",
        "college": "Buddha Institute",
        "name": "THAKUR RUDRAKSH SINGH",
        "roll": "211741823034",
        "branch": "18",
        "marks": 445,
        "remarks": "Carry in - MATHEMATICS-II",
        "theory": 107
    },
    {
        "text": " \n \nRegistration No : 1742523016\nRoll No         : 211742523016\n \nFollowing are the marks obtained by SONU NIGAM\nof Buddha Institute of Technology, Gaya\nat Semester II of Diploma in Mechanical Engineering\nExamination 2024 (EVEN) held in the month of JUL, 2024\n \n \nResult Published On: 30/07/2024\nSTATE BOARD OF TECHNICAL EDUCATION\nBIHAR\n-----------------------------------------------------------------------------------------------\nSUBJECT  FULL MARKS PASS MARKS MARKS OBTAINED\nNAME OF SUBJECTS CREDITS INTFINTOTAL FINTOTAL INT FIN TOTAL GRADE\n-----------------------------------------------------------------------------------------------\nTHEORY PAPERS\nMATHEMATICS-II 4 3070 100 28 40273259  D\nAPPLIED PHYSICS-II 3 3070 100 28 40263056  D\nINTRODUCTION TO IT SYSTEMS 2 3070 100 28 40273259  D\nFUNDA OF ELECT AND EC ENGG 3 3070 100 28 40262854  D\nENGG. MECHANICS 3 3070 100 28 40273764  C\n-----------------------------------------------------------------------------------------------\nPRACTICAL PAPERS\nAPPLIED PHYSICS LAB-II 1 1535 050 - 20143145  A+\nINTRODUCTION TO IT SYSTEM LAB 2 1535 050 - 20143246  A+\nFUNDA OF ELECT AND EC ENGG LAB 1 1535 050 - 20142741  A\nENGG. MECHANICS LAB 2 1535 050 - 20133144  A\n-----------------------------------------------------------------------------------------------\nTERM WORK PAPERS\nC.U MOOCS/ SWAYAM/ ETC/ OTHERS 2 0614 020 - 08061319  A+\nKYP/IT ESSEN/ PYTHON/ OTHERS 1 0614 020 - 08061319  A+\nENVIRONMENTAL SCIENCE 0 10 -010 - 0409 -09  A+\n-----------------------------------------------------------------------------------------------\nGRAND TOTAL 24 750 515\n-----------------------------------------------------------------------------------------------\nSGPA 7.5\n-----------------------------------------------------------------------------------------------\nREMARKS : First Class",
        "college": "Buddha Institute",
        "name": "SONU NIGAM",
        "roll": "211742523016",
        "branch": "25",
        "marks": 515,
        "remarks": "First Class",
        "theory": 159
    },
    {
        "text": " \n \nRegistration No : 1742523002\nRoll No         : 211742523002\n \nFollowing are the marks obtained by SURAJ KUMAR\nof Buddha Institute of Technology, Gaya\nat Semester II of Diploma in Mechanical Engineering\nExamination 2024 (EVEN) held in the month of JUL, 2024\n \n \nResult Published On: 30/07/2024\nSTATE BOARD OF TECHNICAL EDUCATION\nBIHAR\n-----------------------------------------------------------------------------------------------\nSUBJECT  FULL MARKS PASS MARKS MARKS OBTAINED\nNAME OF SUBJECTS CREDITS INTFINTOTAL FINTOTAL INT FIN TOTAL GRADE\n-----------------------------------------------------------------------------------------------\nTHEORY PAPERS\nMATHEMATICS-II 4 3070 100 28 40260935  F\nAPPLIED PHYSICS-II 3 3070 100 28 40260632  F\nINTRODUCTION TO IT SYSTEMS 2 3070 100 28 40261541  E\nFUNDA OF ELECT AND EC ENGG 3 3070 100 28 40262349  E\nENGG. MECHANICS 3 3070 100 28 40261844  E\n-----------------------------------------------------------------------------------------------\nPRACTICAL PAPERS\nAPPLIED PHYSICS LAB-II 1 1535 050 - 20132841  A\nINTRODUCTION TO IT SYSTEM LAB 2 1535 050 - 20133245  A+\nFUNDA OF ELECT AND EC ENGG LAB 1 1535 050 - 20132639  B\nENGG. MECHANICS LAB 2 1535 050 - 20132841  A\n-----------------------------------------------------------------------------------------------\nTERM WORK PAPERS\nC.U MOOCS/ SWAYAM/ ETC/ OTHERS 2 0614 020 - 08051217  A\nKYP/IT ESSEN/ PYTHON/ OTHERS 1 0614 020 - 08051318  A+\nENVIRONMENTAL SCIENCE 0 10 -010 - 0408 -08  A\n-----------------------------------------------------------------------------------------------\nGRAND TOTAL 24 750 410\n-----------------------------------------------------------------------------------------------\nSGPA \n-----------------------------------------------------------------------------------------------\nREMARKS : Fail",
        "college": "Buddha Institute",
        "name": "SURAJ KUMAR",
        "roll": "211742523002",
        "branch": "25",
        "marks": 410,
        "remarks": "Fail",
        "theory": 71
    },
    {
        "text": " \n \nRegistration No : 1742523008\nRoll No         : 211742523008\n \nFollowing are the marks obtained by NIHAL KUMAR\nof Buddha Institute of Technology, Gaya\nat Semester II of Diploma in Mechanical Engineering\nExamination 2024 (EVEN) held in the month of JUL, 2024\n \n \nResult Published On: 30/07/2024\nSTATE BOARD OF TECHNICAL EDUCATION\nBIHAR\n-----------------------------------------------------------------------------------------------\nSUBJECT  FULL MARKS PASS MARKS MARKS OBTAINED\nNAME OF SUBJECTS CREDITS INTFINTOTAL FINTOTAL INT FIN TOTAL GRADE\n-----------------------------------------------------------------------------------------------\nTHEORY PAPERS\nMATHEMATICS-II 4 3070 100 28 40261036  F\nAPPLIED PHYSICS-II 3 3070 100 28 40261036  F\nINTRODUCTION TO IT SYSTEMS 2 3070 100 28 40264672  B\nFUNDA OF ELECT AND EC ENGG 3 3070 100 28 40262854  D\nENGG. MECHANICS 3 3070 100 28 40263561  C\n-----------------------------------------------------------------------------------------------\nPRACTICAL PAPERS\nAPPLIED PHYSICS LAB-II 1 1535 050 - 20142943  A\nINTRODUCTION TO IT SYSTEM LAB 2 1535 050 - 20133144  A\nFUNDA OF ELECT AND EC ENGG LAB 1 1535 050 - 20142842  A\nENGG. MECHANICS LAB 2 1535 050 - 20132841  A\n-----------------------------------------------------------------------------------------------\nTERM WORK PAPERS\nC.U MOOCS/ SWAYAM/ ETC/ OTHERS 2 0614 020 - 08051318  A+\nKYP/IT ESSEN/ PYTHON/ OTHERS 1 0614 020 - 08051217  A\nENVIRONMENTAL SCIENCE 0 10 -010 - 0408 -08  A\n-----------------------------------------------------------------------------------------------\nGRAND TOTAL 24 750 472\n-----------------------------------------------------------------------------------------------\nSGPA \n-----------------------------------------------------------------------------------------------\nREMARKS : Carry in - MATHEMATICS-II\n APPLIED PHYSICS-II",
        "college": "Buddha Institute",
        "name": "NIHAL KUMAR",
        "roll": "211742523008",
        "branch": "25",
        "marks": 472,
        "remarks": "Carry in - MATHEMATICS-II",
        "theory": 129
    },
    {
        "text": " \n \nRegistration No : 1742023008\nRoll No         : 211742023008\n \nFollowing are the marks obtained by HEMANT KUMAR\nof Buddha Institute of Technology, Gaya\nat Semester II of Diploma in Electrical Engineering\nExamination 2024 (EVEN) held in the month of JUL, 2024\n \n \nResult Published On: 30/07/2024\nSTATE BOARD OF TECHNICAL EDUCATION\nBIHAR\n-----------------------------------------------------------------------------------------------\nSUBJECT  FULL MARKS PASS MARKS MARKS OBTAINED\nNAME OF SUBJECTS CREDITS INTFINTOTAL FINTOTAL INT FIN TOTAL GRADE\n-----------------------------------------------------------------------------------------------\nTHEORY PAPERS\nMATHEMATICS-II 4 3070 100 28 40261238  F\nAPPLIED PHYSICS-II 3 3070 100 28 40253055  D\nINTRODUCTION TO IT SYSTEMS 2 3070 100 28 40271744  E\nFUNDA OF ELECT AND EC ENGG 3 3070 100 28 40261339  F\nENGG. MECHANICS 3 3070 100 28 40262147  E\n-----------------------------------------------------------------------------------------------\nPRACTICAL PAPERS\nAPPLIED PHYSICS LAB-II 1 1535 050 - 20132942  A\nINTRODUCTION TO IT SYSTEM LAB 2 1535 050 - 20133245  A+\nFUNDA OF ELECT AND EC ENGG LAB 1 1535 050 - 20132841  A\nENGG. MECHANICS LAB 2 1535 050 - 20132841  A\n-----------------------------------------------------------------------------------------------\nTERM WORK PAPERS\nC.U MOOCS/ SWAYAM/ ETC/ OTHERS 2 0614 020 - 08061218  A+\nKYP/IT ESSEN/ PYTHON/ OTHERS 1 0614 020 - 08061218  A+\nENVIRONMENTAL SCIENCE 0 10 -010 - 0408 -08  A\n-----------------------------------------------------------------------------------------------\nGRAND TOTAL 24 750 436\n-----------------------------------------------------------------------------------------------\nSGPA \n-----------------------------------------------------------------------------------------------\nREMARKS : Fail",
        "college": "Buddha Institute",
        "name": "HEMANT KUMAR",
        "roll": "211742023008",
        "branch": "20",
        "marks": 436,
        "remarks": "Fail",
        "theory": 93
    },
    {
        "text": " \n \nRegistration No : 1742023043\nRoll No         : 211742023043\n \nFollowing are the marks obtained by PRITAM DUBEY\nof Buddha Institute of Technology, Gaya\nat Semester II of Diploma in Electrical Engineering\nExamination 2024 (EVEN) held in the month of JUL, 2024\n \n \nResult Published On: 30/07/2024\nSTATE BOARD OF TECHNICAL EDUCATION\nBIHAR\n-----------------------------------------------------------------------------------------------\nSUBJECT  FULL MARKS PASS MARKS MARKS OBTAINED\nNAME OF SUBJECTS CREDITS INTFINTOTAL FINTOTAL INT FIN TOTAL GRADE\n-----------------------------------------------------------------------------------------------\nTHEORY PAPERS\nMATHEMATICS-II 4 3070 100 28 40260632  F\nAPPLIED PHYSICS-II 3 3070 100 28 40261137  F\nINTRODUCTION TO IT SYSTEMS 2 3070 100 28 40263864  C\nFUNDA OF ELECT AND EC ENGG 3 3070 100 28 40250833  F\nENGG. MECHANICS 3 3070 100 28 40271037  F\n-----------------------------------------------------------------------------------------------\nPRACTICAL PAPERS\nAPPLIED PHYSICS LAB-II 1 1535 050 - 2013 A13  F\nINTRODUCTION TO IT SYSTEM LAB 2 1535 050 - 2013 A13  F\nFUNDA OF ELECT AND EC ENGG LAB 1 1535 050 - 2014 A14  F\nENGG. MECHANICS LAB 2 1535 050 - 2013 A13  F\n-----------------------------------------------------------------------------------------------\nTERM WORK PAPERS\nC.U MOOCS/ SWAYAM/ ETC/ OTHERS 2 0614 020 - 0805 A05  F\nKYP/IT ESSEN/ PYTHON/ OTHERS 1 0614 020 - 0805 A05  F\nENVIRONMENTAL SCIENCE 0 10 -010 - 0408 -08  A\n-----------------------------------------------------------------------------------------------\nGRAND TOTAL 24 750 274\n-----------------------------------------------------------------------------------------------\nSGPA \n-----------------------------------------------------------------------------------------------\nREMARKS : Fail in Term Work",
        "college": "Buddha Institute",
        "name": "PRITAM DUBEY",
        "roll": "211742023043",
        "branch": "20",
        "marks": 274,
        "remarks": "Fail in Term Work",
        "theory": 73
    },
    {
        "text": " \n \nRegistration No : 1742023036\nRoll No         : 211742023036\n \nFollowing are the marks obtained by UDDHAV KUMAR\nof Buddha Institute of Technology, Gaya\nat Semester II of Diploma in Electrical Engineering\nExamination 2024 (EVEN) held in the month of JUL, 2024\n \n \nResult Published On: 30/07/2024\nSTATE BOARD OF TECHNICAL EDUCATION\nBIHAR\n-----------------------------------------------------------------------------------------------\nSUBJECT  FULL MARKS PASS MARKS MARKS OBTAINED\nNAME OF SUBJECTS CREDITS INTFINTOTAL FINTOTAL INT FIN TOTAL GRADE\n-----------------------------------------------------------------------------------------------\nTHEORY PAPERS\nMATHEMATICS-II 4 3070 100 28 40284169  C\nAPPLIED PHYSICS-II 3 3070 100 28 40273764  C\nINTRODUCTION TO IT SYSTEMS 2 3070 100 28 40286290  A+\nFUNDA OF ELECT AND EC ENGG 3 3070 100 28 40273057  D\nENGG. MECHANICS 3 3070 100 28 40264066  C\n-----------------------------------------------------------------------------------------------\nPRACTICAL PAPERS\nAPPLIED PHYSICS LAB-II 1 1535 050 - 20143145  A+\nINTRODUCTION TO IT SYSTEM LAB 2 1535 050 - 20143246  A+\nFUNDA OF ELECT AND EC ENGG LAB 1 1535 050 - 20132942  A\nENGG. MECHANICS LAB 2 1535 050 - 20132942  A\n-----------------------------------------------------------------------------------------------\nTERM WORK PAPERS\nC.U MOOCS/ SWAYAM/ ETC/ OTHERS 2 0614 020 - 08061218  A+\nKYP/IT ESSEN/ PYTHON/ OTHERS 1 0614 020 - 08061218  A+\nENVIRONMENTAL SCIENCE 0 10 -010 - 0409 -09  A+\n-----------------------------------------------------------------------------------------------\nGRAND TOTAL 24 750 566\n-----------------------------------------------------------------------------------------------\nSGPA 8.12\n-----------------------------------------------------------------------------------------------\nREMARKS : First Class with Distinction",
        "college": "Buddha Institute",
        "name": "UDDHAV KUMAR",
        "roll": "211742023036",
        "branch": "20",
        "marks": 566,
        "remarks": "First Class with Distinction",
        "theory": 210
    },
    {
        "text": " \n \nRegistration No : 1742023018\nRoll No         : 211742023018\n \nFollowing are the marks obtained by MANJEET KUMAR\nof Buddha Institute of Technology, Gaya\nat Semester II of Diploma in Electrical Engineering\nExamination 2024 (EVEN) held in the month of JUL, 2024\n \n \nResult Published On: 30/07/2024\nSTATE BOARD OF TECHNICAL EDUCATION\nBIHAR\n-----------------------------------------------------------------------------------------------\nSUBJECT  FULL MARKS PASS MARKS MARKS OBTAINED\nNAME OF SUBJECTS CREDITS INTFINTOTAL FINTOTAL INT FIN TOTAL GRADE\n-----------------------------------------------------------------------------------------------\nTHEORY PAPERS\nMATHEMATICS-II 4 3070 100 28 40260026  F\nAPPLIED PHYSICS-II 3 3070 100 28 40260632  F\nINTRODUCTION TO IT SYSTEMS 2 3070 100 28 40262955  D\nFUNDA OF ELECT AND EC ENGG 3 3070 100 28 40261743  E\nENGG. MECHANICS 3 3070 100 28 40261642  E\n-----------------------------------------------------------------------------------------------\nPRACTICAL PAPERS\nAPPLIED PHYSICS LAB-II 1 1535 050 - 2013 A13  F\nINTRODUCTION TO IT SYSTEM LAB 2 1535 050 - 20133245  A+\nFUNDA OF ELECT AND EC ENGG LAB 1 1535 050 - 20132639  B\nENGG. MECHANICS LAB 2 1535 050 - 2013 A13  F\n-----------------------------------------------------------------------------------------------\nTERM WORK PAPERS\nC.U MOOCS/ SWAYAM/ ETC/ OTHERS 2 0614 020 - 08061319  A+\nKYP/IT ESSEN/ PYTHON/ OTHERS 1 0614 020 - 08051318  A+\nENVIRONMENTAL SCIENCE 0 10 -010 - 0408 -08  A\n-----------------------------------------------------------------------------------------------\nGRAND TOTAL 24 750 353\n-----------------------------------------------------------------------------------------------\nSGPA \n-----------------------------------------------------------------------------------------------\nREMARKS : Fail",
        "college": "Buddha Institute",
        "name": "MANJEET KUMAR",
        "roll": "211742023018",
        "branch": "20",
        "marks": 353,
        "remarks": "Fail",
        "theory": 68
    },
    {
        "text": " \n \nRegistration No : 1521823010\nRoll No         : 211521823010\n \nFollowing are the marks obtained by LAVKUSH  KUMAR\nof Government Polytechnic, Bhojpur\nat Semester II of Diploma in Computer Science & Engineering\nExamination 2024 (EVEN) held in the month of JUL, 2024\n \n \nResult Published On: 30/07/2024\nSTATE BOARD OF TECHNICAL EDUCATION\nBIHAR\n-----------------------------------------------------------------------------------------------\nSUBJECT  FULL MARKS PASS MARKS MARKS OBTAINED\nNAME OF SUBJECTS CREDITS INTFINTOTAL FINTOTAL INT FIN TOTAL GRADE\n-----------------------------------------------------------------------------------------------\nTHEORY PAPERS\nMATHEMATICS-II 4 3070 100 28 40172037  F\nAPPLIED PHYSICS-II 3 3070 100 28 40132942  E\nINTRODUCTION TO IT SYSTEMS 2 3070 100 28 40134053  D\nFUNDA OF ELECT AND EC ENGG 3 3070 100 28 40162844  E\nENGG. MECHANICS 3 3070 100 28 40113445  E\n-----------------------------------------------------------------------------------------------\nPRACTICAL PAPERS\nAPPLIED PHYSICS LAB-II 1 1535 050 - 20102939  B\nINTRODUCTION TO IT SYSTEM LAB 2 1535 050 - 20123244  A\nFUNDA OF ELECT AND EC ENGG LAB 1 1535 050 - 20123143  A\nENGG. MECHANICS LAB 2 1535 050 - 20123244  A\n-----------------------------------------------------------------------------------------------\nTERM WORK PAPERS\nC.U MOOCS/ SWAYAM/ ETC/ OTHERS 2 0614 020 - 08041014  B\nKYP/IT ESSEN/ PYTHON/ OTHERS 1 0614 020 - 08041115  B\nENVIRONMENTAL SCIENCE 0 10 -010 - 0408 -08  A\n-----------------------------------------------------------------------------------------------\nGRAND TOTAL 24 750 428\n-----------------------------------------------------------------------------------------------\nSGPA \n-----------------------------------------------------------------------------------------------\nREMARKS : Carry in - MATHEMATICS-II",
        "college": "Government Polytechnic, Bhojpur",
        "name": "LAVKUSH KUMAR",
        "roll": "211521823010",
        "branch": "18",
        "marks": 428,
        "remarks": "Carry in - MATHEMATICS-II",
        "theory": 151
    },
    {
        "text": " \n \nRegistration No : 1521823020\nRoll No         : 211521823020\n \nFollowing are the marks obtained by LAUKESH  KUMAR\nof Government Polytechnic, Bhojpur\nat Semester II of Diploma in Computer Science & Engineering\nExamination 2024 (EVEN) held in the month of JUL, 2024\n \n \nResult Published On: 30/07/2024\nSTATE BOARD OF TECHNICAL EDUCATION\nBIHAR\n-----------------------------------------------------------------------------------------------\nSUBJECT  FULL MARKS PASS MARKS MARKS OBTAINED\nNAME OF SUBJECTS CREDITS INTFINTOTAL FINTOTAL INT FIN TOTAL GRADE\n-----------------------------------------------------------------------------------------------\nTHEORY PAPERS\nMATHEMATICS-II 4 3070 100 28 40210627  F\nAPPLIED PHYSICS-II 3 3070 100 28 40163147  E\nINTRODUCTION TO IT SYSTEMS 2 3070 100 28 40163349  E\nFUNDA OF ELECT AND EC ENGG 3 3070 100 28 40222850  D\nENGG. MECHANICS 3 3070 100 28 40172946  E\n-----------------------------------------------------------------------------------------------\nPRACTICAL PAPERS\nAPPLIED PHYSICS LAB-II 1 1535 050 - 20102939  B\nINTRODUCTION TO IT SYSTEM LAB 2 1535 050 - 20113142  A\nFUNDA OF ELECT AND EC ENGG LAB 1 1535 050 - 20133245  A+\nENGG. MECHANICS LAB 2 1535 050 - 20133346  A+\n-----------------------------------------------------------------------------------------------\nTERM WORK PAPERS\nC.U MOOCS/ SWAYAM/ ETC/ OTHERS 2 0614 020 - 08041014  B\nKYP/IT ESSEN/ PYTHON/ OTHERS 1 0614 020 - 08051015  B\nENVIRONMENTAL SCIENCE 0 10 -010 - 0408 -08  A\n-----------------------------------------------------------------------------------------------\nGRAND TOTAL 24 750 428\n-----------------------------------------------------------------------------------------------\nSGPA \n-----------------------------------------------------------------------------------------------\nREMARKS : Carry in - MATHEMATICS-II",
        "college": "Government Polytechnic, Bhojpur",
        "name": "LAUKESH KUMAR",
        "roll": "211521823020",
        "branch": "18",
        "marks": 428,
        "remarks": "Carry in - MATHEMATICS-II",
        "theory": 127
    },
    {
        "text": " \n \nRegistration No : 1521823034\nRoll No         : 211521823034\n \nFollowing are the marks obtained by YASHPAL KUMAR SINGH\nof Government Polytechnic, Bhojpur\nat Semester II of Diploma in Computer Science & Engineering\nExamination 2024 (EVEN) held in the month of JUL, 2024\n \n \nResult Published On: 30/07/2024\nSTATE BOARD OF TECHNICAL EDUCATION\nBIHAR\n-----------------------------------------------------------------------------------------------\nSUBJECT  FULL MARKS PASS MARKS MARKS OBTAINED\nNAME OF SUBJECTS CREDITS INTFINTOTAL FINTOTAL INT FIN TOTAL GRADE\n-----------------------------------------------------------------------------------------------\nTHEORY PAPERS\nMATHEMATICS-II 4 3070 100 28 40272855  D\nAPPLIED PHYSICS-II 3 3070 100 28 40131326  F\nINTRODUCTION TO IT SYSTEMS 2 3070 100 28 40173249  E\nFUNDA OF ELECT AND EC ENGG 3 3070 100 28 40153045  E\nENGG. MECHANICS 3 3070 100 28 40163551  D\n-----------------------------------------------------------------------------------------------\nPRACTICAL PAPERS\nAPPLIED PHYSICS LAB-II 1 1535 050 - 20102939  B\nINTRODUCTION TO IT SYSTEM LAB 2 1535 050 - 20113041  A\nFUNDA OF ELECT AND EC ENGG LAB 1 1535 050 - 20123143  A\nENGG. MECHANICS LAB 2 1535 050 - 20113243  A\n-----------------------------------------------------------------------------------------------\nTERM WORK PAPERS\nC.U MOOCS/ SWAYAM/ ETC/ OTHERS 2 0614 020 - 08041014  B\nKYP/IT ESSEN/ PYTHON/ OTHERS 1 0614 020 - 08041115  B\nENVIRONMENTAL SCIENCE 0 10 -010 - 0407 -07  B\n-----------------------------------------------------------------------------------------------\nGRAND TOTAL 24 750 428\n-----------------------------------------------------------------------------------------------\nSGPA \n-----------------------------------------------------------------------------------------------\nREMARKS : Carry in - APPLIED PHYSICS-II",
        "college": "Government Polytechnic, Bhojpur",
        "name": "YASHPAL KUMAR SINGH",
        "roll": "211521823034",
        "branch": "18",
        "marks": 428,
        "remarks": "Carry in - APPLIED PHYSICS-II",
        "theory": 138
    },
    {
        "text": " \n \nRegistration No : 1521823056\nRoll No         : 211521823056\n \nFollowing are the marks obtained by ROHAN KUMAR CHOUDHARY\nof Government Polytechnic, Bhojpur\nat Semester II of Diploma in Computer Science & Engineering\nExamination 2024 (EVEN) held in the month of JUL, 2024\n \n \nResult Published On: 30/07/2024\nSTATE BOARD OF TECHNICAL EDUCATION\nBIHAR\n-----------------------------------------------------------------------------------------------\nSUBJECT  FULL MARKS PASS MARKS MARKS OBTAINED\nNAME OF SUBJECTS CREDITS INTFINTOTAL FINTOTAL INT FIN TOTAL GRADE\n-----------------------------------------------------------------------------------------------\nTHEORY PAPERS\nMATHEMATICS-II 4 3070 100 28 40271037  F\nAPPLIED PHYSICS-II 3 3070 100 28 40153752  D\nINTRODUCTION TO IT SYSTEMS 2 3070 100 28 40193150  D\nFUNDA OF ELECT AND EC ENGG 3 3070 100 28 40182846  E\nENGG. MECHANICS 3 3070 100 28 40173855  D\n-----------------------------------------------------------------------------------------------\nPRACTICAL PAPERS\nAPPLIED PHYSICS LAB-II 1 1535 050 - 20103141  A\nINTRODUCTION TO IT SYSTEM LAB 2 1535 050 - 20113142  A\nFUNDA OF ELECT AND EC ENGG LAB 1 1535 050 - 20133144  A\nENGG. MECHANICS LAB 2 1535 050 - 20103040  A\n-----------------------------------------------------------------------------------------------\nTERM WORK PAPERS\nC.U MOOCS/ SWAYAM/ ETC/ OTHERS 2 0614 020 - 08041115  B\nKYP/IT ESSEN/ PYTHON/ OTHERS 1 0614 020 - 08051116  A\nENVIRONMENTAL SCIENCE 0 10 -010 - 0410 -10  A+\n-----------------------------------------------------------------------------------------------\nGRAND TOTAL 24 750 448\n-----------------------------------------------------------------------------------------------\nSGPA \n-----------------------------------------------------------------------------------------------\nREMARKS : Carry in - MATHEMATICS-II",
        "college": "Government Polytechnic, Bhojpur",
        "name": "ROHAN KUMAR CHOUDHARY",
        "roll": "211521823056",
        "branch": "18",
        "marks": 448,
        "remarks": "Carry in - MATHEMATICS-II",
        "theory": 144
    },
    {
        "text": " \n \nRegistration No : 1521823018\nRoll No         : 211521823018\n \nFollowing are the marks obtained by ABHISHEK  KUMAR\nof Government Polytechnic, Bhojpur\nat Semester II of Diploma in Computer Science & Engineering\nExamination 2024 (EVEN) held in the month of JUL, 2024\n \n \nResult Published On: 30/07/2024\nSTATE BOARD OF TECHNICAL EDUCATION\nBIHAR\n-----------------------------------------------------------------------------------------------\nSUBJECT  FULL MARKS PASS MARKS MARKS OBTAINED\nNAME OF SUBJECTS CREDITS INTFINTOTAL FINTOTAL INT FIN TOTAL GRADE\n-----------------------------------------------------------------------------------------------\nTHEORY PAPERS\nMATHEMATICS-II 4 3070 100 28 40273663  C\nAPPLIED PHYSICS-II 3 3070 100 28 40283159  D\nINTRODUCTION TO IT SYSTEMS 2 3070 100 28 40193352  D\nFUNDA OF ELECT AND EC ENGG 3 3070 100 28 40192342  E\nENGG. MECHANICS 3 3070 100 28 40194362  C\n-----------------------------------------------------------------------------------------------\nPRACTICAL PAPERS\nAPPLIED PHYSICS LAB-II 1 1535 050 - 20143145  A+\nINTRODUCTION TO IT SYSTEM LAB 2 1535 050 - 20123244  A\nFUNDA OF ELECT AND EC ENGG LAB 1 1535 050 - 20123143  A\nENGG. MECHANICS LAB 2 1535 050 - 20123143  A\n-----------------------------------------------------------------------------------------------\nTERM WORK PAPERS\nC.U MOOCS/ SWAYAM/ ETC/ OTHERS 2 0614 020 - 08051217  A\nKYP/IT ESSEN/ PYTHON/ OTHERS 1 0614 020 - 08041216  A\nENVIRONMENTAL SCIENCE 0 10 -010 - 0400 -00  F\n-----------------------------------------------------------------------------------------------\nGRAND TOTAL 24 750 486\n-----------------------------------------------------------------------------------------------\nSGPA \n-----------------------------------------------------------------------------------------------\nREMARKS : Fail in Term Work",
        "college": "Government Polytechnic, Bhojpur",
        "name": "ABHISHEK KUMAR",
        "roll": "211521823018",
        "branch": "18",
        "marks": 486,
        "remarks": "Fail in Term Work",
        "theory": 166
    },
    {
        "text": " \n \nRegistration No : 1521823036\nRoll No         : 211521823036\n \nFollowing are the marks obtained by ADITYA  DHANRAJ\nof Government Polytechnic, Bhojpur\nat Semester II of Diploma in Computer Science & Engineering\nExamination 2024 (EVEN) held in the month of JUL, 2024\n \n \nResult Published On: 30/07/2024\nSTATE BOARD OF TECHNICAL EDUCATION\nBIHAR\n-----------------------------------------------------------------------------------------------\nSUBJECT  FULL MARKS PASS MARKS MARKS OBTAINED\nNAME OF SUBJECTS CREDITS INTFINTOTAL FINTOTAL INT FIN TOTAL GRADE\n-----------------------------------------------------------------------------------------------\nTHEORY PAPERS\nMATHEMATICS-II 4 3070 100 28 40210425  F\nAPPLIED PHYSICS-II 3 3070 100 28 40223153  D\nINTRODUCTION TO IT SYSTEMS 2 3070 100 28 40172845  E\nFUNDA OF ELECT AND EC ENGG 3 3070 100 28 40182846  E\nENGG. MECHANICS 3 3070 100 28 40133144  E\n-----------------------------------------------------------------------------------------------\nPRACTICAL PAPERS\nAPPLIED PHYSICS LAB-II 1 1535 050 - 20122840  A\nINTRODUCTION TO IT SYSTEM LAB 2 1535 050 - 20123042  A\nFUNDA OF ELECT AND EC ENGG LAB 1 1535 050 - 20133144  A\nENGG. MECHANICS LAB 2 1535 050 - 20113041  A\n-----------------------------------------------------------------------------------------------\nTERM WORK PAPERS\nC.U MOOCS/ SWAYAM/ ETC/ OTHERS 2 0614 020 - 08041014  B\nKYP/IT ESSEN/ PYTHON/ OTHERS 1 0614 020 - 08040913  C\nENVIRONMENTAL SCIENCE 0 10 -010 - 0408 -08  A\n-----------------------------------------------------------------------------------------------\nGRAND TOTAL 24 750 415\n-----------------------------------------------------------------------------------------------\nSGPA \n-----------------------------------------------------------------------------------------------\nREMARKS : Carry in - MATHEMATICS-II",
        "college": "Government Polytechnic, Bhojpur",
        "name": "ADITYA DHANRAJ",
        "roll": "211521823036",
        "branch": "18",
        "marks": 415,
        "remarks": "Carry in - MATHEMATICS-II",
        "theory": 122
    },
    {
        "text": " \n \nRegistration No : 1521823040\nRoll No         : 211521823040\n \nFollowing are the marks obtained by ASIF  ALAM\nof Government Polytechnic, Bhojpur\nat Semester II of Diploma in Computer Science & Engineering\nExamination 2024 (EVEN) held in the month of JUL, 2024\n \n \nResult Published On: 30/07/2024\nSTATE BOARD OF TECHNICAL EDUCATION\nBIHAR\n-----------------------------------------------------------------------------------------------\nSUBJECT  FULL MARKS PASS MARKS MARKS OBTAINED\nNAME OF SUBJECTS CREDITS INTFINTOTAL FINTOTAL INT FIN TOTAL GRADE\n-----------------------------------------------------------------------------------------------\nTHEORY PAPERS\nMATHEMATICS-II 4 3070 100 28 40152035  F\nAPPLIED PHYSICS-II 3 3070 100 28 40122941  E\nINTRODUCTION TO IT SYSTEMS 2 3070 100 28 40124759  D\nFUNDA OF ELECT AND EC ENGG 3 3070 100 28 40151530  F\nENGG. MECHANICS 3 3070 100 28 40154358  D\n-----------------------------------------------------------------------------------------------\nPRACTICAL PAPERS\nAPPLIED PHYSICS LAB-II 1 1535 050 - 20102939  B\nINTRODUCTION TO IT SYSTEM LAB 2 1535 050 - 20123042  A\nFUNDA OF ELECT AND EC ENGG LAB 1 1535 050 - 20133043  A\nENGG. MECHANICS LAB 2 1535 050 - 20103040  A\n-----------------------------------------------------------------------------------------------\nTERM WORK PAPERS\nC.U MOOCS/ SWAYAM/ ETC/ OTHERS 2 0614 020 - 08051015  B\nKYP/IT ESSEN/ PYTHON/ OTHERS 1 0614 020 - 08041014  B\nENVIRONMENTAL SCIENCE 0 10 -010 - 0408 -08  A\n-----------------------------------------------------------------------------------------------\nGRAND TOTAL 24 750 424\n-----------------------------------------------------------------------------------------------\nSGPA \n-----------------------------------------------------------------------------------------------\nREMARKS : Carry in - MATHEMATICS-II\n FUNDA OF ELECT AND EC ENGG",
        "college": "Government Polytechnic, Bhojpur",
        "name": "ASIF ALAM",
        "roll": "211521823040",
        "branch": "18",
        "marks": 424,
        "remarks": "Carry in - MATHEMATICS-II",
        "theory": 154
    },
    {
        "text": " \n \nRegistration No : 1521823025\nRoll No         : 211521823025\n \nFollowing are the marks obtained by RAJA  KUMAR\nof Government Polytechnic, Bhojpur\nat Semester II of Diploma in Computer Science & Engineering\nExamination 2024 (EVEN) held in the month of JUL, 2024\n \n \nResult Published On: 30/07/2024\nSTATE BOARD OF TECHNICAL EDUCATION\nBIHAR\n-----------------------------------------------------------------------------------------------\nSUBJECT  FULL MARKS PASS MARKS MARKS OBTAINED\nNAME OF SUBJECTS CREDITS INTFINTOTAL FINTOTAL INT FIN TOTAL GRADE\n-----------------------------------------------------------------------------------------------\nTHEORY PAPERS\nMATHEMATICS-II 4 3070 100 28 40203353  D\nAPPLIED PHYSICS-II 3 3070 100 28 4015 A15  F\nINTRODUCTION TO IT SYSTEMS 2 3070 100 28 40123446  E\nFUNDA OF ELECT AND EC ENGG 3 3070 100 28 40161329  F\nENGG. MECHANICS 3 3070 100 28 40111930  F\n-----------------------------------------------------------------------------------------------\nPRACTICAL PAPERS\nAPPLIED PHYSICS LAB-II 1 1535 050 - 20102838  B\nINTRODUCTION TO IT SYSTEM LAB 2 1535 050 - 20133043  A\nFUNDA OF ELECT AND EC ENGG LAB 1 1535 050 - 20123042  A\nENGG. MECHANICS LAB 2 1535 050 - 20113041  A\n-----------------------------------------------------------------------------------------------\nTERM WORK PAPERS\nC.U MOOCS/ SWAYAM/ ETC/ OTHERS 2 0614 020 - 08050914  B\nKYP/IT ESSEN/ PYTHON/ OTHERS 1 0614 020 - 08050914  B\nENVIRONMENTAL SCIENCE 0 10 -010 - 0408 -08  A\n-----------------------------------------------------------------------------------------------\nGRAND TOTAL 24 750 373\n-----------------------------------------------------------------------------------------------\nSGPA \n-----------------------------------------------------------------------------------------------\nREMARKS : Carry in - APPLIED PHYSICS-II\n FUNDA OF ELECT AND EC ENGG\n ENGG. MECHANICS",
        "college": "Government Polytechnic, Bhojpur",
        "name": "RAJA KUMAR",
        "roll": "211521823025",
        "branch": "18",
        "marks": 373,
        "remarks": "Carry in - APPLIED PHYSICS-II",
        "theory": 99
    },
    {
        "text": " \n \nRegistration No : 1521823015\nRoll No         : 211521823015\n \nFollowing are the marks obtained by SHUBHAM  KUMAR\nof Government Polytechnic, Bhojpur\nat Semester II of Diploma in Computer Science & Engineering\nExamination 2024 (EVEN) held in the month of JUL, 2024\n \n \nResult Published On: 30/07/2024\nSTATE BOARD OF TECHNICAL EDUCATION\nBIHAR\n-----------------------------------------------------------------------------------------------\nSUBJECT  FULL MARKS PASS MARKS MARKS OBTAINED\nNAME OF SUBJECTS CREDITS INTFINTOTAL FINTOTAL INT FIN TOTAL GRADE\n-----------------------------------------------------------------------------------------------\nTHEORY PAPERS\nMATHEMATICS-II 4 3070 100 28 40233053  D\nAPPLIED PHYSICS-II 3 3070 100 28 40153651  D\nINTRODUCTION TO IT SYSTEMS 2 3070 100 28 40153550  D\nFUNDA OF ELECT AND EC ENGG 3 3070 100 28 40202848  E\nENGG. MECHANICS 3 3070 100 28 40204969  C\n-----------------------------------------------------------------------------------------------\nPRACTICAL PAPERS\nAPPLIED PHYSICS LAB-II 1 1535 050 - 20103141  A\nINTRODUCTION TO IT SYSTEM LAB 2 1535 050 - 20113243  A\nFUNDA OF ELECT AND EC ENGG LAB 1 1535 050 - 20123143  A\nENGG. MECHANICS LAB 2 1535 050 - 20113142  A\n-----------------------------------------------------------------------------------------------\nTERM WORK PAPERS\nC.U MOOCS/ SWAYAM/ ETC/ OTHERS 2 0614 020 - 08051116  A\nKYP/IT ESSEN/ PYTHON/ OTHERS 1 0614 020 - 08051116  A\nENVIRONMENTAL SCIENCE 0 10 -010 - 0408 -08  A\n-----------------------------------------------------------------------------------------------\nGRAND TOTAL 24 750 480\n-----------------------------------------------------------------------------------------------\nSGPA 7.12\n-----------------------------------------------------------------------------------------------\nREMARKS : First Class",
        "college": "Government Polytechnic, Bhojpur",
        "name": "SHUBHAM KUMAR",
        "roll": "211521823015",
        "branch": "18",
        "marks": 480,
        "remarks": "First Class",
        "theory": 178
    },
    {
        "text": " \n \nRegistration No : 1521823027\nRoll No         : 211521823027\n \nFollowing are the marks obtained by SAKSHI  VIDYARTHI\nof Government Polytechnic, Bhojpur\nat Semester II of Diploma in Computer Science & Engineering\nExamination 2024 (EVEN) held in the month of JUL, 2024\n \n \nResult Published On: 30/07/2024\nSTATE BOARD OF TECHNICAL EDUCATION\nBIHAR\n-----------------------------------------------------------------------------------------------\nSUBJECT  FULL MARKS PASS MARKS MARKS OBTAINED\nNAME OF SUBJECTS CREDITS INTFINTOTAL FINTOTAL INT FIN TOTAL GRADE\n-----------------------------------------------------------------------------------------------\nTHEORY PAPERS\nMATHEMATICS-II 4 3070 100 28 40211435  F\nAPPLIED PHYSICS-II 3 3070 100 28 40215172  B\nINTRODUCTION TO IT SYSTEMS 2 3070 100 28 40214263  C\nFUNDA OF ELECT AND EC ENGG 3 3070 100 28 40172845  E\nENGG. MECHANICS 3 3070 100 28 40222850  D\n-----------------------------------------------------------------------------------------------\nPRACTICAL PAPERS\nAPPLIED PHYSICS LAB-II 1 1535 050 - 20133144  A\nINTRODUCTION TO IT SYSTEM LAB 2 1535 050 - 20123345  A+\nFUNDA OF ELECT AND EC ENGG LAB 1 1535 050 - 20133043  A\nENGG. MECHANICS LAB 2 1535 050 - 20143347  A+\n-----------------------------------------------------------------------------------------------\nTERM WORK PAPERS\nC.U MOOCS/ SWAYAM/ ETC/ OTHERS 2 0614 020 - 08051217  A\nKYP/IT ESSEN/ PYTHON/ OTHERS 1 0614 020 - 08051217  A\nENVIRONMENTAL SCIENCE 0 10 -010 - 0408 -08  A\n-----------------------------------------------------------------------------------------------\nGRAND TOTAL 24 750 486\n-----------------------------------------------------------------------------------------------\nSGPA \n-----------------------------------------------------------------------------------------------\nREMARKS : Carry in - MATHEMATICS-II",
        "college": "Government Polytechnic, Bhojpur",
        "name": "SAKSHI VIDYARTHI",
        "roll": "211521823027",
        "branch": "18",
        "marks": 486,
        "remarks": "Carry in - MATHEMATICS-II",
        "theory": 163
    },
    {
        "text": " \n \nRegistration No : 1521823050\nRoll No         : 211521823050\n \nFollowing are the marks obtained by PRINCE KUMAR SINHA\nof Government Polytechnic, Bhojpur\nat Semester II of Diploma in Computer Science & Engineering\nExamination 2024 (EVEN) held in the month of JUL, 2024\n \n \nResult Published On: 30/07/2024\nSTATE BOARD OF TECHNICAL EDUCATION\nBIHAR\n-----------------------------------------------------------------------------------------------\nSUBJECT  FULL MARKS PASS MARKS MARKS OBTAINED\nNAME OF SUBJECTS CREDITS INTFINTOTAL FINTOTAL INT FIN TOTAL GRADE\n-----------------------------------------------------------------------------------------------\nTHEORY PAPERS\nMATHEMATICS-II 4 3070 100 28 40221436  F\nAPPLIED PHYSICS-II 3 3070 100 28 40154459  D\nINTRODUCTION TO IT SYSTEMS 2 3070 100 28 40235679  B\nFUNDA OF ELECT AND EC ENGG 3 3070 100 28 40203454  D\nENGG. MECHANICS 3 3070 100 28 40223254  D\n-----------------------------------------------------------------------------------------------\nPRACTICAL PAPERS\nAPPLIED PHYSICS LAB-II 1 1535 050 - 20113142  A\nINTRODUCTION TO IT SYSTEM LAB 2 1535 050 - 20113344  A\nFUNDA OF ELECT AND EC ENGG LAB 1 1535 050 - 20133144  A\nENGG. MECHANICS LAB 2 1535 050 - 20143246  A+\n-----------------------------------------------------------------------------------------------\nTERM WORK PAPERS\nC.U MOOCS/ SWAYAM/ ETC/ OTHERS 2 0614 020 - 08041115  B\nKYP/IT ESSEN/ PYTHON/ OTHERS 1 0614 020 - 08041216  A\nENVIRONMENTAL SCIENCE 0 10 -010 - 0410 -10  A+\n-----------------------------------------------------------------------------------------------\nGRAND TOTAL 24 750 499\n-----------------------------------------------------------------------------------------------\nSGPA \n-----------------------------------------------------------------------------------------------\nREMARKS : Carry in - MATHEMATICS-II",
        "college": "Government Polytechnic, Bhojpur",
        "name": "PRINCE KUMAR SINHA",
        "roll": "211521823050",
        "branch": "18",
        "marks": 499,
        "remarks": "Carry in - MATHEMATICS-II",
        "theory": 180
    },
    {
        "text": " \n \nRegistration No : 1521823038\nRoll No         : 211521823038\n \nFollowing are the marks obtained by DEV  WARSI\nof Government Polytechnic, Bhojpur\nat Semester II of Diploma in Computer Science & Engineering\nExamination 2024 (EVEN) held in the month of JUL, 2024\n \n \nResult Published On: 30/07/2024\nSTATE BOARD OF TECHNICAL EDUCATION\nBIHAR\n-----------------------------------------------------------------------------------------------\nSUBJECT  FULL MARKS PASS MARKS MARKS OBTAINED\nNAME OF SUBJECTS CREDITS INTFINTOTAL FINTOTAL INT FIN TOTAL GRADE\n-----------------------------------------------------------------------------------------------\nTHEORY PAPERS\nMATHEMATICS-II 4 3070 100 28 40260632  F\nAPPLIED PHYSICS-II 3 3070 100 28 40053136  F\nINTRODUCTION TO IT SYSTEMS 2 3070 100 28 40165066  C\nFUNDA OF ELECT AND EC ENGG 3 3070 100 28 40171835  F\nENGG. MECHANICS 3 3070 100 28 40181836  F\n-----------------------------------------------------------------------------------------------\nPRACTICAL PAPERS\nAPPLIED PHYSICS LAB-II 1 1535 050 - 20112940  A\nINTRODUCTION TO IT SYSTEM LAB 2 1535 050 - 20113041  A\nFUNDA OF ELECT AND EC ENGG LAB 1 1535 050 - 20123042  A\nENGG. MECHANICS LAB 2 1535 050 - 20103141  A\n-----------------------------------------------------------------------------------------------\nTERM WORK PAPERS\nC.U MOOCS/ SWAYAM/ ETC/ OTHERS 2 0614 020 - 08040913  C\nKYP/IT ESSEN/ PYTHON/ OTHERS 1 0614 020 - 08041014  B\nENVIRONMENTAL SCIENCE 0 10 -010 - 0408 -08  A\n-----------------------------------------------------------------------------------------------\nGRAND TOTAL 24 750 404\n-----------------------------------------------------------------------------------------------\nSGPA \n-----------------------------------------------------------------------------------------------\nREMARKS : Fail",
        "college": "Government Polytechnic, Bhojpur",
        "name": "DEV WARSI",
        "roll": "211521823038",
        "branch": "18",
        "marks": 404,
        "remarks": "Fail",
        "theory": 123
    },
    {
        "text": " \n \nRegistration No : 1521823043\nRoll No         : 211521823043\n \nFollowing are the marks obtained by SHIVAM  RAJ\nof Government Polytechnic, Bhojpur\nat Semester II of Diploma in Computer Science & Engineering\nExamination 2024 (EVEN) held in the month of JUL, 2024\n \n \nResult Published On: 30/07/2024\nSTATE BOARD OF TECHNICAL EDUCATION\nBIHAR\n-----------------------------------------------------------------------------------------------\nSUBJECT  FULL MARKS PASS MARKS MARKS OBTAINED\nNAME OF SUBJECTS CREDITS INTFINTOTAL FINTOTAL INT FIN TOTAL GRADE\n-----------------------------------------------------------------------------------------------\nTHEORY PAPERS\nMATHEMATICS-II 4 3070 100 28 40223254  D\nAPPLIED PHYSICS-II 3 3070 100 28 40183250  D\nINTRODUCTION TO IT SYSTEMS 2 3070 100 28 40173754  D\nFUNDA OF ELECT AND EC ENGG 3 3070 100 28 40153348  E\nENGG. MECHANICS 3 3070 100 28 40185876  B\n-----------------------------------------------------------------------------------------------\nPRACTICAL PAPERS\nAPPLIED PHYSICS LAB-II 1 1535 050 - 20113142  A\nINTRODUCTION TO IT SYSTEM LAB 2 1535 050 - 20123244  A\nFUNDA OF ELECT AND EC ENGG LAB 1 1535 050 - 20123143  A\nENGG. MECHANICS LAB 2 1535 050 - 20123244  A\n-----------------------------------------------------------------------------------------------\nTERM WORK PAPERS\nC.U MOOCS/ SWAYAM/ ETC/ OTHERS 2 0614 020 - 08051015  B\nKYP/IT ESSEN/ PYTHON/ OTHERS 1 0614 020 - 08040913  C\nENVIRONMENTAL SCIENCE 0 10 -010 - 0408 -08  A\n-----------------------------------------------------------------------------------------------\nGRAND TOTAL 24 750 491\n-----------------------------------------------------------------------------------------------\nSGPA 7.08\n-----------------------------------------------------------------------------------------------\nREMARKS : First Class",
        "college": "Government Polytechnic, Bhojpur",
        "name": "SHIVAM RAJ",
        "roll": "211521823043",
        "branch": "18",
        "marks": 491,
        "remarks": "First Class",
        "theory": 192
    },
    {
        "text": " \n \nRegistration No : 1521823044\nRoll No         : 211521823044\n \nFollowing are the marks obtained by HARSH KUMAR SINGH\nof Government Polytechnic, Bhojpur\nat Semester II of Diploma in Computer Science & Engineering\nExamination 2024 (EVEN) held in the month of JUL, 2024\n \n \nResult Published On: 30/07/2024\nSTATE BOARD OF TECHNICAL EDUCATION\nBIHAR\n-----------------------------------------------------------------------------------------------\nSUBJECT  FULL MARKS PASS MARKS MARKS OBTAINED\nNAME OF SUBJECTS CREDITS INTFINTOTAL FINTOTAL INT FIN TOTAL GRADE\n-----------------------------------------------------------------------------------------------\nTHEORY PAPERS\nMATHEMATICS-II 4 3070 100 28 40242953  D\nAPPLIED PHYSICS-II 3 3070 100 28 40153449  E\nINTRODUCTION TO IT SYSTEMS 2 3070 100 28 40204464  C\nFUNDA OF ELECT AND EC ENGG 3 3070 100 28 40192948  E\nENGG. MECHANICS 3 3070 100 28 40154459  D\n-----------------------------------------------------------------------------------------------\nPRACTICAL PAPERS\nAPPLIED PHYSICS LAB-II 1 1535 050 - 20113142  A\nINTRODUCTION TO IT SYSTEM LAB 2 1535 050 - 20123345  A+\nFUNDA OF ELECT AND EC ENGG LAB 1 1535 050 - 20122840  A\nENGG. MECHANICS LAB 2 1535 050 - 20123143  A\n-----------------------------------------------------------------------------------------------\nTERM WORK PAPERS\nC.U MOOCS/ SWAYAM/ ETC/ OTHERS 2 0614 020 - 08041115  B\nKYP/IT ESSEN/ PYTHON/ OTHERS 1 0614 020 - 08051015  B\nENVIRONMENTAL SCIENCE 0 10 -010 - 0408 -08  A\n-----------------------------------------------------------------------------------------------\nGRAND TOTAL 24 750 481\n-----------------------------------------------------------------------------------------------\nSGPA 6.92\n-----------------------------------------------------------------------------------------------\nREMARKS : First Class",
        "college": "Government Polytechnic, Bhojpur",
        "name": "HARSH KUMAR SINGH",
        "roll": "211521823044",
        "branch": "18",
        "marks": 481,
        "remarks": "First Class",
        "theory": 180
    },
    {
        "text": " \n \nRegistration No : 1521823042\nRoll No         : 211521823042\n \nFollowing are the marks obtained by VIVEK  KUMAR\nof Government Polytechnic, Bhojpur\nat Semester II of Diploma in Computer Science & Engineering\nExamination 2024 (EVEN) held in the month of JUL, 2024\n \n \nResult Published On: 30/07/2024\nSTATE BOARD OF TECHNICAL EDUCATION\nBIHAR\n-----------------------------------------------------------------------------------------------\nSUBJECT  FULL MARKS PASS MARKS MARKS OBTAINED\nNAME OF SUBJECTS CREDITS INTFINTOTAL FINTOTAL INT FIN TOTAL GRADE\n-----------------------------------------------------------------------------------------------\nTHEORY PAPERS\nMATHEMATICS-II 4 3070 100 28 40250833  F\nAPPLIED PHYSICS-II 3 3070 100 28 40141933  F\nINTRODUCTION TO IT SYSTEMS 2 3070 100 28 40182846  E\nFUNDA OF ELECT AND EC ENGG 3 3070 100 28 40181331  F\nENGG. MECHANICS 3 3070 100 28 40171936  F\n-----------------------------------------------------------------------------------------------\nPRACTICAL PAPERS\nAPPLIED PHYSICS LAB-II 1 1535 050 - 20102939  B\nINTRODUCTION TO IT SYSTEM LAB 2 1535 050 - 20113142  A\nFUNDA OF ELECT AND EC ENGG LAB 1 1535 050 - 20133043  A\nENGG. MECHANICS LAB 2 1535 050 - 20103141  A\n-----------------------------------------------------------------------------------------------\nTERM WORK PAPERS\nC.U MOOCS/ SWAYAM/ ETC/ OTHERS 2 0614 020 - 08051217  A\nKYP/IT ESSEN/ PYTHON/ OTHERS 1 0614 020 - 08051015  B\nENVIRONMENTAL SCIENCE 0 10 -010 - 0407 -07  B\n-----------------------------------------------------------------------------------------------\nGRAND TOTAL 24 750 383\n-----------------------------------------------------------------------------------------------\nSGPA \n-----------------------------------------------------------------------------------------------\nREMARKS : Fail",
        "college": "Government Polytechnic, Bhojpur",
        "name": "VIVEK KUMAR",
        "roll": "211521823042",
        "branch": "18",
        "marks": 383,
        "remarks": "Fail",
        "theory": 87
    },
    {
        "text": " \n \nRegistration No : 1521823014\nRoll No         : 211521823014\n \nFollowing are the marks obtained by HARSH  RANJAN\nof Government Polytechnic, Bhojpur\nat Semester II of Diploma in Computer Science & Engineering\nExamination 2024 (EVEN) held in the month of JUL, 2024\n \n \nResult Published On: 30/07/2024\nSTATE BOARD OF TECHNICAL EDUCATION\nBIHAR\n-----------------------------------------------------------------------------------------------\nSUBJECT  FULL MARKS PASS MARKS MARKS OBTAINED\nNAME OF SUBJECTS CREDITS INTFINTOTAL FINTOTAL INT FIN TOTAL GRADE\n-----------------------------------------------------------------------------------------------\nTHEORY PAPERS\nMATHEMATICS-II 4 3070 100 28 40283058  D\nAPPLIED PHYSICS-II 3 3070 100 28 4025 A25  F\nINTRODUCTION TO IT SYSTEMS 2 3070 100 28 40123244  E\nFUNDA OF ELECT AND EC ENGG 3 3070 100 28 40214364  C\nENGG. MECHANICS 3 3070 100 28 40224769  C\n-----------------------------------------------------------------------------------------------\nPRACTICAL PAPERS\nAPPLIED PHYSICS LAB-II 1 1535 050 - 20133144  A\nINTRODUCTION TO IT SYSTEM LAB 2 1535 050 - 20123244  A\nFUNDA OF ELECT AND EC ENGG LAB 1 1535 050 - 20133043  A\nENGG. MECHANICS LAB 2 1535 050 - 20123244  A\n-----------------------------------------------------------------------------------------------\nTERM WORK PAPERS\nC.U MOOCS/ SWAYAM/ ETC/ OTHERS 2 0614 020 - 08041014  B\nKYP/IT ESSEN/ PYTHON/ OTHERS 1 0614 020 - 08041115  B\nENVIRONMENTAL SCIENCE 0 10 -010 - 0408 -08  A\n-----------------------------------------------------------------------------------------------\nGRAND TOTAL 24 750 472\n-----------------------------------------------------------------------------------------------\nSGPA \n-----------------------------------------------------------------------------------------------\nREMARKS : Carry in - APPLIED PHYSICS-II",
        "college": "Government Polytechnic, Bhojpur",
        "name": "HARSH RANJAN",
        "roll": "211521823014",
        "branch": "18",
        "marks": 472,
        "remarks": "Carry in - APPLIED PHYSICS-II",
        "theory": 152
    },
    {
        "text": " \n \nRegistration No : 1521823009\nRoll No         : 211521823009\n \nFollowing are the marks obtained by ROSHAN KUMAR TIWARY\nof Government Polytechnic, Bhojpur\nat Semester II of Diploma in Computer Science & Engineering\nExamination 2024 (EVEN) held in the month of JUL, 2024\n \n \nResult Published On: 30/07/2024\nSTATE BOARD OF TECHNICAL EDUCATION\nBIHAR\n-----------------------------------------------------------------------------------------------\nSUBJECT  FULL MARKS PASS MARKS MARKS OBTAINED\nNAME OF SUBJECTS CREDITS INTFINTOTAL FINTOTAL INT FIN TOTAL GRADE\n-----------------------------------------------------------------------------------------------\nTHEORY PAPERS\nMATHEMATICS-II 4 3070 100 28 40211839  F\nAPPLIED PHYSICS-II 3 3070 100 28 40223355  D\nINTRODUCTION TO IT SYSTEMS 2 3070 100 28 40203151  D\nFUNDA OF ELECT AND EC ENGG 3 3070 100 28 40153146  E\nENGG. MECHANICS 3 3070 100 28 40122840  E\n-----------------------------------------------------------------------------------------------\nPRACTICAL PAPERS\nAPPLIED PHYSICS LAB-II 1 1535 050 - 20123143  A\nINTRODUCTION TO IT SYSTEM LAB 2 1535 050 - 20123143  A\nFUNDA OF ELECT AND EC ENGG LAB 1 1535 050 - 20123042  A\nENGG. MECHANICS LAB 2 1535 050 - 20133346  A+\n-----------------------------------------------------------------------------------------------\nTERM WORK PAPERS\nC.U MOOCS/ SWAYAM/ ETC/ OTHERS 2 0614 020 - 08041014  B\nKYP/IT ESSEN/ PYTHON/ OTHERS 1 0614 020 - 08051015  B\nENVIRONMENTAL SCIENCE 0 10 -010 - 0408 -08  A\n-----------------------------------------------------------------------------------------------\nGRAND TOTAL 24 750 442\n-----------------------------------------------------------------------------------------------\nSGPA \n-----------------------------------------------------------------------------------------------\nREMARKS : Carry in - MATHEMATICS-II",
        "college": "Government Polytechnic, Bhojpur",
        "name": "ROSHAN KUMAR TIWARY",
        "roll": "211521823009",
        "branch": "18",
        "marks": 442,
        "remarks": "Carry in - MATHEMATICS-II",
        "theory": 141
    },
    {
        "text": " \n \nRegistration No : 1521823024\nRoll No         : 211521823024\n \nFollowing are the marks obtained by PAYAL  KUMARI\nof Government Polytechnic, Bhojpur\nat Semester II of Diploma in Computer Science & Engineering\nExamination 2024 (EVEN) held in the month of JUL, 2024\n \n \nResult Published On: 30/07/2024\nSTATE BOARD OF TECHNICAL EDUCATION\nBIHAR\n-----------------------------------------------------------------------------------------------\nSUBJECT  FULL MARKS PASS MARKS MARKS OBTAINED\nNAME OF SUBJECTS CREDITS INTFINTOTAL FINTOTAL INT FIN TOTAL GRADE\n-----------------------------------------------------------------------------------------------\nTHEORY PAPERS\nMATHEMATICS-II 4 3070 100 28 4022 A22  F\nAPPLIED PHYSICS-II 3 3070 100 28 4013 A13  F\nINTRODUCTION TO IT SYSTEMS 2 3070 100 28 40153853  D\nFUNDA OF ELECT AND EC ENGG 3 3070 100 28 40151126  F\nENGG. MECHANICS 3 3070 100 28 40130720  F\n-----------------------------------------------------------------------------------------------\nPRACTICAL PAPERS\nAPPLIED PHYSICS LAB-II 1 1535 050 - 20102838  B\nINTRODUCTION TO IT SYSTEM LAB 2 1535 050 - 20123042  A\nFUNDA OF ELECT AND EC ENGG LAB 1 1535 050 - 20133144  A\nENGG. MECHANICS LAB 2 1535 050 - 20123244  A\n-----------------------------------------------------------------------------------------------\nTERM WORK PAPERS\nC.U MOOCS/ SWAYAM/ ETC/ OTHERS 2 0614 020 - 08040913  C\nKYP/IT ESSEN/ PYTHON/ OTHERS 1 0614 020 - 08051015  B\nENVIRONMENTAL SCIENCE 0 10 -010 - 0410 -10  A+\n-----------------------------------------------------------------------------------------------\nGRAND TOTAL 24 750 340\n-----------------------------------------------------------------------------------------------\nSGPA \n-----------------------------------------------------------------------------------------------\nREMARKS : Fail",
        "college": "Government Polytechnic, Bhojpur",
        "name": "PAYAL KUMARI",
        "roll": "211521823024",
        "branch": "18",
        "marks": 340,
        "remarks": "Fail",
        "theory": 56
    },
    {
        "text": " \n \nRegistration No : 1521823048\nRoll No         : 211521823048\n \nFollowing are the marks obtained by ANANYA  RAY\nof Government Polytechnic, Bhojpur\nat Semester II of Diploma in Computer Science & Engineering\nExamination 2024 (EVEN) held in the month of JUL, 2024\n \n \nResult Published On: 30/07/2024\nSTATE BOARD OF TECHNICAL EDUCATION\nBIHAR\n-----------------------------------------------------------------------------------------------\nSUBJECT  FULL MARKS PASS MARKS MARKS OBTAINED\nNAME OF SUBJECTS CREDITS INTFINTOTAL FINTOTAL INT FIN TOTAL GRADE\n-----------------------------------------------------------------------------------------------\nTHEORY PAPERS\nMATHEMATICS-II 4 3070 100 28 40232851  D\nAPPLIED PHYSICS-II 3 3070 100 28 40214768  C\nINTRODUCTION TO IT SYSTEMS 2 3070 100 28 40224668  C\nFUNDA OF ELECT AND EC ENGG 3 3070 100 28 40214061  C\nENGG. MECHANICS 3 3070 100 28 40256388  A\n-----------------------------------------------------------------------------------------------\nPRACTICAL PAPERS\nAPPLIED PHYSICS LAB-II 1 1535 050 - 20133043  A\nINTRODUCTION TO IT SYSTEM LAB 2 1535 050 - 20123345  A+\nFUNDA OF ELECT AND EC ENGG LAB 1 1535 050 - 20133346  A+\nENGG. MECHANICS LAB 2 1535 050 - 20143448  A+\n-----------------------------------------------------------------------------------------------\nTERM WORK PAPERS\nC.U MOOCS/ SWAYAM/ ETC/ OTHERS 2 0614 020 - 08051217  A\nKYP/IT ESSEN/ PYTHON/ OTHERS 1 0614 020 - 08051217  A\nENVIRONMENTAL SCIENCE 0 10 -010 - 0410 -10  A+\n-----------------------------------------------------------------------------------------------\nGRAND TOTAL 24 750 562\n-----------------------------------------------------------------------------------------------\nSGPA 8.04\n-----------------------------------------------------------------------------------------------\nREMARKS : First Class",
        "college": "Government Polytechnic, Bhojpur",
        "name": "ANANYA RAY",
        "roll": "211521823048",
        "branch": "18",
        "marks": 562,
        "remarks": "First Class",
        "theory": 224
    },
    {
        "text": " \n \nRegistration No : 1521823055\nRoll No         : 211521823055\n \nFollowing are the marks obtained by AMIT  RAJ\nof Government Polytechnic, Bhojpur\nat Semester II of Diploma in Computer Science & Engineering\nExamination 2024 (EVEN) held in the month of JUL, 2024\n \n \nResult Published On: 30/07/2024\nSTATE BOARD OF TECHNICAL EDUCATION\nBIHAR\n-----------------------------------------------------------------------------------------------\nSUBJECT  FULL MARKS PASS MARKS MARKS OBTAINED\nNAME OF SUBJECTS CREDITS INTFINTOTAL FINTOTAL INT FIN TOTAL GRADE\n-----------------------------------------------------------------------------------------------\nTHEORY PAPERS\nMATHEMATICS-II 4 3070 100 28 40183351  D\nAPPLIED PHYSICS-II 3 3070 100 28 40273461  C\nINTRODUCTION TO IT SYSTEMS 2 3070 100 28 40215980  A\nFUNDA OF ELECT AND EC ENGG 3 3070 100 28 40184260  C\nENGG. MECHANICS 3 3070 100 28 40215576  B\n-----------------------------------------------------------------------------------------------\nPRACTICAL PAPERS\nAPPLIED PHYSICS LAB-II 1 1535 050 - 20143145  A+\nINTRODUCTION TO IT SYSTEM LAB 2 1535 050 - 20123345  A+\nFUNDA OF ELECT AND EC ENGG LAB 1 1535 050 - 20133043  A\nENGG. MECHANICS LAB 2 1535 050 - 20123143  A\n-----------------------------------------------------------------------------------------------\nTERM WORK PAPERS\nC.U MOOCS/ SWAYAM/ ETC/ OTHERS 2 0614 020 - 08051015  B\nKYP/IT ESSEN/ PYTHON/ OTHERS 1 0614 020 - 08041115  B\nENVIRONMENTAL SCIENCE 0 10 -010 - 0408 -08  A\n-----------------------------------------------------------------------------------------------\nGRAND TOTAL 24 750 542\n-----------------------------------------------------------------------------------------------\nSGPA 7.88\n-----------------------------------------------------------------------------------------------\nREMARKS : First Class",
        "college": "Government Polytechnic, Bhojpur",
        "name": "AMIT RAJ",
        "roll": "211521823055",
        "branch": "18",
        "marks": 542,
        "remarks": "First Class",
        "theory": 223
    },
    {
        "text": " \n \nRegistration No : 1521823031\nRoll No         : 211521823031\n \nFollowing are the marks obtained by ANKIT  KUMAR\nof Government Polytechnic, Bhojpur\nat Semester II of Diploma in Computer Science & Engineering\nExamination 2024 (EVEN) held in the month of JUL, 2024\n \n \nResult Published On: 30/07/2024\nSTATE BOARD OF TECHNICAL EDUCATION\nBIHAR\n-----------------------------------------------------------------------------------------------\nSUBJECT  FULL MARKS PASS MARKS MARKS OBTAINED\nNAME OF SUBJECTS CREDITS INTFINTOTAL FINTOTAL INT FIN TOTAL GRADE\n-----------------------------------------------------------------------------------------------\nTHEORY PAPERS\nMATHEMATICS-II 4 3070 100 28 40210425  F\nAPPLIED PHYSICS-II 3 3070 100 28 40121325  F\nINTRODUCTION TO IT SYSTEMS 2 3070 100 28 40112839  F\nFUNDA OF ELECT AND EC ENGG 3 3070 100 28 40171027  F\nENGG. MECHANICS 3 3070 100 28 40132942  E\n-----------------------------------------------------------------------------------------------\nPRACTICAL PAPERS\nAPPLIED PHYSICS LAB-II 1 1535 050 - 20102939  B\nINTRODUCTION TO IT SYSTEM LAB 2 1535 050 - 20123143  A\nFUNDA OF ELECT AND EC ENGG LAB 1 1535 050 - 20122941  A\nENGG. MECHANICS LAB 2 1535 050 - 20103040  A\n-----------------------------------------------------------------------------------------------\nTERM WORK PAPERS\nC.U MOOCS/ SWAYAM/ ETC/ OTHERS 2 0614 020 - 08041115  B\nKYP/IT ESSEN/ PYTHON/ OTHERS 1 0614 020 - 08041014  B\nENVIRONMENTAL SCIENCE 0 10 -010 - 0408 -08  A\n-----------------------------------------------------------------------------------------------\nGRAND TOTAL 24 750 358\n-----------------------------------------------------------------------------------------------\nSGPA \n-----------------------------------------------------------------------------------------------\nREMARKS : Fail",
        "college": "Government Polytechnic, Bhojpur",
        "name": "ANKIT KUMAR",
        "roll": "211521823031",
        "branch": "18",
        "marks": 358,
        "remarks": "Fail",
        "theory": 84
    },
    {
        "text": " \n \nRegistration No : 1521823019\nRoll No         : 211521823019\n \nFollowing are the marks obtained by RITU  RAJ\nof Government Polytechnic, Bhojpur\nat Semester II of Diploma in Computer Science & Engineering\nExamination 2024 (EVEN) held in the month of JUL, 2024\n \n \nResult Published On: 30/07/2024\nSTATE BOARD OF TECHNICAL EDUCATION\nBIHAR\n-----------------------------------------------------------------------------------------------\nSUBJECT  FULL MARKS PASS MARKS MARKS OBTAINED\nNAME OF SUBJECTS CREDITS INTFINTOTAL FINTOTAL INT FIN TOTAL GRADE\n-----------------------------------------------------------------------------------------------\nTHEORY PAPERS\nMATHEMATICS-II 4 3070 100 28 40222850  D\nAPPLIED PHYSICS-II 3 3070 100 28 40182947  E\nINTRODUCTION TO IT SYSTEMS 2 3070 100 28 40162844  E\nFUNDA OF ELECT AND EC ENGG 3 3070 100 28 40161834  F\nENGG. MECHANICS 3 3070 100 28 40122840  E\n-----------------------------------------------------------------------------------------------\nPRACTICAL PAPERS\nAPPLIED PHYSICS LAB-II 1 1535 050 - 20102939  B\nINTRODUCTION TO IT SYSTEM LAB 2 1535 050 - 20123143  A\nFUNDA OF ELECT AND EC ENGG LAB 1 1535 050 - 20123042  A\nENGG. MECHANICS LAB 2 1535 050 - 20123143  A\n-----------------------------------------------------------------------------------------------\nTERM WORK PAPERS\nC.U MOOCS/ SWAYAM/ ETC/ OTHERS 2 0614 020 - 08031114  B\nKYP/IT ESSEN/ PYTHON/ OTHERS 1 0614 020 - 08041115  B\nENVIRONMENTAL SCIENCE 0 10 -010 - 0410 -10  A+\n-----------------------------------------------------------------------------------------------\nGRAND TOTAL 24 750 421\n-----------------------------------------------------------------------------------------------\nSGPA \n-----------------------------------------------------------------------------------------------\nREMARKS : Carry in - FUNDA OF ELECT AND EC ENGG",
        "college": "Government Polytechnic, Bhojpur",
        "name": "RITU RAJ",
        "roll": "211521823019",
        "branch": "18",
        "marks": 421,
        "remarks": "Carry in - FUNDA OF ELECT AND EC ENGG",
        "theory": 131
    },
    {
        "text": " \n \nRegistration No : 1521823032\nRoll No         : 211521823032\n \nFollowing are the marks obtained by PRIYANSHU  KUMAR\nof Government Polytechnic, Bhojpur\nat Semester II of Diploma in Computer Science & Engineering\nExamination 2024 (EVEN) held in the month of JUL, 2024\n \n \nResult Published On: 30/07/2024\nSTATE BOARD OF TECHNICAL EDUCATION\nBIHAR\n-----------------------------------------------------------------------------------------------\nSUBJECT  FULL MARKS PASS MARKS MARKS OBTAINED\nNAME OF SUBJECTS CREDITS INTFINTOTAL FINTOTAL INT FIN TOTAL GRADE\n-----------------------------------------------------------------------------------------------\nTHEORY PAPERS\nMATHEMATICS-II 4 3070 100 28 40232851  D\nAPPLIED PHYSICS-II 3 3070 100 28 40252853  D\nINTRODUCTION TO IT SYSTEMS 2 3070 100 28 40234265  C\nFUNDA OF ELECT AND EC ENGG 3 3070 100 28 40162844  E\nENGG. MECHANICS 3 3070 100 28 40184563  C\n-----------------------------------------------------------------------------------------------\nPRACTICAL PAPERS\nAPPLIED PHYSICS LAB-II 1 1535 050 - 20132942  A\nINTRODUCTION TO IT SYSTEM LAB 2 1535 050 - 20123244  A\nFUNDA OF ELECT AND EC ENGG LAB 1 1535 050 - 20122840  A\nENGG. MECHANICS LAB 2 1535 050 - 20113243  A\n-----------------------------------------------------------------------------------------------\nTERM WORK PAPERS\nC.U MOOCS/ SWAYAM/ ETC/ OTHERS 2 0614 020 - 08051116  A\nKYP/IT ESSEN/ PYTHON/ OTHERS 1 0614 020 - 08041014  B\nENVIRONMENTAL SCIENCE 0 10 -010 - 0410 -10  A+\n-----------------------------------------------------------------------------------------------\nGRAND TOTAL 24 750 485\n-----------------------------------------------------------------------------------------------\nSGPA 7.17\n-----------------------------------------------------------------------------------------------\nREMARKS : First Class",
        "college": "Government Polytechnic, Bhojpur",
        "name": "PRIYANSHU KUMAR",
        "roll": "211521823032",
        "branch": "18",
        "marks": 485,
        "remarks": "First Class",
        "theory": 171
    },
    {
        "text": " \n \nRegistration No : 1521823023\nRoll No         : 211521823023\n \nFollowing are the marks obtained by ADITYA  KUMAR\nof Government Polytechnic, Bhojpur\nat Semester II of Diploma in Computer Science & Engineering\nExamination 2024 (EVEN) held in the month of JUL, 2024\n \n \nResult Published On: 30/07/2024\nSTATE BOARD OF TECHNICAL EDUCATION\nBIHAR\n-----------------------------------------------------------------------------------------------\nSUBJECT  FULL MARKS PASS MARKS MARKS OBTAINED\nNAME OF SUBJECTS CREDITS INTFINTOTAL FINTOTAL INT FIN TOTAL GRADE\n-----------------------------------------------------------------------------------------------\nTHEORY PAPERS\nMATHEMATICS-II 4 3070 100 28 40182139  F\nAPPLIED PHYSICS-II 3 3070 100 28 40131629  F\nINTRODUCTION TO IT SYSTEMS 2 3070 100 28 40043034  F\nFUNDA OF ELECT AND EC ENGG 3 3070 100 28 40081321  F\nENGG. MECHANICS 3 3070 100 28 40173047  E\n-----------------------------------------------------------------------------------------------\nPRACTICAL PAPERS\nAPPLIED PHYSICS LAB-II 1 1535 050 - 20102939  B\nINTRODUCTION TO IT SYSTEM LAB 2 1535 050 - 2011 A11  F\nFUNDA OF ELECT AND EC ENGG LAB 1 1535 050 - 20123042  A\nENGG. MECHANICS LAB 2 1535 050 - 20123244  A\n-----------------------------------------------------------------------------------------------\nTERM WORK PAPERS\nC.U MOOCS/ SWAYAM/ ETC/ OTHERS 2 0614 020 - 08051015  B\nKYP/IT ESSEN/ PYTHON/ OTHERS 1 0614 020 - 0804 A04  F\nENVIRONMENTAL SCIENCE 0 10 -010 - 0410 -10  A+\n-----------------------------------------------------------------------------------------------\nGRAND TOTAL 24 750 335\n-----------------------------------------------------------------------------------------------\nSGPA \n-----------------------------------------------------------------------------------------------\nREMARKS : Fail in Term Work",
        "college": "Government Polytechnic, Bhojpur",
        "name": "ADITYA KUMAR",
        "roll": "211521823023",
        "branch": "18",
        "marks": 335,
        "remarks": "Fail in Term Work",
        "theory": 110
    },
    {
        "text": " \n \nRegistration No : 1521823001\nRoll No         : 211521823001\n \nFollowing are the marks obtained by SACHIN  KUMAR\nof Government Polytechnic, Bhojpur\nat Semester II of Diploma in Computer Science & Engineering\nExamination 2024 (EVEN) held in the month of JUL, 2024\n \n \nResult Published On: 30/07/2024\nSTATE BOARD OF TECHNICAL EDUCATION\nBIHAR\n-----------------------------------------------------------------------------------------------\nSUBJECT  FULL MARKS PASS MARKS MARKS OBTAINED\nNAME OF SUBJECTS CREDITS INTFINTOTAL FINTOTAL INT FIN TOTAL GRADE\n-----------------------------------------------------------------------------------------------\nTHEORY PAPERS\nMATHEMATICS-II 4 3070 100 28 40233255  D\nAPPLIED PHYSICS-II 3 3070 100 28 40162945  E\nINTRODUCTION TO IT SYSTEMS 2 3070 100 28 40203757  D\nFUNDA OF ELECT AND EC ENGG 3 3070 100 28 40152944  E\nENGG. MECHANICS 3 3070 100 28 40163652  D\n-----------------------------------------------------------------------------------------------\nPRACTICAL PAPERS\nAPPLIED PHYSICS LAB-II 1 1535 050 - 20102838  B\nINTRODUCTION TO IT SYSTEM LAB 2 1535 050 - 20123042  A\nFUNDA OF ELECT AND EC ENGG LAB 1 1535 050 - 20113041  A\nENGG. MECHANICS LAB 2 1535 050 - 20143145  A+\n-----------------------------------------------------------------------------------------------\nTERM WORK PAPERS\nC.U MOOCS/ SWAYAM/ ETC/ OTHERS 2 0614 020 - 08041115  B\nKYP/IT ESSEN/ PYTHON/ OTHERS 1 0614 020 - 08040812  C\nENVIRONMENTAL SCIENCE 0 10 -010 - 0409 -09  A+\n-----------------------------------------------------------------------------------------------\nGRAND TOTAL 24 750 455\n-----------------------------------------------------------------------------------------------\nSGPA 6.75\n-----------------------------------------------------------------------------------------------\nREMARKS : First Class",
        "college": "Government Polytechnic, Bhojpur",
        "name": "SACHIN KUMAR",
        "roll": "211521823001",
        "branch": "18",
        "marks": 455,
        "remarks": "First Class",
        "theory": 163
    },
    {
        "text": " \n \nRegistration No : 1521823011\nRoll No         : 211521823011\n \nFollowing are the marks obtained by VIKASH  KUMAR\nof Government Polytechnic, Bhojpur\nat Semester II of Diploma in Computer Science & Engineering\nExamination 2024 (EVEN) held in the month of JUL, 2024\n \n \nResult Published On: 30/07/2024\nSTATE BOARD OF TECHNICAL EDUCATION\nBIHAR\n-----------------------------------------------------------------------------------------------\nSUBJECT  FULL MARKS PASS MARKS MARKS OBTAINED\nNAME OF SUBJECTS CREDITS INTFINTOTAL FINTOTAL INT FIN TOTAL GRADE\n-----------------------------------------------------------------------------------------------\nTHEORY PAPERS\nMATHEMATICS-II 4 3070 100 28 40251641  E\nAPPLIED PHYSICS-II 3 3070 100 28 40123244  E\nINTRODUCTION TO IT SYSTEMS 2 3070 100 28 40213657  D\nFUNDA OF ELECT AND EC ENGG 3 3070 100 28 40173047  E\nENGG. MECHANICS 3 3070 100 28 40161834  F\n-----------------------------------------------------------------------------------------------\nPRACTICAL PAPERS\nAPPLIED PHYSICS LAB-II 1 1535 050 - 20102939  B\nINTRODUCTION TO IT SYSTEM LAB 2 1535 050 - 20113243  A\nFUNDA OF ELECT AND EC ENGG LAB 1 1535 050 - 20113041  A\nENGG. MECHANICS LAB 2 1535 050 - 20123143  A\n-----------------------------------------------------------------------------------------------\nTERM WORK PAPERS\nC.U MOOCS/ SWAYAM/ ETC/ OTHERS 2 0614 020 - 08041216  A\nKYP/IT ESSEN/ PYTHON/ OTHERS 1 0614 020 - 08051015  B\nENVIRONMENTAL SCIENCE 0 10 -010 - 0407 -07  B\n-----------------------------------------------------------------------------------------------\nGRAND TOTAL 24 750 427\n-----------------------------------------------------------------------------------------------\nSGPA \n-----------------------------------------------------------------------------------------------\nREMARKS : Carry in - MATHEMATICS-II\n ENGG. MECHANICS",
        "college": "Government Polytechnic, Bhojpur",
        "name": "VIKASH KUMAR",
        "roll": "211521823011",
        "branch": "18",
        "marks": 427,
        "remarks": "Carry in - MATHEMATICS-II",
        "theory": 132
    },
    {
        "text": " \n \nRegistration No : 1521823002\nRoll No         : 211521823002\n \nFollowing are the marks obtained by RAVI  RAJ\nof Government Polytechnic, Bhojpur\nat Semester II of Diploma in Computer Science & Engineering\nExamination 2024 (EVEN) held in the month of JUL, 2024\n \n \nResult Published On: 30/07/2024\nSTATE BOARD OF TECHNICAL EDUCATION\nBIHAR\n-----------------------------------------------------------------------------------------------\nSUBJECT  FULL MARKS PASS MARKS MARKS OBTAINED\nNAME OF SUBJECTS CREDITS INTFINTOTAL FINTOTAL INT FIN TOTAL GRADE\n-----------------------------------------------------------------------------------------------\nTHEORY PAPERS\nMATHEMATICS-II 4 3070 100 28 40243357  D\nAPPLIED PHYSICS-II 3 3070 100 28 40164056  D\nINTRODUCTION TO IT SYSTEMS 2 3070 100 28 40214667  C\nFUNDA OF ELECT AND EC ENGG 3 3070 100 28 40173855  D\nENGG. MECHANICS 3 3070 100 28 40215071  B\n-----------------------------------------------------------------------------------------------\nPRACTICAL PAPERS\nAPPLIED PHYSICS LAB-II 1 1535 050 - 20103141  A\nINTRODUCTION TO IT SYSTEM LAB 2 1535 050 - 20113243  A\nFUNDA OF ELECT AND EC ENGG LAB 1 1535 050 - 20123143  A\nENGG. MECHANICS LAB 2 1535 050 - 20143347  A+\n-----------------------------------------------------------------------------------------------\nTERM WORK PAPERS\nC.U MOOCS/ SWAYAM/ ETC/ OTHERS 2 0614 020 - 08051116  A\nKYP/IT ESSEN/ PYTHON/ OTHERS 1 0614 020 - 08051116  A\nENVIRONMENTAL SCIENCE 0 10 -010 - 0408 -08  A\n-----------------------------------------------------------------------------------------------\nGRAND TOTAL 24 750 520\n-----------------------------------------------------------------------------------------------\nSGPA 7.54\n-----------------------------------------------------------------------------------------------\nREMARKS : First Class",
        "college": "Government Polytechnic, Bhojpur",
        "name": "RAVI RAJ",
        "roll": "211521823002",
        "branch": "18",
        "marks": 520,
        "remarks": "First Class",
        "theory": 207
    },
    {
        "text": " \n \nRegistration No : 1521823007\nRoll No         : 211521823007\n \nFollowing are the marks obtained by MANJIT  KUMAR\nof Government Polytechnic, Bhojpur\nat Semester II of Diploma in Computer Science & Engineering\nExamination 2024 (EVEN) held in the month of JUL, 2024\n \n \nResult Published On: 30/07/2024\nSTATE BOARD OF TECHNICAL EDUCATION\nBIHAR\n-----------------------------------------------------------------------------------------------\nSUBJECT  FULL MARKS PASS MARKS MARKS OBTAINED\nNAME OF SUBJECTS CREDITS INTFINTOTAL FINTOTAL INT FIN TOTAL GRADE\n-----------------------------------------------------------------------------------------------\nTHEORY PAPERS\nMATHEMATICS-II 4 3070 100 28 40244266  C\nAPPLIED PHYSICS-II 3 3070 100 28 40244266  C\nINTRODUCTION TO IT SYSTEMS 2 3070 100 28 40164763  C\nFUNDA OF ELECT AND EC ENGG 3 3070 100 28 40162844  E\nENGG. MECHANICS 3 3070 100 28 40194463  C\n-----------------------------------------------------------------------------------------------\nPRACTICAL PAPERS\nAPPLIED PHYSICS LAB-II 1 1535 050 - 20122941  A\nINTRODUCTION TO IT SYSTEM LAB 2 1535 050 - 20123143  A\nFUNDA OF ELECT AND EC ENGG LAB 1 1535 050 - 20123042  A\nENGG. MECHANICS LAB 2 1535 050 - 20133245  A+\n-----------------------------------------------------------------------------------------------\nTERM WORK PAPERS\nC.U MOOCS/ SWAYAM/ ETC/ OTHERS 2 0614 020 - 08051015  B\nKYP/IT ESSEN/ PYTHON/ OTHERS 1 0614 020 - 08041115  B\nENVIRONMENTAL SCIENCE 0 10 -010 - 0408 -08  A\n-----------------------------------------------------------------------------------------------\nGRAND TOTAL 24 750 511\n-----------------------------------------------------------------------------------------------\nSGPA 7.46\n-----------------------------------------------------------------------------------------------\nREMARKS : First Class",
        "college": "Government Polytechnic, Bhojpur",
        "name": "MANJIT KUMAR",
        "roll": "211521823007",
        "branch": "18",
        "marks": 511,
        "remarks": "First Class",
        "theory": 203
    },
    {
        "text": " \n \nRegistration No : 1521823028\nRoll No         : 211521823028\n \nFollowing are the marks obtained by SHIVAM  KUMAR\nof Government Polytechnic, Bhojpur\nat Semester II of Diploma in Computer Science & Engineering\nExamination 2024 (EVEN) held in the month of JUL, 2024\n \n \nResult Published On: 30/07/2024\nSTATE BOARD OF TECHNICAL EDUCATION\nBIHAR\n-----------------------------------------------------------------------------------------------\nSUBJECT  FULL MARKS PASS MARKS MARKS OBTAINED\nNAME OF SUBJECTS CREDITS INTFINTOTAL FINTOTAL INT FIN TOTAL GRADE\n-----------------------------------------------------------------------------------------------\nTHEORY PAPERS\nMATHEMATICS-II 4 3070 100 28 40231134  F\nAPPLIED PHYSICS-II 3 3070 100 28 40253762  C\nINTRODUCTION TO IT SYSTEMS 2 3070 100 28 40265177  B\nFUNDA OF ELECT AND EC ENGG 3 3070 100 28 40183452  D\nENGG. MECHANICS 3 3070 100 28 40243256  D\n-----------------------------------------------------------------------------------------------\nPRACTICAL PAPERS\nAPPLIED PHYSICS LAB-II 1 1535 050 - 20133144  A\nINTRODUCTION TO IT SYSTEM LAB 2 1535 050 - 20123345  A+\nFUNDA OF ELECT AND EC ENGG LAB 1 1535 050 - 20133144  A\nENGG. MECHANICS LAB 2 1535 050 - 20143347  A+\n-----------------------------------------------------------------------------------------------\nTERM WORK PAPERS\nC.U MOOCS/ SWAYAM/ ETC/ OTHERS 2 0614 020 - 08051015  B\nKYP/IT ESSEN/ PYTHON/ OTHERS 1 0614 020 - 08051217  A\nENVIRONMENTAL SCIENCE 0 10 -010 - 0410 -10  A+\n-----------------------------------------------------------------------------------------------\nGRAND TOTAL 24 750 503\n-----------------------------------------------------------------------------------------------\nSGPA \n-----------------------------------------------------------------------------------------------\nREMARKS : Carry in - MATHEMATICS-II",
        "college": "Government Polytechnic, Bhojpur",
        "name": "SHIVAM KUMAR",
        "roll": "211521823028",
        "branch": "18",
        "marks": 503,
        "remarks": "Carry in - MATHEMATICS-II",
        "theory": 165
    },
    {
        "text": " \n \nRegistration No : 1521823016\nRoll No         : 211521823016\n \nFollowing are the marks obtained by CHANDANI  KUMARI\nof Government Polytechnic, Bhojpur\nat Semester II of Diploma in Computer Science & Engineering\nExamination 2024 (EVEN) held in the month of JUL, 2024\n \n \nResult Published On: 30/07/2024\nSTATE BOARD OF TECHNICAL EDUCATION\nBIHAR\n-----------------------------------------------------------------------------------------------\nSUBJECT  FULL MARKS PASS MARKS MARKS OBTAINED\nNAME OF SUBJECTS CREDITS INTFINTOTAL FINTOTAL INT FIN TOTAL GRADE\n-----------------------------------------------------------------------------------------------\nTHEORY PAPERS\nMATHEMATICS-II 4 3070 100 28 40241337  F\nAPPLIED PHYSICS-II 3 3070 100 28 40130821  F\nINTRODUCTION TO IT SYSTEMS 2 3070 100 28 40133245  E\nFUNDA OF ELECT AND EC ENGG 3 3070 100 28 40172138  F\nENGG. MECHANICS 3 3070 100 28 40133649  E\n-----------------------------------------------------------------------------------------------\nPRACTICAL PAPERS\nAPPLIED PHYSICS LAB-II 1 1535 050 - 20102838  B\nINTRODUCTION TO IT SYSTEM LAB 2 1535 050 - 20123042  A\nFUNDA OF ELECT AND EC ENGG LAB 1 1535 050 - 20133043  A\nENGG. MECHANICS LAB 2 1535 050 - 20133245  A+\n-----------------------------------------------------------------------------------------------\nTERM WORK PAPERS\nC.U MOOCS/ SWAYAM/ ETC/ OTHERS 2 0614 020 - 08041014  B\nKYP/IT ESSEN/ PYTHON/ OTHERS 1 0614 020 - 08041014  B\nENVIRONMENTAL SCIENCE 0 10 -010 - 0410 -10  A+\n-----------------------------------------------------------------------------------------------\nGRAND TOTAL 24 750 396\n-----------------------------------------------------------------------------------------------\nSGPA \n-----------------------------------------------------------------------------------------------\nREMARKS : Carry in - MATHEMATICS-II\n APPLIED PHYSICS-II\n FUNDA OF ELECT AND EC ENGG",
        "college": "Government Polytechnic, Bhojpur",
        "name": "CHANDANI KUMARI",
        "roll": "211521823016",
        "branch": "18",
        "marks": 396,
        "remarks": "Carry in - MATHEMATICS-II",
        "theory": 110
    },
    {
        "text": " \n \nRegistration No : 1521823047\nRoll No         : 211521823047\n \nFollowing are the marks obtained by SHUBHAM  KUMAR\nof Government Polytechnic, Bhojpur\nat Semester II of Diploma in Computer Science & Engineering\nExamination 2024 (EVEN) held in the month of JUL, 2024\n \n \nResult Published On: 30/07/2024\nSTATE BOARD OF TECHNICAL EDUCATION\nBIHAR\n-----------------------------------------------------------------------------------------------\nSUBJECT  FULL MARKS PASS MARKS MARKS OBTAINED\nNAME OF SUBJECTS CREDITS INTFINTOTAL FINTOTAL INT FIN TOTAL GRADE\n-----------------------------------------------------------------------------------------------\nTHEORY PAPERS\nMATHEMATICS-II 4 3070 100 28 40222850  D\nAPPLIED PHYSICS-II 3 3070 100 28 40193352  D\nINTRODUCTION TO IT SYSTEMS 2 3070 100 28 40212849  E\nFUNDA OF ELECT AND EC ENGG 3 3070 100 28 40181937  F\nENGG. MECHANICS 3 3070 100 28 40174259  D\n-----------------------------------------------------------------------------------------------\nPRACTICAL PAPERS\nAPPLIED PHYSICS LAB-II 1 1535 050 - 20132942  A\nINTRODUCTION TO IT SYSTEM LAB 2 1535 050 - 20113243  A\nFUNDA OF ELECT AND EC ENGG LAB 1 1535 050 - 20133043  A\nENGG. MECHANICS LAB 2 1535 050 - 20143448  A+\n-----------------------------------------------------------------------------------------------\nTERM WORK PAPERS\nC.U MOOCS/ SWAYAM/ ETC/ OTHERS 2 0614 020 - 08051015  B\nKYP/IT ESSEN/ PYTHON/ OTHERS 1 0614 020 - 08041115  B\nENVIRONMENTAL SCIENCE 0 10 -010 - 0410 -10  A+\n-----------------------------------------------------------------------------------------------\nGRAND TOTAL 24 750 463\n-----------------------------------------------------------------------------------------------\nSGPA \n-----------------------------------------------------------------------------------------------\nREMARKS : Carry in - FUNDA OF ELECT AND EC ENGG",
        "college": "Government Polytechnic, Bhojpur",
        "name": "SHUBHAM KUMAR",
        "roll": "211521823047",
        "branch": "18",
        "marks": 463,
        "remarks": "Carry in - FUNDA OF ELECT AND EC ENGG",
        "theory": 150
    },
    {
        "text": " \n \nRegistration No : 1521823008\nRoll No         : 211521823008\n \nFollowing are the marks obtained by MUSKAN  KASHISH\nof Government Polytechnic, Bhojpur\nat Semester II of Diploma in Computer Science & Engineering\nExamination 2024 (EVEN) held in the month of JUL, 2024\n \n \nResult Published On: 30/07/2024\nSTATE BOARD OF TECHNICAL EDUCATION\nBIHAR\n-----------------------------------------------------------------------------------------------\nSUBJECT  FULL MARKS PASS MARKS MARKS OBTAINED\nNAME OF SUBJECTS CREDITS INTFINTOTAL FINTOTAL INT FIN TOTAL GRADE\n-----------------------------------------------------------------------------------------------\nTHEORY PAPERS\nMATHEMATICS-II 4 3070 100 28 40254166  C\nAPPLIED PHYSICS-II 3 3070 100 28 40164056  D\nINTRODUCTION TO IT SYSTEMS 2 3070 100 28 40196483  A\nFUNDA OF ELECT AND EC ENGG 3 3070 100 28 40163450  D\nENGG. MECHANICS 3 3070 100 28 40194766  C\n-----------------------------------------------------------------------------------------------\nPRACTICAL PAPERS\nAPPLIED PHYSICS LAB-II 1 1535 050 - 20113142  A\nINTRODUCTION TO IT SYSTEM LAB 2 1535 050 - 20123244  A\nFUNDA OF ELECT AND EC ENGG LAB 1 1535 050 - 20113142  A\nENGG. MECHANICS LAB 2 1535 050 - 20133245  A+\n-----------------------------------------------------------------------------------------------\nTERM WORK PAPERS\nC.U MOOCS/ SWAYAM/ ETC/ OTHERS 2 0614 020 - 08041115  B\nKYP/IT ESSEN/ PYTHON/ OTHERS 1 0614 020 - 08041115  B\nENVIRONMENTAL SCIENCE 0 10 -010 - 0410 -10  A+\n-----------------------------------------------------------------------------------------------\nGRAND TOTAL 24 750 534\n-----------------------------------------------------------------------------------------------\nSGPA 7.62\n-----------------------------------------------------------------------------------------------\nREMARKS : First Class",
        "college": "Government Polytechnic, Bhojpur",
        "name": "MUSKAN KASHISH",
        "roll": "211521823008",
        "branch": "18",
        "marks": 534,
        "remarks": "First Class",
        "theory": 226
    },
    {
        "text": " \n \nRegistration No : 1521823046\nRoll No         : 211521823046\n \nFollowing are the marks obtained by SANOJ  KUMAR\nof Government Polytechnic, Bhojpur\nat Semester II of Diploma in Computer Science & Engineering\nExamination 2024 (EVEN) held in the month of JUL, 2024\n \n \nResult Published On: 30/07/2024\nSTATE BOARD OF TECHNICAL EDUCATION\nBIHAR\n-----------------------------------------------------------------------------------------------\nSUBJECT  FULL MARKS PASS MARKS MARKS OBTAINED\nNAME OF SUBJECTS CREDITS INTFINTOTAL FINTOTAL INT FIN TOTAL GRADE\n-----------------------------------------------------------------------------------------------\nTHEORY PAPERS\nMATHEMATICS-II 4 3070 100 28 40263157  D\nAPPLIED PHYSICS-II 3 3070 100 28 40282856  D\nINTRODUCTION TO IT SYSTEMS 2 3070 100 28 40195574  B\nFUNDA OF ELECT AND EC ENGG 3 3070 100 28 40152843  E\nENGG. MECHANICS 3 3070 100 28 40184462  C\n-----------------------------------------------------------------------------------------------\nPRACTICAL PAPERS\nAPPLIED PHYSICS LAB-II 1 1535 050 - 20143145  A+\nINTRODUCTION TO IT SYSTEM LAB 2 1535 050 - 20113142  A\nFUNDA OF ELECT AND EC ENGG LAB 1 1535 050 - 20123143  A\nENGG. MECHANICS LAB 2 1535 050 - 20123143  A\n-----------------------------------------------------------------------------------------------\nTERM WORK PAPERS\nC.U MOOCS/ SWAYAM/ ETC/ OTHERS 2 0614 020 - 08041115  B\nKYP/IT ESSEN/ PYTHON/ OTHERS 1 0614 020 - 08051116  A\nENVIRONMENTAL SCIENCE 0 10 -010 - 0408 -08  A\n-----------------------------------------------------------------------------------------------\nGRAND TOTAL 24 750 504\n-----------------------------------------------------------------------------------------------\nSGPA 7.25\n-----------------------------------------------------------------------------------------------\nREMARKS : First Class",
        "college": "Government Polytechnic, Bhojpur",
        "name": "SANOJ KUMAR",
        "roll": "211521823046",
        "branch": "18",
        "marks": 504,
        "remarks": "First Class",
        "theory": 186
    },
    {
        "text": " \n \nRegistration No : 1521823005\nRoll No         : 211521823005\n \nFollowing are the marks obtained by VAISHNAVI  KUMARI\nof Government Polytechnic, Bhojpur\nat Semester II of Diploma in Computer Science & Engineering\nExamination 2024 (EVEN) held in the month of JUL, 2024\n \n \nResult Published On: 30/07/2024\nSTATE BOARD OF TECHNICAL EDUCATION\nBIHAR\n-----------------------------------------------------------------------------------------------\nSUBJECT  FULL MARKS PASS MARKS MARKS OBTAINED\nNAME OF SUBJECTS CREDITS INTFINTOTAL FINTOTAL INT FIN TOTAL GRADE\n-----------------------------------------------------------------------------------------------\nTHEORY PAPERS\nMATHEMATICS-II 4 3070 100 28 40273158  D\nAPPLIED PHYSICS-II 3 3070 100 28 40183957  D\nINTRODUCTION TO IT SYSTEMS 2 3070 100 28 40245377  B\nFUNDA OF ELECT AND EC ENGG 3 3070 100 28 40235376  B\nENGG. MECHANICS 3 3070 100 28 40265278  B\n-----------------------------------------------------------------------------------------------\nPRACTICAL PAPERS\nAPPLIED PHYSICS LAB-II 1 1535 050 - 20123143  A\nINTRODUCTION TO IT SYSTEM LAB 2 1535 050 - 20143347  A+\nFUNDA OF ELECT AND EC ENGG LAB 1 1535 050 - 20133043  A\nENGG. MECHANICS LAB 2 1535 050 - 20143448  A+\n-----------------------------------------------------------------------------------------------\nTERM WORK PAPERS\nC.U MOOCS/ SWAYAM/ ETC/ OTHERS 2 0614 020 - 08061218  A+\nKYP/IT ESSEN/ PYTHON/ OTHERS 1 0614 020 - 08061319  A+\nENVIRONMENTAL SCIENCE 0 10 -010 - 0410 -10  A+\n-----------------------------------------------------------------------------------------------\nGRAND TOTAL 24 750 574\n-----------------------------------------------------------------------------------------------\nSGPA 8.08\n-----------------------------------------------------------------------------------------------\nREMARKS : First Class with Distinction",
        "college": "Government Polytechnic, Bhojpur",
        "name": "VAISHNAVI KUMARI",
        "roll": "211521823005",
        "branch": "18",
        "marks": 574,
        "remarks": "First Class with Distinction",
        "theory": 228
    },
    {
        "text": " \n \nRegistration No : 1521823041\nRoll No         : 211521823041\n \nFollowing are the marks obtained by ASHISH  RANJAN\nof Government Polytechnic, Bhojpur\nat Semester II of Diploma in Computer Science & Engineering\nExamination 2024 (EVEN) held in the month of JUL, 2024\n \n \nResult Published On: 30/07/2024\nSTATE BOARD OF TECHNICAL EDUCATION\nBIHAR\n-----------------------------------------------------------------------------------------------\nSUBJECT  FULL MARKS PASS MARKS MARKS OBTAINED\nNAME OF SUBJECTS CREDITS INTFINTOTAL FINTOTAL INT FIN TOTAL GRADE\n-----------------------------------------------------------------------------------------------\nTHEORY PAPERS\nMATHEMATICS-II 4 3070 100 28 40233053  D\nAPPLIED PHYSICS-II 3 3070 100 28 40162844  E\nINTRODUCTION TO IT SYSTEMS 2 3070 100 28 40193554  D\nFUNDA OF ELECT AND EC ENGG 3 3070 100 28 40152843  E\nENGG. MECHANICS 3 3070 100 28 40213152  D\n-----------------------------------------------------------------------------------------------\nPRACTICAL PAPERS\nAPPLIED PHYSICS LAB-II 1 1535 050 - 20103141  A\nINTRODUCTION TO IT SYSTEM LAB 2 1535 050 - 20113041  A\nFUNDA OF ELECT AND EC ENGG LAB 1 1535 050 - 20133144  A\nENGG. MECHANICS LAB 2 1535 050 - 20133245  A+\n-----------------------------------------------------------------------------------------------\nTERM WORK PAPERS\nC.U MOOCS/ SWAYAM/ ETC/ OTHERS 2 0614 020 - 08041115  B\nKYP/IT ESSEN/ PYTHON/ OTHERS 1 0614 020 - 08041014  B\nENVIRONMENTAL SCIENCE 0 10 -010 - 0410 -10  A+\n-----------------------------------------------------------------------------------------------\nGRAND TOTAL 24 750 456\n-----------------------------------------------------------------------------------------------\nSGPA 6.83\n-----------------------------------------------------------------------------------------------\nREMARKS : First Class",
        "college": "Government Polytechnic, Bhojpur",
        "name": "ASHISH RANJAN",
        "roll": "211521823041",
        "branch": "18",
        "marks": 456,
        "remarks": "First Class",
        "theory": 152
    },
    {
        "text": " \n \nRegistration No : 1521823006\nRoll No         : 211521823006\n \nFollowing are the marks obtained by HARSHVARDHAN  ANAND\nof Government Polytechnic, Bhojpur\nat Semester II of Diploma in Computer Science & Engineering\nExamination 2024 (EVEN) held in the month of JUL, 2024\n \n \nResult Published On: 30/07/2024\nSTATE BOARD OF TECHNICAL EDUCATION\nBIHAR\n-----------------------------------------------------------------------------------------------\nSUBJECT  FULL MARKS PASS MARKS MARKS OBTAINED\nNAME OF SUBJECTS CREDITS INTFINTOTAL FINTOTAL INT FIN TOTAL GRADE\n-----------------------------------------------------------------------------------------------\nTHEORY PAPERS\nMATHEMATICS-II 4 3070 100 28 40251540  E\nAPPLIED PHYSICS-II 3 3070 100 28 40133144  E\nINTRODUCTION TO IT SYSTEMS 2 3070 100 28 40122840  E\nFUNDA OF ELECT AND EC ENGG 3 3070 100 28 40151631  F\nENGG. MECHANICS 3 3070 100 28 40143650  D\n-----------------------------------------------------------------------------------------------\nPRACTICAL PAPERS\nAPPLIED PHYSICS LAB-II 1 1535 050 - 20102939  B\nINTRODUCTION TO IT SYSTEM LAB 2 1535 050 - 20113041  A\nFUNDA OF ELECT AND EC ENGG LAB 1 1535 050 - 20112839  B\nENGG. MECHANICS LAB 2 1535 050 - 20133245  A+\n-----------------------------------------------------------------------------------------------\nTERM WORK PAPERS\nC.U MOOCS/ SWAYAM/ ETC/ OTHERS 2 0614 020 - 08041014  B\nKYP/IT ESSEN/ PYTHON/ OTHERS 1 0614 020 - 08040610  D\nENVIRONMENTAL SCIENCE 0 10 -010 - 0408 -08  A\n-----------------------------------------------------------------------------------------------\nGRAND TOTAL 24 750 401\n-----------------------------------------------------------------------------------------------\nSGPA \n-----------------------------------------------------------------------------------------------\nREMARKS : Carry in - MATHEMATICS-II\n FUNDA OF ELECT AND EC ENGG",
        "college": "Government Polytechnic, Bhojpur",
        "name": "HARSHVARDHAN ANAND",
        "roll": "211521823006",
        "branch": "18",
        "marks": 401,
        "remarks": "Carry in - MATHEMATICS-II",
        "theory": 126
    },
    {
        "text": " \n \nRegistration No : 1521823049\nRoll No         : 211521823049\n \nFollowing are the marks obtained by RAVI  KUMAR\nof Government Polytechnic, Bhojpur\nat Semester II of Diploma in Computer Science & Engineering\nExamination 2024 (EVEN) held in the month of JUL, 2024\n \n \nResult Published On: 30/07/2024\nSTATE BOARD OF TECHNICAL EDUCATION\nBIHAR\n-----------------------------------------------------------------------------------------------\nSUBJECT  FULL MARKS PASS MARKS MARKS OBTAINED\nNAME OF SUBJECTS CREDITS INTFINTOTAL FINTOTAL INT FIN TOTAL GRADE\n-----------------------------------------------------------------------------------------------\nTHEORY PAPERS\nMATHEMATICS-II 4 3070 100 28 40271946  E\nAPPLIED PHYSICS-II 3 3070 100 28 40122840  E\nINTRODUCTION TO IT SYSTEMS 2 3070 100 28 40132841  E\nFUNDA OF ELECT AND EC ENGG 3 3070 100 28 40191231  F\nENGG. MECHANICS 3 3070 100 28 40133043  E\n-----------------------------------------------------------------------------------------------\nPRACTICAL PAPERS\nAPPLIED PHYSICS LAB-II 1 1535 050 - 20102838  B\nINTRODUCTION TO IT SYSTEM LAB 2 1535 050 - 20113041  A\nFUNDA OF ELECT AND EC ENGG LAB 1 1535 050 - 20123042  A\nENGG. MECHANICS LAB 2 1535 050 - 20103040  A\n-----------------------------------------------------------------------------------------------\nTERM WORK PAPERS\nC.U MOOCS/ SWAYAM/ ETC/ OTHERS 2 0614 020 - 08041014  B\nKYP/IT ESSEN/ PYTHON/ OTHERS 1 0614 020 - 08050712  C\nENVIRONMENTAL SCIENCE 0 10 -010 - 0407 -07  B\n-----------------------------------------------------------------------------------------------\nGRAND TOTAL 24 750 395\n-----------------------------------------------------------------------------------------------\nSGPA \n-----------------------------------------------------------------------------------------------\nREMARKS : Carry in - MATHEMATICS-II\n FUNDA OF ELECT AND EC ENGG",
        "college": "Government Polytechnic, Bhojpur",
        "name": "RAVI KUMAR",
        "roll": "211521823049",
        "branch": "18",
        "marks": 395,
        "remarks": "Carry in - MATHEMATICS-II",
        "theory": 117
    },
    {
        "text": " \n \nRegistration No : 1521823033\nRoll No         : 211521823033\n \nFollowing are the marks obtained by NITISH  KUMAR\nof Government Polytechnic, Bhojpur\nat Semester II of Diploma in Computer Science & Engineering\nExamination 2024 (EVEN) held in the month of JUL, 2024\n \n \nResult Published On: 30/07/2024\nSTATE BOARD OF TECHNICAL EDUCATION\nBIHAR\n-----------------------------------------------------------------------------------------------\nSUBJECT  FULL MARKS PASS MARKS MARKS OBTAINED\nNAME OF SUBJECTS CREDITS INTFINTOTAL FINTOTAL INT FIN TOTAL GRADE\n-----------------------------------------------------------------------------------------------\nTHEORY PAPERS\nMATHEMATICS-II 4 3070 100 28 40231639  F\nAPPLIED PHYSICS-II 3 3070 100 28 40271340  E\nINTRODUCTION TO IT SYSTEMS 2 3070 100 28 40173047  E\nFUNDA OF ELECT AND EC ENGG 3 3070 100 28 40182846  E\nENGG. MECHANICS 3 3070 100 28 40132336  F\n-----------------------------------------------------------------------------------------------\nPRACTICAL PAPERS\nAPPLIED PHYSICS LAB-II 1 1535 050 - 20142842  A\nINTRODUCTION TO IT SYSTEM LAB 2 1535 050 - 20123042  A\nFUNDA OF ELECT AND EC ENGG LAB 1 1535 050 - 20123042  A\nENGG. MECHANICS LAB 2 1535 050 - 20113243  A\n-----------------------------------------------------------------------------------------------\nTERM WORK PAPERS\nC.U MOOCS/ SWAYAM/ ETC/ OTHERS 2 0614 020 - 08061016  A\nKYP/IT ESSEN/ PYTHON/ OTHERS 1 0614 020 - 08051116  A\nENVIRONMENTAL SCIENCE 0 10 -010 - 0408 -08  A\n-----------------------------------------------------------------------------------------------\nGRAND TOTAL 24 750 417\n-----------------------------------------------------------------------------------------------\nSGPA \n-----------------------------------------------------------------------------------------------\nREMARKS : Fail",
        "college": "Government Polytechnic, Bhojpur",
        "name": "NITISH KUMAR",
        "roll": "211521823033",
        "branch": "18",
        "marks": 417,
        "remarks": "Fail",
        "theory": 110
    },
    {
        "text": " \n \nRegistration No : 1521823045\nRoll No         : 211521823045\n \nFollowing are the marks obtained by SHEKHAR  SINGH\nof Government Polytechnic, Bhojpur\nat Semester II of Diploma in Computer Science & Engineering\nExamination 2024 (EVEN) held in the month of JUL, 2024\n \n \nResult Published On: 30/07/2024\nSTATE BOARD OF TECHNICAL EDUCATION\nBIHAR\n-----------------------------------------------------------------------------------------------\nSUBJECT  FULL MARKS PASS MARKS MARKS OBTAINED\nNAME OF SUBJECTS CREDITS INTFINTOTAL FINTOTAL INT FIN TOTAL GRADE\n-----------------------------------------------------------------------------------------------\nTHEORY PAPERS\nMATHEMATICS-II 4 3070 100 28 402425+352  D\nAPPLIED PHYSICS-II 3 3070 100 28 402539-361  C\nINTRODUCTION TO IT SYSTEMS 2 3070 100 28 40173855  D\nFUNDA OF ELECT AND EC ENGG 3 3070 100 28 40182846  E\nENGG. MECHANICS 3 3070 100 28 40193150  D\n-----------------------------------------------------------------------------------------------\nPRACTICAL PAPERS\nAPPLIED PHYSICS LAB-II 1 1535 050 - 20133144  A\nINTRODUCTION TO IT SYSTEM LAB 2 1535 050 - 20133144  A\nFUNDA OF ELECT AND EC ENGG LAB 1 1535 050 - 20123042  A\nENGG. MECHANICS LAB 2 1535 050 - 20103141  A\n-----------------------------------------------------------------------------------------------\nTERM WORK PAPERS\nC.U MOOCS/ SWAYAM/ ETC/ OTHERS 2 0614 020 - 08041014  B\nKYP/IT ESSEN/ PYTHON/ OTHERS 1 0614 020 - 08041115  B\nENVIRONMENTAL SCIENCE 0 10 -010 - 0408 -08  A\n-----------------------------------------------------------------------------------------------\nGRAND TOTAL 24 750 472\n-----------------------------------------------------------------------------------------------\nSGPA 7.0\n-----------------------------------------------------------------------------------------------\nREMARKS : First Class (U/R)",
        "college": "Government Polytechnic, Bhojpur",
        "name": "SHEKHAR SINGH",
        "roll": "211521823045",
        "branch": "18",
        "marks": 472,
        "remarks": "First Class (U/R)",
        "theory": 161
    },
    {
        "text": " \n \nRegistration No : 1521823026\nRoll No         : 211521823026\n \nFollowing are the marks obtained by SALONI  KUMARI\nof Government Polytechnic, Bhojpur\nat Semester II of Diploma in Computer Science & Engineering\nExamination 2024 (EVEN) held in the month of JUL, 2024\n \n \nResult Published On: 30/07/2024\nSTATE BOARD OF TECHNICAL EDUCATION\nBIHAR\n-----------------------------------------------------------------------------------------------\nSUBJECT  FULL MARKS PASS MARKS MARKS OBTAINED\nNAME OF SUBJECTS CREDITS INTFINTOTAL FINTOTAL INT FIN TOTAL GRADE\n-----------------------------------------------------------------------------------------------\nTHEORY PAPERS\nMATHEMATICS-II 4 3070 100 28 40130518  F\nAPPLIED PHYSICS-II 3 3070 100 28 40142842  E\nINTRODUCTION TO IT SYSTEMS 2 3070 100 28 40132033  F\nFUNDA OF ELECT AND EC ENGG 3 3070 100 28 40182846  E\nENGG. MECHANICS 3 3070 100 28 40222042  E\n-----------------------------------------------------------------------------------------------\nPRACTICAL PAPERS\nAPPLIED PHYSICS LAB-II 1 1535 050 - 20112839  B\nINTRODUCTION TO IT SYSTEM LAB 2 1535 050 - 20133043  A\nFUNDA OF ELECT AND EC ENGG LAB 1 1535 050 - 20133245  A+\nENGG. MECHANICS LAB 2 1535 050 - 20143246  A+\n-----------------------------------------------------------------------------------------------\nTERM WORK PAPERS\nC.U MOOCS/ SWAYAM/ ETC/ OTHERS 2 0614 020 - 08041014  B\nKYP/IT ESSEN/ PYTHON/ OTHERS 1 0614 020 - 08041014  B\nENVIRONMENTAL SCIENCE 0 10 -010 - 0409 -09  A+\n-----------------------------------------------------------------------------------------------\nGRAND TOTAL 24 750 391\n-----------------------------------------------------------------------------------------------\nSGPA \n-----------------------------------------------------------------------------------------------\nREMARKS : Fail",
        "college": "Government Polytechnic, Bhojpur",
        "name": "SALONI KUMARI",
        "roll": "211521823026",
        "branch": "18",
        "marks": 391,
        "remarks": "Fail",
        "theory": 101
    },
    {
        "text": " \n \nRegistration No : 1521823035\nRoll No         : 211521823035\n \nFollowing are the marks obtained by RESHAM  KUMARI\nof Government Polytechnic, Bhojpur\nat Semester II of Diploma in Computer Science & Engineering\nExamination 2024 (EVEN) held in the month of JUL, 2024\n \n \nResult Published On: 30/07/2024\nSTATE BOARD OF TECHNICAL EDUCATION\nBIHAR\n-----------------------------------------------------------------------------------------------\nSUBJECT  FULL MARKS PASS MARKS MARKS OBTAINED\nNAME OF SUBJECTS CREDITS INTFINTOTAL FINTOTAL INT FIN TOTAL GRADE\n-----------------------------------------------------------------------------------------------\nTHEORY PAPERS\nMATHEMATICS-II 4 3070 100 28 4017 A17  F\nAPPLIED PHYSICS-II 3 3070 100 28 4007 A07  F\nINTRODUCTION TO IT SYSTEMS 2 3070 100 28 4015 A15  F\nFUNDA OF ELECT AND EC ENGG 3 3070 100 28 4020 A20  F\nENGG. MECHANICS 3 3070 100 28 4015 A15  F\n-----------------------------------------------------------------------------------------------\nPRACTICAL PAPERS\nAPPLIED PHYSICS LAB-II 1 1535 050 - 2012 A12  F\nINTRODUCTION TO IT SYSTEM LAB 2 1535 050 - 2012 A12  F\nFUNDA OF ELECT AND EC ENGG LAB 1 1535 050 - 2013 A13  F\nENGG. MECHANICS LAB 2 1535 050 - 2013 A13  F\n-----------------------------------------------------------------------------------------------\nTERM WORK PAPERS\nC.U MOOCS/ SWAYAM/ ETC/ OTHERS 2 0614 020 - 0804 A04  F\nKYP/IT ESSEN/ PYTHON/ OTHERS 1 0614 020 - 0805 A05  F\nENVIRONMENTAL SCIENCE 0 10 -010 - 0408 -08  A\n-----------------------------------------------------------------------------------------------\nGRAND TOTAL 24 750 141\n-----------------------------------------------------------------------------------------------\nSGPA \n-----------------------------------------------------------------------------------------------\nREMARKS : Fail in Term Work",
        "college": "Government Polytechnic, Bhojpur",
        "name": "RESHAM KUMARI",
        "roll": "211521823035",
        "branch": "18",
        "marks": 141,
        "remarks": "Fail in Term Work",
        "theory": 0
    },
    {
        "text": " \n \nRegistration No : 1521823052\nRoll No         : 211521823052\n \nFollowing are the marks obtained by BIBHAM  KUMAR\nof Government Polytechnic, Bhojpur\nat Semester II of Diploma in Computer Science & Engineering\nExamination 2024 (EVEN) held in the month of JUL, 2024\n \n \nResult Published On: 30/07/2024\nSTATE BOARD OF TECHNICAL EDUCATION\nBIHAR\n-----------------------------------------------------------------------------------------------\nSUBJECT  FULL MARKS PASS MARKS MARKS OBTAINED\nNAME OF SUBJECTS CREDITS INTFINTOTAL FINTOTAL INT FIN TOTAL GRADE\n-----------------------------------------------------------------------------------------------\nTHEORY PAPERS\nMATHEMATICS-II 4 3070 100 28 40293160  C\nAPPLIED PHYSICS-II 3 3070 100 28 40274269  C\nINTRODUCTION TO IT SYSTEMS 2 3070 100 28 40225072  B\nFUNDA OF ELECT AND EC ENGG 3 3070 100 28 40223860  C\nENGG. MECHANICS 3 3070 100 28 40165672  B\n-----------------------------------------------------------------------------------------------\nPRACTICAL PAPERS\nAPPLIED PHYSICS LAB-II 1 1535 050 - 20142943  A\nINTRODUCTION TO IT SYSTEM LAB 2 1535 050 - 20123042  A\nFUNDA OF ELECT AND EC ENGG LAB 1 1535 050 - 20132942  A\nENGG. MECHANICS LAB 2 1535 050 - 20123244  A\n-----------------------------------------------------------------------------------------------\nTERM WORK PAPERS\nC.U MOOCS/ SWAYAM/ ETC/ OTHERS 2 0614 020 - 08041216  A\nKYP/IT ESSEN/ PYTHON/ OTHERS 1 0614 020 - 08051217  A\nENVIRONMENTAL SCIENCE 0 10 -010 - 0410 -10  A+\n-----------------------------------------------------------------------------------------------\nGRAND TOTAL 24 750 547\n-----------------------------------------------------------------------------------------------\nSGPA 7.96\n-----------------------------------------------------------------------------------------------\nREMARKS : First Class",
        "college": "Government Polytechnic, Bhojpur",
        "name": "BIBHAM KUMAR",
        "roll": "211521823052",
        "branch": "18",
        "marks": 547,
        "remarks": "First Class",
        "theory": 217
    },
    {
        "text": " \n \nRegistration No : 1521823013\nRoll No         : 211521823013\n \nFollowing are the marks obtained by VISHWAS KUMAR RANJAN\nof Government Polytechnic, Bhojpur\nat Semester II of Diploma in Computer Science & Engineering\nExamination 2024 (EVEN) held in the month of JUL, 2024\n \n \nResult Published On: 30/07/2024\nSTATE BOARD OF TECHNICAL EDUCATION\nBIHAR\n-----------------------------------------------------------------------------------------------\nSUBJECT  FULL MARKS PASS MARKS MARKS OBTAINED\nNAME OF SUBJECTS CREDITS INTFINTOTAL FINTOTAL INT FIN TOTAL GRADE\n-----------------------------------------------------------------------------------------------\nTHEORY PAPERS\nMATHEMATICS-II 4 3070 100 28 40292857  D\nAPPLIED PHYSICS-II 3 3070 100 28 40243559  D\nINTRODUCTION TO IT SYSTEMS 2 3070 100 28 40244670  B\nFUNDA OF ELECT AND EC ENGG 3 3070 100 28 40223153  D\nENGG. MECHANICS 3 3070 100 28 40212041  E\n-----------------------------------------------------------------------------------------------\nPRACTICAL PAPERS\nAPPLIED PHYSICS LAB-II 1 1535 050 - 20132942  A\nINTRODUCTION TO IT SYSTEM LAB 2 1535 050 - 20133346  A+\nFUNDA OF ELECT AND EC ENGG LAB 1 1535 050 - 20133144  A\nENGG. MECHANICS LAB 2 1535 050 - 20143347  A+\n-----------------------------------------------------------------------------------------------\nTERM WORK PAPERS\nC.U MOOCS/ SWAYAM/ ETC/ OTHERS 2 0614 020 - 08051217  A\nKYP/IT ESSEN/ PYTHON/ OTHERS 1 0614 020 - 08061016  A\nENVIRONMENTAL SCIENCE 0 10 -010 - 0410 -10  A+\n-----------------------------------------------------------------------------------------------\nGRAND TOTAL 24 750 502\n-----------------------------------------------------------------------------------------------\nSGPA \n-----------------------------------------------------------------------------------------------\nREMARKS : Carry in - ENGG. MECHANICS",
        "college": "Government Polytechnic, Bhojpur",
        "name": "VISHWAS KUMAR RANJAN",
        "roll": "211521823013",
        "branch": "18",
        "marks": 502,
        "remarks": "Carry in - ENGG. MECHANICS",
        "theory": 160
    },
    {
        "text": " \n \nRegistration No : 1521823039\nRoll No         : 211521823039\n \nFollowing are the marks obtained by SHIVAM  KUMAR\nof Government Polytechnic, Bhojpur\nat Semester II of Diploma in Computer Science & Engineering\nExamination 2024 (EVEN) held in the month of JUL, 2024\n \n \nResult Published On: 30/07/2024\nSTATE BOARD OF TECHNICAL EDUCATION\nBIHAR\n-----------------------------------------------------------------------------------------------\nSUBJECT  FULL MARKS PASS MARKS MARKS OBTAINED\nNAME OF SUBJECTS CREDITS INTFINTOTAL FINTOTAL INT FIN TOTAL GRADE\n-----------------------------------------------------------------------------------------------\nTHEORY PAPERS\nMATHEMATICS-II 4 3070 100 28 40200828  F\nAPPLIED PHYSICS-II 3 3070 100 28 40191332  F\nINTRODUCTION TO IT SYSTEMS 2 3070 100 28 40121729  F\nFUNDA OF ELECT AND EC ENGG 3 3070 100 28 40161026  F\nENGG. MECHANICS 3 3070 100 28 40133447  E\n-----------------------------------------------------------------------------------------------\nPRACTICAL PAPERS\nAPPLIED PHYSICS LAB-II 1 1535 050 - 20123143  A\nINTRODUCTION TO IT SYSTEM LAB 2 1535 050 - 20123143  A\nFUNDA OF ELECT AND EC ENGG LAB 1 1535 050 - 20133144  A\nENGG. MECHANICS LAB 2 1535 050 - 20113041  A\n-----------------------------------------------------------------------------------------------\nTERM WORK PAPERS\nC.U MOOCS/ SWAYAM/ ETC/ OTHERS 2 0614 020 - 08041014  B\nKYP/IT ESSEN/ PYTHON/ OTHERS 1 0614 020 - 08051116  A\nENVIRONMENTAL SCIENCE 0 10 -010 - 0408 -08  A\n-----------------------------------------------------------------------------------------------\nGRAND TOTAL 24 750 371\n-----------------------------------------------------------------------------------------------\nSGPA \n-----------------------------------------------------------------------------------------------\nREMARKS : Fail",
        "college": "Government Polytechnic, Bhojpur",
        "name": "SHIVAM KUMAR",
        "roll": "211521823039",
        "branch": "18",
        "marks": 371,
        "remarks": "Fail",
        "theory": 82
    },
    {
        "text": " \n \nRegistration No : 1522523047\nRoll No         : 211522523047\n \nFollowing are the marks obtained by SNEHAL  CHANDRA\nof Government Polytechnic, Bhojpur\nat Semester II of Diploma in Mechanical Engineering\nExamination 2024 (EVEN) held in the month of JUL, 2024\n \n \nResult Published On: 30/07/2024\nSTATE BOARD OF TECHNICAL EDUCATION\nBIHAR\n-----------------------------------------------------------------------------------------------\nSUBJECT  FULL MARKS PASS MARKS MARKS OBTAINED\nNAME OF SUBJECTS CREDITS INTFINTOTAL FINTOTAL INT FIN TOTAL GRADE\n-----------------------------------------------------------------------------------------------\nTHEORY PAPERS\nMATHEMATICS-II 4 3070 100 28 40220830  F\nAPPLIED PHYSICS-II 3 3070 100 28 40163955  D\nINTRODUCTION TO IT SYSTEMS 2 3070 100 28 40124961  C\nFUNDA OF ELECT AND EC ENGG 3 3070 100 28 40171734  F\nENGG. MECHANICS 3 3070 100 28 40163248  E\n-----------------------------------------------------------------------------------------------\nPRACTICAL PAPERS\nAPPLIED PHYSICS LAB-II 1 1535 050 - 20113142  A\nINTRODUCTION TO IT SYSTEM LAB 2 1535 050 - 20113142  A\nFUNDA OF ELECT AND EC ENGG LAB 1 1535 050 - 20123345  A+\nENGG. MECHANICS LAB 2 1535 050 - 20103040  A\n-----------------------------------------------------------------------------------------------\nTERM WORK PAPERS\nC.U MOOCS/ SWAYAM/ ETC/ OTHERS 2 0614 020 - 08041216  A\nKYP/IT ESSEN/ PYTHON/ OTHERS 1 0614 020 - 08061117  A\nENVIRONMENTAL SCIENCE 0 10 -010 - 0408 -08  A\n-----------------------------------------------------------------------------------------------\nGRAND TOTAL 24 750 438\n-----------------------------------------------------------------------------------------------\nSGPA \n-----------------------------------------------------------------------------------------------\nREMARKS : Carry in - MATHEMATICS-II\n FUNDA OF ELECT AND EC ENGG",
        "college": "Government Polytechnic, Bhojpur",
        "name": "SNEHAL CHANDRA",
        "roll": "211522523047",
        "branch": "25",
        "marks": 438,
        "remarks": "Carry in - MATHEMATICS-II",
        "theory": 145
    },
    {
        "text": " \n \nRegistration No : 1522523009\nRoll No         : 211522523009\n \nFollowing are the marks obtained by GAURAV  PASWAN\nof Government Polytechnic, Bhojpur\nat Semester II of Diploma in Mechanical Engineering\nExamination 2024 (EVEN) held in the month of JUL, 2024\n \n \nResult Published On: 30/07/2024\nSTATE BOARD OF TECHNICAL EDUCATION\nBIHAR\n-----------------------------------------------------------------------------------------------\nSUBJECT  FULL MARKS PASS MARKS MARKS OBTAINED\nNAME OF SUBJECTS CREDITS INTFINTOTAL FINTOTAL INT FIN TOTAL GRADE\n-----------------------------------------------------------------------------------------------\nTHEORY PAPERS\nMATHEMATICS-II 4 3070 100 28 40241640  E\nAPPLIED PHYSICS-II 3 3070 100 28 40122840  E\nINTRODUCTION TO IT SYSTEMS 2 3070 100 28 40123244  E\nFUNDA OF ELECT AND EC ENGG 3 3070 100 28 40162945  E\nENGG. MECHANICS 3 3070 100 28 40133952  D\n-----------------------------------------------------------------------------------------------\nPRACTICAL PAPERS\nAPPLIED PHYSICS LAB-II 1 1535 050 - 20103141  A\nINTRODUCTION TO IT SYSTEM LAB 2 1535 050 - 20123042  A\nFUNDA OF ELECT AND EC ENGG LAB 1 1535 050 - 20133346  A+\nENGG. MECHANICS LAB 2 1535 050 - 20123244  A\n-----------------------------------------------------------------------------------------------\nTERM WORK PAPERS\nC.U MOOCS/ SWAYAM/ ETC/ OTHERS 2 0614 020 - 08041014  B\nKYP/IT ESSEN/ PYTHON/ OTHERS 1 0614 020 - 08041115  B\nENVIRONMENTAL SCIENCE 0 10 -010 - 0408 -08  A\n-----------------------------------------------------------------------------------------------\nGRAND TOTAL 24 750 431\n-----------------------------------------------------------------------------------------------\nSGPA \n-----------------------------------------------------------------------------------------------\nREMARKS : Carry in - MATHEMATICS-II",
        "college": "Government Polytechnic, Bhojpur",
        "name": "GAURAV PASWAN",
        "roll": "211522523009",
        "branch": "25",
        "marks": 431,
        "remarks": "Carry in - MATHEMATICS-II",
        "theory": 144
    },
    {
        "text": " \n \nRegistration No : 1522523006\nRoll No         : 211522523006\n \nFollowing are the marks obtained by NAVIN  KUMAR\nof Government Polytechnic, Bhojpur\nat Semester II of Diploma in Mechanical Engineering\nExamination 2024 (EVEN) held in the month of JUL, 2024\n \n \nResult Published On: 30/07/2024\nSTATE BOARD OF TECHNICAL EDUCATION\nBIHAR\n-----------------------------------------------------------------------------------------------\nSUBJECT  FULL MARKS PASS MARKS MARKS OBTAINED\nNAME OF SUBJECTS CREDITS INTFINTOTAL FINTOTAL INT FIN TOTAL GRADE\n-----------------------------------------------------------------------------------------------\nTHEORY PAPERS\nMATHEMATICS-II 4 3070 100 28 40200828  F\nAPPLIED PHYSICS-II 3 3070 100 28 40122840  E\nINTRODUCTION TO IT SYSTEMS 2 3070 100 28 40184866  C\nFUNDA OF ELECT AND EC ENGG 3 3070 100 28 40162844  E\nENGG. MECHANICS 3 3070 100 28 40163147  E\n-----------------------------------------------------------------------------------------------\nPRACTICAL PAPERS\nAPPLIED PHYSICS LAB-II 1 1535 050 - 20142842  A\nINTRODUCTION TO IT SYSTEM LAB 2 1535 050 - 20123143  A\nFUNDA OF ELECT AND EC ENGG LAB 1 1535 050 - 20123143  A\nENGG. MECHANICS LAB 2 1535 050 - 20113142  A\n-----------------------------------------------------------------------------------------------\nTERM WORK PAPERS\nC.U MOOCS/ SWAYAM/ ETC/ OTHERS 2 0614 020 - 08061117  A\nKYP/IT ESSEN/ PYTHON/ OTHERS 1 0614 020 - 08051015  B\nENVIRONMENTAL SCIENCE 0 10 -010 - 0408 -08  A\n-----------------------------------------------------------------------------------------------\nGRAND TOTAL 24 750 435\n-----------------------------------------------------------------------------------------------\nSGPA \n-----------------------------------------------------------------------------------------------\nREMARKS : Carry in - MATHEMATICS-II",
        "college": "Government Polytechnic, Bhojpur",
        "name": "NAVIN KUMAR",
        "roll": "211522523006",
        "branch": "25",
        "marks": 435,
        "remarks": "Carry in - MATHEMATICS-II",
        "theory": 143
    },
    {
        "text": " \n \nRegistration No : 1522523053\nRoll No         : 211522523053\n \nFollowing are the marks obtained by RUPESH  KUMAR\nof Government Polytechnic, Bhojpur\nat Semester II of Diploma in Mechanical Engineering\nExamination 2024 (EVEN) held in the month of JUL, 2024\n \n \nResult Published On: 30/07/2024\nSTATE BOARD OF TECHNICAL EDUCATION\nBIHAR\n-----------------------------------------------------------------------------------------------\nSUBJECT  FULL MARKS PASS MARKS MARKS OBTAINED\nNAME OF SUBJECTS CREDITS INTFINTOTAL FINTOTAL INT FIN TOTAL GRADE\n-----------------------------------------------------------------------------------------------\nTHEORY PAPERS\nMATHEMATICS-II 4 3070 100 28 40274572  B\nAPPLIED PHYSICS-II 3 3070 100 28 40255378  B\nINTRODUCTION TO IT SYSTEMS 2 3070 100 28 40205272  B\nFUNDA OF ELECT AND EC ENGG 3 3070 100 28 40233356  D\nENGG. MECHANICS 3 3070 100 28 40246488  A\n-----------------------------------------------------------------------------------------------\nPRACTICAL PAPERS\nAPPLIED PHYSICS LAB-II 1 1535 050 - 20133043  A\nINTRODUCTION TO IT SYSTEM LAB 2 1535 050 - 20133245  A+\nFUNDA OF ELECT AND EC ENGG LAB 1 1535 050 - 20133245  A+\nENGG. MECHANICS LAB 2 1535 050 - 20133447  A+\n-----------------------------------------------------------------------------------------------\nTERM WORK PAPERS\nC.U MOOCS/ SWAYAM/ ETC/ OTHERS 2 0614 020 - 08051015  B\nKYP/IT ESSEN/ PYTHON/ OTHERS 1 0614 020 - 08041014  B\nENVIRONMENTAL SCIENCE 0 10 -010 - 0410 -10  A+\n-----------------------------------------------------------------------------------------------\nGRAND TOTAL 24 750 585\n-----------------------------------------------------------------------------------------------\nSGPA 8.33\n-----------------------------------------------------------------------------------------------\nREMARKS : First Class with Distinction",
        "college": "Government Polytechnic, Bhojpur",
        "name": "RUPESH KUMAR",
        "roll": "211522523053",
        "branch": "25",
        "marks": 585,
        "remarks": "First Class with Distinction",
        "theory": 247
    },
    {
        "text": " \n \nRegistration No : 1522523051\nRoll No         : 211522523051\n \nFollowing are the marks obtained by SHIVAM  KUMAR\nof Government Polytechnic, Bhojpur\nat Semester II of Diploma in Mechanical Engineering\nExamination 2024 (EVEN) held in the month of JUL, 2024\n \n \nResult Published On: 30/07/2024\nSTATE BOARD OF TECHNICAL EDUCATION\nBIHAR\n-----------------------------------------------------------------------------------------------\nSUBJECT  FULL MARKS PASS MARKS MARKS OBTAINED\nNAME OF SUBJECTS CREDITS INTFINTOTAL FINTOTAL INT FIN TOTAL GRADE\n-----------------------------------------------------------------------------------------------\nTHEORY PAPERS\nMATHEMATICS-II 4 3070 100 28 40203555  D\nAPPLIED PHYSICS-II 3 3070 100 28 40194160  C\nINTRODUCTION TO IT SYSTEMS 2 3070 100 28 40134558  D\nFUNDA OF ELECT AND EC ENGG 3 3070 100 28 40182846  E\nENGG. MECHANICS 3 3070 100 28 40144862  C\n-----------------------------------------------------------------------------------------------\nPRACTICAL PAPERS\nAPPLIED PHYSICS LAB-II 1 1535 050 - 20123042  A\nINTRODUCTION TO IT SYSTEM LAB 2 1535 050 - 20133043  A\nFUNDA OF ELECT AND EC ENGG LAB 1 1535 050 - 20123345  A+\nENGG. MECHANICS LAB 2 1535 050 - 20103040  A\n-----------------------------------------------------------------------------------------------\nTERM WORK PAPERS\nC.U MOOCS/ SWAYAM/ ETC/ OTHERS 2 0614 020 - 08061117  A\nKYP/IT ESSEN/ PYTHON/ OTHERS 1 0614 020 - 08051015  B\nENVIRONMENTAL SCIENCE 0 10 -010 - 0408 -08  A\n-----------------------------------------------------------------------------------------------\nGRAND TOTAL 24 750 491\n-----------------------------------------------------------------------------------------------\nSGPA 7.25\n-----------------------------------------------------------------------------------------------\nREMARKS : First Class",
        "college": "Government Polytechnic, Bhojpur",
        "name": "SHIVAM KUMAR",
        "roll": "211522523051",
        "branch": "25",
        "marks": 491,
        "remarks": "First Class",
        "theory": 197
    },
    {
        "text": " \n \nRegistration No : 1522523002\nRoll No         : 211522523002\n \nFollowing are the marks obtained by DEEPAK KUMAR\nof Government Polytechnic, Bhojpur\nat Semester II of Diploma in Mechanical Engineering\nExamination 2024 (EVEN) held in the month of JUL, 2024\n \n \nResult Published On: 30/07/2024\nSTATE BOARD OF TECHNICAL EDUCATION\nBIHAR\n-----------------------------------------------------------------------------------------------\nSUBJECT  FULL MARKS PASS MARKS MARKS OBTAINED\nNAME OF SUBJECTS CREDITS INTFINTOTAL FINTOTAL INT FIN TOTAL GRADE\n-----------------------------------------------------------------------------------------------\nTHEORY PAPERS\nMATHEMATICS-II 4 3070 100 28 40203252  D\nAPPLIED PHYSICS-II 3 3070 100 28 40193958  D\nINTRODUCTION TO IT SYSTEMS 2 3070 100 28 40164258  D\nFUNDA OF ELECT AND EC ENGG 3 3070 100 28 40163652  D\nENGG. MECHANICS 3 3070 100 28 40175269  C\n-----------------------------------------------------------------------------------------------\nPRACTICAL PAPERS\nAPPLIED PHYSICS LAB-II 1 1535 050 - 20122941  A\nINTRODUCTION TO IT SYSTEM LAB 2 1535 050 - 20113243  A\nFUNDA OF ELECT AND EC ENGG LAB 1 1535 050 - 20133144  A\nENGG. MECHANICS LAB 2 1535 050 - 20103040  A\n-----------------------------------------------------------------------------------------------\nTERM WORK PAPERS\nC.U MOOCS/ SWAYAM/ ETC/ OTHERS 2 0614 020 - 08031215  B\nKYP/IT ESSEN/ PYTHON/ OTHERS 1 0614 020 - 08041115  B\nENVIRONMENTAL SCIENCE 0 10 -010 - 0408 -08  A\n-----------------------------------------------------------------------------------------------\nGRAND TOTAL 24 750 495\n-----------------------------------------------------------------------------------------------\nSGPA 7.12\n-----------------------------------------------------------------------------------------------\nREMARKS : First Class",
        "college": "Government Polytechnic, Bhojpur",
        "name": "DEEPAK KUMAR",
        "roll": "211522523002",
        "branch": "25",
        "marks": 495,
        "remarks": "First Class",
        "theory": 201
    },
    {
        "text": " \n \nRegistration No : 1522523054\nRoll No         : 211522523054\n \nFollowing are the marks obtained by PRIYANSHU  SINGH\nof Government Polytechnic, Bhojpur\nat Semester II of Diploma in Mechanical Engineering\nExamination 2024 (EVEN) held in the month of JUL, 2024\n \n \nResult Published On: 30/07/2024\nSTATE BOARD OF TECHNICAL EDUCATION\nBIHAR\n-----------------------------------------------------------------------------------------------\nSUBJECT  FULL MARKS PASS MARKS MARKS OBTAINED\nNAME OF SUBJECTS CREDITS INTFINTOTAL FINTOTAL INT FIN TOTAL GRADE\n-----------------------------------------------------------------------------------------------\nTHEORY PAPERS\nMATHEMATICS-II 4 3070 100 28 40241438  F\nAPPLIED PHYSICS-II 3 3070 100 28 40194564  C\nINTRODUCTION TO IT SYSTEMS 2 3070 100 28 40125264  C\nFUNDA OF ELECT AND EC ENGG 3 3070 100 28 40133043  E\nENGG. MECHANICS 3 3070 100 28 40175067  C\n-----------------------------------------------------------------------------------------------\nPRACTICAL PAPERS\nAPPLIED PHYSICS LAB-II 1 1535 050 - 20123143  A\nINTRODUCTION TO IT SYSTEM LAB 2 1535 050 - 20123143  A\nFUNDA OF ELECT AND EC ENGG LAB 1 1535 050 - 20133144  A\nENGG. MECHANICS LAB 2 1535 050 - 20103040  A\n-----------------------------------------------------------------------------------------------\nTERM WORK PAPERS\nC.U MOOCS/ SWAYAM/ ETC/ OTHERS 2 0614 020 - 08041115  B\nKYP/IT ESSEN/ PYTHON/ OTHERS 1 0614 020 - 08051116  A\nENVIRONMENTAL SCIENCE 0 10 -010 - 0408 -08  A\n-----------------------------------------------------------------------------------------------\nGRAND TOTAL 24 750 485\n-----------------------------------------------------------------------------------------------\nSGPA \n-----------------------------------------------------------------------------------------------\nREMARKS : Carry in - MATHEMATICS-II",
        "college": "Government Polytechnic, Bhojpur",
        "name": "PRIYANSHU SINGH",
        "roll": "211522523054",
        "branch": "25",
        "marks": 485,
        "remarks": "Carry in - MATHEMATICS-II",
        "theory": 191
    },
    {
        "text": " \n \nRegistration No : 1522523046\nRoll No         : 211522523046\n \nFollowing are the marks obtained by ANAND  KUMAR\nof Government Polytechnic, Bhojpur\nat Semester II of Diploma in Mechanical Engineering\nExamination 2024 (EVEN) held in the month of JUL, 2024\n \n \nResult Published On: 30/07/2024\nSTATE BOARD OF TECHNICAL EDUCATION\nBIHAR\n-----------------------------------------------------------------------------------------------\nSUBJECT  FULL MARKS PASS MARKS MARKS OBTAINED\nNAME OF SUBJECTS CREDITS INTFINTOTAL FINTOTAL INT FIN TOTAL GRADE\n-----------------------------------------------------------------------------------------------\nTHEORY PAPERS\nMATHEMATICS-II 4 3070 100 28 4022 A22  F\nAPPLIED PHYSICS-II 3 3070 100 28 40285179  B\nINTRODUCTION TO IT SYSTEMS 2 3070 100 28 40225274  B\nFUNDA OF ELECT AND EC ENGG 3 3070 100 28 40244872  B\nENGG. MECHANICS 3 3070 100 28 40236790  A+\n-----------------------------------------------------------------------------------------------\nPRACTICAL PAPERS\nAPPLIED PHYSICS LAB-II 1 1535 050 - 20133144  A\nINTRODUCTION TO IT SYSTEM LAB 2 1535 050 - 20123143  A\nFUNDA OF ELECT AND EC ENGG LAB 1 1535 050 - 20133245  A+\nENGG. MECHANICS LAB 2 1535 050 - 20123244  A\n-----------------------------------------------------------------------------------------------\nTERM WORK PAPERS\nC.U MOOCS/ SWAYAM/ ETC/ OTHERS 2 0614 020 - 08051015  B\nKYP/IT ESSEN/ PYTHON/ OTHERS 1 0614 020 - 08041216  A\nENVIRONMENTAL SCIENCE 0 10 -010 - 0410 -10  A+\n-----------------------------------------------------------------------------------------------\nGRAND TOTAL 24 750 554\n-----------------------------------------------------------------------------------------------\nSGPA \n-----------------------------------------------------------------------------------------------\nREMARKS : Carry in - MATHEMATICS-II",
        "college": "Government Polytechnic, Bhojpur",
        "name": "ANAND KUMAR",
        "roll": "211522523046",
        "branch": "25",
        "marks": 554,
        "remarks": "Carry in - MATHEMATICS-II",
        "theory": 218
    },
    {
        "text": " \n \nRegistration No : 1522523056\nRoll No         : 211522523056\n \nFollowing are the marks obtained by RAHUL  RAJ\nof Government Polytechnic, Bhojpur\nat Semester II of Diploma in Mechanical Engineering\nExamination 2024 (EVEN) held in the month of JUL, 2024\n \n \nResult Published On: 30/07/2024\nSTATE BOARD OF TECHNICAL EDUCATION\nBIHAR\n-----------------------------------------------------------------------------------------------\nSUBJECT  FULL MARKS PASS MARKS MARKS OBTAINED\nNAME OF SUBJECTS CREDITS INTFINTOTAL FINTOTAL INT FIN TOTAL GRADE\n-----------------------------------------------------------------------------------------------\nTHEORY PAPERS\nMATHEMATICS-II 4 3070 100 28 40231841  E\nAPPLIED PHYSICS-II 3 3070 100 28 4019 A19  F\nINTRODUCTION TO IT SYSTEMS 2 3070 100 28 40003131  F\nFUNDA OF ELECT AND EC ENGG 3 3070 100 28 40074148  E\nENGG. MECHANICS 3 3070 100 28 40043034  F\n-----------------------------------------------------------------------------------------------\nPRACTICAL PAPERS\nAPPLIED PHYSICS LAB-II 1 1535 050 - 20103040  A\nINTRODUCTION TO IT SYSTEM LAB 2 1535 050 - 20113041  A\nFUNDA OF ELECT AND EC ENGG LAB 1 1535 050 - 20123244  A\nENGG. MECHANICS LAB 2 1535 050 - 20103040  A\n-----------------------------------------------------------------------------------------------\nTERM WORK PAPERS\nC.U MOOCS/ SWAYAM/ ETC/ OTHERS 2 0614 020 - 08051116  A\nKYP/IT ESSEN/ PYTHON/ OTHERS 1 0614 020 - 08041216  A\nENVIRONMENTAL SCIENCE 0 10 -010 - 0408 -08  A\n-----------------------------------------------------------------------------------------------\nGRAND TOTAL 24 750 378\n-----------------------------------------------------------------------------------------------\nSGPA \n-----------------------------------------------------------------------------------------------\nREMARKS : Fail",
        "college": "Government Polytechnic, Bhojpur",
        "name": "RAHUL RAJ",
        "roll": "211522523056",
        "branch": "25",
        "marks": 378,
        "remarks": "Fail",
        "theory": 120
    },
    {
        "text": " \n \nRegistration No : 1522523028\nRoll No         : 211522523028\n \nFollowing are the marks obtained by PIYUSH  KUMAR\nof Government Polytechnic, Bhojpur\nat Semester II of Diploma in Mechanical Engineering\nExamination 2024 (EVEN) held in the month of JUL, 2024\n \n \nResult Published On: 30/07/2024\nSTATE BOARD OF TECHNICAL EDUCATION\nBIHAR\n-----------------------------------------------------------------------------------------------\nSUBJECT  FULL MARKS PASS MARKS MARKS OBTAINED\nNAME OF SUBJECTS CREDITS INTFINTOTAL FINTOTAL INT FIN TOTAL GRADE\n-----------------------------------------------------------------------------------------------\nTHEORY PAPERS\nMATHEMATICS-II 4 3070 100 28 40190423  F\nAPPLIED PHYSICS-II 3 3070 100 28 40193453  D\nINTRODUCTION TO IT SYSTEMS 2 3070 100 28 40144357  D\nFUNDA OF ELECT AND EC ENGG 3 3070 100 28 40172845  E\nENGG. MECHANICS 3 3070 100 28 40134053  D\n-----------------------------------------------------------------------------------------------\nPRACTICAL PAPERS\nAPPLIED PHYSICS LAB-II 1 1535 050 - 20143044  A\nINTRODUCTION TO IT SYSTEM LAB 2 1535 050 - 20133043  A\nFUNDA OF ELECT AND EC ENGG LAB 1 1535 050 - 20113243  A\nENGG. MECHANICS LAB 2 1535 050 - 20133144  A\n-----------------------------------------------------------------------------------------------\nTERM WORK PAPERS\nC.U MOOCS/ SWAYAM/ ETC/ OTHERS 2 0614 020 - 08061117  A\nKYP/IT ESSEN/ PYTHON/ OTHERS 1 0614 020 - 08051116  A\nENVIRONMENTAL SCIENCE 0 10 -010 - 0408 -08  A\n-----------------------------------------------------------------------------------------------\nGRAND TOTAL 24 750 446\n-----------------------------------------------------------------------------------------------\nSGPA \n-----------------------------------------------------------------------------------------------\nREMARKS : Carry in - MATHEMATICS-II",
        "college": "Government Polytechnic, Bhojpur",
        "name": "PIYUSH KUMAR",
        "roll": "211522523028",
        "branch": "25",
        "marks": 446,
        "remarks": "Carry in - MATHEMATICS-II",
        "theory": 149
    },
    {
        "text": " \n \nRegistration No : 1522523043\nRoll No         : 211522523043\n \nFollowing are the marks obtained by AKASH  KUMAR\nof Government Polytechnic, Bhojpur\nat Semester II of Diploma in Mechanical Engineering\nExamination 2024 (EVEN) held in the month of JUL, 2024\n \n \nResult Published On: 30/07/2024\nSTATE BOARD OF TECHNICAL EDUCATION\nBIHAR\n-----------------------------------------------------------------------------------------------\nSUBJECT  FULL MARKS PASS MARKS MARKS OBTAINED\nNAME OF SUBJECTS CREDITS INTFINTOTAL FINTOTAL INT FIN TOTAL GRADE\n-----------------------------------------------------------------------------------------------\nTHEORY PAPERS\nMATHEMATICS-II 4 3070 100 28 40252853  D\nAPPLIED PHYSICS-II 3 3070 100 28 40183250  D\nINTRODUCTION TO IT SYSTEMS 2 3070 100 28 40164561  C\nFUNDA OF ELECT AND EC ENGG 3 3070 100 28 40153449  E\nENGG. MECHANICS 3 3070 100 28 40143246  E\n-----------------------------------------------------------------------------------------------\nPRACTICAL PAPERS\nAPPLIED PHYSICS LAB-II 1 1535 050 - 20112839  B\nINTRODUCTION TO IT SYSTEM LAB 2 1535 050 - 20123143  A\nFUNDA OF ELECT AND EC ENGG LAB 1 1535 050 - 20123244  A\nENGG. MECHANICS LAB 2 1535 050 - 20113142  A\n-----------------------------------------------------------------------------------------------\nTERM WORK PAPERS\nC.U MOOCS/ SWAYAM/ ETC/ OTHERS 2 0614 020 - 08041115  B\nKYP/IT ESSEN/ PYTHON/ OTHERS 1 0614 020 - 08051217  A\nENVIRONMENTAL SCIENCE 0 10 -010 - 0410 -10  A+\n-----------------------------------------------------------------------------------------------\nGRAND TOTAL 24 750 469\n-----------------------------------------------------------------------------------------------\nSGPA 6.83\n-----------------------------------------------------------------------------------------------\nREMARKS : First Class",
        "college": "Government Polytechnic, Bhojpur",
        "name": "AKASH KUMAR",
        "roll": "211522523043",
        "branch": "25",
        "marks": 469,
        "remarks": "First Class",
        "theory": 171
    },
    {
        "text": " \n \nRegistration No : 1522523027\nRoll No         : 211522523027\n \nFollowing are the marks obtained by ADITYA KUMAR RAJAK\nof Government Polytechnic, Bhojpur\nat Semester II of Diploma in Mechanical Engineering\nExamination 2024 (EVEN) held in the month of JUL, 2024\n \n \nResult Published On: 30/07/2024\nSTATE BOARD OF TECHNICAL EDUCATION\nBIHAR\n-----------------------------------------------------------------------------------------------\nSUBJECT  FULL MARKS PASS MARKS MARKS OBTAINED\nNAME OF SUBJECTS CREDITS INTFINTOTAL FINTOTAL INT FIN TOTAL GRADE\n-----------------------------------------------------------------------------------------------\nTHEORY PAPERS\nMATHEMATICS-II 4 3070 100 28 40261137  F\nAPPLIED PHYSICS-II 3 3070 100 28 40122840  E\nINTRODUCTION TO IT SYSTEMS 2 3070 100 28 40123446  E\nFUNDA OF ELECT AND EC ENGG 3 3070 100 28 40193251  D\nENGG. MECHANICS 3 3070 100 28 40112839  F\n-----------------------------------------------------------------------------------------------\nPRACTICAL PAPERS\nAPPLIED PHYSICS LAB-II 1 1535 050 - 20122840  A\nINTRODUCTION TO IT SYSTEM LAB 2 1535 050 - 20123143  A\nFUNDA OF ELECT AND EC ENGG LAB 1 1535 050 - 20123446  A+\nENGG. MECHANICS LAB 2 1535 050 - 20103040  A\n-----------------------------------------------------------------------------------------------\nTERM WORK PAPERS\nC.U MOOCS/ SWAYAM/ ETC/ OTHERS 2 0614 020 - 08061117  A\nKYP/IT ESSEN/ PYTHON/ OTHERS 1 0614 020 - 08041216  A\nENVIRONMENTAL SCIENCE 0 10 -010 - 0408 -08  A\n-----------------------------------------------------------------------------------------------\nGRAND TOTAL 24 750 423\n-----------------------------------------------------------------------------------------------\nSGPA \n-----------------------------------------------------------------------------------------------\nREMARKS : Carry in - MATHEMATICS-II\n ENGG. MECHANICS",
        "college": "Government Polytechnic, Bhojpur",
        "name": "ADITYA KUMAR RAJAK",
        "roll": "211522523027",
        "branch": "25",
        "marks": 423,
        "remarks": "Carry in - MATHEMATICS-II",
        "theory": 133
    },
    {
        "text": " \n \nRegistration No : 1522523029\nRoll No         : 211522523029\n \nFollowing are the marks obtained by MD SHAMIM UDDIN\nof Government Polytechnic, Bhojpur\nat Semester II of Diploma in Mechanical Engineering\nExamination 2024 (EVEN) held in the month of JUL, 2024\n \n \nResult Published On: 30/07/2024\nSTATE BOARD OF TECHNICAL EDUCATION\nBIHAR\n-----------------------------------------------------------------------------------------------\nSUBJECT  FULL MARKS PASS MARKS MARKS OBTAINED\nNAME OF SUBJECTS CREDITS INTFINTOTAL FINTOTAL INT FIN TOTAL GRADE\n-----------------------------------------------------------------------------------------------\nTHEORY PAPERS\nMATHEMATICS-II 4 3070 100 28 40184563  C\nAPPLIED PHYSICS-II 3 3070 100 28 40153550  D\nINTRODUCTION TO IT SYSTEMS 2 3070 100 28 40103545  E\nFUNDA OF ELECT AND EC ENGG 3 3070 100 28 40161632  F\nENGG. MECHANICS 3 3070 100 28 40103141  E\n-----------------------------------------------------------------------------------------------\nPRACTICAL PAPERS\nAPPLIED PHYSICS LAB-II 1 1535 050 - 20102939  B\nINTRODUCTION TO IT SYSTEM LAB 2 1535 050 - 20123143  A\nFUNDA OF ELECT AND EC ENGG LAB 1 1535 050 - 20123345  A+\nENGG. MECHANICS LAB 2 1535 050 - 20103040  A\n-----------------------------------------------------------------------------------------------\nTERM WORK PAPERS\nC.U MOOCS/ SWAYAM/ ETC/ OTHERS 2 0614 020 - 08041014  B\nKYP/IT ESSEN/ PYTHON/ OTHERS 1 0614 020 - 08051015  B\nENVIRONMENTAL SCIENCE 0 10 -010 - 0407 -07  B\n-----------------------------------------------------------------------------------------------\nGRAND TOTAL 24 750 434\n-----------------------------------------------------------------------------------------------\nSGPA \n-----------------------------------------------------------------------------------------------\nREMARKS : Carry in - FUNDA OF ELECT AND EC ENGG",
        "college": "Government Polytechnic, Bhojpur",
        "name": "MD SHAMIM UDDIN",
        "roll": "211522523029",
        "branch": "25",
        "marks": 434,
        "remarks": "Carry in - FUNDA OF ELECT AND EC ENGG",
        "theory": 162
    },
    {
        "text": " \n \nRegistration No : 1522523016\nRoll No         : 211522523016\n \nFollowing are the marks obtained by VIVEK  KUMAR\nof Government Polytechnic, Bhojpur\nat Semester II of Diploma in Mechanical Engineering\nExamination 2024 (EVEN) held in the month of JUL, 2024\n \n \nResult Published On: 30/07/2024\nSTATE BOARD OF TECHNICAL EDUCATION\nBIHAR\n-----------------------------------------------------------------------------------------------\nSUBJECT  FULL MARKS PASS MARKS MARKS OBTAINED\nNAME OF SUBJECTS CREDITS INTFINTOTAL FINTOTAL INT FIN TOTAL GRADE\n-----------------------------------------------------------------------------------------------\nTHEORY PAPERS\nMATHEMATICS-II 4 3070 100 28 40234669  C\nAPPLIED PHYSICS-II 3 3070 100 28 40183755  D\nINTRODUCTION TO IT SYSTEMS 2 3070 100 28 40174360  C\nFUNDA OF ELECT AND EC ENGG 3 3070 100 28 40212950  D\nENGG. MECHANICS 3 3070 100 28 40144862  C\n-----------------------------------------------------------------------------------------------\nPRACTICAL PAPERS\nAPPLIED PHYSICS LAB-II 1 1535 050 - 20133144  A\nINTRODUCTION TO IT SYSTEM LAB 2 1535 050 - 20123244  A\nFUNDA OF ELECT AND EC ENGG LAB 1 1535 050 - 20143246  A+\nENGG. MECHANICS LAB 2 1535 050 - 20123244  A\n-----------------------------------------------------------------------------------------------\nTERM WORK PAPERS\nC.U MOOCS/ SWAYAM/ ETC/ OTHERS 2 0614 020 - 08051217  A\nKYP/IT ESSEN/ PYTHON/ OTHERS 1 0614 020 - 08051015  B\nENVIRONMENTAL SCIENCE 0 10 -010 - 0408 -08  A\n-----------------------------------------------------------------------------------------------\nGRAND TOTAL 24 750 514\n-----------------------------------------------------------------------------------------------\nSGPA 7.5\n-----------------------------------------------------------------------------------------------\nREMARKS : First Class",
        "college": "Government Polytechnic, Bhojpur",
        "name": "VIVEK KUMAR",
        "roll": "211522523016",
        "branch": "25",
        "marks": 514,
        "remarks": "First Class",
        "theory": 203
    },
    {
        "text": " \n \nRegistration No : 1522523015\nRoll No         : 211522523015\n \nFollowing are the marks obtained by SUMIT  KUMAR\nof Government Polytechnic, Bhojpur\nat Semester II of Diploma in Mechanical Engineering\nExamination 2024 (EVEN) held in the month of JUL, 2024\n \n \nResult Published On: 30/07/2024\nSTATE BOARD OF TECHNICAL EDUCATION\nBIHAR\n-----------------------------------------------------------------------------------------------\nSUBJECT  FULL MARKS PASS MARKS MARKS OBTAINED\nNAME OF SUBJECTS CREDITS INTFINTOTAL FINTOTAL INT FIN TOTAL GRADE\n-----------------------------------------------------------------------------------------------\nTHEORY PAPERS\nMATHEMATICS-II 4 3070 100 28 40234568  C\nAPPLIED PHYSICS-II 3 3070 100 28 40195473  B\nINTRODUCTION TO IT SYSTEMS 2 3070 100 28 40145064  C\nFUNDA OF ELECT AND EC ENGG 3 3070 100 28 40173047  E\nENGG. MECHANICS 3 3070 100 28 40135871  B\n-----------------------------------------------------------------------------------------------\nPRACTICAL PAPERS\nAPPLIED PHYSICS LAB-II 1 1535 050 - 20112435  B\nINTRODUCTION TO IT SYSTEM LAB 2 1535 050 - 20133144  A\nFUNDA OF ELECT AND EC ENGG LAB 1 1535 050 - 20123345  A+\nENGG. MECHANICS LAB 2 1535 050 - 20113142  A\n-----------------------------------------------------------------------------------------------\nTERM WORK PAPERS\nC.U MOOCS/ SWAYAM/ ETC/ OTHERS 2 0614 020 - 08051116  A\nKYP/IT ESSEN/ PYTHON/ OTHERS 1 0614 020 - 08041014  B\nENVIRONMENTAL SCIENCE 0 10 -010 - 0408 -08  A\n-----------------------------------------------------------------------------------------------\nGRAND TOTAL 24 750 527\n-----------------------------------------------------------------------------------------------\nSGPA 7.71\n-----------------------------------------------------------------------------------------------\nREMARKS : First Class",
        "college": "Government Polytechnic, Bhojpur",
        "name": "SUMIT KUMAR",
        "roll": "211522523015",
        "branch": "25",
        "marks": 527,
        "remarks": "First Class",
        "theory": 237
    },
    {
        "text": " \n \nRegistration No : 1522523020\nRoll No         : 211522523020\n \nFollowing are the marks obtained by ANKIT  KUMAR\nof Government Polytechnic, Bhojpur\nat Semester II of Diploma in Mechanical Engineering\nExamination 2024 (EVEN) held in the month of JUL, 2024\n \n \nResult Published On: 30/07/2024\nSTATE BOARD OF TECHNICAL EDUCATION\nBIHAR\n-----------------------------------------------------------------------------------------------\nSUBJECT  FULL MARKS PASS MARKS MARKS OBTAINED\nNAME OF SUBJECTS CREDITS INTFINTOTAL FINTOTAL INT FIN TOTAL GRADE\n-----------------------------------------------------------------------------------------------\nTHEORY PAPERS\nMATHEMATICS-II 4 3070 100 28 40262854  D\nAPPLIED PHYSICS-II 3 3070 100 28 40163147  E\nINTRODUCTION TO IT SYSTEMS 2 3070 100 28 40132942  E\nFUNDA OF ELECT AND EC ENGG 3 3070 100 28 40181836  F\nENGG. MECHANICS 3 3070 100 28 40142842  E\n-----------------------------------------------------------------------------------------------\nPRACTICAL PAPERS\nAPPLIED PHYSICS LAB-II 1 1535 050 - 20112839  B\nINTRODUCTION TO IT SYSTEM LAB 2 1535 050 - 20123244  A\nFUNDA OF ELECT AND EC ENGG LAB 1 1535 050 - 20143246  A+\nENGG. MECHANICS LAB 2 1535 050 - 20133144  A\n-----------------------------------------------------------------------------------------------\nTERM WORK PAPERS\nC.U MOOCS/ SWAYAM/ ETC/ OTHERS 2 0614 020 - 08061117  A\nKYP/IT ESSEN/ PYTHON/ OTHERS 1 0614 020 - 08061016  A\nENVIRONMENTAL SCIENCE 0 10 -010 - 0408 -08  A\n-----------------------------------------------------------------------------------------------\nGRAND TOTAL 24 750 435\n-----------------------------------------------------------------------------------------------\nSGPA \n-----------------------------------------------------------------------------------------------\nREMARKS : Carry in - FUNDA OF ELECT AND EC ENGG",
        "college": "Government Polytechnic, Bhojpur",
        "name": "ANKIT KUMAR",
        "roll": "211522523020",
        "branch": "25",
        "marks": 435,
        "remarks": "Carry in - FUNDA OF ELECT AND EC ENGG",
        "theory": 134
    },
    {
        "text": " \n \nRegistration No : 1522523055\nRoll No         : 211522523055\n \nFollowing are the marks obtained by JYOTI  KUMARI\nof Government Polytechnic, Bhojpur\nat Semester II of Diploma in Mechanical Engineering\nExamination 2024 (EVEN) held in the month of JUL, 2024\n \n \nResult Published On: 30/07/2024\nSTATE BOARD OF TECHNICAL EDUCATION\nBIHAR\n-----------------------------------------------------------------------------------------------\nSUBJECT  FULL MARKS PASS MARKS MARKS OBTAINED\nNAME OF SUBJECTS CREDITS INTFINTOTAL FINTOTAL INT FIN TOTAL GRADE\n-----------------------------------------------------------------------------------------------\nTHEORY PAPERS\nMATHEMATICS-II 4 3070 100 28 40251035  F\nAPPLIED PHYSICS-II 3 3070 100 28 40121628  F\nINTRODUCTION TO IT SYSTEMS 2 3070 100 28 40113748  E\nFUNDA OF ELECT AND EC ENGG 3 3070 100 28 40152944  E\nENGG. MECHANICS 3 3070 100 28 40103040  E\n-----------------------------------------------------------------------------------------------\nPRACTICAL PAPERS\nAPPLIED PHYSICS LAB-II 1 1535 050 - 20103040  A\nINTRODUCTION TO IT SYSTEM LAB 2 1535 050 - 20123143  A\nFUNDA OF ELECT AND EC ENGG LAB 1 1535 050 - 20123244  A\nENGG. MECHANICS LAB 2 1535 050 - 20103141  A\n-----------------------------------------------------------------------------------------------\nTERM WORK PAPERS\nC.U MOOCS/ SWAYAM/ ETC/ OTHERS 2 0614 020 - 08041216  A\nKYP/IT ESSEN/ PYTHON/ OTHERS 1 0614 020 - 08051217  A\nENVIRONMENTAL SCIENCE 0 10 -010 - 0408 -08  A\n-----------------------------------------------------------------------------------------------\nGRAND TOTAL 24 750 404\n-----------------------------------------------------------------------------------------------\nSGPA \n-----------------------------------------------------------------------------------------------\nREMARKS : Carry in - MATHEMATICS-II\n APPLIED PHYSICS-II",
        "college": "Government Polytechnic, Bhojpur",
        "name": "JYOTI KUMARI",
        "roll": "211522523055",
        "branch": "25",
        "marks": 404,
        "remarks": "Carry in - MATHEMATICS-II",
        "theory": 122
    },
    {
        "text": " \n \nRegistration No : 1522523004\nRoll No         : 211522523004\n \nFollowing are the marks obtained by MD IMRAN ANSARI\nof Government Polytechnic, Bhojpur\nat Semester II of Diploma in Mechanical Engineering\nExamination 2024 (EVEN) held in the month of JUL, 2024\n \n \nResult Published On: 30/07/2024\nSTATE BOARD OF TECHNICAL EDUCATION\nBIHAR\n-----------------------------------------------------------------------------------------------\nSUBJECT  FULL MARKS PASS MARKS MARKS OBTAINED\nNAME OF SUBJECTS CREDITS INTFINTOTAL FINTOTAL INT FIN TOTAL GRADE\n-----------------------------------------------------------------------------------------------\nTHEORY PAPERS\nMATHEMATICS-II 4 3070 100 28 40133346  E\nAPPLIED PHYSICS-II 3 3070 100 28 40053035  F\nINTRODUCTION TO IT SYSTEMS 2 3070 100 28 40143852  D\nFUNDA OF ELECT AND EC ENGG 3 3070 100 28 40164258  D\nENGG. MECHANICS 3 3070 100 28 40154156  D\n-----------------------------------------------------------------------------------------------\nPRACTICAL PAPERS\nAPPLIED PHYSICS LAB-II 1 1535 050 - 20103141  A\nINTRODUCTION TO IT SYSTEM LAB 2 1535 050 - 20123143  A\nFUNDA OF ELECT AND EC ENGG LAB 1 1535 050 - 20123345  A+\nENGG. MECHANICS LAB 2 1535 050 - 20103040  A\n-----------------------------------------------------------------------------------------------\nTERM WORK PAPERS\nC.U MOOCS/ SWAYAM/ ETC/ OTHERS 2 0614 020 - 08031215  B\nKYP/IT ESSEN/ PYTHON/ OTHERS 1 0614 020 - 08031114  B\nENVIRONMENTAL SCIENCE 0 10 -010 - 0408 -08  A\n-----------------------------------------------------------------------------------------------\nGRAND TOTAL 24 750 453\n-----------------------------------------------------------------------------------------------\nSGPA \n-----------------------------------------------------------------------------------------------\nREMARKS : Carry in - APPLIED PHYSICS-II",
        "college": "Government Polytechnic, Bhojpur",
        "name": "MD IMRAN ANSARI",
        "roll": "211522523004",
        "branch": "25",
        "marks": 453,
        "remarks": "Carry in - APPLIED PHYSICS-II",
        "theory": 184
    },
    {
        "text": " \n \nRegistration No : 1522523024\nRoll No         : 211522523024\n \nFollowing are the marks obtained by NISHANT  KUMAR\nof Government Polytechnic, Bhojpur\nat Semester II of Diploma in Mechanical Engineering\nExamination 2024 (EVEN) held in the month of JUL, 2024\n \n \nResult Published On: 30/07/2024\nSTATE BOARD OF TECHNICAL EDUCATION\nBIHAR\n-----------------------------------------------------------------------------------------------\nSUBJECT  FULL MARKS PASS MARKS MARKS OBTAINED\nNAME OF SUBJECTS CREDITS INTFINTOTAL FINTOTAL INT FIN TOTAL GRADE\n-----------------------------------------------------------------------------------------------\nTHEORY PAPERS\nMATHEMATICS-II 4 3070 100 28 40231841  E\nAPPLIED PHYSICS-II 3 3070 100 28 40193554  D\nINTRODUCTION TO IT SYSTEMS 2 3070 100 28 40163854  D\nFUNDA OF ELECT AND EC ENGG 3 3070 100 28 40182846  E\nENGG. MECHANICS 3 3070 100 28 40124153  D\n-----------------------------------------------------------------------------------------------\nPRACTICAL PAPERS\nAPPLIED PHYSICS LAB-II 1 1535 050 - 20132841  A\nINTRODUCTION TO IT SYSTEM LAB 2 1535 050 - 20113142  A\nFUNDA OF ELECT AND EC ENGG LAB 1 1535 050 - 20133346  A+\nENGG. MECHANICS LAB 2 1535 050 - 20113142  A\n-----------------------------------------------------------------------------------------------\nTERM WORK PAPERS\nC.U MOOCS/ SWAYAM/ ETC/ OTHERS 2 0614 020 - 08051015  B\nKYP/IT ESSEN/ PYTHON/ OTHERS 1 0614 020 - 08041216  A\nENVIRONMENTAL SCIENCE 0 10 -010 - 0407 -07  B\n-----------------------------------------------------------------------------------------------\nGRAND TOTAL 24 750 457\n-----------------------------------------------------------------------------------------------\nSGPA \n-----------------------------------------------------------------------------------------------\nREMARKS : Carry in - MATHEMATICS-II",
        "college": "Government Polytechnic, Bhojpur",
        "name": "NISHANT KUMAR",
        "roll": "211522523024",
        "branch": "25",
        "marks": 457,
        "remarks": "Carry in - MATHEMATICS-II",
        "theory": 160
    },
    {
        "text": " \n \nRegistration No : 1522523039\nRoll No         : 211522523039\n \nFollowing are the marks obtained by KHUSHI  KUMARI\nof Government Polytechnic, Bhojpur\nat Semester II of Diploma in Mechanical Engineering\nExamination 2024 (EVEN) held in the month of JUL, 2024\n \n \nResult Published On: 30/07/2024\nSTATE BOARD OF TECHNICAL EDUCATION\nBIHAR\n-----------------------------------------------------------------------------------------------\nSUBJECT  FULL MARKS PASS MARKS MARKS OBTAINED\nNAME OF SUBJECTS CREDITS INTFINTOTAL FINTOTAL INT FIN TOTAL GRADE\n-----------------------------------------------------------------------------------------------\nTHEORY PAPERS\nMATHEMATICS-II 4 3070 100 28 40212849  E\nAPPLIED PHYSICS-II 3 3070 100 28 40245276  B\nINTRODUCTION TO IT SYSTEMS 2 3070 100 28 40205474  B\nFUNDA OF ELECT AND EC ENGG 3 3070 100 28 40224567  C\nENGG. MECHANICS 3 3070 100 28 40233962  C\n-----------------------------------------------------------------------------------------------\nPRACTICAL PAPERS\nAPPLIED PHYSICS LAB-II 1 1535 050 - 20133144  A\nINTRODUCTION TO IT SYSTEM LAB 2 1535 050 - 20133245  A+\nFUNDA OF ELECT AND EC ENGG LAB 1 1535 050 - 20133346  A+\nENGG. MECHANICS LAB 2 1535 050 - 20143347  A+\n-----------------------------------------------------------------------------------------------\nTERM WORK PAPERS\nC.U MOOCS/ SWAYAM/ ETC/ OTHERS 2 0614 020 - 08051015  B\nKYP/IT ESSEN/ PYTHON/ OTHERS 1 0614 020 - 08051116  A\nENVIRONMENTAL SCIENCE 0 10 -010 - 0410 -10  A+\n-----------------------------------------------------------------------------------------------\nGRAND TOTAL 24 750 551\n-----------------------------------------------------------------------------------------------\nSGPA 7.75\n-----------------------------------------------------------------------------------------------\nREMARKS : First Class",
        "college": "Government Polytechnic, Bhojpur",
        "name": "KHUSHI KUMARI",
        "roll": "211522523039",
        "branch": "25",
        "marks": 551,
        "remarks": "First Class",
        "theory": 218
    },
    {
        "text": " \n \nRegistration No : 1522523005\nRoll No         : 211522523005\n \nFollowing are the marks obtained by SHREYA  RAJ\nof Government Polytechnic, Bhojpur\nat Semester II of Diploma in Mechanical Engineering\nExamination 2024 (EVEN) held in the month of JUL, 2024\n \n \nResult Published On: 30/07/2024\nSTATE BOARD OF TECHNICAL EDUCATION\nBIHAR\n-----------------------------------------------------------------------------------------------\nSUBJECT  FULL MARKS PASS MARKS MARKS OBTAINED\nNAME OF SUBJECTS CREDITS INTFINTOTAL FINTOTAL INT FIN TOTAL GRADE\n-----------------------------------------------------------------------------------------------\nTHEORY PAPERS\nMATHEMATICS-II 4 3070 100 28 4019 A19  F\nAPPLIED PHYSICS-II 3 3070 100 28 40124052  D\nINTRODUCTION TO IT SYSTEMS 2 3070 100 28 40163248  E\nFUNDA OF ELECT AND EC ENGG 3 3070 100 28 40182846  E\nENGG. MECHANICS 3 3070 100 28 40163248  E\n-----------------------------------------------------------------------------------------------\nPRACTICAL PAPERS\nAPPLIED PHYSICS LAB-II 1 1535 050 - 20103040  A\nINTRODUCTION TO IT SYSTEM LAB 2 1535 050 - 20133245  A+\nFUNDA OF ELECT AND EC ENGG LAB 1 1535 050 - 20143246  A+\nENGG. MECHANICS LAB 2 1535 050 - 20113243  A\n-----------------------------------------------------------------------------------------------\nTERM WORK PAPERS\nC.U MOOCS/ SWAYAM/ ETC/ OTHERS 2 0614 020 - 08041115  B\nKYP/IT ESSEN/ PYTHON/ OTHERS 1 0614 020 - 08051015  B\nENVIRONMENTAL SCIENCE 0 10 -010 - 0410 -10  A+\n-----------------------------------------------------------------------------------------------\nGRAND TOTAL 24 750 427\n-----------------------------------------------------------------------------------------------\nSGPA \n-----------------------------------------------------------------------------------------------\nREMARKS : Carry in - MATHEMATICS-II",
        "college": "Government Polytechnic, Bhojpur",
        "name": "SHREYA RAJ",
        "roll": "211522523005",
        "branch": "25",
        "marks": 427,
        "remarks": "Carry in - MATHEMATICS-II",
        "theory": 132
    },
    {
        "text": " \n \nRegistration No : 1522523036\nRoll No         : 211522523036\n \nFollowing are the marks obtained by RAHUL  KUMAR\nof Government Polytechnic, Bhojpur\nat Semester II of Diploma in Mechanical Engineering\nExamination 2024 (EVEN) held in the month of JUL, 2024\n \n \nResult Published On: 30/07/2024\nSTATE BOARD OF TECHNICAL EDUCATION\nBIHAR\n-----------------------------------------------------------------------------------------------\nSUBJECT  FULL MARKS PASS MARKS MARKS OBTAINED\nNAME OF SUBJECTS CREDITS INTFINTOTAL FINTOTAL INT FIN TOTAL GRADE\n-----------------------------------------------------------------------------------------------\nTHEORY PAPERS\nMATHEMATICS-II 4 3070 100 28 40194463  C\nAPPLIED PHYSICS-II 3 3070 100 28 40283967  C\nINTRODUCTION TO IT SYSTEMS 2 3070 100 28 40225173  B\nFUNDA OF ELECT AND EC ENGG 3 3070 100 28 40205575  B\nENGG. MECHANICS 3 3070 100 28 40225678  B\n-----------------------------------------------------------------------------------------------\nPRACTICAL PAPERS\nAPPLIED PHYSICS LAB-II 1 1535 050 - 20133144  A\nINTRODUCTION TO IT SYSTEM LAB 2 1535 050 - 20123143  A\nFUNDA OF ELECT AND EC ENGG LAB 1 1535 050 - 20113344  A\nENGG. MECHANICS LAB 2 1535 050 - 20123244  A\n-----------------------------------------------------------------------------------------------\nTERM WORK PAPERS\nC.U MOOCS/ SWAYAM/ ETC/ OTHERS 2 0614 020 - 08061117  A\nKYP/IT ESSEN/ PYTHON/ OTHERS 1 0614 020 - 08051116  A\nENVIRONMENTAL SCIENCE 0 10 -010 - 0408 -08  A\n-----------------------------------------------------------------------------------------------\nGRAND TOTAL 24 750 572\n-----------------------------------------------------------------------------------------------\nSGPA 8.08\n-----------------------------------------------------------------------------------------------\nREMARKS : First Class with Distinction",
        "college": "Government Polytechnic, Bhojpur",
        "name": "RAHUL KUMAR",
        "roll": "211522523036",
        "branch": "25",
        "marks": 572,
        "remarks": "First Class with Distinction",
        "theory": 245
    },
    {
        "text": " \n \nRegistration No : 1522523001\nRoll No         : 211522523001\n \nFollowing are the marks obtained by AYUSH  KUMAR\nof Government Polytechnic, Bhojpur\nat Semester II of Diploma in Mechanical Engineering\nExamination 2024 (EVEN) held in the month of JUL, 2024\n \n \nResult Published On: 30/07/2024\nSTATE BOARD OF TECHNICAL EDUCATION\nBIHAR\n-----------------------------------------------------------------------------------------------\nSUBJECT  FULL MARKS PASS MARKS MARKS OBTAINED\nNAME OF SUBJECTS CREDITS INTFINTOTAL FINTOTAL INT FIN TOTAL GRADE\n-----------------------------------------------------------------------------------------------\nTHEORY PAPERS\nMATHEMATICS-II 4 3070 100 28 40211233  F\nAPPLIED PHYSICS-II 3 3070 100 28 40182846  E\nINTRODUCTION TO IT SYSTEMS 2 3070 100 28 40143246  E\nFUNDA OF ELECT AND EC ENGG 3 3070 100 28 40182846  E\nENGG. MECHANICS 3 3070 100 28 40143448  E\n-----------------------------------------------------------------------------------------------\nPRACTICAL PAPERS\nAPPLIED PHYSICS LAB-II 1 1535 050 - 20132942  A\nINTRODUCTION TO IT SYSTEM LAB 2 1535 050 - 20123143  A\nFUNDA OF ELECT AND EC ENGG LAB 1 1535 050 - 20133245  A+\nENGG. MECHANICS LAB 2 1535 050 - 20123244  A\n-----------------------------------------------------------------------------------------------\nTERM WORK PAPERS\nC.U MOOCS/ SWAYAM/ ETC/ OTHERS 2 0614 020 - 08051318  A+\nKYP/IT ESSEN/ PYTHON/ OTHERS 1 0614 020 - 08051217  A\nENVIRONMENTAL SCIENCE 0 10 -010 - 0410 -10  A+\n-----------------------------------------------------------------------------------------------\nGRAND TOTAL 24 750 438\n-----------------------------------------------------------------------------------------------\nSGPA \n-----------------------------------------------------------------------------------------------\nREMARKS : Carry in - MATHEMATICS-II",
        "college": "Government Polytechnic, Bhojpur",
        "name": "AYUSH KUMAR",
        "roll": "211522523001",
        "branch": "25",
        "marks": 438,
        "remarks": "Carry in - MATHEMATICS-II",
        "theory": 134
    },
    {
        "text": " \n \nRegistration No : 1522523032\nRoll No         : 211522523032\n \nFollowing are the marks obtained by ADARSH  GUPTA\nof Government Polytechnic, Bhojpur\nat Semester II of Diploma in Mechanical Engineering\nExamination 2024 (EVEN) held in the month of JUL, 2024\n \n \nResult Published On: 30/07/2024\nSTATE BOARD OF TECHNICAL EDUCATION\nBIHAR\n-----------------------------------------------------------------------------------------------\nSUBJECT  FULL MARKS PASS MARKS MARKS OBTAINED\nNAME OF SUBJECTS CREDITS INTFINTOTAL FINTOTAL INT FIN TOTAL GRADE\n-----------------------------------------------------------------------------------------------\nTHEORY PAPERS\nMATHEMATICS-II 4 3070 100 28 40223456  D\nAPPLIED PHYSICS-II 3 3070 100 28 40134760  C\nINTRODUCTION TO IT SYSTEMS 2 3070 100 28 40164763  C\nFUNDA OF ELECT AND EC ENGG 3 3070 100 28 40172845  E\nENGG. MECHANICS 3 3070 100 28 40135366  C\n-----------------------------------------------------------------------------------------------\nPRACTICAL PAPERS\nAPPLIED PHYSICS LAB-II 1 1535 050 - 20102939  B\nINTRODUCTION TO IT SYSTEM LAB 2 1535 050 - 20113041  A\nFUNDA OF ELECT AND EC ENGG LAB 1 1535 050 - 20123345  A+\nENGG. MECHANICS LAB 2 1535 050 - 20113041  A\n-----------------------------------------------------------------------------------------------\nTERM WORK PAPERS\nC.U MOOCS/ SWAYAM/ ETC/ OTHERS 2 0614 020 - 08051217  A\nKYP/IT ESSEN/ PYTHON/ OTHERS 1 0614 020 - 08061218  A+\nENVIRONMENTAL SCIENCE 0 10 -010 - 0408 -08  A\n-----------------------------------------------------------------------------------------------\nGRAND TOTAL 24 750 499\n-----------------------------------------------------------------------------------------------\nSGPA 7.38\n-----------------------------------------------------------------------------------------------\nREMARKS : First Class",
        "college": "Government Polytechnic, Bhojpur",
        "name": "ADARSH GUPTA",
        "roll": "211522523032",
        "branch": "25",
        "marks": 499,
        "remarks": "First Class",
        "theory": 209
    },
    {
        "text": " \n \nRegistration No : 1522523023\nRoll No         : 211522523023\n \nFollowing are the marks obtained by HARSH KUMAR PRASAD\nof Government Polytechnic, Bhojpur\nat Semester II of Diploma in Mechanical Engineering\nExamination 2024 (EVEN) held in the month of JUL, 2024\n \n \nResult Published On: 30/07/2024\nSTATE BOARD OF TECHNICAL EDUCATION\nBIHAR\n-----------------------------------------------------------------------------------------------\nSUBJECT  FULL MARKS PASS MARKS MARKS OBTAINED\nNAME OF SUBJECTS CREDITS INTFINTOTAL FINTOTAL INT FIN TOTAL GRADE\n-----------------------------------------------------------------------------------------------\nTHEORY PAPERS\nMATHEMATICS-II 4 3070 100 28 40060814  F\nAPPLIED PHYSICS-II 3 3070 100 28 40122840  E\nINTRODUCTION TO IT SYSTEMS 2 3070 100 28 40122941  E\nFUNDA OF ELECT AND EC ENGG 3 3070 100 28 40151025  F\nENGG. MECHANICS 3 3070 100 28 40142842  E\n-----------------------------------------------------------------------------------------------\nPRACTICAL PAPERS\nAPPLIED PHYSICS LAB-II 1 1535 050 - 20122941  A\nINTRODUCTION TO IT SYSTEM LAB 2 1535 050 - 20133043  A\nFUNDA OF ELECT AND EC ENGG LAB 1 1535 050 - 20123345  A+\nENGG. MECHANICS LAB 2 1535 050 - 20143145  A+\n-----------------------------------------------------------------------------------------------\nTERM WORK PAPERS\nC.U MOOCS/ SWAYAM/ ETC/ OTHERS 2 0614 020 - 08051015  B\nKYP/IT ESSEN/ PYTHON/ OTHERS 1 0614 020 - 08061016  A\nENVIRONMENTAL SCIENCE 0 10 -010 - 0408 -08  A\n-----------------------------------------------------------------------------------------------\nGRAND TOTAL 24 750 375\n-----------------------------------------------------------------------------------------------\nSGPA \n-----------------------------------------------------------------------------------------------\nREMARKS : Carry in - MATHEMATICS-II\n FUNDA OF ELECT AND EC ENGG",
        "college": "Government Polytechnic, Bhojpur",
        "name": "HARSH KUMAR PRASAD",
        "roll": "211522523023",
        "branch": "25",
        "marks": 375,
        "remarks": "Carry in - MATHEMATICS-II",
        "theory": 103
    },
    {
        "text": " \n \nRegistration No : 1522523030\nRoll No         : 211522523030\n \nFollowing are the marks obtained by SUMIT KUMAR\nof Government Polytechnic, Bhojpur\nat Semester II of Diploma in Mechanical Engineering\nExamination 2024 (EVEN) held in the month of JUL, 2024\n \n \nResult Published On: 30/07/2024\nSTATE BOARD OF TECHNICAL EDUCATION\nBIHAR\n-----------------------------------------------------------------------------------------------\nSUBJECT  FULL MARKS PASS MARKS MARKS OBTAINED\nNAME OF SUBJECTS CREDITS INTFINTOTAL FINTOTAL INT FIN TOTAL GRADE\n-----------------------------------------------------------------------------------------------\nTHEORY PAPERS\nMATHEMATICS-II 4 3070 100 28 40273360  C\nAPPLIED PHYSICS-II 3 3070 100 28 40223355  D\nINTRODUCTION TO IT SYSTEMS 2 3070 100 28 40184866  C\nFUNDA OF ELECT AND EC ENGG 3 3070 100 28 40182846  E\nENGG. MECHANICS 3 3070 100 28 40225072  B\n-----------------------------------------------------------------------------------------------\nPRACTICAL PAPERS\nAPPLIED PHYSICS LAB-II 1 1535 050 - 20133043  A\nINTRODUCTION TO IT SYSTEM LAB 2 1535 050 - 20123244  A\nFUNDA OF ELECT AND EC ENGG LAB 1 1535 050 - 20133245  A+\nENGG. MECHANICS LAB 2 1535 050 - 20123345  A+\n-----------------------------------------------------------------------------------------------\nTERM WORK PAPERS\nC.U MOOCS/ SWAYAM/ ETC/ OTHERS 2 0614 020 - 08041115  B\nKYP/IT ESSEN/ PYTHON/ OTHERS 1 0614 020 - 08041216  A\nENVIRONMENTAL SCIENCE 0 10 -010 - 0410 -10  A+\n-----------------------------------------------------------------------------------------------\nGRAND TOTAL 24 750 517\n-----------------------------------------------------------------------------------------------\nSGPA 7.54\n-----------------------------------------------------------------------------------------------\nREMARKS : First Class",
        "college": "Government Polytechnic, Bhojpur",
        "name": "SUMIT KUMAR",
        "roll": "211522523030",
        "branch": "25",
        "marks": 517,
        "remarks": "First Class",
        "theory": 192
    },
    {
        "text": " \n \nRegistration No : 1522523003\nRoll No         : 211522523003\n \nFollowing are the marks obtained by PREM  KUMAR\nof Government Polytechnic, Bhojpur\nat Semester II of Diploma in Mechanical Engineering\nExamination 2024 (EVEN) held in the month of JUL, 2024\n \n \nResult Published On: 30/07/2024\nSTATE BOARD OF TECHNICAL EDUCATION\nBIHAR\n-----------------------------------------------------------------------------------------------\nSUBJECT  FULL MARKS PASS MARKS MARKS OBTAINED\nNAME OF SUBJECTS CREDITS INTFINTOTAL FINTOTAL INT FIN TOTAL GRADE\n-----------------------------------------------------------------------------------------------\nTHEORY PAPERS\nMATHEMATICS-II 4 3070 100 28 40221234  F\nAPPLIED PHYSICS-II 3 3070 100 28 40193655  D\nINTRODUCTION TO IT SYSTEMS 2 3070 100 28 40203555  D\nFUNDA OF ELECT AND EC ENGG 3 3070 100 28 40183149  E\nENGG. MECHANICS 3 3070 100 28 40192847  E\n-----------------------------------------------------------------------------------------------\nPRACTICAL PAPERS\nAPPLIED PHYSICS LAB-II 1 1535 050 - 20132841  A\nINTRODUCTION TO IT SYSTEM LAB 2 1535 050 - 20143246  A+\nFUNDA OF ELECT AND EC ENGG LAB 1 1535 050 - 20143246  A+\nENGG. MECHANICS LAB 2 1535 050 - 20143347  A+\n-----------------------------------------------------------------------------------------------\nTERM WORK PAPERS\nC.U MOOCS/ SWAYAM/ ETC/ OTHERS 2 0614 020 - 08051318  A+\nKYP/IT ESSEN/ PYTHON/ OTHERS 1 0614 020 - 08041216  A\nENVIRONMENTAL SCIENCE 0 10 -010 - 0410 -10  A+\n-----------------------------------------------------------------------------------------------\nGRAND TOTAL 24 750 464\n-----------------------------------------------------------------------------------------------\nSGPA \n-----------------------------------------------------------------------------------------------\nREMARKS : Carry in - MATHEMATICS-II",
        "college": "Government Polytechnic, Bhojpur",
        "name": "PREM KUMAR",
        "roll": "211522523003",
        "branch": "25",
        "marks": 464,
        "remarks": "Carry in - MATHEMATICS-II",
        "theory": 142
    },
    {
        "text": " \n \nRegistration No : 1522523035\nRoll No         : 211522523035\n \nFollowing are the marks obtained by SUBHAM  RANJAN\nof Government Polytechnic, Bhojpur\nat Semester II of Diploma in Mechanical Engineering\nExamination 2024 (EVEN) held in the month of JUL, 2024\n \n \nResult Published On: 30/07/2024\nSTATE BOARD OF TECHNICAL EDUCATION\nBIHAR\n-----------------------------------------------------------------------------------------------\nSUBJECT  FULL MARKS PASS MARKS MARKS OBTAINED\nNAME OF SUBJECTS CREDITS INTFINTOTAL FINTOTAL INT FIN TOTAL GRADE\n-----------------------------------------------------------------------------------------------\nTHEORY PAPERS\nMATHEMATICS-II 4 3070 100 28 40255277  B\nAPPLIED PHYSICS-II 3 3070 100 28 40274976  B\nINTRODUCTION TO IT SYSTEMS 2 3070 100 28 40254166  C\nFUNDA OF ELECT AND EC ENGG 3 3070 100 28 40264268  C\nENGG. MECHANICS 3 3070 100 28 40245983  A\n-----------------------------------------------------------------------------------------------\nPRACTICAL PAPERS\nAPPLIED PHYSICS LAB-II 1 1535 050 - 20123143  A\nINTRODUCTION TO IT SYSTEM LAB 2 1535 050 - 20113041  A\nFUNDA OF ELECT AND EC ENGG LAB 1 1535 050 - 20113243  A\nENGG. MECHANICS LAB 2 1535 050 - 20143448  A+\n-----------------------------------------------------------------------------------------------\nTERM WORK PAPERS\nC.U MOOCS/ SWAYAM/ ETC/ OTHERS 2 0614 020 - 08051217  A\nKYP/IT ESSEN/ PYTHON/ OTHERS 1 0614 020 - 08041216  A\nENVIRONMENTAL SCIENCE 0 10 -010 - 0410 -10  A+\n-----------------------------------------------------------------------------------------------\nGRAND TOTAL 24 750 588\n-----------------------------------------------------------------------------------------------\nSGPA 8.38\n-----------------------------------------------------------------------------------------------\nREMARKS : First Class with Distinction",
        "college": "Government Polytechnic, Bhojpur",
        "name": "SUBHAM RANJAN",
        "roll": "211522523035",
        "branch": "25",
        "marks": 588,
        "remarks": "First Class with Distinction",
        "theory": 243
    },
    {
        "text": " \n \nRegistration No : 1522523017\nRoll No         : 211522523017\n \nFollowing are the marks obtained by NIHAL KUMAR AMBASHTA\nof Government Polytechnic, Bhojpur\nat Semester II of Diploma in Mechanical Engineering\nExamination 2024 (EVEN) held in the month of JUL, 2024\n \n \nResult Published On: 30/07/2024\nSTATE BOARD OF TECHNICAL EDUCATION\nBIHAR\n-----------------------------------------------------------------------------------------------\nSUBJECT  FULL MARKS PASS MARKS MARKS OBTAINED\nNAME OF SUBJECTS CREDITS INTFINTOTAL FINTOTAL INT FIN TOTAL GRADE\n-----------------------------------------------------------------------------------------------\nTHEORY PAPERS\nMATHEMATICS-II 4 3070 100 28 40231639  F\nAPPLIED PHYSICS-II 3 3070 100 28 40123244  E\nINTRODUCTION TO IT SYSTEMS 2 3070 100 28 40163551  D\nFUNDA OF ELECT AND EC ENGG 3 3070 100 28 40151934  F\nENGG. MECHANICS 3 3070 100 28 40122941  E\n-----------------------------------------------------------------------------------------------\nPRACTICAL PAPERS\nAPPLIED PHYSICS LAB-II 1 1535 050 - 20132942  A\nINTRODUCTION TO IT SYSTEM LAB 2 1535 050 - 20113142  A\nFUNDA OF ELECT AND EC ENGG LAB 1 1535 050 - 20133447  A+\nENGG. MECHANICS LAB 2 1535 050 - 20103040  A\n-----------------------------------------------------------------------------------------------\nTERM WORK PAPERS\nC.U MOOCS/ SWAYAM/ ETC/ OTHERS 2 0614 020 - 08061016  A\nKYP/IT ESSEN/ PYTHON/ OTHERS 1 0614 020 - 08051116  A\nENVIRONMENTAL SCIENCE 0 10 -010 - 0408 -08  A\n-----------------------------------------------------------------------------------------------\nGRAND TOTAL 24 750 420\n-----------------------------------------------------------------------------------------------\nSGPA \n-----------------------------------------------------------------------------------------------\nREMARKS : Carry in - MATHEMATICS-II\n FUNDA OF ELECT AND EC ENGG",
        "college": "Government Polytechnic, Bhojpur",
        "name": "NIHAL KUMAR AMBASHTA",
        "roll": "211522523017",
        "branch": "25",
        "marks": 420,
        "remarks": "Carry in - MATHEMATICS-II",
        "theory": 131
    },
    {
        "text": " \n \nRegistration No : 1522523037\nRoll No         : 211522523037\n \nFollowing are the marks obtained by KUMARI  SNEHA\nof Government Polytechnic, Bhojpur\nat Semester II of Diploma in Mechanical Engineering\nExamination 2024 (EVEN) held in the month of JUL, 2024\n \n \nResult Published On: 30/07/2024\nSTATE BOARD OF TECHNICAL EDUCATION\nBIHAR\n-----------------------------------------------------------------------------------------------\nSUBJECT  FULL MARKS PASS MARKS MARKS OBTAINED\nNAME OF SUBJECTS CREDITS INTFINTOTAL FINTOTAL INT FIN TOTAL GRADE\n-----------------------------------------------------------------------------------------------\nTHEORY PAPERS\nMATHEMATICS-II 4 3070 100 28 40273966  C\nAPPLIED PHYSICS-II 3 3070 100 28 40224365  C\nINTRODUCTION TO IT SYSTEMS 2 3070 100 28 40223254  D\nFUNDA OF ELECT AND EC ENGG 3 3070 100 28 40174865  C\nENGG. MECHANICS 3 3070 100 28 40234467  C\n-----------------------------------------------------------------------------------------------\nPRACTICAL PAPERS\nAPPLIED PHYSICS LAB-II 1 1535 050 - 20123143  A\nINTRODUCTION TO IT SYSTEM LAB 2 1535 050 - 20123143  A\nFUNDA OF ELECT AND EC ENGG LAB 1 1535 050 - 20123446  A+\nENGG. MECHANICS LAB 2 1535 050 - 20133346  A+\n-----------------------------------------------------------------------------------------------\nTERM WORK PAPERS\nC.U MOOCS/ SWAYAM/ ETC/ OTHERS 2 0614 020 - 08051318  A+\nKYP/IT ESSEN/ PYTHON/ OTHERS 1 0614 020 - 08061016  A\nENVIRONMENTAL SCIENCE 0 10 -010 - 0410 -10  A+\n-----------------------------------------------------------------------------------------------\nGRAND TOTAL 24 750 539\n-----------------------------------------------------------------------------------------------\nSGPA 7.88\n-----------------------------------------------------------------------------------------------\nREMARKS : First Class",
        "college": "Government Polytechnic, Bhojpur",
        "name": "KUMARI SNEHA",
        "roll": "211522523037",
        "branch": "25",
        "marks": 539,
        "remarks": "First Class",
        "theory": 206
    },
    {
        "text": " \n \nRegistration No : 1522523021\nRoll No         : 211522523021\n \nFollowing are the marks obtained by MD NAKIB ALAM\nof Government Polytechnic, Bhojpur\nat Semester II of Diploma in Mechanical Engineering\nExamination 2024 (EVEN) held in the month of JUL, 2024\n \n \nResult Published On: 30/07/2024\nSTATE BOARD OF TECHNICAL EDUCATION\nBIHAR\n-----------------------------------------------------------------------------------------------\nSUBJECT  FULL MARKS PASS MARKS MARKS OBTAINED\nNAME OF SUBJECTS CREDITS INTFINTOTAL FINTOTAL INT FIN TOTAL GRADE\n-----------------------------------------------------------------------------------------------\nTHEORY PAPERS\nMATHEMATICS-II 4 3070 100 28 40221436  F\nAPPLIED PHYSICS-II 3 3070 100 28 40052833  F\nINTRODUCTION TO IT SYSTEMS 2 3070 100 28 40083442  E\nFUNDA OF ELECT AND EC ENGG 3 3070 100 28 40171229  F\nENGG. MECHANICS 3 3070 100 28 40123345  E\n-----------------------------------------------------------------------------------------------\nPRACTICAL PAPERS\nAPPLIED PHYSICS LAB-II 1 1535 050 - 20112839  B\nINTRODUCTION TO IT SYSTEM LAB 2 1535 050 - 20123143  A\nFUNDA OF ELECT AND EC ENGG LAB 1 1535 050 - 20113344  A\nENGG. MECHANICS LAB 2 1535 050 - 20103040  A\n-----------------------------------------------------------------------------------------------\nTERM WORK PAPERS\nC.U MOOCS/ SWAYAM/ ETC/ OTHERS 2 0614 020 - 08040812  C\nKYP/IT ESSEN/ PYTHON/ OTHERS 1 0614 020 - 08050813  C\nENVIRONMENTAL SCIENCE 0 10 -010 - 0407 -07  B\n-----------------------------------------------------------------------------------------------\nGRAND TOTAL 24 750 383\n-----------------------------------------------------------------------------------------------\nSGPA \n-----------------------------------------------------------------------------------------------\nREMARKS : Fail",
        "college": "Government Polytechnic, Bhojpur",
        "name": "MD NAKIB ALAM",
        "roll": "211522523021",
        "branch": "25",
        "marks": 383,
        "remarks": "Fail",
        "theory": 121
    },
    {
        "text": " \n \nRegistration No : 1522523044\nRoll No         : 211522523044\n \nFollowing are the marks obtained by SOBHIT  RAJ\nof Government Polytechnic, Bhojpur\nat Semester II of Diploma in Mechanical Engineering\nExamination 2024 (EVEN) held in the month of JUL, 2024\n \n \nResult Published On: 30/07/2024\nSTATE BOARD OF TECHNICAL EDUCATION\nBIHAR\n-----------------------------------------------------------------------------------------------\nSUBJECT  FULL MARKS PASS MARKS MARKS OBTAINED\nNAME OF SUBJECTS CREDITS INTFINTOTAL FINTOTAL INT FIN TOTAL GRADE\n-----------------------------------------------------------------------------------------------\nTHEORY PAPERS\nMATHEMATICS-II 4 3070 100 28 40231336  F\nAPPLIED PHYSICS-II 3 3070 100 28 40192948  E\nINTRODUCTION TO IT SYSTEMS 2 3070 100 28 40153954  D\nFUNDA OF ELECT AND EC ENGG 3 3070 100 28 40192847  E\nENGG. MECHANICS 3 3070 100 28 40164258  D\n-----------------------------------------------------------------------------------------------\nPRACTICAL PAPERS\nAPPLIED PHYSICS LAB-II 1 1535 050 - 20123143  A\nINTRODUCTION TO IT SYSTEM LAB 2 1535 050 - 20113041  A\nFUNDA OF ELECT AND EC ENGG LAB 1 1535 050 - 20123143  A\nENGG. MECHANICS LAB 2 1535 050 - 20113142  A\n-----------------------------------------------------------------------------------------------\nTERM WORK PAPERS\nC.U MOOCS/ SWAYAM/ ETC/ OTHERS 2 0614 020 - 08051015  B\nKYP/IT ESSEN/ PYTHON/ OTHERS 1 0614 020 - 08061218  A+\nENVIRONMENTAL SCIENCE 0 10 -010 - 0408 -08  A\n-----------------------------------------------------------------------------------------------\nGRAND TOTAL 24 750 453\n-----------------------------------------------------------------------------------------------\nSGPA \n-----------------------------------------------------------------------------------------------\nREMARKS : Carry in - MATHEMATICS-II",
        "college": "Government Polytechnic, Bhojpur",
        "name": "SOBHIT RAJ",
        "roll": "211522523044",
        "branch": "25",
        "marks": 453,
        "remarks": "Carry in - MATHEMATICS-II",
        "theory": 151
    },
    {
        "text": " \n \nRegistration No : 1522523019\nRoll No         : 211522523019\n \nFollowing are the marks obtained by ADITYA  KUMAR\nof Government Polytechnic, Bhojpur\nat Semester II of Diploma in Mechanical Engineering\nExamination 2024 (EVEN) held in the month of JUL, 2024\n \n \nResult Published On: 30/07/2024\nSTATE BOARD OF TECHNICAL EDUCATION\nBIHAR\n-----------------------------------------------------------------------------------------------\nSUBJECT  FULL MARKS PASS MARKS MARKS OBTAINED\nNAME OF SUBJECTS CREDITS INTFINTOTAL FINTOTAL INT FIN TOTAL GRADE\n-----------------------------------------------------------------------------------------------\nTHEORY PAPERS\nMATHEMATICS-II 4 3070 100 28 40232851  D\nAPPLIED PHYSICS-II 3 3070 100 28 40144155  D\nINTRODUCTION TO IT SYSTEMS 2 3070 100 28 40143549  E\nFUNDA OF ELECT AND EC ENGG 3 3070 100 28 40183149  E\nENGG. MECHANICS 3 3070 100 28 40164662  C\n-----------------------------------------------------------------------------------------------\nPRACTICAL PAPERS\nAPPLIED PHYSICS LAB-II 1 1535 050 - 20122941  A\nINTRODUCTION TO IT SYSTEM LAB 2 1535 050 - 20133144  A\nFUNDA OF ELECT AND EC ENGG LAB 1 1535 050 - 20123345  A+\nENGG. MECHANICS LAB 2 1535 050 - 20123244  A\n-----------------------------------------------------------------------------------------------\nTERM WORK PAPERS\nC.U MOOCS/ SWAYAM/ ETC/ OTHERS 2 0614 020 - 08051217  A\nKYP/IT ESSEN/ PYTHON/ OTHERS 1 0614 020 - 08051217  A\nENVIRONMENTAL SCIENCE 0 10 -010 - 0408 -08  A\n-----------------------------------------------------------------------------------------------\nGRAND TOTAL 24 750 482\n-----------------------------------------------------------------------------------------------\nSGPA 7.08\n-----------------------------------------------------------------------------------------------\nREMARKS : First Class",
        "college": "Government Polytechnic, Bhojpur",
        "name": "ADITYA KUMAR",
        "roll": "211522523019",
        "branch": "25",
        "marks": 482,
        "remarks": "First Class",
        "theory": 181
    },
    {
        "text": " \n \nRegistration No : 1522523050\nRoll No         : 211522523050\n \nFollowing are the marks obtained by AKASH  KUMAR\nof Government Polytechnic, Bhojpur\nat Semester II of Diploma in Mechanical Engineering\nExamination 2024 (EVEN) held in the month of JUL, 2024\n \n \nResult Published On: 30/07/2024\nSTATE BOARD OF TECHNICAL EDUCATION\nBIHAR\n-----------------------------------------------------------------------------------------------\nSUBJECT  FULL MARKS PASS MARKS MARKS OBTAINED\nNAME OF SUBJECTS CREDITS INTFINTOTAL FINTOTAL INT FIN TOTAL GRADE\n-----------------------------------------------------------------------------------------------\nTHEORY PAPERS\nMATHEMATICS-II 4 3070 100 28 40230831  F\nAPPLIED PHYSICS-II 3 3070 100 28 40124153  D\nINTRODUCTION TO IT SYSTEMS 2 3070 100 28 40054146  E\nFUNDA OF ELECT AND EC ENGG 3 3070 100 28 40181533  F\nENGG. MECHANICS 3 3070 100 28 40133144  E\n-----------------------------------------------------------------------------------------------\nPRACTICAL PAPERS\nAPPLIED PHYSICS LAB-II 1 1535 050 - 20102939  B\nINTRODUCTION TO IT SYSTEM LAB 2 1535 050 - 20123244  A\nFUNDA OF ELECT AND EC ENGG LAB 1 1535 050 - 20123244  A\nENGG. MECHANICS LAB 2 1535 050 - 20113041  A\n-----------------------------------------------------------------------------------------------\nTERM WORK PAPERS\nC.U MOOCS/ SWAYAM/ ETC/ OTHERS 2 0614 020 - 08051217  A\nKYP/IT ESSEN/ PYTHON/ OTHERS 1 0614 020 - 08041014  B\nENVIRONMENTAL SCIENCE 0 10 -010 - 0407 -07  B\n-----------------------------------------------------------------------------------------------\nGRAND TOTAL 24 750 413\n-----------------------------------------------------------------------------------------------\nSGPA \n-----------------------------------------------------------------------------------------------\nREMARKS : Carry in - MATHEMATICS-II\n FUNDA OF ELECT AND EC ENGG",
        "college": "Government Polytechnic, Bhojpur",
        "name": "AKASH KUMAR",
        "roll": "211522523050",
        "branch": "25",
        "marks": 413,
        "remarks": "Carry in - MATHEMATICS-II",
        "theory": 136
    },
    {
        "text": " \n \nRegistration No : 1522523026\nRoll No         : 211522523026\n \nFollowing are the marks obtained by BIRAJ  KUMAR\nof Government Polytechnic, Bhojpur\nat Semester II of Diploma in Mechanical Engineering\nExamination 2024 (EVEN) held in the month of JUL, 2024\n \n \nResult Published On: 30/07/2024\nSTATE BOARD OF TECHNICAL EDUCATION\nBIHAR\n-----------------------------------------------------------------------------------------------\nSUBJECT  FULL MARKS PASS MARKS MARKS OBTAINED\nNAME OF SUBJECTS CREDITS INTFINTOTAL FINTOTAL INT FIN TOTAL GRADE\n-----------------------------------------------------------------------------------------------\nTHEORY PAPERS\nMATHEMATICS-II 4 3070 100 28 40233457  D\nAPPLIED PHYSICS-II 3 3070 100 28 40243256  D\nINTRODUCTION TO IT SYSTEMS 2 3070 100 28 40113748  E\nFUNDA OF ELECT AND EC ENGG 3 3070 100 28 40153853  D\nENGG. MECHANICS 3 3070 100 28 40105363  C\n-----------------------------------------------------------------------------------------------\nPRACTICAL PAPERS\nAPPLIED PHYSICS LAB-II 1 1535 050 - 20122941  A\nINTRODUCTION TO IT SYSTEM LAB 2 1535 050 - 20123244  A\nFUNDA OF ELECT AND EC ENGG LAB 1 1535 050 - 20133245  A+\nENGG. MECHANICS LAB 2 1535 050 - 20103040  A\n-----------------------------------------------------------------------------------------------\nTERM WORK PAPERS\nC.U MOOCS/ SWAYAM/ ETC/ OTHERS 2 0614 020 - 08061117  A\nKYP/IT ESSEN/ PYTHON/ OTHERS 1 0614 020 - 08051116  A\nENVIRONMENTAL SCIENCE 0 10 -010 - 0407 -07  B\n-----------------------------------------------------------------------------------------------\nGRAND TOTAL 24 750 487\n-----------------------------------------------------------------------------------------------\nSGPA 7.21\n-----------------------------------------------------------------------------------------------\nREMARKS : First Class",
        "college": "Government Polytechnic, Bhojpur",
        "name": "BIRAJ KUMAR",
        "roll": "211522523026",
        "branch": "25",
        "marks": 487,
        "remarks": "First Class",
        "theory": 194
    },
    {
        "text": " \n \nRegistration No : 1522523038\nRoll No         : 211522523038\n \nFollowing are the marks obtained by MAHI  KUMARI\nof Government Polytechnic, Bhojpur\nat Semester II of Diploma in Mechanical Engineering\nExamination 2024 (EVEN) held in the month of JUL, 2024\n \n \nResult Published On: 30/07/2024\nSTATE BOARD OF TECHNICAL EDUCATION\nBIHAR\n-----------------------------------------------------------------------------------------------\nSUBJECT  FULL MARKS PASS MARKS MARKS OBTAINED\nNAME OF SUBJECTS CREDITS INTFINTOTAL FINTOTAL INT FIN TOTAL GRADE\n-----------------------------------------------------------------------------------------------\nTHEORY PAPERS\nMATHEMATICS-II 4 3070 100 28 40223961  C\nAPPLIED PHYSICS-II 3 3070 100 28 40245074  B\nINTRODUCTION TO IT SYSTEMS 2 3070 100 28 40206787  A\nFUNDA OF ELECT AND EC ENGG 3 3070 100 28 40225072  B\nENGG. MECHANICS 3 3070 100 28 40255277  B\n-----------------------------------------------------------------------------------------------\nPRACTICAL PAPERS\nAPPLIED PHYSICS LAB-II 1 1535 050 - 20143145  A+\nINTRODUCTION TO IT SYSTEM LAB 2 1535 050 - 20133245  A+\nFUNDA OF ELECT AND EC ENGG LAB 1 1535 050 - 20133346  A+\nENGG. MECHANICS LAB 2 1535 050 - 20143347  A+\n-----------------------------------------------------------------------------------------------\nTERM WORK PAPERS\nC.U MOOCS/ SWAYAM/ ETC/ OTHERS 2 0614 020 - 08051116  A\nKYP/IT ESSEN/ PYTHON/ OTHERS 1 0614 020 - 08041115  B\nENVIRONMENTAL SCIENCE 0 10 -010 - 0410 -10  A+\n-----------------------------------------------------------------------------------------------\nGRAND TOTAL 24 750 595\n-----------------------------------------------------------------------------------------------\nSGPA 8.5\n-----------------------------------------------------------------------------------------------\nREMARKS : First Class with Distinction",
        "college": "Government Polytechnic, Bhojpur",
        "name": "MAHI KUMARI",
        "roll": "211522523038",
        "branch": "25",
        "marks": 595,
        "remarks": "First Class with Distinction",
        "theory": 258
    },
    {
        "text": " \n \nRegistration No : 1522523018\nRoll No         : 211522523018\n \nFollowing are the marks obtained by PRIYANSHU  RANJAN\nof Government Polytechnic, Bhojpur\nat Semester II of Diploma in Mechanical Engineering\nExamination 2024 (EVEN) held in the month of JUL, 2024\n \n \nResult Published On: 30/07/2024\nSTATE BOARD OF TECHNICAL EDUCATION\nBIHAR\n-----------------------------------------------------------------------------------------------\nSUBJECT  FULL MARKS PASS MARKS MARKS OBTAINED\nNAME OF SUBJECTS CREDITS INTFINTOTAL FINTOTAL INT FIN TOTAL GRADE\n-----------------------------------------------------------------------------------------------\nTHEORY PAPERS\nMATHEMATICS-II 4 3070 100 28 40251338  F\nAPPLIED PHYSICS-II 3 3070 100 28 40243256  D\nINTRODUCTION TO IT SYSTEMS 2 3070 100 28 40132942  E\nFUNDA OF ELECT AND EC ENGG 3 3070 100 28 40202848  E\nENGG. MECHANICS 3 3070 100 28 40142943  E\n-----------------------------------------------------------------------------------------------\nPRACTICAL PAPERS\nAPPLIED PHYSICS LAB-II 1 1535 050 - 20122840  A\nINTRODUCTION TO IT SYSTEM LAB 2 1535 050 - 20123042  A\nFUNDA OF ELECT AND EC ENGG LAB 1 1535 050 - 20123244  A\nENGG. MECHANICS LAB 2 1535 050 - 20123244  A\n-----------------------------------------------------------------------------------------------\nTERM WORK PAPERS\nC.U MOOCS/ SWAYAM/ ETC/ OTHERS 2 0614 020 - 08051116  A\nKYP/IT ESSEN/ PYTHON/ OTHERS 1 0614 020 - 08041216  A\nENVIRONMENTAL SCIENCE 0 10 -010 - 0408 -08  A\n-----------------------------------------------------------------------------------------------\nGRAND TOTAL 24 750 437\n-----------------------------------------------------------------------------------------------\nSGPA \n-----------------------------------------------------------------------------------------------\nREMARKS : Carry in - MATHEMATICS-II",
        "college": "Government Polytechnic, Bhojpur",
        "name": "PRIYANSHU RANJAN",
        "roll": "211522523018",
        "branch": "25",
        "marks": 437,
        "remarks": "Carry in - MATHEMATICS-II",
        "theory": 131
    },
    {
        "text": " \n \nRegistration No : 1522523031\nRoll No         : 211522523031\n \nFollowing are the marks obtained by ADITYA  KUMAR\nof Government Polytechnic, Bhojpur\nat Semester II of Diploma in Mechanical Engineering\nExamination 2024 (EVEN) held in the month of JUL, 2024\n \n \nResult Published On: 30/07/2024\nSTATE BOARD OF TECHNICAL EDUCATION\nBIHAR\n-----------------------------------------------------------------------------------------------\nSUBJECT  FULL MARKS PASS MARKS MARKS OBTAINED\nNAME OF SUBJECTS CREDITS INTFINTOTAL FINTOTAL INT FIN TOTAL GRADE\n-----------------------------------------------------------------------------------------------\nTHEORY PAPERS\nMATHEMATICS-II 4 3070 100 28 40236184  A\nAPPLIED PHYSICS-II 3 3070 100 28 40254065  C\nINTRODUCTION TO IT SYSTEMS 2 3070 100 28 40183957  D\nFUNDA OF ELECT AND EC ENGG 3 3070 100 28 40172946  E\nENGG. MECHANICS 3 3070 100 28 40164056  D\n-----------------------------------------------------------------------------------------------\nPRACTICAL PAPERS\nAPPLIED PHYSICS LAB-II 1 1535 050 - 20133144  A\nINTRODUCTION TO IT SYSTEM LAB 2 1535 050 - 20133144  A\nFUNDA OF ELECT AND EC ENGG LAB 1 1535 050 - 20133346  A+\nENGG. MECHANICS LAB 2 1535 050 - 20103040  A\n-----------------------------------------------------------------------------------------------\nTERM WORK PAPERS\nC.U MOOCS/ SWAYAM/ ETC/ OTHERS 2 0614 020 - 08051015  B\nKYP/IT ESSEN/ PYTHON/ OTHERS 1 0614 020 - 08051318  A+\nENVIRONMENTAL SCIENCE 0 10 -010 - 0408 -08  A\n-----------------------------------------------------------------------------------------------\nGRAND TOTAL 24 750 523\n-----------------------------------------------------------------------------------------------\nSGPA 7.62\n-----------------------------------------------------------------------------------------------\nREMARKS : First Class",
        "college": "Government Polytechnic, Bhojpur",
        "name": "ADITYA KUMAR",
        "roll": "211522523031",
        "branch": "25",
        "marks": 523,
        "remarks": "First Class",
        "theory": 209
    },
    {
        "text": " \n \nRegistration No : 1522023023\nRoll No         : 211522023023\n \nFollowing are the marks obtained by RITESH  KUMAR\nof Government Polytechnic, Bhojpur\nat Semester II of Diploma in Electrical Engineering\nExamination 2024 (EVEN) held in the month of JUL, 2024\n \n \nResult Published On: 30/07/2024\nSTATE BOARD OF TECHNICAL EDUCATION\nBIHAR\n-----------------------------------------------------------------------------------------------\nSUBJECT  FULL MARKS PASS MARKS MARKS OBTAINED\nNAME OF SUBJECTS CREDITS INTFINTOTAL FINTOTAL INT FIN TOTAL GRADE\n-----------------------------------------------------------------------------------------------\nTHEORY PAPERS\nMATHEMATICS-II 4 3070 100 28 40230831  F\nAPPLIED PHYSICS-II 3 3070 100 28 40120921  F\nINTRODUCTION TO IT SYSTEMS 2 3070 100 28 40102838  F\nFUNDA OF ELECT AND EC ENGG 3 3070 100 28 40211435  F\nENGG. MECHANICS 3 3070 100 28 40111728  F\n-----------------------------------------------------------------------------------------------\nPRACTICAL PAPERS\nAPPLIED PHYSICS LAB-II 1 1535 050 - 20112940  A\nINTRODUCTION TO IT SYSTEM LAB 2 1535 050 - 20113142  A\nFUNDA OF ELECT AND EC ENGG LAB 1 1535 050 - 20133346  A+\nENGG. MECHANICS LAB 2 1535 050 - 20113142  A\n-----------------------------------------------------------------------------------------------\nTERM WORK PAPERS\nC.U MOOCS/ SWAYAM/ ETC/ OTHERS 2 0614 020 - 08051217  A\nKYP/IT ESSEN/ PYTHON/ OTHERS 1 0614 020 - 08041115  B\nENVIRONMENTAL SCIENCE 0 10 -010 - 0408 -08  A\n-----------------------------------------------------------------------------------------------\nGRAND TOTAL 24 750 363\n-----------------------------------------------------------------------------------------------\nSGPA \n-----------------------------------------------------------------------------------------------\nREMARKS : Fail",
        "college": "Government Polytechnic, Bhojpur",
        "name": "RITESH KUMAR",
        "roll": "211522023023",
        "branch": "20",
        "marks": 363,
        "remarks": "Fail",
        "theory": 76
    },
    {
        "text": " \n \nRegistration No : 1522023026\nRoll No         : 211522023026\n \nFollowing are the marks obtained by DEEPAK KUMAR MURMU\nof Government Polytechnic, Bhojpur\nat Semester II of Diploma in Electrical Engineering\nExamination 2024 (EVEN) held in the month of JUL, 2024\n \n \nResult Published On: 30/07/2024\nSTATE BOARD OF TECHNICAL EDUCATION\nBIHAR\n-----------------------------------------------------------------------------------------------\nSUBJECT  FULL MARKS PASS MARKS MARKS OBTAINED\nNAME OF SUBJECTS CREDITS INTFINTOTAL FINTOTAL INT FIN TOTAL GRADE\n-----------------------------------------------------------------------------------------------\nTHEORY PAPERS\nMATHEMATICS-II 4 3070 100 28 40221335  F\nAPPLIED PHYSICS-II 3 3070 100 28 40163450  D\nINTRODUCTION TO IT SYSTEMS 2 3070 100 28 40122840  E\nFUNDA OF ELECT AND EC ENGG 3 3070 100 28 40182846  E\nENGG. MECHANICS 3 3070 100 28 40133750  D\n-----------------------------------------------------------------------------------------------\nPRACTICAL PAPERS\nAPPLIED PHYSICS LAB-II 1 1535 050 - 20103141  A\nINTRODUCTION TO IT SYSTEM LAB 2 1535 050 - 20123244  A\nFUNDA OF ELECT AND EC ENGG LAB 1 1535 050 - 20123244  A\nENGG. MECHANICS LAB 2 1535 050 - 20113142  A\n-----------------------------------------------------------------------------------------------\nTERM WORK PAPERS\nC.U MOOCS/ SWAYAM/ ETC/ OTHERS 2 0614 020 - 08031114  B\nKYP/IT ESSEN/ PYTHON/ OTHERS 1 0614 020 - 08041115  B\nENVIRONMENTAL SCIENCE 0 10 -010 - 0408 -08  A\n-----------------------------------------------------------------------------------------------\nGRAND TOTAL 24 750 429\n-----------------------------------------------------------------------------------------------\nSGPA \n-----------------------------------------------------------------------------------------------\nREMARKS : Carry in - MATHEMATICS-II",
        "college": "Government Polytechnic, Bhojpur",
        "name": "DEEPAK KUMAR MURMU",
        "roll": "211522023026",
        "branch": "20",
        "marks": 429,
        "remarks": "Carry in - MATHEMATICS-II",
        "theory": 140
    },
    {
        "text": " \n \nRegistration No : 1522023057\nRoll No         : 211522023057\n \nFollowing are the marks obtained by PRAMOD  KUMAR\nof Government Polytechnic, Bhojpur\nat Semester II of Diploma in Electrical Engineering\nExamination 2024 (EVEN) held in the month of JUL, 2024\n \n \nResult Published On: 30/07/2024\nSTATE BOARD OF TECHNICAL EDUCATION\nBIHAR\n-----------------------------------------------------------------------------------------------\nSUBJECT  FULL MARKS PASS MARKS MARKS OBTAINED\nNAME OF SUBJECTS CREDITS INTFINTOTAL FINTOTAL INT FIN TOTAL GRADE\n-----------------------------------------------------------------------------------------------\nTHEORY PAPERS\nMATHEMATICS-II 4 3070 100 28 40193655  D\nAPPLIED PHYSICS-II 3 3070 100 28 40184058  D\nINTRODUCTION TO IT SYSTEMS 2 3070 100 28 40102939  F\nFUNDA OF ELECT AND EC ENGG 3 3070 100 28 40192847  E\nENGG. MECHANICS 3 3070 100 28 40143145  E\n-----------------------------------------------------------------------------------------------\nPRACTICAL PAPERS\nAPPLIED PHYSICS LAB-II 1 1535 050 - 20113041  A\nINTRODUCTION TO IT SYSTEM LAB 2 1535 050 - 20133144  A\nFUNDA OF ELECT AND EC ENGG LAB 1 1535 050 - 20133245  A+\nENGG. MECHANICS LAB 2 1535 050 - 20103040  A\n-----------------------------------------------------------------------------------------------\nTERM WORK PAPERS\nC.U MOOCS/ SWAYAM/ ETC/ OTHERS 2 0614 020 - 08051015  B\nKYP/IT ESSEN/ PYTHON/ OTHERS 1 0614 020 - 08041115  B\nENVIRONMENTAL SCIENCE 0 10 -010 - 0408 -08  A\n-----------------------------------------------------------------------------------------------\nGRAND TOTAL 24 750 452\n-----------------------------------------------------------------------------------------------\nSGPA \n-----------------------------------------------------------------------------------------------\nREMARKS : Carry in - INTRODUCTION TO IT SYSTEMS",
        "college": "Government Polytechnic, Bhojpur",
        "name": "PRAMOD KUMAR",
        "roll": "211522023057",
        "branch": "20",
        "marks": 452,
        "remarks": "Carry in - INTRODUCTION TO IT SYSTEMS",
        "theory": 164
    },
    {
        "text": " \n \nRegistration No : 1522023049\nRoll No         : 211522023049\n \nFollowing are the marks obtained by ROHIT  KUMAR\nof Government Polytechnic, Bhojpur\nat Semester II of Diploma in Electrical Engineering\nExamination 2024 (EVEN) held in the month of JUL, 2024\n \n \nResult Published On: 30/07/2024\nSTATE BOARD OF TECHNICAL EDUCATION\nBIHAR\n-----------------------------------------------------------------------------------------------\nSUBJECT  FULL MARKS PASS MARKS MARKS OBTAINED\nNAME OF SUBJECTS CREDITS INTFINTOTAL FINTOTAL INT FIN TOTAL GRADE\n-----------------------------------------------------------------------------------------------\nTHEORY PAPERS\nMATHEMATICS-II 4 3070 100 28 40222850  D\nAPPLIED PHYSICS-II 3 3070 100 28 40223052  D\nINTRODUCTION TO IT SYSTEMS 2 3070 100 28 40224264  C\nFUNDA OF ELECT AND EC ENGG 3 3070 100 28 40163248  E\nENGG. MECHANICS 3 3070 100 28 40203757  D\n-----------------------------------------------------------------------------------------------\nPRACTICAL PAPERS\nAPPLIED PHYSICS LAB-II 1 1535 050 - 20132841  A\nINTRODUCTION TO IT SYSTEM LAB 2 1535 050 - 20123244  A\nFUNDA OF ELECT AND EC ENGG LAB 1 1535 050 - 20133245  A+\nENGG. MECHANICS LAB 2 1535 050 - 20143347  A+\n-----------------------------------------------------------------------------------------------\nTERM WORK PAPERS\nC.U MOOCS/ SWAYAM/ ETC/ OTHERS 2 0614 020 - 08041115  B\nKYP/IT ESSEN/ PYTHON/ OTHERS 1 0614 020 - 08041115  B\nENVIRONMENTAL SCIENCE 0 10 -010 - 0408 -08  A\n-----------------------------------------------------------------------------------------------\nGRAND TOTAL 24 750 486\n-----------------------------------------------------------------------------------------------\nSGPA 7.08\n-----------------------------------------------------------------------------------------------\nREMARKS : First Class",
        "college": "Government Polytechnic, Bhojpur",
        "name": "ROHIT KUMAR",
        "roll": "211522023049",
        "branch": "20",
        "marks": 486,
        "remarks": "First Class",
        "theory": 169
    },
    {
        "text": " \n \nRegistration No : 1522023014\nRoll No         : 211522023014\n \nFollowing are the marks obtained by HIMANSHU  PATEL\nof Government Polytechnic, Bhojpur\nat Semester II of Diploma in Electrical Engineering\nExamination 2024 (EVEN) held in the month of JUL, 2024\n \n \nResult Published On: 30/07/2024\nSTATE BOARD OF TECHNICAL EDUCATION\nBIHAR\n-----------------------------------------------------------------------------------------------\nSUBJECT  FULL MARKS PASS MARKS MARKS OBTAINED\nNAME OF SUBJECTS CREDITS INTFINTOTAL FINTOTAL INT FIN TOTAL GRADE\n-----------------------------------------------------------------------------------------------\nTHEORY PAPERS\nMATHEMATICS-II 4 3070 100 28 40222850  D\nAPPLIED PHYSICS-II 3 3070 100 28 40214566  C\nINTRODUCTION TO IT SYSTEMS 2 3070 100 28 40193352  D\nFUNDA OF ELECT AND EC ENGG 3 3070 100 28 40214566  C\nENGG. MECHANICS 3 3070 100 28 40195372  B\n-----------------------------------------------------------------------------------------------\nPRACTICAL PAPERS\nAPPLIED PHYSICS LAB-II 1 1535 050 - 20143145  A+\nINTRODUCTION TO IT SYSTEM LAB 2 1535 050 - 20123042  A\nFUNDA OF ELECT AND EC ENGG LAB 1 1535 050 - 20133245  A+\nENGG. MECHANICS LAB 2 1535 050 - 20123244  A\n-----------------------------------------------------------------------------------------------\nTERM WORK PAPERS\nC.U MOOCS/ SWAYAM/ ETC/ OTHERS 2 0614 020 - 08041115  B\nKYP/IT ESSEN/ PYTHON/ OTHERS 1 0614 020 - 08041115  B\nENVIRONMENTAL SCIENCE 0 10 -010 - 0408 -08  A\n-----------------------------------------------------------------------------------------------\nGRAND TOTAL 24 750 520\n-----------------------------------------------------------------------------------------------\nSGPA 7.58\n-----------------------------------------------------------------------------------------------\nREMARKS : First Class",
        "college": "Government Polytechnic, Bhojpur",
        "name": "HIMANSHU PATEL",
        "roll": "211522023014",
        "branch": "20",
        "marks": 520,
        "remarks": "First Class",
        "theory": 204
    },
    {
        "text": " \n \nRegistration No : 1522023030\nRoll No         : 211522023030\n \nFollowing are the marks obtained by SUMANT  KUMAR\nof Government Polytechnic, Bhojpur\nat Semester II of Diploma in Electrical Engineering\nExamination 2024 (EVEN) held in the month of JUL, 2024\n \n \nResult Published On: 30/07/2024\nSTATE BOARD OF TECHNICAL EDUCATION\nBIHAR\n-----------------------------------------------------------------------------------------------\nSUBJECT  FULL MARKS PASS MARKS MARKS OBTAINED\nNAME OF SUBJECTS CREDITS INTFINTOTAL FINTOTAL INT FIN TOTAL GRADE\n-----------------------------------------------------------------------------------------------\nTHEORY PAPERS\nMATHEMATICS-II 4 3070 100 28 40163955  D\nAPPLIED PHYSICS-II 3 3070 100 28 40243862  C\nINTRODUCTION TO IT SYSTEMS 2 3070 100 28 40193453  D\nFUNDA OF ELECT AND EC ENGG 3 3070 100 28 40153449  E\nENGG. MECHANICS 3 3070 100 28 40195473  B\n-----------------------------------------------------------------------------------------------\nPRACTICAL PAPERS\nAPPLIED PHYSICS LAB-II 1 1535 050 - 20133144  A\nINTRODUCTION TO IT SYSTEM LAB 2 1535 050 - 20123143  A\nFUNDA OF ELECT AND EC ENGG LAB 1 1535 050 - 20143246  A+\nENGG. MECHANICS LAB 2 1535 050 - 20123345  A+\n-----------------------------------------------------------------------------------------------\nTERM WORK PAPERS\nC.U MOOCS/ SWAYAM/ ETC/ OTHERS 2 0614 020 - 08051015  B\nKYP/IT ESSEN/ PYTHON/ OTHERS 1 0614 020 - 08041115  B\nENVIRONMENTAL SCIENCE 0 10 -010 - 0410 -10  A+\n-----------------------------------------------------------------------------------------------\nGRAND TOTAL 24 750 510\n-----------------------------------------------------------------------------------------------\nSGPA 7.38\n-----------------------------------------------------------------------------------------------\nREMARKS : First Class",
        "college": "Government Polytechnic, Bhojpur",
        "name": "SUMANT KUMAR",
        "roll": "211522023030",
        "branch": "20",
        "marks": 510,
        "remarks": "First Class",
        "theory": 199
    },
    {
        "text": " \n \nRegistration No : 1522023003\nRoll No         : 211522023003\n \nFollowing are the marks obtained by SAURAV  KUMAR\nof Government Polytechnic, Bhojpur\nat Semester II of Diploma in Electrical Engineering\nExamination 2024 (EVEN) held in the month of JUL, 2024\n \n \nResult Published On: 30/07/2024\nSTATE BOARD OF TECHNICAL EDUCATION\nBIHAR\n-----------------------------------------------------------------------------------------------\nSUBJECT  FULL MARKS PASS MARKS MARKS OBTAINED\nNAME OF SUBJECTS CREDITS INTFINTOTAL FINTOTAL INT FIN TOTAL GRADE\n-----------------------------------------------------------------------------------------------\nTHEORY PAPERS\nMATHEMATICS-II 4 3070 100 28 40215475  B\nAPPLIED PHYSICS-II 3 3070 100 28 40275279  B\nINTRODUCTION TO IT SYSTEMS 2 3070 100 28 40204868  C\nFUNDA OF ELECT AND EC ENGG 3 3070 100 28 40224668  C\nENGG. MECHANICS 3 3070 100 28 40275077  B\n-----------------------------------------------------------------------------------------------\nPRACTICAL PAPERS\nAPPLIED PHYSICS LAB-II 1 1535 050 - 20132942  A\nINTRODUCTION TO IT SYSTEM LAB 2 1535 050 - 20133144  A\nFUNDA OF ELECT AND EC ENGG LAB 1 1535 050 - 20133346  A+\nENGG. MECHANICS LAB 2 1535 050 - 20143448  A+\n-----------------------------------------------------------------------------------------------\nTERM WORK PAPERS\nC.U MOOCS/ SWAYAM/ ETC/ OTHERS 2 0614 020 - 08031114  B\nKYP/IT ESSEN/ PYTHON/ OTHERS 1 0614 020 - 08041216  A\nENVIRONMENTAL SCIENCE 0 10 -010 - 0408 -08  A\n-----------------------------------------------------------------------------------------------\nGRAND TOTAL 24 750 585\n-----------------------------------------------------------------------------------------------\nSGPA 8.21\n-----------------------------------------------------------------------------------------------\nREMARKS : First Class with Distinction",
        "college": "Government Polytechnic, Bhojpur",
        "name": "SAURAV KUMAR",
        "roll": "211522023003",
        "branch": "20",
        "marks": 585,
        "remarks": "First Class with Distinction",
        "theory": 250
    },
    {
        "text": " \n \nRegistration No : 1522023051\nRoll No         : 211522023051\n \nFollowing are the marks obtained by SURAJ  KUMAR\nof Government Polytechnic, Bhojpur\nat Semester II of Diploma in Electrical Engineering\nExamination 2024 (EVEN) held in the month of JUL, 2024\n \n \nResult Published On: 30/07/2024\nSTATE BOARD OF TECHNICAL EDUCATION\nBIHAR\n-----------------------------------------------------------------------------------------------\nSUBJECT  FULL MARKS PASS MARKS MARKS OBTAINED\nNAME OF SUBJECTS CREDITS INTFINTOTAL FINTOTAL INT FIN TOTAL GRADE\n-----------------------------------------------------------------------------------------------\nTHEORY PAPERS\nMATHEMATICS-II 4 3070 100 28 40191433  F\nAPPLIED PHYSICS-II 3 3070 100 28 40253358  D\nINTRODUCTION TO IT SYSTEMS 2 3070 100 28 40173653  D\nFUNDA OF ELECT AND EC ENGG 3 3070 100 28 40233457  D\nENGG. MECHANICS 3 3070 100 28 40213152  D\n-----------------------------------------------------------------------------------------------\nPRACTICAL PAPERS\nAPPLIED PHYSICS LAB-II 1 1535 050 - 20113142  A\nINTRODUCTION TO IT SYSTEM LAB 2 1535 050 - 20133144  A\nFUNDA OF ELECT AND EC ENGG LAB 1 1535 050 - 20133245  A+\nENGG. MECHANICS LAB 2 1535 050 - 20123244  A\n-----------------------------------------------------------------------------------------------\nTERM WORK PAPERS\nC.U MOOCS/ SWAYAM/ ETC/ OTHERS 2 0614 020 - 08051217  A\nKYP/IT ESSEN/ PYTHON/ OTHERS 1 0614 020 - 08041216  A\nENVIRONMENTAL SCIENCE 0 10 -010 - 0410 -10  A+\n-----------------------------------------------------------------------------------------------\nGRAND TOTAL 24 750 471\n-----------------------------------------------------------------------------------------------\nSGPA \n-----------------------------------------------------------------------------------------------\nREMARKS : Carry in - MATHEMATICS-II",
        "college": "Government Polytechnic, Bhojpur",
        "name": "SURAJ KUMAR",
        "roll": "211522023051",
        "branch": "20",
        "marks": 471,
        "remarks": "Carry in - MATHEMATICS-II",
        "theory": 148
    },
    {
        "text": " \n \nRegistration No : 1522023038\nRoll No         : 211522023038\n \nFollowing are the marks obtained by NISHU  KUMARI\nof Government Polytechnic, Bhojpur\nat Semester II of Diploma in Electrical Engineering\nExamination 2024 (EVEN) held in the month of JUL, 2024\n \n \nResult Published On: 30/07/2024\nSTATE BOARD OF TECHNICAL EDUCATION\nBIHAR\n-----------------------------------------------------------------------------------------------\nSUBJECT  FULL MARKS PASS MARKS MARKS OBTAINED\nNAME OF SUBJECTS CREDITS INTFINTOTAL FINTOTAL INT FIN TOTAL GRADE\n-----------------------------------------------------------------------------------------------\nTHEORY PAPERS\nMATHEMATICS-II 4 3070 100 28 40211435  F\nAPPLIED PHYSICS-II 3 3070 100 28 40144660  C\nINTRODUCTION TO IT SYSTEMS 2 3070 100 28 40223860  C\nFUNDA OF ELECT AND EC ENGG 3 3070 100 28 40172845  E\nENGG. MECHANICS 3 3070 100 28 40194564  C\n-----------------------------------------------------------------------------------------------\nPRACTICAL PAPERS\nAPPLIED PHYSICS LAB-II 1 1535 050 - 20123042  A\nINTRODUCTION TO IT SYSTEM LAB 2 1535 050 - 20133245  A+\nFUNDA OF ELECT AND EC ENGG LAB 1 1535 050 - 20133346  A+\nENGG. MECHANICS LAB 2 1535 050 - 20143347  A+\n-----------------------------------------------------------------------------------------------\nTERM WORK PAPERS\nC.U MOOCS/ SWAYAM/ ETC/ OTHERS 2 0614 020 - 08041216  A\nKYP/IT ESSEN/ PYTHON/ OTHERS 1 0614 020 - 08051217  A\nENVIRONMENTAL SCIENCE 0 10 -010 - 0410 -10  A+\n-----------------------------------------------------------------------------------------------\nGRAND TOTAL 24 750 487\n-----------------------------------------------------------------------------------------------\nSGPA \n-----------------------------------------------------------------------------------------------\nREMARKS : Carry in - MATHEMATICS-II",
        "college": "Government Polytechnic, Bhojpur",
        "name": "NISHU KUMARI",
        "roll": "211522023038",
        "branch": "20",
        "marks": 487,
        "remarks": "Carry in - MATHEMATICS-II",
        "theory": 171
    },
    {
        "text": " \n \nRegistration No : 1522023054\nRoll No         : 211522023054\n \nFollowing are the marks obtained by VIJAY  KUMAR\nof Government Polytechnic, Bhojpur\nat Semester II of Diploma in Electrical Engineering\nExamination 2024 (EVEN) held in the month of JUL, 2024\n \n \nResult Published On: 30/07/2024\nSTATE BOARD OF TECHNICAL EDUCATION\nBIHAR\n-----------------------------------------------------------------------------------------------\nSUBJECT  FULL MARKS PASS MARKS MARKS OBTAINED\nNAME OF SUBJECTS CREDITS INTFINTOTAL FINTOTAL INT FIN TOTAL GRADE\n-----------------------------------------------------------------------------------------------\nTHEORY PAPERS\nMATHEMATICS-II 4 3070 100 28 40252045  E\nAPPLIED PHYSICS-II 3 3070 100 28 40053641  E\nINTRODUCTION TO IT SYSTEMS 2 3070 100 28 40143044  E\nFUNDA OF ELECT AND EC ENGG 3 3070 100 28 40193049  E\nENGG. MECHANICS 3 3070 100 28 40124254  D\n-----------------------------------------------------------------------------------------------\nPRACTICAL PAPERS\nAPPLIED PHYSICS LAB-II 1 1535 050 - 20112435  B\nINTRODUCTION TO IT SYSTEM LAB 2 1535 050 - 20133043  A\nFUNDA OF ELECT AND EC ENGG LAB 1 1535 050 - 20123345  A+\nENGG. MECHANICS LAB 2 1535 050 - 20103040  A\n-----------------------------------------------------------------------------------------------\nTERM WORK PAPERS\nC.U MOOCS/ SWAYAM/ ETC/ OTHERS 2 0614 020 - 08050914  B\nKYP/IT ESSEN/ PYTHON/ OTHERS 1 0614 020 - 08040812  C\nENVIRONMENTAL SCIENCE 0 10 -010 - 0406 -06  C\n-----------------------------------------------------------------------------------------------\nGRAND TOTAL 24 750 428\n-----------------------------------------------------------------------------------------------\nSGPA \n-----------------------------------------------------------------------------------------------\nREMARKS : Carry in - MATHEMATICS-II",
        "college": "Government Polytechnic, Bhojpur",
        "name": "VIJAY KUMAR",
        "roll": "211522023054",
        "branch": "20",
        "marks": 428,
        "remarks": "Carry in - MATHEMATICS-II",
        "theory": 158
    },
    {
        "text": " \n \nRegistration No : 1522023055\nRoll No         : 211522023055\n \nFollowing are the marks obtained by ASHISH  KUMAR\nof Government Polytechnic, Bhojpur\nat Semester II of Diploma in Electrical Engineering\nExamination 2024 (EVEN) held in the month of JUL, 2024\n \n \nResult Published On: 30/07/2024\nSTATE BOARD OF TECHNICAL EDUCATION\nBIHAR\n-----------------------------------------------------------------------------------------------\nSUBJECT  FULL MARKS PASS MARKS MARKS OBTAINED\nNAME OF SUBJECTS CREDITS INTFINTOTAL FINTOTAL INT FIN TOTAL GRADE\n-----------------------------------------------------------------------------------------------\nTHEORY PAPERS\nMATHEMATICS-II 4 3070 100 28 40225880  A\nAPPLIED PHYSICS-II 3 3070 100 28 40275279  B\nINTRODUCTION TO IT SYSTEMS 2 3070 100 28 40193150  D\nFUNDA OF ELECT AND EC ENGG 3 3070 100 28 40224870  B\nENGG. MECHANICS 3 3070 100 28 40246589  A\n-----------------------------------------------------------------------------------------------\nPRACTICAL PAPERS\nAPPLIED PHYSICS LAB-II 1 1535 050 - 20133144  A\nINTRODUCTION TO IT SYSTEM LAB 2 1535 050 - 20133144  A\nFUNDA OF ELECT AND EC ENGG LAB 1 1535 050 - 20133245  A+\nENGG. MECHANICS LAB 2 1535 050 - 20123244  A\n-----------------------------------------------------------------------------------------------\nTERM WORK PAPERS\nC.U MOOCS/ SWAYAM/ ETC/ OTHERS 2 0614 020 - 08041014  B\nKYP/IT ESSEN/ PYTHON/ OTHERS 1 0614 020 - 08051015  B\nENVIRONMENTAL SCIENCE 0 10 -010 - 0408 -08  A\n-----------------------------------------------------------------------------------------------\nGRAND TOTAL 24 750 582\n-----------------------------------------------------------------------------------------------\nSGPA 8.42\n-----------------------------------------------------------------------------------------------\nREMARKS : First Class with Distinction",
        "college": "Government Polytechnic, Bhojpur",
        "name": "ASHISH KUMAR",
        "roll": "211522023055",
        "branch": "20",
        "marks": 582,
        "remarks": "First Class with Distinction",
        "theory": 254
    },
    {
        "text": " \n \nRegistration No : 1522023033\nRoll No         : 211522023033\n \nFollowing are the marks obtained by KOMAL  RAJ\nof Government Polytechnic, Bhojpur\nat Semester II of Diploma in Electrical Engineering\nExamination 2024 (EVEN) held in the month of JUL, 2024\n \n \nResult Published On: 30/07/2024\nSTATE BOARD OF TECHNICAL EDUCATION\nBIHAR\n-----------------------------------------------------------------------------------------------\nSUBJECT  FULL MARKS PASS MARKS MARKS OBTAINED\nNAME OF SUBJECTS CREDITS INTFINTOTAL FINTOTAL INT FIN TOTAL GRADE\n-----------------------------------------------------------------------------------------------\nTHEORY PAPERS\nMATHEMATICS-II 4 3070 100 28 4022 A22  F\nAPPLIED PHYSICS-II 3 3070 100 28 40215071  B\nINTRODUCTION TO IT SYSTEMS 2 3070 100 28 40124961  C\nFUNDA OF ELECT AND EC ENGG 3 3070 100 28 40234164  C\nENGG. MECHANICS 3 3070 100 28 40174057  D\n-----------------------------------------------------------------------------------------------\nPRACTICAL PAPERS\nAPPLIED PHYSICS LAB-II 1 1535 050 - 20132942  A\nINTRODUCTION TO IT SYSTEM LAB 2 1535 050 - 20123143  A\nFUNDA OF ELECT AND EC ENGG LAB 1 1535 050 - 20133346  A+\nENGG. MECHANICS LAB 2 1535 050 - 20123244  A\n-----------------------------------------------------------------------------------------------\nTERM WORK PAPERS\nC.U MOOCS/ SWAYAM/ ETC/ OTHERS 2 0614 020 - 08041014  B\nKYP/IT ESSEN/ PYTHON/ OTHERS 1 0614 020 - 08051217  A\nENVIRONMENTAL SCIENCE 0 10 -010 - 0410 -10  A+\n-----------------------------------------------------------------------------------------------\nGRAND TOTAL 24 750 491\n-----------------------------------------------------------------------------------------------\nSGPA \n-----------------------------------------------------------------------------------------------\nREMARKS : Carry in - MATHEMATICS-II",
        "college": "Government Polytechnic, Bhojpur",
        "name": "KOMAL RAJ",
        "roll": "211522023033",
        "branch": "20",
        "marks": 491,
        "remarks": "Carry in - MATHEMATICS-II",
        "theory": 180
    },
    {
        "text": " \n \nRegistration No : 1522023042\nRoll No         : 211522023042\n \nFollowing are the marks obtained by HARSH  RAJ\nof Government Polytechnic, Bhojpur\nat Semester II of Diploma in Electrical Engineering\nExamination 2024 (EVEN) held in the month of JUL, 2024\n \n \nResult Published On: 30/07/2024\nSTATE BOARD OF TECHNICAL EDUCATION\nBIHAR\n-----------------------------------------------------------------------------------------------\nSUBJECT  FULL MARKS PASS MARKS MARKS OBTAINED\nNAME OF SUBJECTS CREDITS INTFINTOTAL FINTOTAL INT FIN TOTAL GRADE\n-----------------------------------------------------------------------------------------------\nTHEORY PAPERS\nMATHEMATICS-II 4 3070 100 28 40183755  D\nAPPLIED PHYSICS-II 3 3070 100 28 40195069  C\nINTRODUCTION TO IT SYSTEMS 2 3070 100 28 40142943  E\nFUNDA OF ELECT AND EC ENGG 3 3070 100 28 40212849  E\nENGG. MECHANICS 3 3070 100 28 40163046  E\n-----------------------------------------------------------------------------------------------\nPRACTICAL PAPERS\nAPPLIED PHYSICS LAB-II 1 1535 050 - 20132942  A\nINTRODUCTION TO IT SYSTEM LAB 2 1535 050 - 20133144  A\nFUNDA OF ELECT AND EC ENGG LAB 1 1535 050 - 20123345  A+\nENGG. MECHANICS LAB 2 1535 050 - 20123244  A\n-----------------------------------------------------------------------------------------------\nTERM WORK PAPERS\nC.U MOOCS/ SWAYAM/ ETC/ OTHERS 2 0614 020 - 08041115  B\nKYP/IT ESSEN/ PYTHON/ OTHERS 1 0614 020 - 08051116  A\nENVIRONMENTAL SCIENCE 0 10 -010 - 0408 -08  A\n-----------------------------------------------------------------------------------------------\nGRAND TOTAL 24 750 476\n-----------------------------------------------------------------------------------------------\nSGPA 6.88\n-----------------------------------------------------------------------------------------------\nREMARKS : First Class",
        "college": "Government Polytechnic, Bhojpur",
        "name": "HARSH RAJ",
        "roll": "211522023042",
        "branch": "20",
        "marks": 476,
        "remarks": "First Class",
        "theory": 174
    },
    {
        "text": " \n \nRegistration No : 1522023022\nRoll No         : 211522023022\n \nFollowing are the marks obtained by DHANISH  KUMAR\nof Government Polytechnic, Bhojpur\nat Semester II of Diploma in Electrical Engineering\nExamination 2024 (EVEN) held in the month of JUL, 2024\n \n \nResult Published On: 30/07/2024\nSTATE BOARD OF TECHNICAL EDUCATION\nBIHAR\n-----------------------------------------------------------------------------------------------\nSUBJECT  FULL MARKS PASS MARKS MARKS OBTAINED\nNAME OF SUBJECTS CREDITS INTFINTOTAL FINTOTAL INT FIN TOTAL GRADE\n-----------------------------------------------------------------------------------------------\nTHEORY PAPERS\nMATHEMATICS-II 4 3070 100 28 40230831  F\nAPPLIED PHYSICS-II 3 3070 100 28 40143650  D\nINTRODUCTION TO IT SYSTEMS 2 3070 100 28 40175168  C\nFUNDA OF ELECT AND EC ENGG 3 3070 100 28 40152843  E\nENGG. MECHANICS 3 3070 100 28 40154762  C\n-----------------------------------------------------------------------------------------------\nPRACTICAL PAPERS\nAPPLIED PHYSICS LAB-II 1 1535 050 - 20123143  A\nINTRODUCTION TO IT SYSTEM LAB 2 1535 050 - 20113041  A\nFUNDA OF ELECT AND EC ENGG LAB 1 1535 050 - 20143347  A+\nENGG. MECHANICS LAB 2 1535 050 - 20123244  A\n-----------------------------------------------------------------------------------------------\nTERM WORK PAPERS\nC.U MOOCS/ SWAYAM/ ETC/ OTHERS 2 0614 020 - 08041115  B\nKYP/IT ESSEN/ PYTHON/ OTHERS 1 0614 020 - 08051015  B\nENVIRONMENTAL SCIENCE 0 10 -010 - 0408 -08  A\n-----------------------------------------------------------------------------------------------\nGRAND TOTAL 24 750 467\n-----------------------------------------------------------------------------------------------\nSGPA \n-----------------------------------------------------------------------------------------------\nREMARKS : Carry in - MATHEMATICS-II",
        "college": "Government Polytechnic, Bhojpur",
        "name": "DHANISH KUMAR",
        "roll": "211522023022",
        "branch": "20",
        "marks": 467,
        "remarks": "Carry in - MATHEMATICS-II",
        "theory": 170
    },
    {
        "text": " \n \nRegistration No : 1522023012\nRoll No         : 211522023012\n \nFollowing are the marks obtained by SANDIP  KUMAR\nof Government Polytechnic, Bhojpur\nat Semester II of Diploma in Electrical Engineering\nExamination 2024 (EVEN) held in the month of JUL, 2024\n \n \nResult Published On: 30/07/2024\nSTATE BOARD OF TECHNICAL EDUCATION\nBIHAR\n-----------------------------------------------------------------------------------------------\nSUBJECT  FULL MARKS PASS MARKS MARKS OBTAINED\nNAME OF SUBJECTS CREDITS INTFINTOTAL FINTOTAL INT FIN TOTAL GRADE\n-----------------------------------------------------------------------------------------------\nTHEORY PAPERS\nMATHEMATICS-II 4 3070 100 28 40181836  F\nAPPLIED PHYSICS-II 3 3070 100 28 40192847  E\nINTRODUCTION TO IT SYSTEMS 2 3070 100 28 40064551  D\nFUNDA OF ELECT AND EC ENGG 3 3070 100 28 40174562  C\nENGG. MECHANICS 3 3070 100 28 40153853  D\n-----------------------------------------------------------------------------------------------\nPRACTICAL PAPERS\nAPPLIED PHYSICS LAB-II 1 1535 050 - 20122638  B\nINTRODUCTION TO IT SYSTEM LAB 2 1535 050 - 20133043  A\nFUNDA OF ELECT AND EC ENGG LAB 1 1535 050 - 20122840  A\nENGG. MECHANICS LAB 2 1535 050 - 20123244  A\n-----------------------------------------------------------------------------------------------\nTERM WORK PAPERS\nC.U MOOCS/ SWAYAM/ ETC/ OTHERS 2 0614 020 - 08031013  C\nKYP/IT ESSEN/ PYTHON/ OTHERS 1 0614 020 - 08051015  B\nENVIRONMENTAL SCIENCE 0 10 -010 - 0410 -10  A+\n-----------------------------------------------------------------------------------------------\nGRAND TOTAL 24 750 452\n-----------------------------------------------------------------------------------------------\nSGPA \n-----------------------------------------------------------------------------------------------\nREMARKS : Carry in - MATHEMATICS-II",
        "college": "Government Polytechnic, Bhojpur",
        "name": "SANDIP KUMAR",
        "roll": "211522023012",
        "branch": "20",
        "marks": 452,
        "remarks": "Carry in - MATHEMATICS-II",
        "theory": 174
    },
    {
        "text": " \n \nRegistration No : 1522023016\nRoll No         : 211522023016\n \nFollowing are the marks obtained by KASHISH  KUMARI\nof Government Polytechnic, Bhojpur\nat Semester II of Diploma in Electrical Engineering\nExamination 2024 (EVEN) held in the month of JUL, 2024\n \n \nResult Published On: 30/07/2024\nSTATE BOARD OF TECHNICAL EDUCATION\nBIHAR\n-----------------------------------------------------------------------------------------------\nSUBJECT  FULL MARKS PASS MARKS MARKS OBTAINED\nNAME OF SUBJECTS CREDITS INTFINTOTAL FINTOTAL INT FIN TOTAL GRADE\n-----------------------------------------------------------------------------------------------\nTHEORY PAPERS\nMATHEMATICS-II 4 3070 100 28 40212849  E\nAPPLIED PHYSICS-II 3 3070 100 28 40132841  E\nINTRODUCTION TO IT SYSTEMS 2 3070 100 28 40214768  C\nFUNDA OF ELECT AND EC ENGG 3 3070 100 28 40223254  D\nENGG. MECHANICS 3 3070 100 28 40223456  D\n-----------------------------------------------------------------------------------------------\nPRACTICAL PAPERS\nAPPLIED PHYSICS LAB-II 1 1535 050 - 20133144  A\nINTRODUCTION TO IT SYSTEM LAB 2 1535 050 - 20133245  A+\nFUNDA OF ELECT AND EC ENGG LAB 1 1535 050 - 20143448  A+\nENGG. MECHANICS LAB 2 1535 050 - 20133245  A+\n-----------------------------------------------------------------------------------------------\nTERM WORK PAPERS\nC.U MOOCS/ SWAYAM/ ETC/ OTHERS 2 0614 020 - 08051217  A\nKYP/IT ESSEN/ PYTHON/ OTHERS 1 0614 020 - 08041216  A\nENVIRONMENTAL SCIENCE 0 10 -010 - 0410 -10  A+\n-----------------------------------------------------------------------------------------------\nGRAND TOTAL 24 750 493\n-----------------------------------------------------------------------------------------------\nSGPA 7.12\n-----------------------------------------------------------------------------------------------\nREMARKS : First Class",
        "college": "Government Polytechnic, Bhojpur",
        "name": "KASHISH KUMARI",
        "roll": "211522023016",
        "branch": "20",
        "marks": 493,
        "remarks": "First Class",
        "theory": 169
    },
    {
        "text": " \n \nRegistration No : 1522023032\nRoll No         : 211522023032\n \nFollowing are the marks obtained by RANVIR  KUMAR\nof Government Polytechnic, Bhojpur\nat Semester II of Diploma in Electrical Engineering\nExamination 2024 (EVEN) held in the month of JUL, 2024\n \n \nResult Published On: 30/07/2024\nSTATE BOARD OF TECHNICAL EDUCATION\nBIHAR\n-----------------------------------------------------------------------------------------------\nSUBJECT  FULL MARKS PASS MARKS MARKS OBTAINED\nNAME OF SUBJECTS CREDITS INTFINTOTAL FINTOTAL INT FIN TOTAL GRADE\n-----------------------------------------------------------------------------------------------\nTHEORY PAPERS\nMATHEMATICS-II 4 3070 100 28 40202848  E\nAPPLIED PHYSICS-II 3 3070 100 28 40243256  D\nINTRODUCTION TO IT SYSTEMS 2 3070 100 28 40123951  D\nFUNDA OF ELECT AND EC ENGG 3 3070 100 28 40131932  F\nENGG. MECHANICS 3 3070 100 28 40182846  E\n-----------------------------------------------------------------------------------------------\nPRACTICAL PAPERS\nAPPLIED PHYSICS LAB-II 1 1535 050 - 20122941  A\nINTRODUCTION TO IT SYSTEM LAB 2 1535 050 - 20123143  A\nFUNDA OF ELECT AND EC ENGG LAB 1 1535 050 - 20123244  A\nENGG. MECHANICS LAB 2 1535 050 - 20123244  A\n-----------------------------------------------------------------------------------------------\nTERM WORK PAPERS\nC.U MOOCS/ SWAYAM/ ETC/ OTHERS 2 0614 020 - 08051116  A\nKYP/IT ESSEN/ PYTHON/ OTHERS 1 0614 020 - 08041216  A\nENVIRONMENTAL SCIENCE 0 10 -010 - 0408 -08  A\n-----------------------------------------------------------------------------------------------\nGRAND TOTAL 24 750 445\n-----------------------------------------------------------------------------------------------\nSGPA \n-----------------------------------------------------------------------------------------------\nREMARKS : Carry in - FUNDA OF ELECT AND EC ENGG",
        "college": "Government Polytechnic, Bhojpur",
        "name": "RANVIR KUMAR",
        "roll": "211522023032",
        "branch": "20",
        "marks": 445,
        "remarks": "Carry in - FUNDA OF ELECT AND EC ENGG",
        "theory": 146
    },
    {
        "text": " \n \nRegistration No : 1522023053\nRoll No         : 211522023053\n \nFollowing are the marks obtained by ANSHU  KUMAR\nof Government Polytechnic, Bhojpur\nat Semester II of Diploma in Electrical Engineering\nExamination 2024 (EVEN) held in the month of JUL, 2024\n \n \nResult Published On: 30/07/2024\nSTATE BOARD OF TECHNICAL EDUCATION\nBIHAR\n-----------------------------------------------------------------------------------------------\nSUBJECT  FULL MARKS PASS MARKS MARKS OBTAINED\nNAME OF SUBJECTS CREDITS INTFINTOTAL FINTOTAL INT FIN TOTAL GRADE\n-----------------------------------------------------------------------------------------------\nTHEORY PAPERS\nMATHEMATICS-II 4 3070 100 28 40141428  F\nAPPLIED PHYSICS-II 3 3070 100 28 40255075  B\nINTRODUCTION TO IT SYSTEMS 2 3070 100 28 40124557  D\nFUNDA OF ELECT AND EC ENGG 3 3070 100 28 40172845  E\nENGG. MECHANICS 3 3070 100 28 40153954  D\n-----------------------------------------------------------------------------------------------\nPRACTICAL PAPERS\nAPPLIED PHYSICS LAB-II 1 1535 050 - 20133144  A\nINTRODUCTION TO IT SYSTEM LAB 2 1535 050 - 20143145  A+\nFUNDA OF ELECT AND EC ENGG LAB 1 1535 050 - 20133245  A+\nENGG. MECHANICS LAB 2 1535 050 - 20123345  A+\n-----------------------------------------------------------------------------------------------\nTERM WORK PAPERS\nC.U MOOCS/ SWAYAM/ ETC/ OTHERS 2 0614 020 - 08041115  B\nKYP/IT ESSEN/ PYTHON/ OTHERS 1 0614 020 - 08051217  A\nENVIRONMENTAL SCIENCE 0 10 -010 - 0408 -08  A\n-----------------------------------------------------------------------------------------------\nGRAND TOTAL 24 750 478\n-----------------------------------------------------------------------------------------------\nSGPA \n-----------------------------------------------------------------------------------------------\nREMARKS : Carry in - MATHEMATICS-II",
        "college": "Government Polytechnic, Bhojpur",
        "name": "ANSHU KUMAR",
        "roll": "211522023053",
        "branch": "20",
        "marks": 478,
        "remarks": "Carry in - MATHEMATICS-II",
        "theory": 176
    },
    {
        "text": " \n \nRegistration No : 1522023027\nRoll No         : 211522023027\n \nFollowing are the marks obtained by MD GULJAR AHMAD\nof Government Polytechnic, Bhojpur\nat Semester II of Diploma in Electrical Engineering\nExamination 2024 (EVEN) held in the month of JUL, 2024\n \n \nResult Published On: 30/07/2024\nSTATE BOARD OF TECHNICAL EDUCATION\nBIHAR\n-----------------------------------------------------------------------------------------------\nSUBJECT  FULL MARKS PASS MARKS MARKS OBTAINED\nNAME OF SUBJECTS CREDITS INTFINTOTAL FINTOTAL INT FIN TOTAL GRADE\n-----------------------------------------------------------------------------------------------\nTHEORY PAPERS\nMATHEMATICS-II 4 3070 100 28 40133548  E\nAPPLIED PHYSICS-II 3 3070 100 28 40134457  D\nINTRODUCTION TO IT SYSTEMS 2 3070 100 28 40103040  E\nFUNDA OF ELECT AND EC ENGG 3 3070 100 28 40140115  F\nENGG. MECHANICS 3 3070 100 28 40124456  D\n-----------------------------------------------------------------------------------------------\nPRACTICAL PAPERS\nAPPLIED PHYSICS LAB-II 1 1535 050 - 20123042  A\nINTRODUCTION TO IT SYSTEM LAB 2 1535 050 - 20123143  A\nFUNDA OF ELECT AND EC ENGG LAB 1 1535 050 - 20133245  A+\nENGG. MECHANICS LAB 2 1535 050 - 20103040  A\n-----------------------------------------------------------------------------------------------\nTERM WORK PAPERS\nC.U MOOCS/ SWAYAM/ ETC/ OTHERS 2 0614 020 - 08041014  B\nKYP/IT ESSEN/ PYTHON/ OTHERS 1 0614 020 - 08001010  D\nENVIRONMENTAL SCIENCE 0 10 -010 - 0408 -08  A\n-----------------------------------------------------------------------------------------------\nGRAND TOTAL 24 750 418\n-----------------------------------------------------------------------------------------------\nSGPA \n-----------------------------------------------------------------------------------------------\nREMARKS : Carry in - FUNDA OF ELECT AND EC ENGG",
        "college": "Government Polytechnic, Bhojpur",
        "name": "MD GULJAR AHMAD",
        "roll": "211522023027",
        "branch": "20",
        "marks": 418,
        "remarks": "Carry in - FUNDA OF ELECT AND EC ENGG",
        "theory": 154
    },
    {
        "text": " \n \nRegistration No : 1522023056\nRoll No         : 211522023056\n \nFollowing are the marks obtained by NURALAM  ANSARI\nof Government Polytechnic, Bhojpur\nat Semester II of Diploma in Electrical Engineering\nExamination 2024 (EVEN) held in the month of JUL, 2024\n \n \nResult Published On: 30/07/2024\nSTATE BOARD OF TECHNICAL EDUCATION\nBIHAR\n-----------------------------------------------------------------------------------------------\nSUBJECT  FULL MARKS PASS MARKS MARKS OBTAINED\nNAME OF SUBJECTS CREDITS INTFINTOTAL FINTOTAL INT FIN TOTAL GRADE\n-----------------------------------------------------------------------------------------------\nTHEORY PAPERS\nMATHEMATICS-II 4 3070 100 28 40166278  B\nAPPLIED PHYSICS-II 3 3070 100 28 40255378  B\nINTRODUCTION TO IT SYSTEMS 2 3070 100 28 40155065  C\nFUNDA OF ELECT AND EC ENGG 3 3070 100 28 40214970  B\nENGG. MECHANICS 3 3070 100 28 40216687  A\n-----------------------------------------------------------------------------------------------\nPRACTICAL PAPERS\nAPPLIED PHYSICS LAB-II 1 1535 050 - 20133144  A\nINTRODUCTION TO IT SYSTEM LAB 2 1535 050 - 20123244  A\nFUNDA OF ELECT AND EC ENGG LAB 1 1535 050 - 20123244  A\nENGG. MECHANICS LAB 2 1535 050 - 20123244  A\n-----------------------------------------------------------------------------------------------\nTERM WORK PAPERS\nC.U MOOCS/ SWAYAM/ ETC/ OTHERS 2 0614 020 - 08051116  A\nKYP/IT ESSEN/ PYTHON/ OTHERS 1 0614 020 - 08051015  B\nENVIRONMENTAL SCIENCE 0 10 -010 - 0410 -10  A+\n-----------------------------------------------------------------------------------------------\nGRAND TOTAL 24 750 595\n-----------------------------------------------------------------------------------------------\nSGPA 8.38\n-----------------------------------------------------------------------------------------------\nREMARKS : First Class with Distinction",
        "college": "Government Polytechnic, Bhojpur",
        "name": "NURALAM ANSARI",
        "roll": "211522023056",
        "branch": "20",
        "marks": 595,
        "remarks": "First Class with Distinction",
        "theory": 280
    },
    {
        "text": " \n \nRegistration No : 1522023045\nRoll No         : 211522023045\n \nFollowing are the marks obtained by ROHIT  KUMAR\nof Government Polytechnic, Bhojpur\nat Semester II of Diploma in Electrical Engineering\nExamination 2024 (EVEN) held in the month of JUL, 2024\n \n \nResult Published On: 30/07/2024\nSTATE BOARD OF TECHNICAL EDUCATION\nBIHAR\n-----------------------------------------------------------------------------------------------\nSUBJECT  FULL MARKS PASS MARKS MARKS OBTAINED\nNAME OF SUBJECTS CREDITS INTFINTOTAL FINTOTAL INT FIN TOTAL GRADE\n-----------------------------------------------------------------------------------------------\nTHEORY PAPERS\nMATHEMATICS-II 4 3070 100 28 40246084  A\nAPPLIED PHYSICS-II 3 3070 100 28 40285886  A\nINTRODUCTION TO IT SYSTEMS 2 3070 100 28 40184462  C\nFUNDA OF ELECT AND EC ENGG 3 3070 100 28 40254772  B\nENGG. MECHANICS 3 3070 100 28 40215677  B\n-----------------------------------------------------------------------------------------------\nPRACTICAL PAPERS\nAPPLIED PHYSICS LAB-II 1 1535 050 - 20143145  A+\nINTRODUCTION TO IT SYSTEM LAB 2 1535 050 - 20123042  A\nFUNDA OF ELECT AND EC ENGG LAB 1 1535 050 - 20133346  A+\nENGG. MECHANICS LAB 2 1535 050 - 20133346  A+\n-----------------------------------------------------------------------------------------------\nTERM WORK PAPERS\nC.U MOOCS/ SWAYAM/ ETC/ OTHERS 2 0614 020 - 08041014  B\nKYP/IT ESSEN/ PYTHON/ OTHERS 1 0614 020 - 08041115  B\nENVIRONMENTAL SCIENCE 0 10 -010 - 0410 -10  A+\n-----------------------------------------------------------------------------------------------\nGRAND TOTAL 24 750 599\n-----------------------------------------------------------------------------------------------\nSGPA 8.62\n-----------------------------------------------------------------------------------------------\nREMARKS : First Class with Distinction",
        "college": "Government Polytechnic, Bhojpur",
        "name": "ROHIT KUMAR",
        "roll": "211522023045",
        "branch": "20",
        "marks": 599,
        "remarks": "First Class with Distinction",
        "theory": 265
    },
    {
        "text": " \n \nRegistration No : 1522023008\nRoll No         : 211522023008\n \nFollowing are the marks obtained by ANKU  KUMAR\nof Government Polytechnic, Bhojpur\nat Semester II of Diploma in Electrical Engineering\nExamination 2024 (EVEN) held in the month of JUL, 2024\n \n \nResult Published On: 30/07/2024\nSTATE BOARD OF TECHNICAL EDUCATION\nBIHAR\n-----------------------------------------------------------------------------------------------\nSUBJECT  FULL MARKS PASS MARKS MARKS OBTAINED\nNAME OF SUBJECTS CREDITS INTFINTOTAL FINTOTAL INT FIN TOTAL GRADE\n-----------------------------------------------------------------------------------------------\nTHEORY PAPERS\nMATHEMATICS-II 4 3070 100 28 402125+349  E\nAPPLIED PHYSICS-II 3 3070 100 28 40273663  C\nINTRODUCTION TO IT SYSTEMS 2 3070 100 28 40222951  D\nFUNDA OF ELECT AND EC ENGG 3 3070 100 28 40273360  C\nENGG. MECHANICS 3 3070 100 28 402148-366  C\n-----------------------------------------------------------------------------------------------\nPRACTICAL PAPERS\nAPPLIED PHYSICS LAB-II 1 1535 050 - 20113142  A\nINTRODUCTION TO IT SYSTEM LAB 2 1535 050 - 20133346  A+\nFUNDA OF ELECT AND EC ENGG LAB 1 1535 050 - 20143448  A+\nENGG. MECHANICS LAB 2 1535 050 - 20143448  A+\n-----------------------------------------------------------------------------------------------\nTERM WORK PAPERS\nC.U MOOCS/ SWAYAM/ ETC/ OTHERS 2 0614 020 - 08051217  A\nKYP/IT ESSEN/ PYTHON/ OTHERS 1 0614 020 - 08031316  A\nENVIRONMENTAL SCIENCE 0 10 -010 - 0408 -08  A\n-----------------------------------------------------------------------------------------------\nGRAND TOTAL 24 750 514\n-----------------------------------------------------------------------------------------------\nSGPA 7.54\n-----------------------------------------------------------------------------------------------\nREMARKS : First Class (U/R)",
        "college": "Government Polytechnic, Bhojpur",
        "name": "ANKU KUMAR",
        "roll": "211522023008",
        "branch": "20",
        "marks": 514,
        "remarks": "First Class (U/R)",
        "theory": 171
    },
    {
        "text": " \n \nRegistration No : 1522023009\nRoll No         : 211522023009\n \nFollowing are the marks obtained by BHAWNA KUMARI PANDIT\nof Government Polytechnic, Bhojpur\nat Semester II of Diploma in Electrical Engineering\nExamination 2024 (EVEN) held in the month of JUL, 2024\n \n \nResult Published On: 30/07/2024\nSTATE BOARD OF TECHNICAL EDUCATION\nBIHAR\n-----------------------------------------------------------------------------------------------\nSUBJECT  FULL MARKS PASS MARKS MARKS OBTAINED\nNAME OF SUBJECTS CREDITS INTFINTOTAL FINTOTAL INT FIN TOTAL GRADE\n-----------------------------------------------------------------------------------------------\nTHEORY PAPERS\nMATHEMATICS-II 4 3070 100 28 40285482  A\nAPPLIED PHYSICS-II 3 3070 100 28 40254065  C\nINTRODUCTION TO IT SYSTEMS 2 3070 100 28 40164864  C\nFUNDA OF ELECT AND EC ENGG 3 3070 100 28 40264672  B\nENGG. MECHANICS 3 3070 100 28 40235982  A\n-----------------------------------------------------------------------------------------------\nPRACTICAL PAPERS\nAPPLIED PHYSICS LAB-II 1 1535 050 - 20102939  B\nINTRODUCTION TO IT SYSTEM LAB 2 1535 050 - 20133245  A+\nFUNDA OF ELECT AND EC ENGG LAB 1 1535 050 - 20143448  A+\nENGG. MECHANICS LAB 2 1535 050 - 20133346  A+\n-----------------------------------------------------------------------------------------------\nTERM WORK PAPERS\nC.U MOOCS/ SWAYAM/ ETC/ OTHERS 2 0614 020 - 08051217  A\nKYP/IT ESSEN/ PYTHON/ OTHERS 1 0614 020 - 08041317  A\nENVIRONMENTAL SCIENCE 0 10 -010 - 0410 -10  A+\n-----------------------------------------------------------------------------------------------\nGRAND TOTAL 24 750 587\n-----------------------------------------------------------------------------------------------\nSGPA 8.62\n-----------------------------------------------------------------------------------------------\nREMARKS : First Class with Distinction",
        "college": "Government Polytechnic, Bhojpur",
        "name": "BHAWNA KUMARI PANDIT",
        "roll": "211522023009",
        "branch": "20",
        "marks": 587,
        "remarks": "First Class with Distinction",
        "theory": 247
    },
    {
        "text": " \n \nRegistration No : 1522023018\nRoll No         : 211522023018\n \nFollowing are the marks obtained by ASHISH  RAJ\nof Government Polytechnic, Bhojpur\nat Semester II of Diploma in Electrical Engineering\nExamination 2024 (EVEN) held in the month of JUL, 2024\n \n \nResult Published On: 30/07/2024\nSTATE BOARD OF TECHNICAL EDUCATION\nBIHAR\n-----------------------------------------------------------------------------------------------\nSUBJECT  FULL MARKS PASS MARKS MARKS OBTAINED\nNAME OF SUBJECTS CREDITS INTFINTOTAL FINTOTAL INT FIN TOTAL GRADE\n-----------------------------------------------------------------------------------------------\nTHEORY PAPERS\nMATHEMATICS-II 4 3070 100 28 40214667  C\nAPPLIED PHYSICS-II 3 3070 100 28 40244367  C\nINTRODUCTION TO IT SYSTEMS 2 3070 100 28 40214162  C\nFUNDA OF ELECT AND EC ENGG 3 3070 100 28 40203555  D\nENGG. MECHANICS 3 3070 100 28 40265985  A\n-----------------------------------------------------------------------------------------------\nPRACTICAL PAPERS\nAPPLIED PHYSICS LAB-II 1 1535 050 - 20123143  A\nINTRODUCTION TO IT SYSTEM LAB 2 1535 050 - 20113243  A\nFUNDA OF ELECT AND EC ENGG LAB 1 1535 050 - 20123244  A\nENGG. MECHANICS LAB 2 1535 050 - 20143448  A+\n-----------------------------------------------------------------------------------------------\nTERM WORK PAPERS\nC.U MOOCS/ SWAYAM/ ETC/ OTHERS 2 0614 020 - 08051116  A\nKYP/IT ESSEN/ PYTHON/ OTHERS 1 0614 020 - 08051015  B\nENVIRONMENTAL SCIENCE 0 10 -010 - 0408 -08  A\n-----------------------------------------------------------------------------------------------\nGRAND TOTAL 24 750 553\n-----------------------------------------------------------------------------------------------\nSGPA 7.92\n-----------------------------------------------------------------------------------------------\nREMARKS : First Class",
        "college": "Government Polytechnic, Bhojpur",
        "name": "ASHISH RAJ",
        "roll": "211522023018",
        "branch": "20",
        "marks": 553,
        "remarks": "First Class",
        "theory": 224
    },
    {
        "text": " \n \nRegistration No : 1522023046\nRoll No         : 211522023046\n \nFollowing are the marks obtained by KESHAW KUMAR TIWARI\nof Government Polytechnic, Bhojpur\nat Semester II of Diploma in Electrical Engineering\nExamination 2024 (EVEN) held in the month of JUL, 2024\n \n \nResult Published On: 30/07/2024\nSTATE BOARD OF TECHNICAL EDUCATION\nBIHAR\n-----------------------------------------------------------------------------------------------\nSUBJECT  FULL MARKS PASS MARKS MARKS OBTAINED\nNAME OF SUBJECTS CREDITS INTFINTOTAL FINTOTAL INT FIN TOTAL GRADE\n-----------------------------------------------------------------------------------------------\nTHEORY PAPERS\nMATHEMATICS-II 4 3070 100 28 40153651  D\nAPPLIED PHYSICS-II 3 3070 100 28 40255075  B\nINTRODUCTION TO IT SYSTEMS 2 3070 100 28 40134255  D\nFUNDA OF ELECT AND EC ENGG 3 3070 100 28 40223557  D\nENGG. MECHANICS 3 3070 100 28 40194564  C\n-----------------------------------------------------------------------------------------------\nPRACTICAL PAPERS\nAPPLIED PHYSICS LAB-II 1 1535 050 - 20133144  A\nINTRODUCTION TO IT SYSTEM LAB 2 1535 050 - 20133144  A\nFUNDA OF ELECT AND EC ENGG LAB 1 1535 050 - 20133245  A+\nENGG. MECHANICS LAB 2 1535 050 - 20123244  A\n-----------------------------------------------------------------------------------------------\nTERM WORK PAPERS\nC.U MOOCS/ SWAYAM/ ETC/ OTHERS 2 0614 020 - 08041216  A\nKYP/IT ESSEN/ PYTHON/ OTHERS 1 0614 020 - 08041014  B\nENVIRONMENTAL SCIENCE 0 10 -010 - 0410 -10  A+\n-----------------------------------------------------------------------------------------------\nGRAND TOTAL 24 750 519\n-----------------------------------------------------------------------------------------------\nSGPA 7.5\n-----------------------------------------------------------------------------------------------\nREMARKS : First Class",
        "college": "Government Polytechnic, Bhojpur",
        "name": "KESHAW KUMAR TIWARI",
        "roll": "211522023046",
        "branch": "20",
        "marks": 519,
        "remarks": "First Class",
        "theory": 208
    },
    {
        "text": " \n \nRegistration No : 1522023043\nRoll No         : 211522023043\n \nFollowing are the marks obtained by ALISHA  SINGH\nof Government Polytechnic, Bhojpur\nat Semester II of Diploma in Electrical Engineering\nExamination 2024 (EVEN) held in the month of JUL, 2024\n \n \nResult Published On: 30/07/2024\nSTATE BOARD OF TECHNICAL EDUCATION\nBIHAR\n-----------------------------------------------------------------------------------------------\nSUBJECT  FULL MARKS PASS MARKS MARKS OBTAINED\nNAME OF SUBJECTS CREDITS INTFINTOTAL FINTOTAL INT FIN TOTAL GRADE\n-----------------------------------------------------------------------------------------------\nTHEORY PAPERS\nMATHEMATICS-II 4 3070 100 28 40213152  D\nAPPLIED PHYSICS-II 3 3070 100 28 40284876  B\nINTRODUCTION TO IT SYSTEMS 2 3070 100 28 40184462  C\nFUNDA OF ELECT AND EC ENGG 3 3070 100 28 40253762  C\nENGG. MECHANICS 3 3070 100 28 40264167  C\n-----------------------------------------------------------------------------------------------\nPRACTICAL PAPERS\nAPPLIED PHYSICS LAB-II 1 1535 050 - 20142842  A\nINTRODUCTION TO IT SYSTEM LAB 2 1535 050 - 20143246  A+\nFUNDA OF ELECT AND EC ENGG LAB 1 1535 050 - 20143448  A+\nENGG. MECHANICS LAB 2 1535 050 - 20143448  A+\n-----------------------------------------------------------------------------------------------\nTERM WORK PAPERS\nC.U MOOCS/ SWAYAM/ ETC/ OTHERS 2 0614 020 - 08041115  B\nKYP/IT ESSEN/ PYTHON/ OTHERS 1 0614 020 - 08051217  A\nENVIRONMENTAL SCIENCE 0 10 -010 - 0410 -10  A+\n-----------------------------------------------------------------------------------------------\nGRAND TOTAL 24 750 545\n-----------------------------------------------------------------------------------------------\nSGPA 7.83\n-----------------------------------------------------------------------------------------------\nREMARKS : First Class",
        "college": "Government Polytechnic, Bhojpur",
        "name": "ALISHA SINGH",
        "roll": "211522023043",
        "branch": "20",
        "marks": 545,
        "remarks": "First Class",
        "theory": 201
    },
    {
        "text": " \n \nRegistration No : 1522023060\nRoll No         : 211522023060\n \nFollowing are the marks obtained by ANKUR  KUMAR\nof Government Polytechnic, Bhojpur\nat Semester II of Diploma in Electrical Engineering\nExamination 2024 (EVEN) held in the month of JUL, 2024\n \n \nResult Published On: 30/07/2024\nSTATE BOARD OF TECHNICAL EDUCATION\nBIHAR\n-----------------------------------------------------------------------------------------------\nSUBJECT  FULL MARKS PASS MARKS MARKS OBTAINED\nNAME OF SUBJECTS CREDITS INTFINTOTAL FINTOTAL INT FIN TOTAL GRADE\n-----------------------------------------------------------------------------------------------\nTHEORY PAPERS\nMATHEMATICS-II 4 3070 100 28 40161026  F\nAPPLIED PHYSICS-II 3 3070 100 28 40272249  E\nINTRODUCTION TO IT SYSTEMS 2 3070 100 28 40132841  E\nFUNDA OF ELECT AND EC ENGG 3 3070 100 28 40162743  E\nENGG. MECHANICS 3 3070 100 28 40133245  E\n-----------------------------------------------------------------------------------------------\nPRACTICAL PAPERS\nAPPLIED PHYSICS LAB-II 1 1535 050 - 20132841  A\nINTRODUCTION TO IT SYSTEM LAB 2 1535 050 - 20123042  A\nFUNDA OF ELECT AND EC ENGG LAB 1 1535 050 - 20123446  A+\nENGG. MECHANICS LAB 2 1535 050 - 20113142  A\n-----------------------------------------------------------------------------------------------\nTERM WORK PAPERS\nC.U MOOCS/ SWAYAM/ ETC/ OTHERS 2 0614 020 - 08061016  A\nKYP/IT ESSEN/ PYTHON/ OTHERS 1 0614 020 - 08041216  A\nENVIRONMENTAL SCIENCE 0 10 -010 - 0408 -08  A\n-----------------------------------------------------------------------------------------------\nGRAND TOTAL 24 750 415\n-----------------------------------------------------------------------------------------------\nSGPA \n-----------------------------------------------------------------------------------------------\nREMARKS : Fail",
        "college": "Government Polytechnic, Bhojpur",
        "name": "ANKUR KUMAR",
        "roll": "211522023060",
        "branch": "20",
        "marks": 415,
        "remarks": "Fail",
        "theory": 119
    },
    {
        "text": " \n \nRegistration No : 1522023019\nRoll No         : 211522023019\n \nFollowing are the marks obtained by AMARTYA RAJ\nof Government Polytechnic, Bhojpur\nat Semester II of Diploma in Electrical Engineering\nExamination 2024 (EVEN) held in the month of JUL, 2024\n \n \nResult Published On: 30/07/2024\nSTATE BOARD OF TECHNICAL EDUCATION\nBIHAR\n-----------------------------------------------------------------------------------------------\nSUBJECT  FULL MARKS PASS MARKS MARKS OBTAINED\nNAME OF SUBJECTS CREDITS INTFINTOTAL FINTOTAL INT FIN TOTAL GRADE\n-----------------------------------------------------------------------------------------------\nTHEORY PAPERS\nMATHEMATICS-II 4 3070 100 28 40221436  F\nAPPLIED PHYSICS-II 3 3070 100 28 40132336  F\nINTRODUCTION TO IT SYSTEMS 2 3070 100 28 40112940  E\nFUNDA OF ELECT AND EC ENGG 3 3070 100 28 40152843  E\nENGG. MECHANICS 3 3070 100 28 40194463  C\n-----------------------------------------------------------------------------------------------\nPRACTICAL PAPERS\nAPPLIED PHYSICS LAB-II 1 1535 050 - 20102939  B\nINTRODUCTION TO IT SYSTEM LAB 2 1535 050 - 20123143  A\nFUNDA OF ELECT AND EC ENGG LAB 1 1535 050 - 20123244  A\nENGG. MECHANICS LAB 2 1535 050 - 20103040  A\n-----------------------------------------------------------------------------------------------\nTERM WORK PAPERS\nC.U MOOCS/ SWAYAM/ ETC/ OTHERS 2 0614 020 - 08051217  A\nKYP/IT ESSEN/ PYTHON/ OTHERS 1 0614 020 - 08041014  B\nENVIRONMENTAL SCIENCE 0 10 -010 - 0408 -08  A\n-----------------------------------------------------------------------------------------------\nGRAND TOTAL 24 750 423\n-----------------------------------------------------------------------------------------------\nSGPA \n-----------------------------------------------------------------------------------------------\nREMARKS : Carry in - MATHEMATICS-II\n APPLIED PHYSICS-II",
        "college": "Government Polytechnic, Bhojpur",
        "name": "AMARTYA RAJ",
        "roll": "211522023019",
        "branch": "20",
        "marks": 423,
        "remarks": "Carry in - MATHEMATICS-II",
        "theory": 138
    },
    {
        "text": " \n \nRegistration No : 1522023002\nRoll No         : 211522023002\n \nFollowing are the marks obtained by ANISHA  KUMARI\nof Government Polytechnic, Bhojpur\nat Semester II of Diploma in Electrical Engineering\nExamination 2024 (EVEN) held in the month of JUL, 2024\n \n \nResult Published On: 30/07/2024\nSTATE BOARD OF TECHNICAL EDUCATION\nBIHAR\n-----------------------------------------------------------------------------------------------\nSUBJECT  FULL MARKS PASS MARKS MARKS OBTAINED\nNAME OF SUBJECTS CREDITS INTFINTOTAL FINTOTAL INT FIN TOTAL GRADE\n-----------------------------------------------------------------------------------------------\nTHEORY PAPERS\nMATHEMATICS-II 4 3070 100 28 40180624  F\nAPPLIED PHYSICS-II 3 3070 100 28 40162238  F\nINTRODUCTION TO IT SYSTEMS 2 3070 100 28 40114758  D\nFUNDA OF ELECT AND EC ENGG 3 3070 100 28 40252853  D\nENGG. MECHANICS 3 3070 100 28 40203656  D\n-----------------------------------------------------------------------------------------------\nPRACTICAL PAPERS\nAPPLIED PHYSICS LAB-II 1 1535 050 - 20102939  B\nINTRODUCTION TO IT SYSTEM LAB 2 1535 050 - 20143145  A+\nFUNDA OF ELECT AND EC ENGG LAB 1 1535 050 - 20143448  A+\nENGG. MECHANICS LAB 2 1535 050 - 20143347  A+\n-----------------------------------------------------------------------------------------------\nTERM WORK PAPERS\nC.U MOOCS/ SWAYAM/ ETC/ OTHERS 2 0614 020 - 08041115  B\nKYP/IT ESSEN/ PYTHON/ OTHERS 1 0614 020 - 08051116  A\nENVIRONMENTAL SCIENCE 0 10 -010 - 0407 -07  B\n-----------------------------------------------------------------------------------------------\nGRAND TOTAL 24 750 446\n-----------------------------------------------------------------------------------------------\nSGPA \n-----------------------------------------------------------------------------------------------\nREMARKS : Carry in - MATHEMATICS-II\n APPLIED PHYSICS-II",
        "college": "Government Polytechnic, Bhojpur",
        "name": "ANISHA KUMARI",
        "roll": "211522023002",
        "branch": "20",
        "marks": 446,
        "remarks": "Carry in - MATHEMATICS-II",
        "theory": 139
    },
    {
        "text": " \n \nRegistration No : 1522023001\nRoll No         : 211522023001\n \nFollowing are the marks obtained by SAHIL  KUMAR\nof Government Polytechnic, Bhojpur\nat Semester II of Diploma in Electrical Engineering\nExamination 2024 (EVEN) held in the month of JUL, 2024\n \n \nResult Published On: 30/07/2024\nSTATE BOARD OF TECHNICAL EDUCATION\nBIHAR\n-----------------------------------------------------------------------------------------------\nSUBJECT  FULL MARKS PASS MARKS MARKS OBTAINED\nNAME OF SUBJECTS CREDITS INTFINTOTAL FINTOTAL INT FIN TOTAL GRADE\n-----------------------------------------------------------------------------------------------\nTHEORY PAPERS\nMATHEMATICS-II 4 3070 100 28 40225678  B\nAPPLIED PHYSICS-II 3 3070 100 28 40285583  A\nINTRODUCTION TO IT SYSTEMS 2 3070 100 28 40274673  B\nFUNDA OF ELECT AND EC ENGG 3 3070 100 28 40294372  B\nENGG. MECHANICS 3 3070 100 28 40285987  A\n-----------------------------------------------------------------------------------------------\nPRACTICAL PAPERS\nAPPLIED PHYSICS LAB-II 1 1535 050 - 20143145  A+\nINTRODUCTION TO IT SYSTEM LAB 2 1535 050 - 20143347  A+\nFUNDA OF ELECT AND EC ENGG LAB 1 1535 050 - 20153550  A+\nENGG. MECHANICS LAB 2 1535 050 - 20143448  A+\n-----------------------------------------------------------------------------------------------\nTERM WORK PAPERS\nC.U MOOCS/ SWAYAM/ ETC/ OTHERS 2 0614 020 - 08051318  A+\nKYP/IT ESSEN/ PYTHON/ OTHERS 1 0614 020 - 08041317  A\nENVIRONMENTAL SCIENCE 0 10 -010 - 0410 -10  A+\n-----------------------------------------------------------------------------------------------\nGRAND TOTAL 24 750 628\n-----------------------------------------------------------------------------------------------\nSGPA 8.96\n-----------------------------------------------------------------------------------------------\nREMARKS : First Class with Distinction",
        "college": "Government Polytechnic, Bhojpur",
        "name": "SAHIL KUMAR",
        "roll": "211522023001",
        "branch": "20",
        "marks": 628,
        "remarks": "First Class with Distinction",
        "theory": 259
    },
    {
        "text": " \n \nRegistration No : 1522023015\nRoll No         : 211522023015\n \nFollowing are the marks obtained by RISHABH RAJ SINGH\nof Government Polytechnic, Bhojpur\nat Semester II of Diploma in Electrical Engineering\nExamination 2024 (EVEN) held in the month of JUL, 2024\n \n \nResult Published On: 30/07/2024\nSTATE BOARD OF TECHNICAL EDUCATION\nBIHAR\n-----------------------------------------------------------------------------------------------\nSUBJECT  FULL MARKS PASS MARKS MARKS OBTAINED\nNAME OF SUBJECTS CREDITS INTFINTOTAL FINTOTAL INT FIN TOTAL GRADE\n-----------------------------------------------------------------------------------------------\nTHEORY PAPERS\nMATHEMATICS-II 4 3070 100 28 40223355  D\nAPPLIED PHYSICS-II 3 3070 100 28 40215071  B\nINTRODUCTION TO IT SYSTEMS 2 3070 100 28 40174057  D\nFUNDA OF ELECT AND EC ENGG 3 3070 100 28 40262854  D\nENGG. MECHANICS 3 3070 100 28 40205070  B\n-----------------------------------------------------------------------------------------------\nPRACTICAL PAPERS\nAPPLIED PHYSICS LAB-II 1 1535 050 - 20143044  A\nINTRODUCTION TO IT SYSTEM LAB 2 1535 050 - 20123143  A\nFUNDA OF ELECT AND EC ENGG LAB 1 1535 050 - 20133346  A+\nENGG. MECHANICS LAB 2 1535 050 - 20133346  A+\n-----------------------------------------------------------------------------------------------\nTERM WORK PAPERS\nC.U MOOCS/ SWAYAM/ ETC/ OTHERS 2 0614 020 - 08041014  B\nKYP/IT ESSEN/ PYTHON/ OTHERS 1 0614 020 - 08041216  A\nENVIRONMENTAL SCIENCE 0 10 -010 - 0410 -10  A+\n-----------------------------------------------------------------------------------------------\nGRAND TOTAL 24 750 526\n-----------------------------------------------------------------------------------------------\nSGPA 7.67\n-----------------------------------------------------------------------------------------------\nREMARKS : First Class",
        "college": "Government Polytechnic, Bhojpur",
        "name": "RISHABH RAJ SINGH",
        "roll": "211522023015",
        "branch": "20",
        "marks": 526,
        "remarks": "First Class",
        "theory": 201
    },
    {
        "text": " \n \nRegistration No : 1522023007\nRoll No         : 211522023007\n \nFollowing are the marks obtained by RAGHAV KUMAR JHA\nof Government Polytechnic, Bhojpur\nat Semester II of Diploma in Electrical Engineering\nExamination 2024 (EVEN) held in the month of JUL, 2024\n \n \nResult Published On: 30/07/2024\nSTATE BOARD OF TECHNICAL EDUCATION\nBIHAR\n-----------------------------------------------------------------------------------------------\nSUBJECT  FULL MARKS PASS MARKS MARKS OBTAINED\nNAME OF SUBJECTS CREDITS INTFINTOTAL FINTOTAL INT FIN TOTAL GRADE\n-----------------------------------------------------------------------------------------------\nTHEORY PAPERS\nMATHEMATICS-II 4 3070 100 28 40232851  D\nAPPLIED PHYSICS-II 3 3070 100 28 40124153  D\nINTRODUCTION TO IT SYSTEMS 2 3070 100 28 40144256  D\nFUNDA OF ELECT AND EC ENGG 3 3070 100 28 40224567  C\nENGG. MECHANICS 3 3070 100 28 40154257  D\n-----------------------------------------------------------------------------------------------\nPRACTICAL PAPERS\nAPPLIED PHYSICS LAB-II 1 1535 050 - 20123143  A\nINTRODUCTION TO IT SYSTEM LAB 2 1535 050 - 20123143  A\nFUNDA OF ELECT AND EC ENGG LAB 1 1535 050 - 20123244  A\nENGG. MECHANICS LAB 2 1535 050 - 20123244  A\n-----------------------------------------------------------------------------------------------\nTERM WORK PAPERS\nC.U MOOCS/ SWAYAM/ ETC/ OTHERS 2 0614 020 - 08041216  A\nKYP/IT ESSEN/ PYTHON/ OTHERS 1 0614 020 - 08041014  B\nENVIRONMENTAL SCIENCE 0 10 -010 - 0410 -10  A+\n-----------------------------------------------------------------------------------------------\nGRAND TOTAL 24 750 498\n-----------------------------------------------------------------------------------------------\nSGPA 7.21\n-----------------------------------------------------------------------------------------------\nREMARKS : First Class",
        "college": "Government Polytechnic, Bhojpur",
        "name": "RAGHAV KUMAR JHA",
        "roll": "211522023007",
        "branch": "20",
        "marks": 498,
        "remarks": "First Class",
        "theory": 198
    },
    {
        "text": " \n \nRegistration No : 1522023048\nRoll No         : 211522023048\n \nFollowing are the marks obtained by SUSHANT KUMAR OJHA\nof Government Polytechnic, Bhojpur\nat Semester II of Diploma in Electrical Engineering\nExamination 2024 (EVEN) held in the month of JUL, 2024\n \n \nResult Published On: 30/07/2024\nSTATE BOARD OF TECHNICAL EDUCATION\nBIHAR\n-----------------------------------------------------------------------------------------------\nSUBJECT  FULL MARKS PASS MARKS MARKS OBTAINED\nNAME OF SUBJECTS CREDITS INTFINTOTAL FINTOTAL INT FIN TOTAL GRADE\n-----------------------------------------------------------------------------------------------\nTHEORY PAPERS\nMATHEMATICS-II 4 3070 100 28 40212849  E\nAPPLIED PHYSICS-II 3 3070 100 28 40214465  C\nINTRODUCTION TO IT SYSTEMS 2 3070 100 28 40125062  C\nFUNDA OF ELECT AND EC ENGG 3 3070 100 28 40174865  C\nENGG. MECHANICS 3 3070 100 28 40143852  D\n-----------------------------------------------------------------------------------------------\nPRACTICAL PAPERS\nAPPLIED PHYSICS LAB-II 1 1535 050 - 20122941  A\nINTRODUCTION TO IT SYSTEM LAB 2 1535 050 - 20123244  A\nFUNDA OF ELECT AND EC ENGG LAB 1 1535 050 - 20123244  A\nENGG. MECHANICS LAB 2 1535 050 - 20103040  A\n-----------------------------------------------------------------------------------------------\nTERM WORK PAPERS\nC.U MOOCS/ SWAYAM/ ETC/ OTHERS 2 0614 020 - 08041216  A\nKYP/IT ESSEN/ PYTHON/ OTHERS 1 0614 020 - 08051217  A\nENVIRONMENTAL SCIENCE 0 10 -010 - 0408 -08  A\n-----------------------------------------------------------------------------------------------\nGRAND TOTAL 24 750 503\n-----------------------------------------------------------------------------------------------\nSGPA 7.29\n-----------------------------------------------------------------------------------------------\nREMARKS : First Class",
        "college": "Government Polytechnic, Bhojpur",
        "name": "SUSHANT KUMAR OJHA",
        "roll": "211522023048",
        "branch": "20",
        "marks": 503,
        "remarks": "First Class",
        "theory": 208
    },
    {
        "text": " \n \nRegistration No : 1522023017\nRoll No         : 211522023017\n \nFollowing are the marks obtained by GAURAV  KUMAR\nof Government Polytechnic, Bhojpur\nat Semester II of Diploma in Electrical Engineering\nExamination 2024 (EVEN) held in the month of JUL, 2024\n \n \nResult Published On: 30/07/2024\nSTATE BOARD OF TECHNICAL EDUCATION\nBIHAR\n-----------------------------------------------------------------------------------------------\nSUBJECT  FULL MARKS PASS MARKS MARKS OBTAINED\nNAME OF SUBJECTS CREDITS INTFINTOTAL FINTOTAL INT FIN TOTAL GRADE\n-----------------------------------------------------------------------------------------------\nTHEORY PAPERS\nMATHEMATICS-II 4 3070 100 28 40253156  D\nAPPLIED PHYSICS-II 3 3070 100 28 40193756  D\nINTRODUCTION TO IT SYSTEMS 2 3070 100 28 40224870  B\nFUNDA OF ELECT AND EC ENGG 3 3070 100 28 40195170  B\nENGG. MECHANICS 3 3070 100 28 40224163  C\n-----------------------------------------------------------------------------------------------\nPRACTICAL PAPERS\nAPPLIED PHYSICS LAB-II 1 1535 050 - 20122840  A\nINTRODUCTION TO IT SYSTEM LAB 2 1535 050 - 20123143  A\nFUNDA OF ELECT AND EC ENGG LAB 1 1535 050 - 20133245  A+\nENGG. MECHANICS LAB 2 1535 050 - 20143347  A+\n-----------------------------------------------------------------------------------------------\nTERM WORK PAPERS\nC.U MOOCS/ SWAYAM/ ETC/ OTHERS 2 0614 020 - 08041115  B\nKYP/IT ESSEN/ PYTHON/ OTHERS 1 0614 020 - 08041115  B\nENVIRONMENTAL SCIENCE 0 10 -010 - 0410 -10  A+\n-----------------------------------------------------------------------------------------------\nGRAND TOTAL 24 750 530\n-----------------------------------------------------------------------------------------------\nSGPA 7.67\n-----------------------------------------------------------------------------------------------\nREMARKS : First Class",
        "college": "Government Polytechnic, Bhojpur",
        "name": "GAURAV KUMAR",
        "roll": "211522023017",
        "branch": "20",
        "marks": 530,
        "remarks": "First Class",
        "theory": 208
    },
    {
        "text": " \n \nRegistration No : 1522023013\nRoll No         : 211522023013\n \nFollowing are the marks obtained by SUNNY  KUMAR\nof Government Polytechnic, Bhojpur\nat Semester II of Diploma in Electrical Engineering\nExamination 2024 (EVEN) held in the month of JUL, 2024\n \n \nResult Published On: 30/07/2024\nSTATE BOARD OF TECHNICAL EDUCATION\nBIHAR\n-----------------------------------------------------------------------------------------------\nSUBJECT  FULL MARKS PASS MARKS MARKS OBTAINED\nNAME OF SUBJECTS CREDITS INTFINTOTAL FINTOTAL INT FIN TOTAL GRADE\n-----------------------------------------------------------------------------------------------\nTHEORY PAPERS\nMATHEMATICS-II 4 3070 100 28 40224062  C\nAPPLIED PHYSICS-II 3 3070 100 28 40193756  D\nINTRODUCTION TO IT SYSTEMS 2 3070 100 28 40123143  E\nFUNDA OF ELECT AND EC ENGG 3 3070 100 28 40224062  C\nENGG. MECHANICS 3 3070 100 28 40233861  C\n-----------------------------------------------------------------------------------------------\nPRACTICAL PAPERS\nAPPLIED PHYSICS LAB-II 1 1535 050 - 20142943  A\nINTRODUCTION TO IT SYSTEM LAB 2 1535 050 - 20123143  A\nFUNDA OF ELECT AND EC ENGG LAB 1 1535 050 - 20123244  A\nENGG. MECHANICS LAB 2 1535 050 - 20133346  A+\n-----------------------------------------------------------------------------------------------\nTERM WORK PAPERS\nC.U MOOCS/ SWAYAM/ ETC/ OTHERS 2 0614 020 - 08041216  A\nKYP/IT ESSEN/ PYTHON/ OTHERS 1 0614 020 - 08041014  B\nENVIRONMENTAL SCIENCE 0 10 -010 - 0410 -10  A+\n-----------------------------------------------------------------------------------------------\nGRAND TOTAL 24 750 500\n-----------------------------------------------------------------------------------------------\nSGPA 7.5\n-----------------------------------------------------------------------------------------------\nREMARKS : First Class",
        "college": "Government Polytechnic, Bhojpur",
        "name": "SUNNY KUMAR",
        "roll": "211522023013",
        "branch": "20",
        "marks": 500,
        "remarks": "First Class",
        "theory": 186
    },
    {
        "text": " \n \nRegistration No : 1522023044\nRoll No         : 211522023044\n \nFollowing are the marks obtained by KIRAN  KUMARI\nof Government Polytechnic, Bhojpur\nat Semester II of Diploma in Electrical Engineering\nExamination 2024 (EVEN) held in the month of JUL, 2024\n \n \nResult Published On: 30/07/2024\nSTATE BOARD OF TECHNICAL EDUCATION\nBIHAR\n-----------------------------------------------------------------------------------------------\nSUBJECT  FULL MARKS PASS MARKS MARKS OBTAINED\nNAME OF SUBJECTS CREDITS INTFINTOTAL FINTOTAL INT FIN TOTAL GRADE\n-----------------------------------------------------------------------------------------------\nTHEORY PAPERS\nMATHEMATICS-II 4 3070 100 28 40235174  B\nAPPLIED PHYSICS-II 3 3070 100 28 40056065  C\nINTRODUCTION TO IT SYSTEMS 2 3070 100 28 40125062  C\nFUNDA OF ELECT AND EC ENGG 3 3070 100 28 40245478  B\nENGG. MECHANICS 3 3070 100 28 40205474  B\n-----------------------------------------------------------------------------------------------\nPRACTICAL PAPERS\nAPPLIED PHYSICS LAB-II 1 1535 050 - 20123143  A\nINTRODUCTION TO IT SYSTEM LAB 2 1535 050 - 20123244  A\nFUNDA OF ELECT AND EC ENGG LAB 1 1535 050 - 20133447  A+\nENGG. MECHANICS LAB 2 1535 050 - 20103141  A\n-----------------------------------------------------------------------------------------------\nTERM WORK PAPERS\nC.U MOOCS/ SWAYAM/ ETC/ OTHERS 2 0614 020 - 08041115  B\nKYP/IT ESSEN/ PYTHON/ OTHERS 1 0614 020 - 08051217  A\nENVIRONMENTAL SCIENCE 0 10 -010 - 0410 -10  A+\n-----------------------------------------------------------------------------------------------\nGRAND TOTAL 24 750 570\n-----------------------------------------------------------------------------------------------\nSGPA 8.12\n-----------------------------------------------------------------------------------------------\nREMARKS : First Class with Distinction",
        "college": "Government Polytechnic, Bhojpur",
        "name": "KIRAN KUMARI",
        "roll": "211522023044",
        "branch": "20",
        "marks": 570,
        "remarks": "First Class with Distinction",
        "theory": 269
    },
    {
        "text": " \n \nRegistration No : 1522023052\nRoll No         : 211522023052\n \nFollowing are the marks obtained by HIMANSHU  KUMAR\nof Government Polytechnic, Bhojpur\nat Semester II of Diploma in Electrical Engineering\nExamination 2024 (EVEN) held in the month of JUL, 2024\n \n \nResult Published On: 30/07/2024\nSTATE BOARD OF TECHNICAL EDUCATION\nBIHAR\n-----------------------------------------------------------------------------------------------\nSUBJECT  FULL MARKS PASS MARKS MARKS OBTAINED\nNAME OF SUBJECTS CREDITS INTFINTOTAL FINTOTAL INT FIN TOTAL GRADE\n-----------------------------------------------------------------------------------------------\nTHEORY PAPERS\nMATHEMATICS-II 4 3070 100 28 40224365  C\nAPPLIED PHYSICS-II 3 3070 100 28 40164561  C\nINTRODUCTION TO IT SYSTEMS 2 3070 100 28 40122840  E\nFUNDA OF ELECT AND EC ENGG 3 3070 100 28 40221739  F\nENGG. MECHANICS 3 3070 100 28 40123143  E\n-----------------------------------------------------------------------------------------------\nPRACTICAL PAPERS\nAPPLIED PHYSICS LAB-II 1 1535 050 - 20103040  A\nINTRODUCTION TO IT SYSTEM LAB 2 1535 050 - 20133245  A+\nFUNDA OF ELECT AND EC ENGG LAB 1 1535 050 - 20123345  A+\nENGG. MECHANICS LAB 2 1535 050 - 20113142  A\n-----------------------------------------------------------------------------------------------\nTERM WORK PAPERS\nC.U MOOCS/ SWAYAM/ ETC/ OTHERS 2 0614 020 - 08041014  B\nKYP/IT ESSEN/ PYTHON/ OTHERS 1 0614 020 - 08051116  A\nENVIRONMENTAL SCIENCE 0 10 -010 - 0408 -08  A\n-----------------------------------------------------------------------------------------------\nGRAND TOTAL 24 750 458\n-----------------------------------------------------------------------------------------------\nSGPA \n-----------------------------------------------------------------------------------------------\nREMARKS : Carry in - FUNDA OF ELECT AND EC ENGG",
        "college": "Government Polytechnic, Bhojpur",
        "name": "HIMANSHU KUMAR",
        "roll": "211522023052",
        "branch": "20",
        "marks": 458,
        "remarks": "Carry in - FUNDA OF ELECT AND EC ENGG",
        "theory": 164
    },
    {
        "text": " \n \nRegistration No : 1522023010\nRoll No         : 211522023010\n \nFollowing are the marks obtained by AMAN KUMAR SINGH\nof Government Polytechnic, Bhojpur\nat Semester II of Diploma in Electrical Engineering\nExamination 2024 (EVEN) held in the month of JUL, 2024\n \n \nResult Published On: 30/07/2024\nSTATE BOARD OF TECHNICAL EDUCATION\nBIHAR\n-----------------------------------------------------------------------------------------------\nSUBJECT  FULL MARKS PASS MARKS MARKS OBTAINED\nNAME OF SUBJECTS CREDITS INTFINTOTAL FINTOTAL INT FIN TOTAL GRADE\n-----------------------------------------------------------------------------------------------\nTHEORY PAPERS\nMATHEMATICS-II 4 3070 100 28 40232851  D\nAPPLIED PHYSICS-II 3 3070 100 28 40184765  C\nINTRODUCTION TO IT SYSTEMS 2 3070 100 28 40145670  B\nFUNDA OF ELECT AND EC ENGG 3 3070 100 28 40182846  E\nENGG. MECHANICS 3 3070 100 28 40163854  D\n-----------------------------------------------------------------------------------------------\nPRACTICAL PAPERS\nAPPLIED PHYSICS LAB-II 1 1535 050 - 20143145  A+\nINTRODUCTION TO IT SYSTEM LAB 2 1535 050 - 20123143  A\nFUNDA OF ELECT AND EC ENGG LAB 1 1535 050 - 20133447  A+\nENGG. MECHANICS LAB 2 1535 050 - 20123244  A\n-----------------------------------------------------------------------------------------------\nTERM WORK PAPERS\nC.U MOOCS/ SWAYAM/ ETC/ OTHERS 2 0614 020 - 08041115  B\nKYP/IT ESSEN/ PYTHON/ OTHERS 1 0614 020 - 08041216  A\nENVIRONMENTAL SCIENCE 0 10 -010 - 0408 -08  A\n-----------------------------------------------------------------------------------------------\nGRAND TOTAL 24 750 504\n-----------------------------------------------------------------------------------------------\nSGPA 7.29\n-----------------------------------------------------------------------------------------------\nREMARKS : First Class",
        "college": "Government Polytechnic, Bhojpur",
        "name": "AMAN KUMAR SINGH",
        "roll": "211522023010",
        "branch": "20",
        "marks": 504,
        "remarks": "First Class",
        "theory": 197
    },
    {
        "text": " \n \nRegistration No : 1522023034\nRoll No         : 211522023034\n \nFollowing are the marks obtained by PRINCE  KUMAR\nof Government Polytechnic, Bhojpur\nat Semester II of Diploma in Electrical Engineering\nExamination 2024 (EVEN) held in the month of JUL, 2024\n \n \nResult Published On: 30/07/2024\nSTATE BOARD OF TECHNICAL EDUCATION\nBIHAR\n-----------------------------------------------------------------------------------------------\nSUBJECT  FULL MARKS PASS MARKS MARKS OBTAINED\nNAME OF SUBJECTS CREDITS INTFINTOTAL FINTOTAL INT FIN TOTAL GRADE\n-----------------------------------------------------------------------------------------------\nTHEORY PAPERS\nMATHEMATICS-II 4 3070 100 28 40202848  E\nAPPLIED PHYSICS-II 3 3070 100 28 40183351  D\nINTRODUCTION TO IT SYSTEMS 2 3070 100 28 40153045  E\nFUNDA OF ELECT AND EC ENGG 3 3070 100 28 40162844  E\nENGG. MECHANICS 3 3070 100 28 40163652  D\n-----------------------------------------------------------------------------------------------\nPRACTICAL PAPERS\nAPPLIED PHYSICS LAB-II 1 1535 050 - 20113041  A\nINTRODUCTION TO IT SYSTEM LAB 2 1535 050 - 20113041  A\nFUNDA OF ELECT AND EC ENGG LAB 1 1535 050 - 20123244  A\nENGG. MECHANICS LAB 2 1535 050 - 20113142  A\n-----------------------------------------------------------------------------------------------\nTERM WORK PAPERS\nC.U MOOCS/ SWAYAM/ ETC/ OTHERS 2 0614 020 - 08031114  B\nKYP/IT ESSEN/ PYTHON/ OTHERS 1 0614 020 - 08051116  A\nENVIRONMENTAL SCIENCE 0 10 -010 - 0408 -08  A\n-----------------------------------------------------------------------------------------------\nGRAND TOTAL 24 750 446\n-----------------------------------------------------------------------------------------------\nSGPA 6.67\n-----------------------------------------------------------------------------------------------\nREMARKS : Second Class",
        "college": "Government Polytechnic, Bhojpur",
        "name": "PRINCE KUMAR",
        "roll": "211522023034",
        "branch": "20",
        "marks": 446,
        "remarks": "Second Class",
        "theory": 155
    },
    {
        "text": " \n \nRegistration No : 1522023031\nRoll No         : 211522023031\n \nFollowing are the marks obtained by RANJAN  KUMAR\nof Government Polytechnic, Bhojpur\nat Semester II of Diploma in Electrical Engineering\nExamination 2024 (EVEN) held in the month of JUL, 2024\n \n \nResult Published On: 30/07/2024\nSTATE BOARD OF TECHNICAL EDUCATION\nBIHAR\n-----------------------------------------------------------------------------------------------\nSUBJECT  FULL MARKS PASS MARKS MARKS OBTAINED\nNAME OF SUBJECTS CREDITS INTFINTOTAL FINTOTAL INT FIN TOTAL GRADE\n-----------------------------------------------------------------------------------------------\nTHEORY PAPERS\nMATHEMATICS-II 4 3070 100 28 40233558  D\nAPPLIED PHYSICS-II 3 3070 100 28 40213455  D\nINTRODUCTION TO IT SYSTEMS 2 3070 100 28 40163349  E\nFUNDA OF ELECT AND EC ENGG 3 3070 100 28 40203050  D\nENGG. MECHANICS 3 3070 100 28 40163753  D\n-----------------------------------------------------------------------------------------------\nPRACTICAL PAPERS\nAPPLIED PHYSICS LAB-II 1 1535 050 - 20143044  A\nINTRODUCTION TO IT SYSTEM LAB 2 1535 050 - 20113243  A\nFUNDA OF ELECT AND EC ENGG LAB 1 1535 050 - 20133245  A+\nENGG. MECHANICS LAB 2 1535 050 - 20123244  A\n-----------------------------------------------------------------------------------------------\nTERM WORK PAPERS\nC.U MOOCS/ SWAYAM/ ETC/ OTHERS 2 0614 020 - 08041216  A\nKYP/IT ESSEN/ PYTHON/ OTHERS 1 0614 020 - 08041115  B\nENVIRONMENTAL SCIENCE 0 10 -010 - 0410 -10  A+\n-----------------------------------------------------------------------------------------------\nGRAND TOTAL 24 750 482\n-----------------------------------------------------------------------------------------------\nSGPA 7.04\n-----------------------------------------------------------------------------------------------\nREMARKS : First Class",
        "college": "Government Polytechnic, Bhojpur",
        "name": "RANJAN KUMAR",
        "roll": "211522023031",
        "branch": "20",
        "marks": 482,
        "remarks": "First Class",
        "theory": 169
    },
    {
        "text": " \n \nRegistration No : 1522023041\nRoll No         : 211522023041\n \nFollowing are the marks obtained by PIYUSH  RAJ\nof Government Polytechnic, Bhojpur\nat Semester II of Diploma in Electrical Engineering\nExamination 2024 (EVEN) held in the month of JUL, 2024\n \n \nResult Published On: 30/07/2024\nSTATE BOARD OF TECHNICAL EDUCATION\nBIHAR\n-----------------------------------------------------------------------------------------------\nSUBJECT  FULL MARKS PASS MARKS MARKS OBTAINED\nNAME OF SUBJECTS CREDITS INTFINTOTAL FINTOTAL INT FIN TOTAL GRADE\n-----------------------------------------------------------------------------------------------\nTHEORY PAPERS\nMATHEMATICS-II 4 3070 100 28 40203656  D\nAPPLIED PHYSICS-II 3 3070 100 28 40195170  B\nINTRODUCTION TO IT SYSTEMS 2 3070 100 28 40163652  D\nFUNDA OF ELECT AND EC ENGG 3 3070 100 28 40233255  D\nENGG. MECHANICS 3 3070 100 28 40195170  B\n-----------------------------------------------------------------------------------------------\nPRACTICAL PAPERS\nAPPLIED PHYSICS LAB-II 1 1535 050 - 20133043  A\nINTRODUCTION TO IT SYSTEM LAB 2 1535 050 - 20123042  A\nFUNDA OF ELECT AND EC ENGG LAB 1 1535 050 - 20133346  A+\nENGG. MECHANICS LAB 2 1535 050 - 20133346  A+\n-----------------------------------------------------------------------------------------------\nTERM WORK PAPERS\nC.U MOOCS/ SWAYAM/ ETC/ OTHERS 2 0614 020 - 08051217  A\nKYP/IT ESSEN/ PYTHON/ OTHERS 1 0614 020 - 08041216  A\nENVIRONMENTAL SCIENCE 0 10 -010 - 0408 -08  A\n-----------------------------------------------------------------------------------------------\nGRAND TOTAL 24 750 521\n-----------------------------------------------------------------------------------------------\nSGPA 7.75\n-----------------------------------------------------------------------------------------------\nREMARKS : First Class",
        "college": "Government Polytechnic, Bhojpur",
        "name": "PIYUSH RAJ",
        "roll": "211522023041",
        "branch": "20",
        "marks": 521,
        "remarks": "First Class",
        "theory": 206
    },
    {
        "text": " \n \nRegistration No : 1522023004\nRoll No         : 211522023004\n \nFollowing are the marks obtained by PRINCE  RAJ\nof Government Polytechnic, Bhojpur\nat Semester II of Diploma in Electrical Engineering\nExamination 2024 (EVEN) held in the month of JUL, 2024\n \n \nResult Published On: 30/07/2024\nSTATE BOARD OF TECHNICAL EDUCATION\nBIHAR\n-----------------------------------------------------------------------------------------------\nSUBJECT  FULL MARKS PASS MARKS MARKS OBTAINED\nNAME OF SUBJECTS CREDITS INTFINTOTAL FINTOTAL INT FIN TOTAL GRADE\n-----------------------------------------------------------------------------------------------\nTHEORY PAPERS\nMATHEMATICS-II 4 3070 100 28 40132841  E\nAPPLIED PHYSICS-II 3 3070 100 28 40224567  C\nINTRODUCTION TO IT SYSTEMS 2 3070 100 28 40123244  E\nFUNDA OF ELECT AND EC ENGG 3 3070 100 28 40172845  E\nENGG. MECHANICS 3 3070 100 28 40132942  E\n-----------------------------------------------------------------------------------------------\nPRACTICAL PAPERS\nAPPLIED PHYSICS LAB-II 1 1535 050 - 20133144  A\nINTRODUCTION TO IT SYSTEM LAB 2 1535 050 - 20123244  A\nFUNDA OF ELECT AND EC ENGG LAB 1 1535 050 - 20123244  A\nENGG. MECHANICS LAB 2 1535 050 - 20113344  A\n-----------------------------------------------------------------------------------------------\nTERM WORK PAPERS\nC.U MOOCS/ SWAYAM/ ETC/ OTHERS 2 0614 020 - 08041216  A\nKYP/IT ESSEN/ PYTHON/ OTHERS 1 0614 020 - 08041115  B\nENVIRONMENTAL SCIENCE 0 10 -010 - 0407 -07  B\n-----------------------------------------------------------------------------------------------\nGRAND TOTAL 24 750 453\n-----------------------------------------------------------------------------------------------\nSGPA 6.71\n-----------------------------------------------------------------------------------------------\nREMARKS : First Class",
        "college": "Government Polytechnic, Bhojpur",
        "name": "PRINCE RAJ",
        "roll": "211522023004",
        "branch": "20",
        "marks": 453,
        "remarks": "First Class",
        "theory": 162
    },
    {
        "text": " \n \nRegistration No : 1522023036\nRoll No         : 211522023036\n \nFollowing are the marks obtained by PIYUSH  RAJ\nof Government Polytechnic, Bhojpur\nat Semester II of Diploma in Electrical Engineering\nExamination 2024 (EVEN) held in the month of JUL, 2024\n \n \nResult Published On: 30/07/2024\nSTATE BOARD OF TECHNICAL EDUCATION\nBIHAR\n-----------------------------------------------------------------------------------------------\nSUBJECT  FULL MARKS PASS MARKS MARKS OBTAINED\nNAME OF SUBJECTS CREDITS INTFINTOTAL FINTOTAL INT FIN TOTAL GRADE\n-----------------------------------------------------------------------------------------------\nTHEORY PAPERS\nMATHEMATICS-II 4 3070 100 28 40212849  E\nAPPLIED PHYSICS-II 3 3070 100 28 40272855  D\nINTRODUCTION TO IT SYSTEMS 2 3070 100 28 40163955  D\nFUNDA OF ELECT AND EC ENGG 3 3070 100 28 40173047  E\nENGG. MECHANICS 3 3070 100 28 40144054  D\n-----------------------------------------------------------------------------------------------\nPRACTICAL PAPERS\nAPPLIED PHYSICS LAB-II 1 1535 050 - 20133144  A\nINTRODUCTION TO IT SYSTEM LAB 2 1535 050 - 20123042  A\nFUNDA OF ELECT AND EC ENGG LAB 1 1535 050 - 20123244  A\nENGG. MECHANICS LAB 2 1535 050 - 20113142  A\n-----------------------------------------------------------------------------------------------\nTERM WORK PAPERS\nC.U MOOCS/ SWAYAM/ ETC/ OTHERS 2 0614 020 - 08051217  A\nKYP/IT ESSEN/ PYTHON/ OTHERS 1 0614 020 - 08041115  B\nENVIRONMENTAL SCIENCE 0 10 -010 - 0408 -08  A\n-----------------------------------------------------------------------------------------------\nGRAND TOTAL 24 750 472\n-----------------------------------------------------------------------------------------------\nSGPA 6.79\n-----------------------------------------------------------------------------------------------\nREMARKS : First Class",
        "college": "Government Polytechnic, Bhojpur",
        "name": "PIYUSH RAJ",
        "roll": "211522023036",
        "branch": "20",
        "marks": 472,
        "remarks": "First Class",
        "theory": 165
    },
    {
        "text": " \n \nRegistration No : 1522023035\nRoll No         : 211522023035\n \nFollowing are the marks obtained by SANDEEP  KUMAR\nof Government Polytechnic, Bhojpur\nat Semester II of Diploma in Electrical Engineering\nExamination 2024 (EVEN) held in the month of JUL, 2024\n \n \nResult Published On: 30/07/2024\nSTATE BOARD OF TECHNICAL EDUCATION\nBIHAR\n-----------------------------------------------------------------------------------------------\nSUBJECT  FULL MARKS PASS MARKS MARKS OBTAINED\nNAME OF SUBJECTS CREDITS INTFINTOTAL FINTOTAL INT FIN TOTAL GRADE\n-----------------------------------------------------------------------------------------------\nTHEORY PAPERS\nMATHEMATICS-II 4 3070 100 28 40242852  D\nAPPLIED PHYSICS-II 3 3070 100 28 40163349  E\nINTRODUCTION TO IT SYSTEMS 2 3070 100 28 40122840  E\nFUNDA OF ELECT AND EC ENGG 3 3070 100 28 40163046  E\nENGG. MECHANICS 3 3070 100 28 40141933  F\n-----------------------------------------------------------------------------------------------\nPRACTICAL PAPERS\nAPPLIED PHYSICS LAB-II 1 1535 050 - 20102939  B\nINTRODUCTION TO IT SYSTEM LAB 2 1535 050 - 20123143  A\nFUNDA OF ELECT AND EC ENGG LAB 1 1535 050 - 20123244  A\nENGG. MECHANICS LAB 2 1535 050 - 20113142  A\n-----------------------------------------------------------------------------------------------\nTERM WORK PAPERS\nC.U MOOCS/ SWAYAM/ ETC/ OTHERS 2 0614 020 - 08041115  B\nKYP/IT ESSEN/ PYTHON/ OTHERS 1 0614 020 - 08041014  B\nENVIRONMENTAL SCIENCE 0 10 -010 - 0408 -08  A\n-----------------------------------------------------------------------------------------------\nGRAND TOTAL 24 750 425\n-----------------------------------------------------------------------------------------------\nSGPA \n-----------------------------------------------------------------------------------------------\nREMARKS : Carry in - ENGG. MECHANICS",
        "college": "Government Polytechnic, Bhojpur",
        "name": "SANDEEP KUMAR",
        "roll": "211522023035",
        "branch": "20",
        "marks": 425,
        "remarks": "Carry in - ENGG. MECHANICS",
        "theory": 138
    },
    {
        "text": " \n \nRegistration No : 1522023039\nRoll No         : 211522023039\n \nFollowing are the marks obtained by SURAJ  KUMAR\nof Government Polytechnic, Bhojpur\nat Semester II of Diploma in Electrical Engineering\nExamination 2024 (EVEN) held in the month of JUL, 2024\n \n \nResult Published On: 30/07/2024\nSTATE BOARD OF TECHNICAL EDUCATION\nBIHAR\n-----------------------------------------------------------------------------------------------\nSUBJECT  FULL MARKS PASS MARKS MARKS OBTAINED\nNAME OF SUBJECTS CREDITS INTFINTOTAL FINTOTAL INT FIN TOTAL GRADE\n-----------------------------------------------------------------------------------------------\nTHEORY PAPERS\nMATHEMATICS-II 4 3070 100 28 40255479  B\nAPPLIED PHYSICS-II 3 3070 100 28 40285381  A\nINTRODUCTION TO IT SYSTEMS 2 3070 100 28 40215576  B\nFUNDA OF ELECT AND EC ENGG 3 3070 100 28 40245377  B\nENGG. MECHANICS 3 3070 100 28 40256085  A\n-----------------------------------------------------------------------------------------------\nPRACTICAL PAPERS\nAPPLIED PHYSICS LAB-II 1 1535 050 - 20123143  A\nINTRODUCTION TO IT SYSTEM LAB 2 1535 050 - 20143246  A+\nFUNDA OF ELECT AND EC ENGG LAB 1 1535 050 - 20133245  A+\nENGG. MECHANICS LAB 2 1535 050 - 20143448  A+\n-----------------------------------------------------------------------------------------------\nTERM WORK PAPERS\nC.U MOOCS/ SWAYAM/ ETC/ OTHERS 2 0614 020 - 08041317  A\nKYP/IT ESSEN/ PYTHON/ OTHERS 1 0614 020 - 08041317  A\nENVIRONMENTAL SCIENCE 0 10 -010 - 0410 -10  A+\n-----------------------------------------------------------------------------------------------\nGRAND TOTAL 24 750 624\n-----------------------------------------------------------------------------------------------\nSGPA 8.83\n-----------------------------------------------------------------------------------------------\nREMARKS : First Class with Distinction",
        "college": "Government Polytechnic, Bhojpur",
        "name": "SURAJ KUMAR",
        "roll": "211522023039",
        "branch": "20",
        "marks": 624,
        "remarks": "First Class with Distinction",
        "theory": 275
    },
    {
        "text": " \n \nRegistration No : 1522023011\nRoll No         : 211522023011\n \nFollowing are the marks obtained by PRIYA  BHARTI\nof Government Polytechnic, Bhojpur\nat Semester II of Diploma in Electrical Engineering\nExamination 2024 (EVEN) held in the month of JUL, 2024\n \n \nResult Published On: 30/07/2024\nSTATE BOARD OF TECHNICAL EDUCATION\nBIHAR\n-----------------------------------------------------------------------------------------------\nSUBJECT  FULL MARKS PASS MARKS MARKS OBTAINED\nNAME OF SUBJECTS CREDITS INTFINTOTAL FINTOTAL INT FIN TOTAL GRADE\n-----------------------------------------------------------------------------------------------\nTHEORY PAPERS\nMATHEMATICS-II 4 3070 100 28 40211839  F\nAPPLIED PHYSICS-II 3 3070 100 28 40144458  D\nINTRODUCTION TO IT SYSTEMS 2 3070 100 28 40124759  D\nFUNDA OF ELECT AND EC ENGG 3 3070 100 28 40203959  D\nENGG. MECHANICS 3 3070 100 28 40175067  C\n-----------------------------------------------------------------------------------------------\nPRACTICAL PAPERS\nAPPLIED PHYSICS LAB-II 1 1535 050 - 20103040  A\nINTRODUCTION TO IT SYSTEM LAB 2 1535 050 - 20123143  A\nFUNDA OF ELECT AND EC ENGG LAB 1 1535 050 - 20133346  A+\nENGG. MECHANICS LAB 2 1535 050 - 20123244  A\n-----------------------------------------------------------------------------------------------\nTERM WORK PAPERS\nC.U MOOCS/ SWAYAM/ ETC/ OTHERS 2 0614 020 - 08051015  B\nKYP/IT ESSEN/ PYTHON/ OTHERS 1 0614 020 - 08041216  A\nENVIRONMENTAL SCIENCE 0 10 -010 - 0409 -09  A+\n-----------------------------------------------------------------------------------------------\nGRAND TOTAL 24 750 495\n-----------------------------------------------------------------------------------------------\nSGPA \n-----------------------------------------------------------------------------------------------\nREMARKS : Carry in - MATHEMATICS-II",
        "college": "Government Polytechnic, Bhojpur",
        "name": "PRIYA BHARTI",
        "roll": "211522023011",
        "branch": "20",
        "marks": 495,
        "remarks": "Carry in - MATHEMATICS-II",
        "theory": 198
    },
    {
        "text": " \n \nRegistration No : 1522023050\nRoll No         : 211522023050\n \nFollowing are the marks obtained by NISHA  BHARTI\nof Government Polytechnic, Bhojpur\nat Semester II of Diploma in Electrical Engineering\nExamination 2024 (EVEN) held in the month of JUL, 2024\n \n \nResult Published On: 30/07/2024\nSTATE BOARD OF TECHNICAL EDUCATION\nBIHAR\n-----------------------------------------------------------------------------------------------\nSUBJECT  FULL MARKS PASS MARKS MARKS OBTAINED\nNAME OF SUBJECTS CREDITS INTFINTOTAL FINTOTAL INT FIN TOTAL GRADE\n-----------------------------------------------------------------------------------------------\nTHEORY PAPERS\nMATHEMATICS-II 4 3070 100 28 40211031  F\nAPPLIED PHYSICS-II 3 3070 100 28 40052934  F\nINTRODUCTION TO IT SYSTEMS 2 3070 100 28 40123143  E\nFUNDA OF ELECT AND EC ENGG 3 3070 100 28 40181432  F\nENGG. MECHANICS 3 3070 100 28 40133548  E\n-----------------------------------------------------------------------------------------------\nPRACTICAL PAPERS\nAPPLIED PHYSICS LAB-II 1 1535 050 - 20112940  A\nINTRODUCTION TO IT SYSTEM LAB 2 1535 050 - 20123042  A\nFUNDA OF ELECT AND EC ENGG LAB 1 1535 050 - 20123345  A+\nENGG. MECHANICS LAB 2 1535 050 - 20113142  A\n-----------------------------------------------------------------------------------------------\nTERM WORK PAPERS\nC.U MOOCS/ SWAYAM/ ETC/ OTHERS 2 0614 020 - 08041216  A\nKYP/IT ESSEN/ PYTHON/ OTHERS 1 0614 020 - 08051116  A\nENVIRONMENTAL SCIENCE 0 10 -010 - 0408 -08  A\n-----------------------------------------------------------------------------------------------\nGRAND TOTAL 24 750 397\n-----------------------------------------------------------------------------------------------\nSGPA \n-----------------------------------------------------------------------------------------------\nREMARKS : Fail",
        "college": "Government Polytechnic, Bhojpur",
        "name": "NISHA BHARTI",
        "roll": "211522023050",
        "branch": "20",
        "marks": 397,
        "remarks": "Fail",
        "theory": 119
    },
    {
        "text": " \n \nRegistration No : 1522123036\nRoll No         : 211522123036\n \nFollowing are the marks obtained by RAHUL  KUMAR\nof Government Polytechnic, Bhojpur\nat Semester II of Diploma in Electronics Engineering\nExamination 2024 (EVEN) held in the month of JUL, 2024\n \n \nResult Published On: 30/07/2024\nSTATE BOARD OF TECHNICAL EDUCATION\nBIHAR\n-----------------------------------------------------------------------------------------------\nSUBJECT  FULL MARKS PASS MARKS MARKS OBTAINED\nNAME OF SUBJECTS CREDITS INTFINTOTAL FINTOTAL INT FIN TOTAL GRADE\n-----------------------------------------------------------------------------------------------\nTHEORY PAPERS\nMATHEMATICS-I 3 3070 100 28 40122234  F\nAPPLIED PHYSICS-I 3 3070 100 28 40213859  D\nAPPLIED CHEMISTRY 3 3070 100 28 40152843  E\nCOMM. SKILLS IN ENGLISH 2 3070 100 28 40203656  D\nENGG. GRAPHICS 2 3070 100 28 40214162  C\n-----------------------------------------------------------------------------------------------\nPRACTICAL PAPERS\nAPPLIED PHYSICS LAB-I 2 1535 050 - 20123042  A\nAPPLIED CHEMISTRY LAB 2 1535 050 - 20123143  A\nCOMM. SKILLS IN ENGLISH LAB 2 1535 050 - 20122840  A\n-----------------------------------------------------------------------------------------------\nTERM WORK PAPERS\nENGG. WORKSHOP PRACTICE 2 0718 025 - 10061723  A+\nSPORTS AND YOGA 2 0718 025 - 10061622  A\nC/KYP/IT ESSEN/ PYTHON/ OTHERS 1 1535 050 - 20133144  A\n-----------------------------------------------------------------------------------------------\nGRAND TOTAL 24 750 468\n-----------------------------------------------------------------------------------------------\nSGPA \n-----------------------------------------------------------------------------------------------\nREMARKS : Carry in - MATHEMATICS-I",
        "college": "Government Polytechnic, Bhojpur",
        "name": "RAHUL KUMAR",
        "roll": "211522123036",
        "branch": "21",
        "marks": 468,
        "remarks": "Carry in - MATHEMATICS-I",
        "theory": 165
    },
    {
        "text": " \n \nRegistration No : 1522123006\nRoll No         : 211522123006\n \nFollowing are the marks obtained by SATYAM  KUMAR\nof Government Polytechnic, Bhojpur\nat Semester II of Diploma in Electronics Engineering\nExamination 2024 (EVEN) held in the month of JUL, 2024\n \n \nResult Published On: 30/07/2024\nSTATE BOARD OF TECHNICAL EDUCATION\nBIHAR\n-----------------------------------------------------------------------------------------------\nSUBJECT  FULL MARKS PASS MARKS MARKS OBTAINED\nNAME OF SUBJECTS CREDITS INTFINTOTAL FINTOTAL INT FIN TOTAL GRADE\n-----------------------------------------------------------------------------------------------\nTHEORY PAPERS\nMATHEMATICS-I 3 3070 100 28 40243458  D\nAPPLIED PHYSICS-I 3 3070 100 28 40223658  D\nAPPLIED CHEMISTRY 3 3070 100 28 40213354  D\nCOMM. SKILLS IN ENGLISH 2 3070 100 28 40215374  B\nENGG. GRAPHICS 2 3070 100 28 40194059  D\n-----------------------------------------------------------------------------------------------\nPRACTICAL PAPERS\nAPPLIED PHYSICS LAB-I 2 1535 050 - 20122840  A\nAPPLIED CHEMISTRY LAB 2 1535 050 - 20132942  A\nCOMM. SKILLS IN ENGLISH LAB 2 1535 050 - 20112637  B\n-----------------------------------------------------------------------------------------------\nTERM WORK PAPERS\nENGG. WORKSHOP PRACTICE 2 0718 025 - 10051621  A\nSPORTS AND YOGA 2 0718 025 - 10061622  A\nC/KYP/IT ESSEN/ PYTHON/ OTHERS 1 1535 050 - 20113243  A\n-----------------------------------------------------------------------------------------------\nGRAND TOTAL 24 750 508\n-----------------------------------------------------------------------------------------------\nSGPA 7.46\n-----------------------------------------------------------------------------------------------\nREMARKS : First Class",
        "college": "Government Polytechnic, Bhojpur",
        "name": "SATYAM KUMAR",
        "roll": "211522123006",
        "branch": "21",
        "marks": 508,
        "remarks": "First Class",
        "theory": 196
    },
    {
        "text": " \n \nRegistration No : 1522123007\nRoll No         : 211522123007\n \nFollowing are the marks obtained by RISHI  RAJ\nof Government Polytechnic, Bhojpur\nat Semester II of Diploma in Electronics Engineering\nExamination 2024 (EVEN) held in the month of JUL, 2024\n \n \nResult Published On: 30/07/2024\nSTATE BOARD OF TECHNICAL EDUCATION\nBIHAR\n-----------------------------------------------------------------------------------------------\nSUBJECT  FULL MARKS PASS MARKS MARKS OBTAINED\nNAME OF SUBJECTS CREDITS INTFINTOTAL FINTOTAL INT FIN TOTAL GRADE\n-----------------------------------------------------------------------------------------------\nTHEORY PAPERS\nMATHEMATICS-I 3 3070 100 28 401417+031  F\nAPPLIED PHYSICS-I 3 3070 100 28 400534+544  E\nAPPLIED CHEMISTRY 3 3070 100 28 40153247  E\nCOMM. SKILLS IN ENGLISH 2 3070 100 28 40162844  E\nENGG. GRAPHICS 2 3070 100 28 40182846  E\n-----------------------------------------------------------------------------------------------\nPRACTICAL PAPERS\nAPPLIED PHYSICS LAB-I 2 1535 050 - 201228-535  B\nAPPLIED CHEMISTRY LAB 2 1535 050 - 20122840  A\nCOMM. SKILLS IN ENGLISH LAB 2 1535 050 - 20102434  C\n-----------------------------------------------------------------------------------------------\nTERM WORK PAPERS\nENGG. WORKSHOP PRACTICE 2 0718 025 - 10061521  A\nSPORTS AND YOGA 2 0718 025 - 10051520  A\nC/KYP/IT ESSEN/ PYTHON/ OTHERS 1 1535 050 - 20123143  A\n-----------------------------------------------------------------------------------------------\nGRAND TOTAL 24 750 405\n-----------------------------------------------------------------------------------------------\nSGPA 5.96\n-----------------------------------------------------------------------------------------------\nREMARKS : Second Class (U/R)",
        "college": "Government Polytechnic, Bhojpur",
        "name": "RISHI RAJ",
        "roll": "211522123007",
        "branch": "21",
        "marks": 405,
        "remarks": "Second Class (U/R)",
        "theory": 139
    },
    {
        "text": " \n \nRegistration No : 1522123023\nRoll No         : 211522123023\n \nFollowing are the marks obtained by SALONI  SUMAN\nof Government Polytechnic, Bhojpur\nat Semester II of Diploma in Electronics Engineering\nExamination 2024 (EVEN) held in the month of JUL, 2024\n \n \nResult Published On: 30/07/2024\nSTATE BOARD OF TECHNICAL EDUCATION\nBIHAR\n-----------------------------------------------------------------------------------------------\nSUBJECT  FULL MARKS PASS MARKS MARKS OBTAINED\nNAME OF SUBJECTS CREDITS INTFINTOTAL FINTOTAL INT FIN TOTAL GRADE\n-----------------------------------------------------------------------------------------------\nTHEORY PAPERS\nMATHEMATICS-I 3 3070 100 28 40142842  E\nAPPLIED PHYSICS-I 3 3070 100 28 40283058  D\nAPPLIED CHEMISTRY 3 3070 100 28 40204060  C\nCOMM. SKILLS IN ENGLISH 2 3070 100 28 40264268  C\nENGG. GRAPHICS 2 3070 100 28 40254671  B\n-----------------------------------------------------------------------------------------------\nPRACTICAL PAPERS\nAPPLIED PHYSICS LAB-I 2 1535 050 - 20143044  A\nAPPLIED CHEMISTRY LAB 2 1535 050 - 20123143  A\nCOMM. SKILLS IN ENGLISH LAB 2 1535 050 - 20133346  A+\n-----------------------------------------------------------------------------------------------\nTERM WORK PAPERS\nENGG. WORKSHOP PRACTICE 2 0718 025 - 10071724  A+\nSPORTS AND YOGA 2 0718 025 - 10071724  A+\nC/KYP/IT ESSEN/ PYTHON/ OTHERS 1 1535 050 - 20143246  A+\n-----------------------------------------------------------------------------------------------\nGRAND TOTAL 24 750 526\n-----------------------------------------------------------------------------------------------\nSGPA 7.92\n-----------------------------------------------------------------------------------------------\nREMARKS : First Class",
        "college": "Government Polytechnic, Bhojpur",
        "name": "SALONI SUMAN",
        "roll": "211522123023",
        "branch": "21",
        "marks": 526,
        "remarks": "First Class",
        "theory": 186
    },
    {
        "text": " \n \nRegistration No : 1522123039\nRoll No         : 211522123039\n \nFollowing are the marks obtained by PIYUSH  RAJ\nof Government Polytechnic, Bhojpur\nat Semester II of Diploma in Electronics Engineering\nExamination 2024 (EVEN) held in the month of JUL, 2024\n \n \nResult Published On: 30/07/2024\nSTATE BOARD OF TECHNICAL EDUCATION\nBIHAR\n-----------------------------------------------------------------------------------------------\nSUBJECT  FULL MARKS PASS MARKS MARKS OBTAINED\nNAME OF SUBJECTS CREDITS INTFINTOTAL FINTOTAL INT FIN TOTAL GRADE\n-----------------------------------------------------------------------------------------------\nTHEORY PAPERS\nMATHEMATICS-I 3 3070 100 28 40160824  F\nAPPLIED PHYSICS-I 3 3070 100 28 40242852  D\nAPPLIED CHEMISTRY 3 3070 100 28 40251540  E\nCOMM. SKILLS IN ENGLISH 2 3070 100 28 40234972  B\nENGG. GRAPHICS 2 3070 100 28 40212849  E\n-----------------------------------------------------------------------------------------------\nPRACTICAL PAPERS\nAPPLIED PHYSICS LAB-I 2 1535 050 - 20133043  A\nAPPLIED CHEMISTRY LAB 2 1535 050 - 20132841  A\nCOMM. SKILLS IN ENGLISH LAB 2 1535 050 - 20112233  C\n-----------------------------------------------------------------------------------------------\nTERM WORK PAPERS\nENGG. WORKSHOP PRACTICE 2 0718 025 - 10061521  A\nSPORTS AND YOGA 2 0718 025 - 10051520  A\nC/KYP/IT ESSEN/ PYTHON/ OTHERS 1 1535 050 - 20113142  A\n-----------------------------------------------------------------------------------------------\nGRAND TOTAL 24 750 437\n-----------------------------------------------------------------------------------------------\nSGPA \n-----------------------------------------------------------------------------------------------\nREMARKS : Carry in - MATHEMATICS-I\n APPLIED CHEMISTRY",
        "college": "Government Polytechnic, Bhojpur",
        "name": "PIYUSH RAJ",
        "roll": "211522123039",
        "branch": "21",
        "marks": 437,
        "remarks": "Carry in - MATHEMATICS-I",
        "theory": 128
    },
    {
        "text": " \n \nRegistration No : 1522123040\nRoll No         : 211522123040\n \nFollowing are the marks obtained by KHUSHI  RANI\nof Government Polytechnic, Bhojpur\nat Semester II of Diploma in Electronics Engineering\nExamination 2024 (EVEN) held in the month of JUL, 2024\n \n \nResult Published On: 30/07/2024\nSTATE BOARD OF TECHNICAL EDUCATION\nBIHAR\n-----------------------------------------------------------------------------------------------\nSUBJECT  FULL MARKS PASS MARKS MARKS OBTAINED\nNAME OF SUBJECTS CREDITS INTFINTOTAL FINTOTAL INT FIN TOTAL GRADE\n-----------------------------------------------------------------------------------------------\nTHEORY PAPERS\nMATHEMATICS-I 3 3070 100 28 40144559  D\nAPPLIED PHYSICS-I 3 3070 100 28 40255580  A\nAPPLIED CHEMISTRY 3 3070 100 28 40183553  D\nCOMM. SKILLS IN ENGLISH 2 3070 100 28 40255075  B\nENGG. GRAPHICS 2 3070 100 28 40264975  B\n-----------------------------------------------------------------------------------------------\nPRACTICAL PAPERS\nAPPLIED PHYSICS LAB-I 2 1535 050 - 20132942  A\nAPPLIED CHEMISTRY LAB 2 1535 050 - 20123143  A\nCOMM. SKILLS IN ENGLISH LAB 2 1535 050 - 20112334  C\n-----------------------------------------------------------------------------------------------\nTERM WORK PAPERS\nENGG. WORKSHOP PRACTICE 2 0718 025 - 10061622  A\nSPORTS AND YOGA 2 0718 025 - 10061622  A\nC/KYP/IT ESSEN/ PYTHON/ OTHERS 1 1535 050 - 20133245  A+\n-----------------------------------------------------------------------------------------------\nGRAND TOTAL 24 750 550\n-----------------------------------------------------------------------------------------------\nSGPA 7.96\n-----------------------------------------------------------------------------------------------\nREMARKS : First Class",
        "college": "Government Polytechnic, Bhojpur",
        "name": "KHUSHI RANI",
        "roll": "211522123040",
        "branch": "21",
        "marks": 550,
        "remarks": "First Class",
        "theory": 234
    },
    {
        "text": " \n \nRegistration No : 1522123002\nRoll No         : 211522123002\n \nFollowing are the marks obtained by AYUSH  RANJAN\nof Government Polytechnic, Bhojpur\nat Semester II of Diploma in Electronics Engineering\nExamination 2024 (EVEN) held in the month of JUL, 2024\n \n \nResult Published On: 30/07/2024\nSTATE BOARD OF TECHNICAL EDUCATION\nBIHAR\n-----------------------------------------------------------------------------------------------\nSUBJECT  FULL MARKS PASS MARKS MARKS OBTAINED\nNAME OF SUBJECTS CREDITS INTFINTOTAL FINTOTAL INT FIN TOTAL GRADE\n-----------------------------------------------------------------------------------------------\nTHEORY PAPERS\nMATHEMATICS-I 3 3070 100 28 40272855  D\nAPPLIED PHYSICS-I 3 3070 100 28 40163753  D\nAPPLIED CHEMISTRY 3 3070 100 28 40234871  B\nCOMM. SKILLS IN ENGLISH 2 3070 100 28 40264268  C\nENGG. GRAPHICS 2 3070 100 28 40196180  A\n-----------------------------------------------------------------------------------------------\nPRACTICAL PAPERS\nAPPLIED PHYSICS LAB-I 2 1535 050 - 20113142  A\nAPPLIED CHEMISTRY LAB 2 1535 050 - 20123143  A\nCOMM. SKILLS IN ENGLISH LAB 2 1535 050 - 20132740  A\n-----------------------------------------------------------------------------------------------\nTERM WORK PAPERS\nENGG. WORKSHOP PRACTICE 2 0718 025 - 10071623  A+\nSPORTS AND YOGA 2 0718 025 - 10051520  A\nC/KYP/IT ESSEN/ PYTHON/ OTHERS 1 1535 050 - 20133245  A+\n-----------------------------------------------------------------------------------------------\nGRAND TOTAL 24 750 540\n-----------------------------------------------------------------------------------------------\nSGPA 8.08\n-----------------------------------------------------------------------------------------------\nREMARKS : First Class",
        "college": "Government Polytechnic, Bhojpur",
        "name": "AYUSH RANJAN",
        "roll": "211522123002",
        "branch": "21",
        "marks": 540,
        "remarks": "First Class",
        "theory": 216
    },
    {
        "text": " \n \nRegistration No : 1522123035\nRoll No         : 211522123035\n \nFollowing are the marks obtained by MD ARSHAD ANSARI\nof Government Polytechnic, Bhojpur\nat Semester II of Diploma in Electronics Engineering\nExamination 2024 (EVEN) held in the month of JUL, 2024\n \n \nResult Published On: 30/07/2024\nSTATE BOARD OF TECHNICAL EDUCATION\nBIHAR\n-----------------------------------------------------------------------------------------------\nSUBJECT  FULL MARKS PASS MARKS MARKS OBTAINED\nNAME OF SUBJECTS CREDITS INTFINTOTAL FINTOTAL INT FIN TOTAL GRADE\n-----------------------------------------------------------------------------------------------\nTHEORY PAPERS\nMATHEMATICS-I 3 3070 100 28 4012 A12  F\nAPPLIED PHYSICS-I 3 3070 100 28 40130922  F\nAPPLIED CHEMISTRY 3 3070 100 28 40150823  F\nCOMM. SKILLS IN ENGLISH 2 3070 100 28 40162844  E\nENGG. GRAPHICS 2 3070 100 28 40071926  F\n-----------------------------------------------------------------------------------------------\nPRACTICAL PAPERS\nAPPLIED PHYSICS LAB-I 2 1535 050 - 20102838  B\nAPPLIED CHEMISTRY LAB 2 1535 050 - 20122840  A\nCOMM. SKILLS IN ENGLISH LAB 2 1535 050 - 20112435  B\n-----------------------------------------------------------------------------------------------\nTERM WORK PAPERS\nENGG. WORKSHOP PRACTICE 2 0718 025 - 10051621  A\nSPORTS AND YOGA 2 0718 025 - 10051520  A\nC/KYP/IT ESSEN/ PYTHON/ OTHERS 1 1535 050 - 20133144  A\n-----------------------------------------------------------------------------------------------\nGRAND TOTAL 24 750 325\n-----------------------------------------------------------------------------------------------\nSGPA \n-----------------------------------------------------------------------------------------------\nREMARKS : Fail",
        "college": "Government Polytechnic, Bhojpur",
        "name": "MD ARSHAD ANSARI",
        "roll": "211522123035",
        "branch": "21",
        "marks": 325,
        "remarks": "Fail",
        "theory": 64
    },
    {
        "text": " \n \nRegistration No : 1522123025\nRoll No         : 211522123025\n \nFollowing are the marks obtained by ANKUR  KUMAR\nof Government Polytechnic, Bhojpur\nat Semester II of Diploma in Electronics Engineering\nExamination 2024 (EVEN) held in the month of JUL, 2024\n \n \nResult Published On: 30/07/2024\nSTATE BOARD OF TECHNICAL EDUCATION\nBIHAR\n-----------------------------------------------------------------------------------------------\nSUBJECT  FULL MARKS PASS MARKS MARKS OBTAINED\nNAME OF SUBJECTS CREDITS INTFINTOTAL FINTOTAL INT FIN TOTAL GRADE\n-----------------------------------------------------------------------------------------------\nTHEORY PAPERS\nMATHEMATICS-I 3 3070 100 28 40142842  E\nAPPLIED PHYSICS-I 3 3070 100 28 40143246  E\nAPPLIED CHEMISTRY 3 3070 100 28 40161733  F\nCOMM. SKILLS IN ENGLISH 2 3070 100 28 40254671  B\nENGG. GRAPHICS 2 3070 100 28 40193352  D\n-----------------------------------------------------------------------------------------------\nPRACTICAL PAPERS\nAPPLIED PHYSICS LAB-I 2 1535 050 - 20112940  A\nAPPLIED CHEMISTRY LAB 2 1535 050 - 20122840  A\nCOMM. SKILLS IN ENGLISH LAB 2 1535 050 - 20112536  B\n-----------------------------------------------------------------------------------------------\nTERM WORK PAPERS\nENGG. WORKSHOP PRACTICE 2 0718 025 - 10061622  A\nSPORTS AND YOGA 2 0718 025 - 10061622  A\nC/KYP/IT ESSEN/ PYTHON/ OTHERS 1 1535 050 - 20123042  A\n-----------------------------------------------------------------------------------------------\nGRAND TOTAL 24 750 446\n-----------------------------------------------------------------------------------------------\nSGPA \n-----------------------------------------------------------------------------------------------\nREMARKS : Carry in - APPLIED CHEMISTRY",
        "college": "Government Polytechnic, Bhojpur",
        "name": "ANKUR KUMAR",
        "roll": "211522123025",
        "branch": "21",
        "marks": 446,
        "remarks": "Carry in - APPLIED CHEMISTRY",
        "theory": 156
    },
    {
        "text": " \n \nRegistration No : 1522123014\nRoll No         : 211522123014\n \nFollowing are the marks obtained by ROHIT RAJ KUMAR\nof Government Polytechnic, Bhojpur\nat Semester II of Diploma in Electronics Engineering\nExamination 2024 (EVEN) held in the month of JUL, 2024\n \n \nResult Published On: 30/07/2024\nSTATE BOARD OF TECHNICAL EDUCATION\nBIHAR\n-----------------------------------------------------------------------------------------------\nSUBJECT  FULL MARKS PASS MARKS MARKS OBTAINED\nNAME OF SUBJECTS CREDITS INTFINTOTAL FINTOTAL INT FIN TOTAL GRADE\n-----------------------------------------------------------------------------------------------\nTHEORY PAPERS\nMATHEMATICS-I 3 3070 100 28 40160723  F\nAPPLIED PHYSICS-I 3 3070 100 28 40221335  F\nAPPLIED CHEMISTRY 3 3070 100 28 40152035  F\nCOMM. SKILLS IN ENGLISH 2 3070 100 28 40274471  B\nENGG. GRAPHICS 2 3070 100 28 40191534  F\n-----------------------------------------------------------------------------------------------\nPRACTICAL PAPERS\nAPPLIED PHYSICS LAB-I 2 1535 050 - 20122840  A\nAPPLIED CHEMISTRY LAB 2 1535 050 - 20123042  A\nCOMM. SKILLS IN ENGLISH LAB 2 1535 050 - 2012 A12  F\n-----------------------------------------------------------------------------------------------\nTERM WORK PAPERS\nENGG. WORKSHOP PRACTICE 2 0718 025 - 10051520  A\nSPORTS AND YOGA 2 0718 025 - 10051217  C\nC/KYP/IT ESSEN/ PYTHON/ OTHERS 1 1535 050 - 20123143  A\n-----------------------------------------------------------------------------------------------\nGRAND TOTAL 24 750 372\n-----------------------------------------------------------------------------------------------\nSGPA \n-----------------------------------------------------------------------------------------------\nREMARKS : Fail",
        "college": "Government Polytechnic, Bhojpur",
        "name": "ROHIT RAJ KUMAR",
        "roll": "211522123014",
        "branch": "21",
        "marks": 372,
        "remarks": "Fail",
        "theory": 99
    },
    {
        "text": " \n \nRegistration No : 1522123043\nRoll No         : 211522123043\n \nFollowing are the marks obtained by NITISH  KUMAR\nof Government Polytechnic, Bhojpur\nat Semester II of Diploma in Electronics Engineering\nExamination 2024 (EVEN) held in the month of JUL, 2024\n \n \nResult Published On: 30/07/2024\nSTATE BOARD OF TECHNICAL EDUCATION\nBIHAR\n-----------------------------------------------------------------------------------------------\nSUBJECT  FULL MARKS PASS MARKS MARKS OBTAINED\nNAME OF SUBJECTS CREDITS INTFINTOTAL FINTOTAL INT FIN TOTAL GRADE\n-----------------------------------------------------------------------------------------------\nTHEORY PAPERS\nMATHEMATICS-I 3 3070 100 28 40262854  D\nAPPLIED PHYSICS-I 3 3070 100 28 40212849  E\nAPPLIED CHEMISTRY 3 3070 100 28 40261642  E\nCOMM. SKILLS IN ENGLISH 2 3070 100 28 40263662  C\nENGG. GRAPHICS 2 3070 100 28 40204464  C\n-----------------------------------------------------------------------------------------------\nPRACTICAL PAPERS\nAPPLIED PHYSICS LAB-I 2 1535 050 - 20123042  A\nAPPLIED CHEMISTRY LAB 2 1535 050 - 20133043  A\nCOMM. SKILLS IN ENGLISH LAB 2 1535 050 - 20133245  A+\n-----------------------------------------------------------------------------------------------\nTERM WORK PAPERS\nENGG. WORKSHOP PRACTICE 2 0718 025 - 10071623  A+\nSPORTS AND YOGA 2 0718 025 - 10071724  A+\nC/KYP/IT ESSEN/ PYTHON/ OTHERS 1 1535 050 - 20113041  A\n-----------------------------------------------------------------------------------------------\nGRAND TOTAL 24 750 489\n-----------------------------------------------------------------------------------------------\nSGPA \n-----------------------------------------------------------------------------------------------\nREMARKS : Carry in - APPLIED CHEMISTRY",
        "college": "Government Polytechnic, Bhojpur",
        "name": "NITISH KUMAR",
        "roll": "211522123043",
        "branch": "21",
        "marks": 489,
        "remarks": "Carry in - APPLIED CHEMISTRY",
        "theory": 152
    },
    {
        "text": " \n \nRegistration No : 1522123038\nRoll No         : 211522123038\n \nFollowing are the marks obtained by SHUBHAM  KUMAR\nof Government Polytechnic, Bhojpur\nat Semester II of Diploma in Electronics Engineering\nExamination 2024 (EVEN) held in the month of JUL, 2024\n \n \nResult Published On: 30/07/2024\nSTATE BOARD OF TECHNICAL EDUCATION\nBIHAR\n-----------------------------------------------------------------------------------------------\nSUBJECT  FULL MARKS PASS MARKS MARKS OBTAINED\nNAME OF SUBJECTS CREDITS INTFINTOTAL FINTOTAL INT FIN TOTAL GRADE\n-----------------------------------------------------------------------------------------------\nTHEORY PAPERS\nMATHEMATICS-I 3 3070 100 28 40251944  E\nAPPLIED PHYSICS-I 3 3070 100 28 40283967  C\nAPPLIED CHEMISTRY 3 3070 100 28 40214263  C\nCOMM. SKILLS IN ENGLISH 2 3070 100 28 40254368  C\nENGG. GRAPHICS 2 3070 100 28 40242852  D\n-----------------------------------------------------------------------------------------------\nPRACTICAL PAPERS\nAPPLIED PHYSICS LAB-I 2 1535 050 - 20143145  A+\nAPPLIED CHEMISTRY LAB 2 1535 050 - 20132942  A\nCOMM. SKILLS IN ENGLISH LAB 2 1535 050 - 20122436  B\n-----------------------------------------------------------------------------------------------\nTERM WORK PAPERS\nENGG. WORKSHOP PRACTICE 2 0718 025 - 10051621  A\nSPORTS AND YOGA 2 0718 025 - 10071724  A+\nC/KYP/IT ESSEN/ PYTHON/ OTHERS 1 1535 050 - 20123042  A\n-----------------------------------------------------------------------------------------------\nGRAND TOTAL 24 750 504\n-----------------------------------------------------------------------------------------------\nSGPA \n-----------------------------------------------------------------------------------------------\nREMARKS : Carry in - MATHEMATICS-I",
        "college": "Government Polytechnic, Bhojpur",
        "name": "SHUBHAM KUMAR",
        "roll": "211522123038",
        "branch": "21",
        "marks": 504,
        "remarks": "Carry in - MATHEMATICS-I",
        "theory": 171
    },
    {
        "text": " \n \nRegistration No : 1522123010\nRoll No         : 211522123010\n \nFollowing are the marks obtained by SAKSHI  SINGH\nof Government Polytechnic, Bhojpur\nat Semester II of Diploma in Electronics Engineering\nExamination 2024 (EVEN) held in the month of JUL, 2024\n \n \nResult Published On: 30/07/2024\nSTATE BOARD OF TECHNICAL EDUCATION\nBIHAR\n-----------------------------------------------------------------------------------------------\nSUBJECT  FULL MARKS PASS MARKS MARKS OBTAINED\nNAME OF SUBJECTS CREDITS INTFINTOTAL FINTOTAL INT FIN TOTAL GRADE\n-----------------------------------------------------------------------------------------------\nTHEORY PAPERS\nMATHEMATICS-I 3 3070 100 28 40202848  E\nAPPLIED PHYSICS-I 3 3070 100 28 40242953  D\nAPPLIED CHEMISTRY 3 3070 100 28 40151934  F\nCOMM. SKILLS IN ENGLISH 2 3070 100 28 40223153  D\nENGG. GRAPHICS 2 3070 100 28 40253863  C\n-----------------------------------------------------------------------------------------------\nPRACTICAL PAPERS\nAPPLIED PHYSICS LAB-I 2 1535 050 - 20132942  A\nAPPLIED CHEMISTRY LAB 2 1535 050 - 20112940  A\nCOMM. SKILLS IN ENGLISH LAB 2 1535 050 - 20123042  A\n-----------------------------------------------------------------------------------------------\nTERM WORK PAPERS\nENGG. WORKSHOP PRACTICE 2 0718 025 - 10061622  A\nSPORTS AND YOGA 2 0718 025 - 10071724  A+\nC/KYP/IT ESSEN/ PYTHON/ OTHERS 1 1535 050 - 20133144  A\n-----------------------------------------------------------------------------------------------\nGRAND TOTAL 24 750 465\n-----------------------------------------------------------------------------------------------\nSGPA \n-----------------------------------------------------------------------------------------------\nREMARKS : Carry in - APPLIED CHEMISTRY",
        "college": "Government Polytechnic, Bhojpur",
        "name": "SAKSHI SINGH",
        "roll": "211522123010",
        "branch": "21",
        "marks": 465,
        "remarks": "Carry in - APPLIED CHEMISTRY",
        "theory": 145
    },
    {
        "text": " \n \nRegistration No : 1522123029\nRoll No         : 211522123029\n \nFollowing are the marks obtained by SHUBHAM KUMAR\nof Government Polytechnic, Bhojpur\nat Semester II of Diploma in Electronics Engineering\nExamination 2024 (EVEN) held in the month of JUL, 2024\n \n \nResult Published On: 30/07/2024\nSTATE BOARD OF TECHNICAL EDUCATION\nBIHAR\n-----------------------------------------------------------------------------------------------\nSUBJECT  FULL MARKS PASS MARKS MARKS OBTAINED\nNAME OF SUBJECTS CREDITS INTFINTOTAL FINTOTAL INT FIN TOTAL GRADE\n-----------------------------------------------------------------------------------------------\nTHEORY PAPERS\nMATHEMATICS-I 3 3070 100 28 40174259  D\nAPPLIED PHYSICS-I 3 3070 100 28 40224365  C\nAPPLIED CHEMISTRY 3 3070 100 28 40264874  B\nCOMM. SKILLS IN ENGLISH 2 3070 100 28 40264773  B\nENGG. GRAPHICS 2 3070 100 28 40214566  C\n-----------------------------------------------------------------------------------------------\nPRACTICAL PAPERS\nAPPLIED PHYSICS LAB-I 2 1535 050 - 20123042  A\nAPPLIED CHEMISTRY LAB 2 1535 050 - 20133043  A\nCOMM. SKILLS IN ENGLISH LAB 2 1535 050 - 20123042  A\n-----------------------------------------------------------------------------------------------\nTERM WORK PAPERS\nENGG. WORKSHOP PRACTICE 2 0718 025 - 10061521  A\nSPORTS AND YOGA 2 0718 025 - 10061622  A\nC/KYP/IT ESSEN/ PYTHON/ OTHERS 1 1535 050 - 20123143  A\n-----------------------------------------------------------------------------------------------\nGRAND TOTAL 24 750 550\n-----------------------------------------------------------------------------------------------\nSGPA 8.0\n-----------------------------------------------------------------------------------------------\nREMARKS : First Class",
        "college": "Government Polytechnic, Bhojpur",
        "name": "SHUBHAM KUMAR",
        "roll": "211522123029",
        "branch": "21",
        "marks": 550,
        "remarks": "First Class",
        "theory": 225
    },
    {
        "text": " \n \nRegistration No : 1522123042\nRoll No         : 211522123042\n \nFollowing are the marks obtained by ROBIN  RAJ\nof Government Polytechnic, Bhojpur\nat Semester II of Diploma in Electronics Engineering\nExamination 2024 (EVEN) held in the month of JUL, 2024\n \n \nResult Published On: 30/07/2024\nSTATE BOARD OF TECHNICAL EDUCATION\nBIHAR\n-----------------------------------------------------------------------------------------------\nSUBJECT  FULL MARKS PASS MARKS MARKS OBTAINED\nNAME OF SUBJECTS CREDITS INTFINTOTAL FINTOTAL INT FIN TOTAL GRADE\n-----------------------------------------------------------------------------------------------\nTHEORY PAPERS\nMATHEMATICS-I 3 3070 100 28 402423+552  D\nAPPLIED PHYSICS-I 3 3070 100 28 40243458  D\nAPPLIED CHEMISTRY 3 3070 100 28 40254368  C\nCOMM. SKILLS IN ENGLISH 2 3070 100 28 40264773  B\nENGG. GRAPHICS 2 3070 100 28 402450-569  C\n-----------------------------------------------------------------------------------------------\nPRACTICAL PAPERS\nAPPLIED PHYSICS LAB-I 2 1535 050 - 20132841  A\nAPPLIED CHEMISTRY LAB 2 1535 050 - 20122840  A\nCOMM. SKILLS IN ENGLISH LAB 2 1535 050 - 20132639  B\n-----------------------------------------------------------------------------------------------\nTERM WORK PAPERS\nENGG. WORKSHOP PRACTICE 2 0718 025 - 10051621  A\nSPORTS AND YOGA 2 0718 025 - 10061622  A\nC/KYP/IT ESSEN/ PYTHON/ OTHERS 1 1535 050 - 20133043  A\n-----------------------------------------------------------------------------------------------\nGRAND TOTAL 24 750 526\n-----------------------------------------------------------------------------------------------\nSGPA 7.67\n-----------------------------------------------------------------------------------------------\nREMARKS : First Class (U/R)",
        "college": "Government Polytechnic, Bhojpur",
        "name": "ROBIN RAJ",
        "roll": "211522123042",
        "branch": "21",
        "marks": 526,
        "remarks": "First Class (U/R)",
        "theory": 197
    },
    {
        "text": " \n \nRegistration No : 1522123005\nRoll No         : 211522123005\n \nFollowing are the marks obtained by AANCHAL  KUMARI\nof Government Polytechnic, Bhojpur\nat Semester II of Diploma in Electronics Engineering\nExamination 2024 (EVEN) held in the month of JUL, 2024\n \n \nResult Published On: 30/07/2024\nSTATE BOARD OF TECHNICAL EDUCATION\nBIHAR\n-----------------------------------------------------------------------------------------------\nSUBJECT  FULL MARKS PASS MARKS MARKS OBTAINED\nNAME OF SUBJECTS CREDITS INTFINTOTAL FINTOTAL INT FIN TOTAL GRADE\n-----------------------------------------------------------------------------------------------\nTHEORY PAPERS\nMATHEMATICS-I 3 3070 100 28 40152843  E\nAPPLIED PHYSICS-I 3 3070 100 28 4018 A18  F\nAPPLIED CHEMISTRY 3 3070 100 28 40222850  D\nCOMM. SKILLS IN ENGLISH 2 3070 100 28 40243054  D\nENGG. GRAPHICS 2 3070 100 28 40252853  D\n-----------------------------------------------------------------------------------------------\nPRACTICAL PAPERS\nAPPLIED PHYSICS LAB-I 2 1535 050 - 20122840  A\nAPPLIED CHEMISTRY LAB 2 1535 050 - 20123042  A\nCOMM. SKILLS IN ENGLISH LAB 2 1535 050 - 20123042  A\n-----------------------------------------------------------------------------------------------\nTERM WORK PAPERS\nENGG. WORKSHOP PRACTICE 2 0718 025 - 10061622  A\nSPORTS AND YOGA 2 0718 025 - 10071724  A+\nC/KYP/IT ESSEN/ PYTHON/ OTHERS 1 1535 050 - 20123143  A\n-----------------------------------------------------------------------------------------------\nGRAND TOTAL 24 750 431\n-----------------------------------------------------------------------------------------------\nSGPA \n-----------------------------------------------------------------------------------------------\nREMARKS : Carry in - APPLIED PHYSICS-I",
        "college": "Government Polytechnic, Bhojpur",
        "name": "AANCHAL KUMARI",
        "roll": "211522123005",
        "branch": "21",
        "marks": 431,
        "remarks": "Carry in - APPLIED PHYSICS-I",
        "theory": 114
    },
    {
        "text": " \n \nRegistration No : 1522123022\nRoll No         : 211522123022\n \nFollowing are the marks obtained by RAUSHAN  KUMAR\nof Government Polytechnic, Bhojpur\nat Semester II of Diploma in Electronics Engineering\nExamination 2024 (EVEN) held in the month of JUL, 2024\n \n \nResult Published On: 30/07/2024\nSTATE BOARD OF TECHNICAL EDUCATION\nBIHAR\n-----------------------------------------------------------------------------------------------\nSUBJECT  FULL MARKS PASS MARKS MARKS OBTAINED\nNAME OF SUBJECTS CREDITS INTFINTOTAL FINTOTAL INT FIN TOTAL GRADE\n-----------------------------------------------------------------------------------------------\nTHEORY PAPERS\nMATHEMATICS-I 3 3070 100 28 40223052  D\nAPPLIED PHYSICS-I 3 3070 100 28 40253863  C\nAPPLIED CHEMISTRY 3 3070 100 28 40211940  E\nCOMM. SKILLS IN ENGLISH 2 3070 100 28 40205070  B\nENGG. GRAPHICS 2 3070 100 28 40224466  C\n-----------------------------------------------------------------------------------------------\nPRACTICAL PAPERS\nAPPLIED PHYSICS LAB-I 2 1535 050 - 20132942  A\nAPPLIED CHEMISTRY LAB 2 1535 050 - 20122941  A\nCOMM. SKILLS IN ENGLISH LAB 2 1535 050 - 20103141  A\n-----------------------------------------------------------------------------------------------\nTERM WORK PAPERS\nENGG. WORKSHOP PRACTICE 2 0718 025 - 10051621  A\nSPORTS AND YOGA 2 0718 025 - 10051520  A\nC/KYP/IT ESSEN/ PYTHON/ OTHERS 1 1535 050 - 20123042  A\n-----------------------------------------------------------------------------------------------\nGRAND TOTAL 24 750 498\n-----------------------------------------------------------------------------------------------\nSGPA \n-----------------------------------------------------------------------------------------------\nREMARKS : Carry in - APPLIED CHEMISTRY",
        "college": "Government Polytechnic, Bhojpur",
        "name": "RAUSHAN KUMAR",
        "roll": "211522123022",
        "branch": "21",
        "marks": 498,
        "remarks": "Carry in - APPLIED CHEMISTRY",
        "theory": 181
    },
    {
        "text": " \n \nRegistration No : 1522123004\nRoll No         : 211522123004\n \nFollowing are the marks obtained by ADARSH BHARDWAJ SINGH\nof Government Polytechnic, Bhojpur\nat Semester II of Diploma in Electronics Engineering\nExamination 2024 (EVEN) held in the month of JUL, 2024\n \n \nResult Published On: 30/07/2024\nSTATE BOARD OF TECHNICAL EDUCATION\nBIHAR\n-----------------------------------------------------------------------------------------------\nSUBJECT  FULL MARKS PASS MARKS MARKS OBTAINED\nNAME OF SUBJECTS CREDITS INTFINTOTAL FINTOTAL INT FIN TOTAL GRADE\n-----------------------------------------------------------------------------------------------\nTHEORY PAPERS\nMATHEMATICS-I 3 3070 100 28 40191029  F\nAPPLIED PHYSICS-I 3 3070 100 28 40162844  E\nAPPLIED CHEMISTRY 3 3070 100 28 40170623  F\nCOMM. SKILLS IN ENGLISH 2 3070 100 28 40223052  D\nENGG. GRAPHICS 2 3070 100 28 40223355  D\n-----------------------------------------------------------------------------------------------\nPRACTICAL PAPERS\nAPPLIED PHYSICS LAB-I 2 1535 050 - 20112839  B\nAPPLIED CHEMISTRY LAB 2 1535 050 - 20132942  A\nCOMM. SKILLS IN ENGLISH LAB 2 1535 050 - 20122638  B\n-----------------------------------------------------------------------------------------------\nTERM WORK PAPERS\nENGG. WORKSHOP PRACTICE 2 0718 025 - 10051722  A\nSPORTS AND YOGA 2 0718 025 - 10061622  A\nC/KYP/IT ESSEN/ PYTHON/ OTHERS 1 1535 050 - 20123143  A\n-----------------------------------------------------------------------------------------------\nGRAND TOTAL 24 750 409\n-----------------------------------------------------------------------------------------------\nSGPA \n-----------------------------------------------------------------------------------------------\nREMARKS : Carry in - MATHEMATICS-I\n APPLIED CHEMISTRY",
        "college": "Government Polytechnic, Bhojpur",
        "name": "ADARSH BHARDWAJ SINGH",
        "roll": "211522123004",
        "branch": "21",
        "marks": 409,
        "remarks": "Carry in - MATHEMATICS-I",
        "theory": 107
    },
    {
        "text": " \n \nRegistration No : 1522123021\nRoll No         : 211522123021\n \nFollowing are the marks obtained by ANNU  PRAKASH\nof Government Polytechnic, Bhojpur\nat Semester II of Diploma in Electronics Engineering\nExamination 2024 (EVEN) held in the month of JUL, 2024\n \n \nResult Published On: 30/07/2024\nSTATE BOARD OF TECHNICAL EDUCATION\nBIHAR\n-----------------------------------------------------------------------------------------------\nSUBJECT  FULL MARKS PASS MARKS MARKS OBTAINED\nNAME OF SUBJECTS CREDITS INTFINTOTAL FINTOTAL INT FIN TOTAL GRADE\n-----------------------------------------------------------------------------------------------\nTHEORY PAPERS\nMATHEMATICS-I 3 3070 100 28 40111021  F\nAPPLIED PHYSICS-I 3 3070 100 28 40162844  E\nAPPLIED CHEMISTRY 3 3070 100 28 40163349  E\nCOMM. SKILLS IN ENGLISH 2 3070 100 28 40202848  E\nENGG. GRAPHICS 2 3070 100 28 40212950  D\n-----------------------------------------------------------------------------------------------\nPRACTICAL PAPERS\nAPPLIED PHYSICS LAB-I 2 1535 050 - 20112940  A\nAPPLIED CHEMISTRY LAB 2 1535 050 - 20112738  B\nCOMM. SKILLS IN ENGLISH LAB 2 1535 050 - 20122436  B\n-----------------------------------------------------------------------------------------------\nTERM WORK PAPERS\nENGG. WORKSHOP PRACTICE 2 0718 025 - 10061723  A+\nSPORTS AND YOGA 2 0718 025 - 10061622  A\nC/KYP/IT ESSEN/ PYTHON/ OTHERS 1 1535 050 - 20133144  A\n-----------------------------------------------------------------------------------------------\nGRAND TOTAL 24 750 415\n-----------------------------------------------------------------------------------------------\nSGPA \n-----------------------------------------------------------------------------------------------\nREMARKS : Carry in - MATHEMATICS-I",
        "college": "Government Polytechnic, Bhojpur",
        "name": "ANNU PRAKASH",
        "roll": "211522123021",
        "branch": "21",
        "marks": 415,
        "remarks": "Carry in - MATHEMATICS-I",
        "theory": 128
    },
    {
        "text": " \n \nRegistration No : 1522123020\nRoll No         : 211522123020\n \nFollowing are the marks obtained by ISHAN  KASHYAP\nof Government Polytechnic, Bhojpur\nat Semester II of Diploma in Electronics Engineering\nExamination 2024 (EVEN) held in the month of JUL, 2024\n \n \nResult Published On: 30/07/2024\nSTATE BOARD OF TECHNICAL EDUCATION\nBIHAR\n-----------------------------------------------------------------------------------------------\nSUBJECT  FULL MARKS PASS MARKS MARKS OBTAINED\nNAME OF SUBJECTS CREDITS INTFINTOTAL FINTOTAL INT FIN TOTAL GRADE\n-----------------------------------------------------------------------------------------------\nTHEORY PAPERS\nMATHEMATICS-I 3 3070 100 28 40161834  F\nAPPLIED PHYSICS-I 3 3070 100 28 40284068  C\nAPPLIED CHEMISTRY 3 3070 100 28 40202949  E\nCOMM. SKILLS IN ENGLISH 2 3070 100 28 40224264  C\nENGG. GRAPHICS 2 3070 100 28 40203959  D\n-----------------------------------------------------------------------------------------------\nPRACTICAL PAPERS\nAPPLIED PHYSICS LAB-I 2 1535 050 - 20142943  A\nAPPLIED CHEMISTRY LAB 2 1535 050 - 20123042  A\nCOMM. SKILLS IN ENGLISH LAB 2 1535 050 - 20102535  B\n-----------------------------------------------------------------------------------------------\nTERM WORK PAPERS\nENGG. WORKSHOP PRACTICE 2 0718 025 - 10061723  A+\nSPORTS AND YOGA 2 0718 025 - 10051520  A\nC/KYP/IT ESSEN/ PYTHON/ OTHERS 1 1535 050 - 20123042  A\n-----------------------------------------------------------------------------------------------\nGRAND TOTAL 24 750 479\n-----------------------------------------------------------------------------------------------\nSGPA \n-----------------------------------------------------------------------------------------------\nREMARKS : Carry in - MATHEMATICS-I",
        "college": "Government Polytechnic, Bhojpur",
        "name": "ISHAN KASHYAP",
        "roll": "211522123020",
        "branch": "21",
        "marks": 479,
        "remarks": "Carry in - MATHEMATICS-I",
        "theory": 168
    },
    {
        "text": " \n \nRegistration No : 1522123044\nRoll No         : 211522123044\n \nFollowing are the marks obtained by GULSHAN  KUMAR\nof Government Polytechnic, Bhojpur\nat Semester II of Diploma in Electronics Engineering\nExamination 2024 (EVEN) held in the month of JUL, 2024\n \n \nResult Published On: 30/07/2024\nSTATE BOARD OF TECHNICAL EDUCATION\nBIHAR\n-----------------------------------------------------------------------------------------------\nSUBJECT  FULL MARKS PASS MARKS MARKS OBTAINED\nNAME OF SUBJECTS CREDITS INTFINTOTAL FINTOTAL INT FIN TOTAL GRADE\n-----------------------------------------------------------------------------------------------\nTHEORY PAPERS\nMATHEMATICS-I 3 3070 100 28 40211031  F\nAPPLIED PHYSICS-I 3 3070 100 28 40253661  C\nAPPLIED CHEMISTRY 3 3070 100 28 40282856  D\nCOMM. SKILLS IN ENGLISH 2 3070 100 28 40264470  B\nENGG. GRAPHICS 2 3070 100 28 40213051  D\n-----------------------------------------------------------------------------------------------\nPRACTICAL PAPERS\nAPPLIED PHYSICS LAB-I 2 1535 050 - 20133043  A\nAPPLIED CHEMISTRY LAB 2 1535 050 - 20133245  A+\nCOMM. SKILLS IN ENGLISH LAB 2 1535 050 - 20133043  A\n-----------------------------------------------------------------------------------------------\nTERM WORK PAPERS\nENGG. WORKSHOP PRACTICE 2 0718 025 - 10061622  A\nSPORTS AND YOGA 2 0718 025 - 10071724  A+\nC/KYP/IT ESSEN/ PYTHON/ OTHERS 1 1535 050 - 20133144  A\n-----------------------------------------------------------------------------------------------\nGRAND TOTAL 24 750 490\n-----------------------------------------------------------------------------------------------\nSGPA \n-----------------------------------------------------------------------------------------------\nREMARKS : Carry in - MATHEMATICS-I",
        "college": "Government Polytechnic, Bhojpur",
        "name": "GULSHAN KUMAR",
        "roll": "211522123044",
        "branch": "21",
        "marks": 490,
        "remarks": "Carry in - MATHEMATICS-I",
        "theory": 148
    },
    {
        "text": " \n \nRegistration No : 1522123018\nRoll No         : 211522123018\n \nFollowing are the marks obtained by ASHI  SINGH\nof Government Polytechnic, Bhojpur\nat Semester II of Diploma in Electronics Engineering\nExamination 2024 (EVEN) held in the month of JUL, 2024\n \n \nResult Published On: 30/07/2024\nSTATE BOARD OF TECHNICAL EDUCATION\nBIHAR\n-----------------------------------------------------------------------------------------------\nSUBJECT  FULL MARKS PASS MARKS MARKS OBTAINED\nNAME OF SUBJECTS CREDITS INTFINTOTAL FINTOTAL INT FIN TOTAL GRADE\n-----------------------------------------------------------------------------------------------\nTHEORY PAPERS\nMATHEMATICS-I 3 3070 100 28 40123446  E\nAPPLIED PHYSICS-I 3 3070 100 28 40213657  D\nAPPLIED CHEMISTRY 3 3070 100 28 40174057  D\nCOMM. SKILLS IN ENGLISH 2 3070 100 28 40194867  C\nENGG. GRAPHICS 2 3070 100 28 40243660  C\n-----------------------------------------------------------------------------------------------\nPRACTICAL PAPERS\nAPPLIED PHYSICS LAB-I 2 1535 050 - 20133043  A\nAPPLIED CHEMISTRY LAB 2 1535 050 - 20122941  A\nCOMM. SKILLS IN ENGLISH LAB 2 1535 050 - 20113041  A\n-----------------------------------------------------------------------------------------------\nTERM WORK PAPERS\nENGG. WORKSHOP PRACTICE 2 0718 025 - 10061622  A\nSPORTS AND YOGA 2 0718 025 - 10051520  A\nC/KYP/IT ESSEN/ PYTHON/ OTHERS 1 1535 050 - 20123042  A\n-----------------------------------------------------------------------------------------------\nGRAND TOTAL 24 750 496\n-----------------------------------------------------------------------------------------------\nSGPA 7.42\n-----------------------------------------------------------------------------------------------\nREMARKS : First Class",
        "college": "Government Polytechnic, Bhojpur",
        "name": "ASHI SINGH",
        "roll": "211522123018",
        "branch": "21",
        "marks": 496,
        "remarks": "First Class",
        "theory": 194
    },
    {
        "text": " \n \nRegistration No : 1522123041\nRoll No         : 211522123041\n \nFollowing are the marks obtained by DHIRAJ KUMAR SINGH\nof Government Polytechnic, Bhojpur\nat Semester II of Diploma in Electronics Engineering\nExamination 2024 (EVEN) held in the month of JUL, 2024\n \n \nResult Published On: 30/07/2024\nSTATE BOARD OF TECHNICAL EDUCATION\nBIHAR\n-----------------------------------------------------------------------------------------------\nSUBJECT  FULL MARKS PASS MARKS MARKS OBTAINED\nNAME OF SUBJECTS CREDITS INTFINTOTAL FINTOTAL INT FIN TOTAL GRADE\n-----------------------------------------------------------------------------------------------\nTHEORY PAPERS\nMATHEMATICS-I 3 3070 100 28 40154055  D\nAPPLIED PHYSICS-I 3 3070 100 28 4012 A12  F\nAPPLIED CHEMISTRY 3 3070 100 28 40152944  E\nCOMM. SKILLS IN ENGLISH 2 3070 100 28 40142842  E\nENGG. GRAPHICS 2 3070 100 28 40234063  C\n-----------------------------------------------------------------------------------------------\nPRACTICAL PAPERS\nAPPLIED PHYSICS LAB-I 2 1535 050 - 20102939  B\nAPPLIED CHEMISTRY LAB 2 1535 050 - 20122840  A\nCOMM. SKILLS IN ENGLISH LAB 2 1535 050 - 20122436  B\n-----------------------------------------------------------------------------------------------\nTERM WORK PAPERS\nENGG. WORKSHOP PRACTICE 2 0718 025 - 10051722  A\nSPORTS AND YOGA 2 0718 025 - 10051520  A\nC/KYP/IT ESSEN/ PYTHON/ OTHERS 1 1535 050 - 20123143  A\n-----------------------------------------------------------------------------------------------\nGRAND TOTAL 24 750 416\n-----------------------------------------------------------------------------------------------\nSGPA \n-----------------------------------------------------------------------------------------------\nREMARKS : Carry in - APPLIED PHYSICS-I",
        "college": "Government Polytechnic, Bhojpur",
        "name": "DHIRAJ KUMAR SINGH",
        "roll": "211522123041",
        "branch": "21",
        "marks": 416,
        "remarks": "Carry in - APPLIED PHYSICS-I",
        "theory": 137
    },
    {
        "text": " \n \nRegistration No : 1522123027\nRoll No         : 211522123027\n \nFollowing are the marks obtained by ASHISH  PATEL\nof Government Polytechnic, Bhojpur\nat Semester II of Diploma in Electronics Engineering\nExamination 2024 (EVEN) held in the month of JUL, 2024\n \n \nResult Published On: 30/07/2024\nSTATE BOARD OF TECHNICAL EDUCATION\nBIHAR\n-----------------------------------------------------------------------------------------------\nSUBJECT  FULL MARKS PASS MARKS MARKS OBTAINED\nNAME OF SUBJECTS CREDITS INTFINTOTAL FINTOTAL INT FIN TOTAL GRADE\n-----------------------------------------------------------------------------------------------\nTHEORY PAPERS\nMATHEMATICS-I 3 3070 100 28 40275481  A\nAPPLIED PHYSICS-I 3 3070 100 28 40193958  D\nAPPLIED CHEMISTRY 3 3070 100 28 40244670  B\nCOMM. SKILLS IN ENGLISH 2 3070 100 28 40254469  C\nENGG. GRAPHICS 2 3070 100 28 40205171  B\n-----------------------------------------------------------------------------------------------\nPRACTICAL PAPERS\nAPPLIED PHYSICS LAB-I 2 1535 050 - 20122941  A\nAPPLIED CHEMISTRY LAB 2 1535 050 - 20133144  A\nCOMM. SKILLS IN ENGLISH LAB 2 1535 050 - 20122638  B\n-----------------------------------------------------------------------------------------------\nTERM WORK PAPERS\nENGG. WORKSHOP PRACTICE 2 0718 025 - 10051621  A\nSPORTS AND YOGA 2 0718 025 - 10071724  A+\nC/KYP/IT ESSEN/ PYTHON/ OTHERS 1 1535 050 - 20133144  A\n-----------------------------------------------------------------------------------------------\nGRAND TOTAL 24 750 561\n-----------------------------------------------------------------------------------------------\nSGPA 8.25\n-----------------------------------------------------------------------------------------------\nREMARKS : First Class",
        "college": "Government Polytechnic, Bhojpur",
        "name": "ASHISH PATEL",
        "roll": "211522123027",
        "branch": "21",
        "marks": 561,
        "remarks": "First Class",
        "theory": 234
    },
    {
        "text": " \n \nRegistration No : 1522123028\nRoll No         : 211522123028\n \nFollowing are the marks obtained by BIPUL  KUMAR\nof Government Polytechnic, Bhojpur\nat Semester II of Diploma in Electronics Engineering\nExamination 2024 (EVEN) held in the month of JUL, 2024\n \n \nResult Published On: 30/07/2024\nSTATE BOARD OF TECHNICAL EDUCATION\nBIHAR\n-----------------------------------------------------------------------------------------------\nSUBJECT  FULL MARKS PASS MARKS MARKS OBTAINED\nNAME OF SUBJECTS CREDITS INTFINTOTAL FINTOTAL INT FIN TOTAL GRADE\n-----------------------------------------------------------------------------------------------\nTHEORY PAPERS\nMATHEMATICS-I 3 3070 100 28 40171229  F\nAPPLIED PHYSICS-I 3 3070 100 28 40102535  F\nAPPLIED CHEMISTRY 3 3070 100 28 40153045  E\nCOMM. SKILLS IN ENGLISH 2 3070 100 28 40214667  C\nENGG. GRAPHICS 2 3070 100 28 40203454  D\n-----------------------------------------------------------------------------------------------\nPRACTICAL PAPERS\nAPPLIED PHYSICS LAB-I 2 1535 050 - 20102939  B\nAPPLIED CHEMISTRY LAB 2 1535 050 - 20122840  A\nCOMM. SKILLS IN ENGLISH LAB 2 1535 050 - 20102535  B\n-----------------------------------------------------------------------------------------------\nTERM WORK PAPERS\nENGG. WORKSHOP PRACTICE 2 0718 025 - 10061622  A\nSPORTS AND YOGA 2 0718 025 - 10061622  A\nC/KYP/IT ESSEN/ PYTHON/ OTHERS 1 1535 050 - 20123042  A\n-----------------------------------------------------------------------------------------------\nGRAND TOTAL 24 750 430\n-----------------------------------------------------------------------------------------------\nSGPA \n-----------------------------------------------------------------------------------------------\nREMARKS : Carry in - MATHEMATICS-I\n APPLIED PHYSICS-I",
        "college": "Government Polytechnic, Bhojpur",
        "name": "BIPUL KUMAR",
        "roll": "211522123028",
        "branch": "21",
        "marks": 430,
        "remarks": "Carry in - MATHEMATICS-I",
        "theory": 147
    },
    {
        "text": " \n \nRegistration No : 1522123030\nRoll No         : 211522123030\n \nFollowing are the marks obtained by SAROJ  KUMAR\nof Government Polytechnic, Bhojpur\nat Semester II of Diploma in Electronics Engineering\nExamination 2024 (EVEN) held in the month of JUL, 2024\n \n \nResult Published On: 30/07/2024\nSTATE BOARD OF TECHNICAL EDUCATION\nBIHAR\n-----------------------------------------------------------------------------------------------\nSUBJECT  FULL MARKS PASS MARKS MARKS OBTAINED\nNAME OF SUBJECTS CREDITS INTFINTOTAL FINTOTAL INT FIN TOTAL GRADE\n-----------------------------------------------------------------------------------------------\nTHEORY PAPERS\nMATHEMATICS-I 3 3070 100 28 40266490  A+\nAPPLIED PHYSICS-I 3 3070 100 28 40163450  D\nAPPLIED CHEMISTRY 3 3070 100 28 40282856  D\nCOMM. SKILLS IN ENGLISH 2 3070 100 28 40263460  C\nENGG. GRAPHICS 2 3070 100 28 40255782  A\n-----------------------------------------------------------------------------------------------\nPRACTICAL PAPERS\nAPPLIED PHYSICS LAB-I 2 1535 050 - 20113041  A\nAPPLIED CHEMISTRY LAB 2 1535 050 - 20133144  A\nCOMM. SKILLS IN ENGLISH LAB 2 1535 050 - 20122537  B\n-----------------------------------------------------------------------------------------------\nTERM WORK PAPERS\nENGG. WORKSHOP PRACTICE 2 0718 025 - 10071522  A\nSPORTS AND YOGA 2 0718 025 - 10071724  A+\nC/KYP/IT ESSEN/ PYTHON/ OTHERS 1 1535 050 - 20123244  A\n-----------------------------------------------------------------------------------------------\nGRAND TOTAL 24 750 550\n-----------------------------------------------------------------------------------------------\nSGPA 8.21\n-----------------------------------------------------------------------------------------------\nREMARKS : First Class",
        "college": "Government Polytechnic, Bhojpur",
        "name": "SAROJ KUMAR",
        "roll": "211522123030",
        "branch": "21",
        "marks": 550,
        "remarks": "First Class",
        "theory": 217
    },
    {
        "text": " \n \nRegistration No : 1522123046\nRoll No         : 211522123046\n \nFollowing are the marks obtained by INDU  KUMARI\nof Government Polytechnic, Bhojpur\nat Semester II of Diploma in Electronics Engineering\nExamination 2024 (EVEN) held in the month of JUL, 2024\n \n \nResult Published On: 30/07/2024\nSTATE BOARD OF TECHNICAL EDUCATION\nBIHAR\n-----------------------------------------------------------------------------------------------\nSUBJECT  FULL MARKS PASS MARKS MARKS OBTAINED\nNAME OF SUBJECTS CREDITS INTFINTOTAL FINTOTAL INT FIN TOTAL GRADE\n-----------------------------------------------------------------------------------------------\nTHEORY PAPERS\nMATHEMATICS-I 3 3070 100 28 40152843  E\nAPPLIED PHYSICS-I 3 3070 100 28 40132235  F\nAPPLIED CHEMISTRY 3 3070 100 28 40151530  F\nCOMM. SKILLS IN ENGLISH 2 3070 100 28 40142135  F\nENGG. GRAPHICS 2 3070 100 28 40073037  F\n-----------------------------------------------------------------------------------------------\nPRACTICAL PAPERS\nAPPLIED PHYSICS LAB-I 2 1535 050 - 20102939  B\nAPPLIED CHEMISTRY LAB 2 1535 050 - 20122941  A\nCOMM. SKILLS IN ENGLISH LAB 2 1535 050 - 20103141  A\n-----------------------------------------------------------------------------------------------\nTERM WORK PAPERS\nENGG. WORKSHOP PRACTICE 2 0718 025 - 10071623  A+\nSPORTS AND YOGA 2 0718 025 - 10061622  A\nC/KYP/IT ESSEN/ PYTHON/ OTHERS 1 1535 050 - 20133144  A\n-----------------------------------------------------------------------------------------------\nGRAND TOTAL 24 750 390\n-----------------------------------------------------------------------------------------------\nSGPA \n-----------------------------------------------------------------------------------------------\nREMARKS : Fail",
        "college": "Government Polytechnic, Bhojpur",
        "name": "INDU KUMARI",
        "roll": "211522123046",
        "branch": "21",
        "marks": 390,
        "remarks": "Fail",
        "theory": 116
    },
    {
        "text": " \n \nRegistration No : 1522123013\nRoll No         : 211522123013\n \nFollowing are the marks obtained by PAPPU  KUMAR\nof Government Polytechnic, Bhojpur\nat Semester II of Diploma in Electronics Engineering\nExamination 2024 (EVEN) held in the month of JUL, 2024\n \n \nResult Published On: 30/07/2024\nSTATE BOARD OF TECHNICAL EDUCATION\nBIHAR\n-----------------------------------------------------------------------------------------------\nSUBJECT  FULL MARKS PASS MARKS MARKS OBTAINED\nNAME OF SUBJECTS CREDITS INTFINTOTAL FINTOTAL INT FIN TOTAL GRADE\n-----------------------------------------------------------------------------------------------\nTHEORY PAPERS\nMATHEMATICS-I 3 3070 100 28 40262955  D\nAPPLIED PHYSICS-I 3 3070 100 28 40283058  D\nAPPLIED CHEMISTRY 3 3070 100 28 40194665  C\nCOMM. SKILLS IN ENGLISH 2 3070 100 28 40203959  D\nENGG. GRAPHICS 2 3070 100 28 40204666  C\n-----------------------------------------------------------------------------------------------\nPRACTICAL PAPERS\nAPPLIED PHYSICS LAB-I 2 1535 050 - 20142842  A\nAPPLIED CHEMISTRY LAB 2 1535 050 - 20123042  A\nCOMM. SKILLS IN ENGLISH LAB 2 1535 050 - 20102535  B\n-----------------------------------------------------------------------------------------------\nTERM WORK PAPERS\nENGG. WORKSHOP PRACTICE 2 0718 025 - 10061622  A\nSPORTS AND YOGA 2 0718 025 - 10051520  A\nC/KYP/IT ESSEN/ PYTHON/ OTHERS 1 1535 050 - 20123143  A\n-----------------------------------------------------------------------------------------------\nGRAND TOTAL 24 750 507\n-----------------------------------------------------------------------------------------------\nSGPA 7.5\n-----------------------------------------------------------------------------------------------\nREMARKS : First Class",
        "college": "Government Polytechnic, Bhojpur",
        "name": "PAPPU KUMAR",
        "roll": "211522123013",
        "branch": "21",
        "marks": 507,
        "remarks": "First Class",
        "theory": 190
    },
    {
        "text": " \n \nRegistration No : 1522123009\nRoll No         : 211522123009\n \nFollowing are the marks obtained by SATISH  KUMAR\nof Government Polytechnic, Bhojpur\nat Semester II of Diploma in Electronics Engineering\nExamination 2024 (EVEN) held in the month of JUL, 2024\n \n \nResult Published On: 30/07/2024\nSTATE BOARD OF TECHNICAL EDUCATION\nBIHAR\n-----------------------------------------------------------------------------------------------\nSUBJECT  FULL MARKS PASS MARKS MARKS OBTAINED\nNAME OF SUBJECTS CREDITS INTFINTOTAL FINTOTAL INT FIN TOTAL GRADE\n-----------------------------------------------------------------------------------------------\nTHEORY PAPERS\nMATHEMATICS-I 3 3070 100 28 40295483  A\nAPPLIED PHYSICS-I 3 3070 100 28 40283866  C\nAPPLIED CHEMISTRY 3 3070 100 28 40183553  D\nCOMM. SKILLS IN ENGLISH 2 3070 100 28 40193453  D\nENGG. GRAPHICS 2 3070 100 28 40234366  C\n-----------------------------------------------------------------------------------------------\nPRACTICAL PAPERS\nAPPLIED PHYSICS LAB-I 2 1535 050 - 20143044  A\nAPPLIED CHEMISTRY LAB 2 1535 050 - 20113142  A\nCOMM. SKILLS IN ENGLISH LAB 2 1535 050 - 20112839  B\n-----------------------------------------------------------------------------------------------\nTERM WORK PAPERS\nENGG. WORKSHOP PRACTICE 2 0718 025 - 10071623  A+\nSPORTS AND YOGA 2 0718 025 - 10061622  A\nC/KYP/IT ESSEN/ PYTHON/ OTHERS 1 1535 050 - 20123244  A\n-----------------------------------------------------------------------------------------------\nGRAND TOTAL 24 750 535\n-----------------------------------------------------------------------------------------------\nSGPA 7.96\n-----------------------------------------------------------------------------------------------\nREMARKS : First Class",
        "college": "Government Polytechnic, Bhojpur",
        "name": "SATISH KUMAR",
        "roll": "211522123009",
        "branch": "21",
        "marks": 535,
        "remarks": "First Class",
        "theory": 204
    },
    {
        "text": " \n \nRegistration No : 1522123015\nRoll No         : 211522123015\n \nFollowing are the marks obtained by RAM SHUBHAG KUMAR\nof Government Polytechnic, Bhojpur\nat Semester II of Diploma in Electronics Engineering\nExamination 2024 (EVEN) held in the month of JUL, 2024\n \n \nResult Published On: 30/07/2024\nSTATE BOARD OF TECHNICAL EDUCATION\nBIHAR\n-----------------------------------------------------------------------------------------------\nSUBJECT  FULL MARKS PASS MARKS MARKS OBTAINED\nNAME OF SUBJECTS CREDITS INTFINTOTAL FINTOTAL INT FIN TOTAL GRADE\n-----------------------------------------------------------------------------------------------\nTHEORY PAPERS\nMATHEMATICS-I 3 3070 100 28 40172946  E\nAPPLIED PHYSICS-I 3 3070 100 28 40192847  E\nAPPLIED CHEMISTRY 3 3070 100 28 40232851  D\nCOMM. SKILLS IN ENGLISH 2 3070 100 28 40242852  D\nENGG. GRAPHICS 2 3070 100 28 40232851  D\n-----------------------------------------------------------------------------------------------\nPRACTICAL PAPERS\nAPPLIED PHYSICS LAB-I 2 1535 050 - 20112940  A\nAPPLIED CHEMISTRY LAB 2 1535 050 - 20133043  A\nCOMM. SKILLS IN ENGLISH LAB 2 1535 050 - 20122739  B\n-----------------------------------------------------------------------------------------------\nTERM WORK PAPERS\nENGG. WORKSHOP PRACTICE 2 0718 025 - 10051621  A\nSPORTS AND YOGA 2 0718 025 - 10061622  A\nC/KYP/IT ESSEN/ PYTHON/ OTHERS 1 1535 050 - 20123143  A\n-----------------------------------------------------------------------------------------------\nGRAND TOTAL 24 750 455\n-----------------------------------------------------------------------------------------------\nSGPA 7.04\n-----------------------------------------------------------------------------------------------\nREMARKS : First Class",
        "college": "Government Polytechnic, Bhojpur",
        "name": "RAM SHUBHAG KUMAR",
        "roll": "211522123015",
        "branch": "21",
        "marks": 455,
        "remarks": "First Class",
        "theory": 141
    },
    {
        "text": " \n \nRegistration No : 1792523031\nRoll No         : 211792523031\n \nFollowing are the marks obtained by GHANSHYAM KUMAR\nof Shri Ram Polytechnic, Madhubani\nat Semester II of Diploma in Mechanical Engineering\nExamination 2024 (EVEN) held in the month of JUL, 2024\n \n \nResult Published On: 30/07/2024\nSTATE BOARD OF TECHNICAL EDUCATION\nBIHAR\n-----------------------------------------------------------------------------------------------\nSUBJECT  FULL MARKS PASS MARKS MARKS OBTAINED\nNAME OF SUBJECTS CREDITS INTFINTOTAL FINTOTAL INT FIN TOTAL GRADE\n-----------------------------------------------------------------------------------------------\nTHEORY PAPERS\nMATHEMATICS-II 4 3070 100 28 40281745  E\nAPPLIED PHYSICS-II 3 3070 100 28 40274067  C\nINTRODUCTION TO IT SYSTEMS 2 3070 100 28 40263662  C\nFUNDA OF ELECT AND EC ENGG 3 3070 100 28 40253257  D\nENGG. MECHANICS 3 3070 100 28 40262854  D\n-----------------------------------------------------------------------------------------------\nPRACTICAL PAPERS\nAPPLIED PHYSICS LAB-II 1 1535 050 - 20143347  A+\nINTRODUCTION TO IT SYSTEM LAB 2 1535 050 - 20143246  A+\nFUNDA OF ELECT AND EC ENGG LAB 1 1535 050 - 20143246  A+\nENGG. MECHANICS LAB 2 1535 050 - 20133245  A+\n-----------------------------------------------------------------------------------------------\nTERM WORK PAPERS\nC.U MOOCS/ SWAYAM/ ETC/ OTHERS 2 0614 020 - 08051217  A\nKYP/IT ESSEN/ PYTHON/ OTHERS 1 0614 020 - 08051217  A\nENVIRONMENTAL SCIENCE 0 10 -010 - 0409 -09  A+\n-----------------------------------------------------------------------------------------------\nGRAND TOTAL 24 750 512\n-----------------------------------------------------------------------------------------------\nSGPA \n-----------------------------------------------------------------------------------------------\nREMARKS : Carry in - MATHEMATICS-II",
        "college": "Shri Ram Polytechnic, Madhubani",
        "name": "GHANSHYAM KUMAR",
        "roll": "211792523031",
        "branch": "25",
        "marks": 512,
        "remarks": "Carry in - MATHEMATICS-II",
        "theory": 153
    },
    {
        "text": " \n \nRegistration No : 1792523020\nRoll No         : 211792523020\n \nFollowing are the marks obtained by ADITYA KUMAR\nof Shri Ram Polytechnic, Madhubani\nat Semester II of Diploma in Mechanical Engineering\nExamination 2024 (EVEN) held in the month of JUL, 2024\n \n \nResult Published On: 30/07/2024\nSTATE BOARD OF TECHNICAL EDUCATION\nBIHAR\n-----------------------------------------------------------------------------------------------\nSUBJECT  FULL MARKS PASS MARKS MARKS OBTAINED\nNAME OF SUBJECTS CREDITS INTFINTOTAL FINTOTAL INT FIN TOTAL GRADE\n-----------------------------------------------------------------------------------------------\nTHEORY PAPERS\nMATHEMATICS-II 4 3070 100 28 40280836  F\nAPPLIED PHYSICS-II 3 3070 100 28 40263157  D\nINTRODUCTION TO IT SYSTEMS 2 3070 100 28 40262854  D\nFUNDA OF ELECT AND EC ENGG 3 3070 100 28 40253560  C\nENGG. MECHANICS 3 3070 100 28 40283967  C\n-----------------------------------------------------------------------------------------------\nPRACTICAL PAPERS\nAPPLIED PHYSICS LAB-II 1 1535 050 - 20133346  A+\nINTRODUCTION TO IT SYSTEM LAB 2 1535 050 - 20133144  A\nFUNDA OF ELECT AND EC ENGG LAB 1 1535 050 - 20133144  A\nENGG. MECHANICS LAB 2 1535 050 - 20143145  A+\n-----------------------------------------------------------------------------------------------\nTERM WORK PAPERS\nC.U MOOCS/ SWAYAM/ ETC/ OTHERS 2 0614 020 - 08051318  A+\nKYP/IT ESSEN/ PYTHON/ OTHERS 1 0614 020 - 08051318  A+\nENVIRONMENTAL SCIENCE 0 10 -010 - 0409 -09  A+\n-----------------------------------------------------------------------------------------------\nGRAND TOTAL 24 750 498\n-----------------------------------------------------------------------------------------------\nSGPA \n-----------------------------------------------------------------------------------------------\nREMARKS : Carry in - MATHEMATICS-II",
        "college": "Shri Ram Polytechnic, Madhubani",
        "name": "ADITYA KUMAR",
        "roll": "211792523020",
        "branch": "25",
        "marks": 498,
        "remarks": "Carry in - MATHEMATICS-II",
        "theory": 141
    },
    {
        "text": " \n \nRegistration No : 1792523024\nRoll No         : 211792523024\n \nFollowing are the marks obtained by AKASH KUMAR SINGH\nof Shri Ram Polytechnic, Madhubani\nat Semester II of Diploma in Mechanical Engineering\nExamination 2024 (EVEN) held in the month of JUL, 2024\n \n \nResult Published On: 30/07/2024\nSTATE BOARD OF TECHNICAL EDUCATION\nBIHAR\n-----------------------------------------------------------------------------------------------\nSUBJECT  FULL MARKS PASS MARKS MARKS OBTAINED\nNAME OF SUBJECTS CREDITS INTFINTOTAL FINTOTAL INT FIN TOTAL GRADE\n-----------------------------------------------------------------------------------------------\nTHEORY PAPERS\nMATHEMATICS-II 4 3070 100 28 40260834  F\nAPPLIED PHYSICS-II 3 3070 100 28 40231033  F\nINTRODUCTION TO IT SYSTEMS 2 3070 100 28 40251944  E\nFUNDA OF ELECT AND EC ENGG 3 3070 100 28 40250833  F\nENGG. MECHANICS 3 3070 100 28 40240832  F\n-----------------------------------------------------------------------------------------------\nPRACTICAL PAPERS\nAPPLIED PHYSICS LAB-II 1 1535 050 - 20123143  A\nINTRODUCTION TO IT SYSTEM LAB 2 1535 050 - 20143246  A+\nFUNDA OF ELECT AND EC ENGG LAB 1 1535 050 - 20133245  A+\nENGG. MECHANICS LAB 2 1535 050 - 20143246  A+\n-----------------------------------------------------------------------------------------------\nTERM WORK PAPERS\nC.U MOOCS/ SWAYAM/ ETC/ OTHERS 2 0614 020 - 08041418  A+\nKYP/IT ESSEN/ PYTHON/ OTHERS 1 0614 020 - 08041418  A+\nENVIRONMENTAL SCIENCE 0 10 -010 - 0408 -08  A\n-----------------------------------------------------------------------------------------------\nGRAND TOTAL 24 750 400\n-----------------------------------------------------------------------------------------------\nSGPA \n-----------------------------------------------------------------------------------------------\nREMARKS : Fail",
        "college": "Shri Ram Polytechnic, Madhubani",
        "name": "AKASH KUMAR SINGH",
        "roll": "211792523024",
        "branch": "25",
        "marks": 400,
        "remarks": "Fail",
        "theory": 53
    },
    {
        "text": " \n \nRegistration No : 1792023056\nRoll No         : 211792023056\n \nFollowing are the marks obtained by LAKSHMI KUMARI\nof Shri Ram Polytechnic, Madhubani\nat Semester II of Diploma in Electrical Engineering\nExamination 2024 (EVEN) held in the month of JUL, 2024\n \n \nResult Published On: 30/07/2024\nSTATE BOARD OF TECHNICAL EDUCATION\nBIHAR\n-----------------------------------------------------------------------------------------------\nSUBJECT  FULL MARKS PASS MARKS MARKS OBTAINED\nNAME OF SUBJECTS CREDITS INTFINTOTAL FINTOTAL INT FIN TOTAL GRADE\n-----------------------------------------------------------------------------------------------\nTHEORY PAPERS\nMATHEMATICS-II 4 3070 100 28 40241236  F\nAPPLIED PHYSICS-II 3 3070 100 28 40242852  D\nINTRODUCTION TO IT SYSTEMS 2 3070 100 28 40252954  D\nFUNDA OF ELECT AND EC ENGG 3 3070 100 28 40263460  C\nENGG. MECHANICS 3 3070 100 28 40283260  C\n-----------------------------------------------------------------------------------------------\nPRACTICAL PAPERS\nAPPLIED PHYSICS LAB-II 1 1535 050 - 20143347  A+\nINTRODUCTION TO IT SYSTEM LAB 2 1535 050 - 20133346  A+\nFUNDA OF ELECT AND EC ENGG LAB 1 1535 050 - 20133245  A+\nENGG. MECHANICS LAB 2 1535 050 - 20143347  A+\n-----------------------------------------------------------------------------------------------\nTERM WORK PAPERS\nC.U MOOCS/ SWAYAM/ ETC/ OTHERS 2 0614 020 - 08051217  A\nKYP/IT ESSEN/ PYTHON/ OTHERS 1 0614 020 - 08051318  A+\nENVIRONMENTAL SCIENCE 0 10 -010 - 0407 -07  B\n-----------------------------------------------------------------------------------------------\nGRAND TOTAL 24 750 489\n-----------------------------------------------------------------------------------------------\nSGPA \n-----------------------------------------------------------------------------------------------\nREMARKS : Carry in - MATHEMATICS-II",
        "college": "Shri Ram Polytechnic, Madhubani",
        "name": "LAKSHMI KUMARI",
        "roll": "211792023056",
        "branch": "20",
        "marks": 489,
        "remarks": "Carry in - MATHEMATICS-II",
        "theory": 135
    },
    {
        "text": " \n \nRegistration No : 1792023035\nRoll No         : 211792023035\n \nFollowing are the marks obtained by SANDHYA KUMARI\nof Shri Ram Polytechnic, Madhubani\nat Semester II of Diploma in Electrical Engineering\nExamination 2024 (EVEN) held in the month of JUL, 2024\n \n \nResult Published On: 30/07/2024\nSTATE BOARD OF TECHNICAL EDUCATION\nBIHAR\n-----------------------------------------------------------------------------------------------\nSUBJECT  FULL MARKS PASS MARKS MARKS OBTAINED\nNAME OF SUBJECTS CREDITS INTFINTOTAL FINTOTAL INT FIN TOTAL GRADE\n-----------------------------------------------------------------------------------------------\nTHEORY PAPERS\nMATHEMATICS-II 4 3070 100 28 40240832  F\nAPPLIED PHYSICS-II 3 3070 100 28 40232851  D\nINTRODUCTION TO IT SYSTEMS 2 3070 100 28 40261541  E\nFUNDA OF ELECT AND EC ENGG 3 3070 100 28 40260430  F\nENGG. MECHANICS 3 3070 100 28 40281038  F\n-----------------------------------------------------------------------------------------------\nPRACTICAL PAPERS\nAPPLIED PHYSICS LAB-II 1 1535 050 - 20133245  A+\nINTRODUCTION TO IT SYSTEM LAB 2 1535 050 - 20143246  A+\nFUNDA OF ELECT AND EC ENGG LAB 1 1535 050 - 20133245  A+\nENGG. MECHANICS LAB 2 1535 050 - 20143448  A+\n-----------------------------------------------------------------------------------------------\nTERM WORK PAPERS\nC.U MOOCS/ SWAYAM/ ETC/ OTHERS 2 0614 020 - 08051318  A+\nKYP/IT ESSEN/ PYTHON/ OTHERS 1 0614 020 - 08051318  A+\nENVIRONMENTAL SCIENCE 0 10 -010 - 0407 -07  B\n-----------------------------------------------------------------------------------------------\nGRAND TOTAL 24 750 419\n-----------------------------------------------------------------------------------------------\nSGPA \n-----------------------------------------------------------------------------------------------\nREMARKS : Fail",
        "college": "Shri Ram Polytechnic, Madhubani",
        "name": "SANDHYA KUMARI",
        "roll": "211792023035",
        "branch": "20",
        "marks": 419,
        "remarks": "Fail",
        "theory": 65
    },
    {
        "text": " \n \nRegistration No : 1121823057\nRoll No         : 211121823057\n \nFollowing are the marks obtained by BITTU  KUMAR\nof Government Polytechnic, Bhagalpur\nat Semester II of Diploma in Computer Science & Engineering\nExamination 2024 (EVEN) held in the month of JUL, 2024\n \n \nResult Published On: 30/07/2024\nSTATE BOARD OF TECHNICAL EDUCATION\nBIHAR\n-----------------------------------------------------------------------------------------------\nSUBJECT  FULL MARKS PASS MARKS MARKS OBTAINED\nNAME OF SUBJECTS CREDITS INTFINTOTAL FINTOTAL INT FIN TOTAL GRADE\n-----------------------------------------------------------------------------------------------\nTHEORY PAPERS\nMATHEMATICS-II 4 3070 100 28 40284674  B\nAPPLIED PHYSICS-II 3 3070 100 28 40293665  C\nINTRODUCTION TO IT SYSTEMS 2 3070 100 28 40244771  B\nFUNDA OF ELECT AND EC ENGG 3 3070 100 28 40243559  D\nENGG. MECHANICS 3 3070 100 28 40255075  B\n-----------------------------------------------------------------------------------------------\nPRACTICAL PAPERS\nAPPLIED PHYSICS LAB-II 1 1535 050 - 20143347  A+\nINTRODUCTION TO IT SYSTEM LAB 2 1535 050 - 20123446  A+\nFUNDA OF ELECT AND EC ENGG LAB 1 1535 050 - 20133245  A+\nENGG. MECHANICS LAB 2 1535 050 - 20143246  A+\n-----------------------------------------------------------------------------------------------\nTERM WORK PAPERS\nC.U MOOCS/ SWAYAM/ ETC/ OTHERS 2 0614 020 - 08061218  A+\nKYP/IT ESSEN/ PYTHON/ OTHERS 1 0614 020 - 08041216  A\nENVIRONMENTAL SCIENCE 0 10 -010 - 0408 -08  A\n-----------------------------------------------------------------------------------------------\nGRAND TOTAL 24 750 570\n-----------------------------------------------------------------------------------------------\nSGPA 8.33\n-----------------------------------------------------------------------------------------------\nREMARKS : First Class with Distinction",
        "college": "Government Polytechnic, Bhagalpur",
        "name": "BITTU KUMAR",
        "roll": "211121823057",
        "branch": "18",
        "marks": 570,
        "remarks": "First Class with Distinction",
        "theory": 214
    },
    {
        "text": " \n \nRegistration No : 1781823028\nRoll No         : 211781823028\n \nFollowing are the marks obtained by PUSHPA KUMARI\nof Sityog Inst. of Tech., Aurangabad(2nd Shift)\nat Semester II of Diploma in Computer Science & Engineering\nExamination 2024 (EVEN) held in the month of JUL, 2024\n \n \nResult Published On: 30/07/2024\nSTATE BOARD OF TECHNICAL EDUCATION\nBIHAR\n-----------------------------------------------------------------------------------------------\nSUBJECT  FULL MARKS PASS MARKS MARKS OBTAINED\nNAME OF SUBJECTS CREDITS INTFINTOTAL FINTOTAL INT FIN TOTAL GRADE\n-----------------------------------------------------------------------------------------------\nTHEORY PAPERS\nMATHEMATICS-II 4 3070 100 28 40243155  D\nAPPLIED PHYSICS-II 3 3070 100 28 40263359  D\nINTRODUCTION TO IT SYSTEMS 2 3070 100 28 40263359  D\nFUNDA OF ELECT AND EC ENGG 3 3070 100 28 40233255  D\nENGG. MECHANICS 3 3070 100 28 40253863  C\n-----------------------------------------------------------------------------------------------\nPRACTICAL PAPERS\nAPPLIED PHYSICS LAB-II 1 1535 050 - 20133447  A+\nINTRODUCTION TO IT SYSTEM LAB 2 1535 050 - 20123244  A\nFUNDA OF ELECT AND EC ENGG LAB 1 1535 050 - 20113041  A\nENGG. MECHANICS LAB 2 1535 050 - 20143246  A+\n-----------------------------------------------------------------------------------------------\nTERM WORK PAPERS\nC.U MOOCS/ SWAYAM/ ETC/ OTHERS 2 0614 020 - 08051318  A+\nKYP/IT ESSEN/ PYTHON/ OTHERS 1 0614 020 - 08041317  A\nENVIRONMENTAL SCIENCE 0 10 -010 - 0409 -09  A+\n-----------------------------------------------------------------------------------------------\nGRAND TOTAL 24 750 513\n-----------------------------------------------------------------------------------------------\nSGPA 7.46\n-----------------------------------------------------------------------------------------------\nREMARKS : First Class",
        "college": "Sityog Inst.",
        "name": "PUSHPA KUMARI",
        "roll": "211781823028",
        "branch": "18",
        "marks": 513,
        "remarks": "First Class",
        "theory": 167
    },
    {
        "text": " \n \nRegistration No : 1782523011\nRoll No         : 211782523011\n \nFollowing are the marks obtained by DIVYA PRAKASH PANDEY\nof Sityog Inst. of Tech., Aurangabad(2nd Shift)\nat Semester II of Diploma in Mechanical Engineering\nExamination 2024 (EVEN) held in the month of JUL, 2024\n \n \nResult Published On: 30/07/2024\nSTATE BOARD OF TECHNICAL EDUCATION\nBIHAR\n-----------------------------------------------------------------------------------------------\nSUBJECT  FULL MARKS PASS MARKS MARKS OBTAINED\nNAME OF SUBJECTS CREDITS INTFINTOTAL FINTOTAL INT FIN TOTAL GRADE\n-----------------------------------------------------------------------------------------------\nTHEORY PAPERS\nMATHEMATICS-II 4 3070 100 28 40223153  D\nAPPLIED PHYSICS-II 3 3070 100 28 40243761  C\nINTRODUCTION TO IT SYSTEMS 2 3070 100 28 40263864  C\nFUNDA OF ELECT AND EC ENGG 3 3070 100 28 40273461  C\nENGG. MECHANICS 3 3070 100 28 40213556  D\n-----------------------------------------------------------------------------------------------\nPRACTICAL PAPERS\nAPPLIED PHYSICS LAB-II 1 1535 050 - 20122840  A\nINTRODUCTION TO IT SYSTEM LAB 2 1535 050 - 20142438  B\nFUNDA OF ELECT AND EC ENGG LAB 1 1535 050 - 20123042  A\nENGG. MECHANICS LAB 2 1535 050 - 20092837  B\n-----------------------------------------------------------------------------------------------\nTERM WORK PAPERS\nC.U MOOCS/ SWAYAM/ ETC/ OTHERS 2 0614 020 - 08041216  A\nKYP/IT ESSEN/ PYTHON/ OTHERS 1 0614 020 - 08051015  B\nENVIRONMENTAL SCIENCE 0 10 -010 - 0407 -07  B\n-----------------------------------------------------------------------------------------------\nGRAND TOTAL 24 750 490\n-----------------------------------------------------------------------------------------------\nSGPA 7.25\n-----------------------------------------------------------------------------------------------\nREMARKS : First Class",
        "college": "Sityog Inst.",
        "name": "DIVYA PRAKASH PANDEY",
        "roll": "211782523011",
        "branch": "25",
        "marks": 490,
        "remarks": "First Class",
        "theory": 175
    },
    {
        "text": " \n \nRegistration No : 1782523002\nRoll No         : 211782523002\n \nFollowing are the marks obtained by SURAJ  KUMAR\nof Sityog Inst. of Tech., Aurangabad(2nd Shift)\nat Semester II of Diploma in Mechanical Engineering\nExamination 2024 (EVEN) held in the month of JUL, 2024\n \n \nResult Published On: 30/07/2024\nSTATE BOARD OF TECHNICAL EDUCATION\nBIHAR\n-----------------------------------------------------------------------------------------------\nSUBJECT  FULL MARKS PASS MARKS MARKS OBTAINED\nNAME OF SUBJECTS CREDITS INTFINTOTAL FINTOTAL INT FIN TOTAL GRADE\n-----------------------------------------------------------------------------------------------\nTHEORY PAPERS\nMATHEMATICS-II 4 3070 100 28 40286088  A\nAPPLIED PHYSICS-II 3 3070 100 28 40274572  B\nINTRODUCTION TO IT SYSTEMS 2 3070 100 28 40233861  C\nFUNDA OF ELECT AND EC ENGG 3 3070 100 28 40274269  C\nENGG. MECHANICS 3 3070 100 28 40275582  A\n-----------------------------------------------------------------------------------------------\nPRACTICAL PAPERS\nAPPLIED PHYSICS LAB-II 1 1535 050 - 20143448  A+\nINTRODUCTION TO IT SYSTEM LAB 2 1535 050 - 20123345  A+\nFUNDA OF ELECT AND EC ENGG LAB 1 1535 050 - 20133245  A+\nENGG. MECHANICS LAB 2 1535 050 - 20143448  A+\n-----------------------------------------------------------------------------------------------\nTERM WORK PAPERS\nC.U MOOCS/ SWAYAM/ ETC/ OTHERS 2 0614 020 - 08051318  A+\nKYP/IT ESSEN/ PYTHON/ OTHERS 1 0614 020 - 08041317  A\nENVIRONMENTAL SCIENCE 0 10 -010 - 0409 -09  A+\n-----------------------------------------------------------------------------------------------\nGRAND TOTAL 24 750 602\n-----------------------------------------------------------------------------------------------\nSGPA 8.79\n-----------------------------------------------------------------------------------------------\nREMARKS : First Class with Distinction",
        "college": "Sityog Inst.",
        "name": "SURAJ KUMAR",
        "roll": "211782523002",
        "branch": "25",
        "marks": 602,
        "remarks": "First Class with Distinction",
        "theory": 240
    },
    {
        "text": " \n \nRegistration No : 1782523014\nRoll No         : 211782523014\n \nFollowing are the marks obtained by RITIKA  KUMARI\nof Sityog Inst. of Tech., Aurangabad(2nd Shift)\nat Semester II of Diploma in Mechanical Engineering\nExamination 2024 (EVEN) held in the month of JUL, 2024\n \n \nResult Published On: 30/07/2024\nSTATE BOARD OF TECHNICAL EDUCATION\nBIHAR\n-----------------------------------------------------------------------------------------------\nSUBJECT  FULL MARKS PASS MARKS MARKS OBTAINED\nNAME OF SUBJECTS CREDITS INTFINTOTAL FINTOTAL INT FIN TOTAL GRADE\n-----------------------------------------------------------------------------------------------\nTHEORY PAPERS\nMATHEMATICS-II 4 3070 100 28 40272855  D\nAPPLIED PHYSICS-II 3 3070 100 28 40275380  A\nINTRODUCTION TO IT SYSTEMS 2 3070 100 28 40243559  D\nFUNDA OF ELECT AND EC ENGG 3 3070 100 28 40273562  C\nENGG. MECHANICS 3 3070 100 28 40274673  B\n-----------------------------------------------------------------------------------------------\nPRACTICAL PAPERS\nAPPLIED PHYSICS LAB-II 1 1535 050 - 20143448  A+\nINTRODUCTION TO IT SYSTEM LAB 2 1535 050 - 20142741  A\nFUNDA OF ELECT AND EC ENGG LAB 1 1535 050 - 20133346  A+\nENGG. MECHANICS LAB 2 1535 050 - 20143448  A+\n-----------------------------------------------------------------------------------------------\nTERM WORK PAPERS\nC.U MOOCS/ SWAYAM/ ETC/ OTHERS 2 0614 020 - 08051015  B\nKYP/IT ESSEN/ PYTHON/ OTHERS 1 0614 020 - 08051217  A\nENVIRONMENTAL SCIENCE 0 10 -010 - 0409 -09  A+\n-----------------------------------------------------------------------------------------------\nGRAND TOTAL 24 750 553\n-----------------------------------------------------------------------------------------------\nSGPA 7.96\n-----------------------------------------------------------------------------------------------\nREMARKS : First Class",
        "college": "Sityog Inst.",
        "name": "RITIKA KUMARI",
        "roll": "211782523014",
        "branch": "25",
        "marks": 553,
        "remarks": "First Class",
        "theory": 197
    },
    {
        "text": " \n \nRegistration No : 1782523003\nRoll No         : 211782523003\n \nFollowing are the marks obtained by SHIVAM  KUMAR\nof Sityog Inst. of Tech., Aurangabad(2nd Shift)\nat Semester II of Diploma in Mechanical Engineering\nExamination 2024 (EVEN) held in the month of JUL, 2024\n \n \nResult Published On: 30/07/2024\nSTATE BOARD OF TECHNICAL EDUCATION\nBIHAR\n-----------------------------------------------------------------------------------------------\nSUBJECT  FULL MARKS PASS MARKS MARKS OBTAINED\nNAME OF SUBJECTS CREDITS INTFINTOTAL FINTOTAL INT FIN TOTAL GRADE\n-----------------------------------------------------------------------------------------------\nTHEORY PAPERS\nMATHEMATICS-II 4 3070 100 28 40242852  D\nAPPLIED PHYSICS-II 3 3070 100 28 40262854  D\nINTRODUCTION TO IT SYSTEMS 2 3070 100 28 40253055  D\nFUNDA OF ELECT AND EC ENGG 3 3070 100 28 40262854  D\nENGG. MECHANICS 3 3070 100 28 40241842  E\n-----------------------------------------------------------------------------------------------\nPRACTICAL PAPERS\nAPPLIED PHYSICS LAB-II 1 1535 050 - 20133043  A\nINTRODUCTION TO IT SYSTEM LAB 2 1535 050 - 20132740  A\nFUNDA OF ELECT AND EC ENGG LAB 1 1535 050 - 20123143  A\nENGG. MECHANICS LAB 2 1535 050 - 20123042  A\n-----------------------------------------------------------------------------------------------\nTERM WORK PAPERS\nC.U MOOCS/ SWAYAM/ ETC/ OTHERS 2 0614 020 - 08041014  B\nKYP/IT ESSEN/ PYTHON/ OTHERS 1 0614 020 - 08051015  B\nENVIRONMENTAL SCIENCE 0 10 -010 - 0408 -08  A\n-----------------------------------------------------------------------------------------------\nGRAND TOTAL 24 750 462\n-----------------------------------------------------------------------------------------------\nSGPA \n-----------------------------------------------------------------------------------------------\nREMARKS : Carry in - ENGG. MECHANICS",
        "college": "Sityog Inst.",
        "name": "SHIVAM KUMAR",
        "roll": "211782523003",
        "branch": "25",
        "marks": 462,
        "remarks": "Carry in - ENGG. MECHANICS",
        "theory": 132
    },
    {
        "text": " \n \nRegistration No : 1782023008\nRoll No         : 211782023008\n \nFollowing are the marks obtained by HANJALA  ANSARI\nof Sityog Inst. of Tech., Aurangabad(2nd Shift)\nat Semester II of Diploma in Electrical Engineering\nExamination 2024 (EVEN) held in the month of JUL, 2024\n \n \nResult Published On: 30/07/2024\nSTATE BOARD OF TECHNICAL EDUCATION\nBIHAR\n-----------------------------------------------------------------------------------------------\nSUBJECT  FULL MARKS PASS MARKS MARKS OBTAINED\nNAME OF SUBJECTS CREDITS INTFINTOTAL FINTOTAL INT FIN TOTAL GRADE\n-----------------------------------------------------------------------------------------------\nTHEORY PAPERS\nMATHEMATICS-II 4 3070 100 28 40241842  E\nAPPLIED PHYSICS-II 3 3070 100 28 40252853  D\nINTRODUCTION TO IT SYSTEMS 2 3070 100 28 40221840  E\nFUNDA OF ELECT AND EC ENGG 3 3070 100 28 40241539  F\nENGG. MECHANICS 3 3070 100 28 40193150  D\n-----------------------------------------------------------------------------------------------\nPRACTICAL PAPERS\nAPPLIED PHYSICS LAB-II 1 1535 050 - 20133043  A\nINTRODUCTION TO IT SYSTEM LAB 2 1535 050 - 20123042  A\nFUNDA OF ELECT AND EC ENGG LAB 1 1535 050 - 20132942  A\nENGG. MECHANICS LAB 2 1535 050 - 20102838  B\n-----------------------------------------------------------------------------------------------\nTERM WORK PAPERS\nC.U MOOCS/ SWAYAM/ ETC/ OTHERS 2 0614 020 - 08041014  B\nKYP/IT ESSEN/ PYTHON/ OTHERS 1 0614 020 - 08041115  B\nENVIRONMENTAL SCIENCE 0 10 -010 - 0408 -08  A\n-----------------------------------------------------------------------------------------------\nGRAND TOTAL 24 750 426\n-----------------------------------------------------------------------------------------------\nSGPA \n-----------------------------------------------------------------------------------------------\nREMARKS : Fail",
        "college": "Sityog Inst.",
        "name": "HANJALA ANSARI",
        "roll": "211782023008",
        "branch": "20",
        "marks": 426,
        "remarks": "Fail",
        "theory": 110
    },
    {
        "text": " \n \nRegistration No : 1782023013\nRoll No         : 211782023013\n \nFollowing are the marks obtained by PRAMOD  KUMAR\nof Sityog Inst. of Tech., Aurangabad(2nd Shift)\nat Semester II of Diploma in Electrical Engineering\nExamination 2024 (EVEN) held in the month of JUL, 2024\n \n \nResult Published On: 30/07/2024\nSTATE BOARD OF TECHNICAL EDUCATION\nBIHAR\n-----------------------------------------------------------------------------------------------\nSUBJECT  FULL MARKS PASS MARKS MARKS OBTAINED\nNAME OF SUBJECTS CREDITS INTFINTOTAL FINTOTAL INT FIN TOTAL GRADE\n-----------------------------------------------------------------------------------------------\nTHEORY PAPERS\nMATHEMATICS-II 4 3070 100 28 40261844  E\nAPPLIED PHYSICS-II 3 3070 100 28 40152843  E\nINTRODUCTION TO IT SYSTEMS 2 3070 100 28 40222850  D\nFUNDA OF ELECT AND EC ENGG 3 3070 100 28 40251237  F\nENGG. MECHANICS 3 3070 100 28 40164561  C\n-----------------------------------------------------------------------------------------------\nPRACTICAL PAPERS\nAPPLIED PHYSICS LAB-II 1 1535 050 - 20123042  A\nINTRODUCTION TO IT SYSTEM LAB 2 1535 050 - 20122941  A\nFUNDA OF ELECT AND EC ENGG LAB 1 1535 050 - 20132942  A\nENGG. MECHANICS LAB 2 1535 050 - 20103040  A\n-----------------------------------------------------------------------------------------------\nTERM WORK PAPERS\nC.U MOOCS/ SWAYAM/ ETC/ OTHERS 2 0614 020 - 08051015  B\nKYP/IT ESSEN/ PYTHON/ OTHERS 1 0614 020 - 08041115  B\nENVIRONMENTAL SCIENCE 0 10 -010 - 0408 -08  A\n-----------------------------------------------------------------------------------------------\nGRAND TOTAL 24 750 438\n-----------------------------------------------------------------------------------------------\nSGPA \n-----------------------------------------------------------------------------------------------\nREMARKS : Carry in - MATHEMATICS-II\n FUNDA OF ELECT AND EC ENGG",
        "college": "Sityog Inst.",
        "name": "PRAMOD KUMAR",
        "roll": "211782023013",
        "branch": "20",
        "marks": 438,
        "remarks": "Carry in - MATHEMATICS-II",
        "theory": 131
    },
    {
        "text": " \n \nRegistration No : 1782023028\nRoll No         : 211782023028\n \nFollowing are the marks obtained by SUNNY KUMAR\nof Sityog Inst. of Tech., Aurangabad(2nd Shift)\nat Semester II of Diploma in Electrical Engineering\nExamination 2024 (EVEN) held in the month of JUL, 2024\n \n \nResult Published On: 30/07/2024\nSTATE BOARD OF TECHNICAL EDUCATION\nBIHAR\n-----------------------------------------------------------------------------------------------\nSUBJECT  FULL MARKS PASS MARKS MARKS OBTAINED\nNAME OF SUBJECTS CREDITS INTFINTOTAL FINTOTAL INT FIN TOTAL GRADE\n-----------------------------------------------------------------------------------------------\nTHEORY PAPERS\nMATHEMATICS-II 4 3070 100 28 40241842  E\nAPPLIED PHYSICS-II 3 3070 100 28 40153954  D\nINTRODUCTION TO IT SYSTEMS 2 3070 100 28 40223557  D\nFUNDA OF ELECT AND EC ENGG 3 3070 100 28 40243155  D\nENGG. MECHANICS 3 3070 100 28 40243357  D\n-----------------------------------------------------------------------------------------------\nPRACTICAL PAPERS\nAPPLIED PHYSICS LAB-II 1 1535 050 - 20103242  A\nINTRODUCTION TO IT SYSTEM LAB 2 1535 050 - 20103444  A\nFUNDA OF ELECT AND EC ENGG LAB 1 1535 050 - 20133245  A+\nENGG. MECHANICS LAB 2 1535 050 - 20123042  A\n-----------------------------------------------------------------------------------------------\nTERM WORK PAPERS\nC.U MOOCS/ SWAYAM/ ETC/ OTHERS 2 0614 020 - 08041115  B\nKYP/IT ESSEN/ PYTHON/ OTHERS 1 0614 020 - 08051419  A+\nENVIRONMENTAL SCIENCE 0 10 -010 - 0408 -08  A\n-----------------------------------------------------------------------------------------------\nGRAND TOTAL 24 750 480\n-----------------------------------------------------------------------------------------------\nSGPA \n-----------------------------------------------------------------------------------------------\nREMARKS : Carry in - MATHEMATICS-II",
        "college": "Sityog Inst.",
        "name": "SUNNY KUMAR",
        "roll": "211782023028",
        "branch": "20",
        "marks": 480,
        "remarks": "Carry in - MATHEMATICS-II",
        "theory": 156
    },
    {
        "text": " \n \nRegistration No : 1162023041\nRoll No         : 211162023041\n \nFollowing are the marks obtained by SHALU KUMARI\nof Government Polytechnic, Gopalganj\nat Semester II of Diploma in Electrical Engineering\nExamination 2024 (EVEN) held in the month of JUL, 2024\n \n \nResult Published On: 30/07/2024\nSTATE BOARD OF TECHNICAL EDUCATION\nBIHAR\n-----------------------------------------------------------------------------------------------\nSUBJECT  FULL MARKS PASS MARKS MARKS OBTAINED\nNAME OF SUBJECTS CREDITS INTFINTOTAL FINTOTAL INT FIN TOTAL GRADE\n-----------------------------------------------------------------------------------------------\nTHEORY PAPERS\nMATHEMATICS-II 4 3070 100 28 40291847  E\nAPPLIED PHYSICS-II 3 3070 100 28 40293261  C\nINTRODUCTION TO IT SYSTEMS 2 3070 100 28 40264571  B\nFUNDA OF ELECT AND EC ENGG 3 3070 100 28 40252853  D\nENGG. MECHANICS 3 3070 100 28 40244367  C\n-----------------------------------------------------------------------------------------------\nPRACTICAL PAPERS\nAPPLIED PHYSICS LAB-II 1 1535 050 - 20133043  A\nINTRODUCTION TO IT SYSTEM LAB 2 1535 050 - 20143246  A+\nFUNDA OF ELECT AND EC ENGG LAB 1 1535 050 - 20133144  A\nENGG. MECHANICS LAB 2 1535 050 - 20143347  A+\n-----------------------------------------------------------------------------------------------\nTERM WORK PAPERS\nC.U MOOCS/ SWAYAM/ ETC/ OTHERS 2 0614 020 - 08051217  A\nKYP/IT ESSEN/ PYTHON/ OTHERS 1 0614 020 - 08051318  A+\nENVIRONMENTAL SCIENCE 0 10 -010 - 0409 -09  A+\n-----------------------------------------------------------------------------------------------\nGRAND TOTAL 24 750 523\n-----------------------------------------------------------------------------------------------\nSGPA \n-----------------------------------------------------------------------------------------------\nREMARKS : Carry in - MATHEMATICS-II",
        "college": "Government Polytechnic, Gopalganj",
        "name": "SHALU KUMARI",
        "roll": "211162023041",
        "branch": "20",
        "marks": 523,
        "remarks": "Carry in - MATHEMATICS-II",
        "theory": 166
    },
    {
        "text": " \n \nRegistration No : 1752523016\nRoll No         : 211752523016\n \nFollowing are the marks obtained by SHAMSHAD ALAM\nof Buddha Polytechnic Institute, Gaya\nat Semester II of Diploma in Mechanical Engineering\nExamination 2024 (EVEN) held in the month of JUL, 2024\n \n \nResult Published On: 30/07/2024\nSTATE BOARD OF TECHNICAL EDUCATION\nBIHAR\n-----------------------------------------------------------------------------------------------\nSUBJECT  FULL MARKS PASS MARKS MARKS OBTAINED\nNAME OF SUBJECTS CREDITS INTFINTOTAL FINTOTAL INT FIN TOTAL GRADE\n-----------------------------------------------------------------------------------------------\nTHEORY PAPERS\nMATHEMATICS-II 4 3070 100 28 40285684  A\nAPPLIED PHYSICS-II 3 3070 100 28 40273562  C\nINTRODUCTION TO IT SYSTEMS 2 3070 100 28 40255075  B\nFUNDA OF ELECT AND EC ENGG 3 3070 100 28 40254772  B\nENGG. MECHANICS 3 3070 100 28 40274471  B\n-----------------------------------------------------------------------------------------------\nPRACTICAL PAPERS\nAPPLIED PHYSICS LAB-II 1 1535 050 - 20143044  A\nINTRODUCTION TO IT SYSTEM LAB 2 1535 050 - 20143246  A+\nFUNDA OF ELECT AND EC ENGG LAB 1 1535 050 - 20143044  A\nENGG. MECHANICS LAB 2 1535 050 - 20143044  A\n-----------------------------------------------------------------------------------------------\nTERM WORK PAPERS\nC.U MOOCS/ SWAYAM/ ETC/ OTHERS 2 0614 020 - 08061218  A+\nKYP/IT ESSEN/ PYTHON/ OTHERS 1 0614 020 - 08061117  A\nENVIRONMENTAL SCIENCE 0 10 -010 - 0409 -09  A+\n-----------------------------------------------------------------------------------------------\nGRAND TOTAL 24 750 586\n-----------------------------------------------------------------------------------------------\nSGPA 8.58\n-----------------------------------------------------------------------------------------------\nREMARKS : First Class with Distinction",
        "college": "Buddha Polytechnic Institute, Gaya",
        "name": "SHAMSHAD ALAM",
        "roll": "211752523016",
        "branch": "25",
        "marks": 586,
        "remarks": "First Class with Distinction",
        "theory": 232
    },
    {
        "text": " \n \nRegistration No : 1752523006\nRoll No         : 211752523006\n \nFollowing are the marks obtained by OM  RAJ\nof Buddha Polytechnic Institute, Gaya\nat Semester II of Diploma in Mechanical Engineering\nExamination 2024 (EVEN) held in the month of JUL, 2024\n \n \nResult Published On: 30/07/2024\nSTATE BOARD OF TECHNICAL EDUCATION\nBIHAR\n-----------------------------------------------------------------------------------------------\nSUBJECT  FULL MARKS PASS MARKS MARKS OBTAINED\nNAME OF SUBJECTS CREDITS INTFINTOTAL FINTOTAL INT FIN TOTAL GRADE\n-----------------------------------------------------------------------------------------------\nTHEORY PAPERS\nMATHEMATICS-II 4 3070 100 28 40250631  F\nAPPLIED PHYSICS-II 3 3070 100 28 40252853  D\nINTRODUCTION TO IT SYSTEMS 2 3070 100 28 40263662  C\nFUNDA OF ELECT AND EC ENGG 3 3070 100 28 40271542  E\nENGG. MECHANICS 3 3070 100 28 40260935  F\n-----------------------------------------------------------------------------------------------\nPRACTICAL PAPERS\nAPPLIED PHYSICS LAB-II 1 1535 050 - 20133043  A\nINTRODUCTION TO IT SYSTEM LAB 2 1535 050 - 20133245  A+\nFUNDA OF ELECT AND EC ENGG LAB 1 1535 050 - 20133043  A\nENGG. MECHANICS LAB 2 1535 050 - 20132942  A\n-----------------------------------------------------------------------------------------------\nTERM WORK PAPERS\nC.U MOOCS/ SWAYAM/ ETC/ OTHERS 2 0614 020 - 08051217  A\nKYP/IT ESSEN/ PYTHON/ OTHERS 1 0614 020 - 08061117  A\nENVIRONMENTAL SCIENCE 0 10 -010 - 0408 -08  A\n-----------------------------------------------------------------------------------------------\nGRAND TOTAL 24 750 438\n-----------------------------------------------------------------------------------------------\nSGPA \n-----------------------------------------------------------------------------------------------\nREMARKS : Fail",
        "college": "Buddha Polytechnic Institute, Gaya",
        "name": "OM RAJ",
        "roll": "211752523006",
        "branch": "25",
        "marks": 438,
        "remarks": "Fail",
        "theory": 94
    },
    {
        "text": " \n \nRegistration No : 1752523013\nRoll No         : 211752523013\n \nFollowing are the marks obtained by ARJUN  KUMAR\nof Buddha Polytechnic Institute, Gaya\nat Semester II of Diploma in Mechanical Engineering\nExamination 2024 (EVEN) held in the month of JUL, 2024\n \n \nResult Published On: 30/07/2024\nSTATE BOARD OF TECHNICAL EDUCATION\nBIHAR\n-----------------------------------------------------------------------------------------------\nSUBJECT  FULL MARKS PASS MARKS MARKS OBTAINED\nNAME OF SUBJECTS CREDITS INTFINTOTAL FINTOTAL INT FIN TOTAL GRADE\n-----------------------------------------------------------------------------------------------\nTHEORY PAPERS\nMATHEMATICS-II 4 3070 100 28 40264874  B\nAPPLIED PHYSICS-II 3 3070 100 28 40262955  D\nINTRODUCTION TO IT SYSTEMS 2 3070 100 28 40263460  C\nFUNDA OF ELECT AND EC ENGG 3 3070 100 28 40262854  D\nENGG. MECHANICS 3 3070 100 28 40263864  C\n-----------------------------------------------------------------------------------------------\nPRACTICAL PAPERS\nAPPLIED PHYSICS LAB-II 1 1535 050 - 20143044  A\nINTRODUCTION TO IT SYSTEM LAB 2 1535 050 - 20143246  A+\nFUNDA OF ELECT AND EC ENGG LAB 1 1535 050 - 20143044  A\nENGG. MECHANICS LAB 2 1535 050 - 20143145  A+\n-----------------------------------------------------------------------------------------------\nTERM WORK PAPERS\nC.U MOOCS/ SWAYAM/ ETC/ OTHERS 2 0614 020 - 08061117  A\nKYP/IT ESSEN/ PYTHON/ OTHERS 1 0614 020 - 08061218  A+\nENVIRONMENTAL SCIENCE 0 10 -010 - 0409 -09  A+\n-----------------------------------------------------------------------------------------------\nGRAND TOTAL 24 750 530\n-----------------------------------------------------------------------------------------------\nSGPA 7.88\n-----------------------------------------------------------------------------------------------\nREMARKS : First Class",
        "college": "Buddha Polytechnic Institute, Gaya",
        "name": "ARJUN KUMAR",
        "roll": "211752523013",
        "branch": "25",
        "marks": 530,
        "remarks": "First Class",
        "theory": 177
    },
    {
        "text": " \n \nRegistration No : 1752023028\nRoll No         : 211752023028\n \nFollowing are the marks obtained by ANSH  KUMAR\nof Buddha Polytechnic Institute, Gaya\nat Semester II of Diploma in Electrical Engineering\nExamination 2024 (EVEN) held in the month of JUL, 2024\n \n \nResult Published On: 30/07/2024\nSTATE BOARD OF TECHNICAL EDUCATION\nBIHAR\n-----------------------------------------------------------------------------------------------\nSUBJECT  FULL MARKS PASS MARKS MARKS OBTAINED\nNAME OF SUBJECTS CREDITS INTFINTOTAL FINTOTAL INT FIN TOTAL GRADE\n-----------------------------------------------------------------------------------------------\nTHEORY PAPERS\nMATHEMATICS-II 4 3070 100 28 40271138  F\nAPPLIED PHYSICS-II 3 3070 100 28 40261642  E\nINTRODUCTION TO IT SYSTEMS 2 3070 100 28 40274875  B\nFUNDA OF ELECT AND EC ENGG 3 3070 100 28 40253257  D\nENGG. MECHANICS 3 3070 100 28 40262046  E\n-----------------------------------------------------------------------------------------------\nPRACTICAL PAPERS\nAPPLIED PHYSICS LAB-II 1 1535 050 - 20133043  A\nINTRODUCTION TO IT SYSTEM LAB 2 1535 050 - 20133245  A+\nFUNDA OF ELECT AND EC ENGG LAB 1 1535 050 - 20132942  A\nENGG. MECHANICS LAB 2 1535 050 - 20132942  A\n-----------------------------------------------------------------------------------------------\nTERM WORK PAPERS\nC.U MOOCS/ SWAYAM/ ETC/ OTHERS 2 0614 020 - 08051015  B\nKYP/IT ESSEN/ PYTHON/ OTHERS 1 0614 020 - 08051116  A\nENVIRONMENTAL SCIENCE 0 10 -010 - 0408 -08  A\n-----------------------------------------------------------------------------------------------\nGRAND TOTAL 24 750 469\n-----------------------------------------------------------------------------------------------\nSGPA \n-----------------------------------------------------------------------------------------------\nREMARKS : Fail",
        "college": "Buddha Polytechnic Institute, Gaya",
        "name": "ANSH KUMAR",
        "roll": "211752023028",
        "branch": "20",
        "marks": 469,
        "remarks": "Fail",
        "theory": 127
    },
    {
        "text": " \n \nRegistration No : 1752023038\nRoll No         : 211752023038\n \nFollowing are the marks obtained by SUMAN  KUMAR\nof Buddha Polytechnic Institute, Gaya\nat Semester II of Diploma in Electrical Engineering\nExamination 2024 (EVEN) held in the month of JUL, 2024\n \n \nResult Published On: 30/07/2024\nSTATE BOARD OF TECHNICAL EDUCATION\nBIHAR\n-----------------------------------------------------------------------------------------------\nSUBJECT  FULL MARKS PASS MARKS MARKS OBTAINED\nNAME OF SUBJECTS CREDITS INTFINTOTAL FINTOTAL INT FIN TOTAL GRADE\n-----------------------------------------------------------------------------------------------\nTHEORY PAPERS\nMATHEMATICS-II 4 3070 100 28 40271744  E\nAPPLIED PHYSICS-II 3 3070 100 28 40274370  B\nINTRODUCTION TO IT SYSTEMS 2 3070 100 28 40274572  B\nFUNDA OF ELECT AND EC ENGG 3 3070 100 28 40275077  B\nENGG. MECHANICS 3 3070 100 28 40274067  C\n-----------------------------------------------------------------------------------------------\nPRACTICAL PAPERS\nAPPLIED PHYSICS LAB-II 1 1535 050 - 20143246  A+\nINTRODUCTION TO IT SYSTEM LAB 2 1535 050 - 20143347  A+\nFUNDA OF ELECT AND EC ENGG LAB 1 1535 050 - 20143246  A+\nENGG. MECHANICS LAB 2 1535 050 - 20143145  A+\n-----------------------------------------------------------------------------------------------\nTERM WORK PAPERS\nC.U MOOCS/ SWAYAM/ ETC/ OTHERS 2 0614 020 - 08061218  A+\nKYP/IT ESSEN/ PYTHON/ OTHERS 1 0614 020 - 08061016  A\nENVIRONMENTAL SCIENCE 0 10 -010 - 0409 -09  A+\n-----------------------------------------------------------------------------------------------\nGRAND TOTAL 24 750 557\n-----------------------------------------------------------------------------------------------\nSGPA \n-----------------------------------------------------------------------------------------------\nREMARKS : Carry in - MATHEMATICS-II",
        "college": "Buddha Polytechnic Institute, Gaya",
        "name": "SUMAN KUMAR",
        "roll": "211752023038",
        "branch": "20",
        "marks": 557,
        "remarks": "Carry in - MATHEMATICS-II",
        "theory": 195
    },
    {
        "text": " \n \nRegistration No : 1752023007\nRoll No         : 211752023007\n \nFollowing are the marks obtained by MRITUNJAY KUMAR\nof Buddha Polytechnic Institute, Gaya\nat Semester II of Diploma in Electrical Engineering\nExamination 2024 (EVEN) held in the month of JUL, 2024\n \n \nResult Published On: 30/07/2024\nSTATE BOARD OF TECHNICAL EDUCATION\nBIHAR\n-----------------------------------------------------------------------------------------------\nSUBJECT  FULL MARKS PASS MARKS MARKS OBTAINED\nNAME OF SUBJECTS CREDITS INTFINTOTAL FINTOTAL INT FIN TOTAL GRADE\n-----------------------------------------------------------------------------------------------\nTHEORY PAPERS\nMATHEMATICS-II 4 3070 100 28 40260935  F\nAPPLIED PHYSICS-II 3 3070 100 28 40273663  C\nINTRODUCTION TO IT SYSTEMS 2 3070 100 28 40273966  C\nFUNDA OF ELECT AND EC ENGG 3 3070 100 28 40271744  E\nENGG. MECHANICS 3 3070 100 28 40262955  D\n-----------------------------------------------------------------------------------------------\nPRACTICAL PAPERS\nAPPLIED PHYSICS LAB-II 1 1535 050 - 20143044  A\nINTRODUCTION TO IT SYSTEM LAB 2 1535 050 - 20133245  A+\nFUNDA OF ELECT AND EC ENGG LAB 1 1535 050 - 20132942  A\nENGG. MECHANICS LAB 2 1535 050 - 20143044  A\n-----------------------------------------------------------------------------------------------\nTERM WORK PAPERS\nC.U MOOCS/ SWAYAM/ ETC/ OTHERS 2 0614 020 - 08061218  A+\nKYP/IT ESSEN/ PYTHON/ OTHERS 1 0614 020 - 08061117  A\nENVIRONMENTAL SCIENCE 0 10 -010 - 0409 -09  A+\n-----------------------------------------------------------------------------------------------\nGRAND TOTAL 24 750 482\n-----------------------------------------------------------------------------------------------\nSGPA \n-----------------------------------------------------------------------------------------------\nREMARKS : Carry in - MATHEMATICS-II\n FUNDA OF ELECT AND EC ENGG",
        "college": "Buddha Polytechnic Institute, Gaya",
        "name": "MRITUNJAY KUMAR",
        "roll": "211752023007",
        "branch": "20",
        "marks": 482,
        "remarks": "Carry in - MATHEMATICS-II",
        "theory": 130
    }
]
